Workbook

Sheet Summary
A1: Client Rate Comparison 2026 (rates only)
A2: Trips 2 Jan – 30 Sep 2026 · selling price excl. VAT · payment status ignored · haulage and flat trucks only (treated as one); closed-body/canter and Hiab trips excluded
A4: Revenue achieved vs best rate
A5: Revenue achieved: ₦2,391,115,142
A6: Revenue if every trip had been sold at the best (highest) rate on its route: ₦2,569,440,468 — ₦178,325,327 more (+7.5%)
A7: Revenue at the best-paying client’s average rate: ₦2,509,970,801 — ₦118,855,660 more (+5.0%). Detail by client and month: ‘Achieved vs Best Rate’ sheet.
A9: How to read this
A10: Rate level = what a client pays compared with the best-paying client on the same route in the same quarter. 100% = pays the top rate.
A11: Revenue lost = extra revenue if the client had paid the best-paying client’s average rate on those trips.
A13: Key findings
A14: Total revenue lost to lower rates: ₦118.9M (5.0% of 2026 haulage revenue of ₦2.39bn).
A15: Worst on rates: Jamara — pays ~89% of the best rate but, on high volume, costs ₦52.9M (45% of the total).
... A23: Some differences may have reasons not in the trip log (load weight, waiting time, contract terms). Review the largest gaps with each account.

Sheet Achieved vs Best Rate
A1: Revenue achieved vs revenue at the best rate — 2026
A2: Best rate = the highest rate any client paid on the same route and quarter (haulage and flat trucks only). Best client average = the average rate of the best-paying client on that route. Only trips on routes shared by 2+ clients can be repriced.
A4: Headline
B5: Revenue (₦) | C5: Difference vs achieved (₦) | D5: Difference %
A6: Revenue achieved | B6: =C41
A7: Revenue at best rate (highest on route) | B7: =D41 | C7: =E41 | D7: =C7/B6
A8: Revenue at best client average | B8: =G41 | C8: =H41 | D8: =C8/B6
A10: By client
A11: Client | B11: Trips | C11: Revenue achieved (₦) | D11: Revenue at best rate (₦) | E11: Difference (₦) | F11: Difference % | G11: Revenue at best client avg (₦) | H11: Difference (₦) | I11: Difference %
A12: NBL | B12: 355 | C12: 5.766846e+08 | D12: =C12+E12 | E12: 5488758.1 | F12: =IF(C12=0,0,E12/C12) | G12: =C12+H12 | H12: 1058582.5 | I12: =IF(C12=0,0,H12/C12)
A13: Jamara | B13: 252 | C13: 4.7832228e+08 | D13: =C13+E13 | E13: 68525639 | F13: =IF(C13=0,0,E13/C13) | G13: =C13+H13 | H13: 52915476 | I13: =IF(C13=0,0,H13/C13)
A14: MEGA MANU | B14: 126 | C14: 2.4630395e+08 | D14: =C14+E14 | E14: 41530328 | F14: =IF(C14=0,0,E14/C14) | G14: =C14+H14 | H14: 23787322 | I14: =IF(C14=0,0,H14/C14)
A15: SASO | B15: 43 | C15: 1.7476442e+08 | D15: =C15+E15 | E15: 1503255.8 | F15: =IF(C15=0,0,E15/C15) | G15: =C15+H15 | H15: 37209.302 | I15: =IF(C15=0,0,H15/C15)
A16: NATURAL BEAUTY | B16: 34 | C16: 1.2646279e+08 | D16: =C16+E16 | E16: 16911628 | F16: =IF(C16=0,0,E16/C16) | G16: =C16+H16 | H16: 2506976.7 | I16: =IF(C16=0,0,H16/C16)
A17: ORCA DECO LIMITED | B17: 287 | C17: 1.2501978e+08 | D17: =C17+E17 | E17: 0 | F17: =IF(C17=0,0,E17/C17) | G17: =C17+H17 | H17: 0 | I17: =IF(C17=0,0,H17/C17)
A18: AB-INBEV | B18: 46 | C18: 1.1094374e+08 | D18: =C18+E18 | E18: 0 | F18: =IF(C18=0,0,E18/C18) | G18: =C18+H18 | H18: 0 | I18: =IF(C18=0,0,H18/C18)
A19: JUBAILI AGROTEC | B19: 44 | C19: 1.1060117e+08 | D19: =C19+E19 | E19: 6177712.4 | F19: =IF(C19=0,0,E19/C19) | G19: =C19+H19 | H19: 5694126.3 | I19: =IF(C19=0,0,H19/C19)
A20: VENDARA | B20: 24 | C20: 88279070 | D20: =C20+E20 | E20: 6107459.2 | F20: =IF(C20=0,0,E20/C20) | G20: =C20+H20 | H20: 5627459.2 | I20: =IF(C20=0,0,H20/C20)
A21: Lacasera | B21: 69 | C21: 51736810 | D21: =C21+E21 | E21: 14209890 | F21: =IF(C21=0,0,E21/C21) | G21: =C21+H21 | H21: 14209890 | I21: =IF(C21=0,0,H21/C21)
A22: ABBA ABASS | B22: 34 | C22: 48649302 | D22: =C22+E22 | E22: 0 | F22: =IF(C22=0,0,E22/C22) | G22: =C22+H22 | H22: 0 | I22: =IF(C22=0,0,H22/C22)
A23: GIVANAS | B23: 23 | C23: 43741860 | D23: =C23+E23 | E23: 4396778.9 | F23: =IF(C23=0,0,E23/C23) | G23: =C23+H23 | H23: 1373058 | I23: =IF(C23=0,0,H23/C23)
... A40: B2B-ORCA DECO LIMITED (MR LEKAN) | B40: 1 | C40: 350000 | D40: =C40+E40 | E40: 161627.91 | F40: =IF(C40=0,0,E40/C40) | G40: =C40+H40 | H40: 161627.91 | I40: =IF(C40=0,0,H40/C40)
A41: Total | B41: =SUM(B12:B40) | C41: =SUM(C12:C40) | D41: =SUM(D12:D40) | E41: =SUM(E12:E40) | F41: =E41/C41 | G41: =SUM(G12:G40) | H41: =SUM(H12:H40) | I41: =H41/C41
A43: By month
A44: Month | B44: Trips | C44: Revenue achieved (₦) | D44: Revenue at best rate (₦) | E44: Difference (₦) | F44: Difference % | G44: Revenue at best client avg (₦) | H44: Difference (₦) | I44: Difference %
A45: Jan 2026 | B45: 147 | C45: 2.4320157e+08 | D45: =C45+E45 | E45: 28434380 | F45: =E45/C45 | G45: =C45+H45 | H45: 9481184.9 | I45: =H45/C45
A46: Feb 2026 | B46: 170 | C46: 2.0239258e+08 | D46: =C46+E46 | E46: 42478727 | F46: =E46/C46 | G46: =C46+H46 | H46: 21625702 | I46: =H46/C46
A47: Mar 2026 | B47: 199 | C47: 2.5776009e+08 | D47: =C47+E47 | E47: 19708681 | F47: =E47/C47 | G47: =C47+H47 | H47: 7388741.5 | I47: =H47/C47
A48: Apr 2026 | B48: 187 | C48: 2.6254567e+08 | D48: =C48+E48 | E48: 11509064 | F48: =E48/C48 | G48: =C48+H48 | H48: 8857366.1 | I48: =H48/C48
A49: May 2026 | B49: 197 | C49: 2.952948e+08 | D49: =C49+E49 | E49: 12108049 | F49: =E49/C49 | G49: =C49+H49 | H49: 11176353 | I49: =H49/C49
A50: Jun 2026 | B50: 162 | C50: 3.3031219e+08 | D50: =C50+E50 | E50: 13146977 | F50: =E50/C50 | G50: =C50+H50 | H50: 13418276 | I50: =H50/C50
A51: Jul 2026 | B51: 126 | C51: 2.595201e+08 | D51: =C51+E51 | E51: 16103927 | F51: =E51/C51 | G51: =C51+H51 | H51: 15813362 | I51: =H51/C51
A52: Aug 2026 | B52: 121 | C52: 2.651464e+08 | D52: =C52+E52 | E52: 20493000 | F52: =E52/C52 | G52: =C52+H52 | H52: 16229127 | I52: =H52/C52
A53: Sep 2026 | B53: 124 | C53: 2.7494174e+08 | D53: =C53+E53 | E53: 14342522 | F53: =E53/C53 | G53: =C53+H53 | H53: 14865547 | I53: =H53/C53
A54: Total | B54: =SUM(B45:B53) | C54: =SUM(C45:C53) | D54: =SUM(D45:D53) | E54: =SUM(E45:E53) | F54: =E54/C54 | G54: =SUM(G45:G53) | H54: =SUM(H45:H53) | I54: =H54/C54

Sheet Client Rate Ranking
A1: Clients ranked by revenue lost to lower rates
A2: Rate level: 100% = pays the best client’s rate on the same route and quarter. Revenue lost = shortfall against that rate.
A4: Rank | B4: Client | C4: Rate level | D4: Verdict | E4: Revenue lost (₦) | F4: Share of total lost | G4: Lost if priced at highest rate (₦) | H4: Trips on compared routes | I4: Revenue on compared routes (₦) | J4: 2026 revenue (₦) | K4: Routes with biggest gaps
A5: 1 | B5: Jamara | C5: 0.88864022 | D5: Below peers | E5: 52915476 | F5: =IF($E$27=0,0,E5/$E$27) | G5: 68525639 | H5: 175 | I5: 3.9392514e+08 | J5: 4.7832228e+08 | K5: Lagos → Abuja, Lagos → Kano, Lagos → Benin
A6: 2 | B6: MEGA MANU | C6: 0.89551265 | D6: Below peers | E6: 23787322 | F6: =IF($E$27=0,0,E6/$E$27) | G6: 41530328 | H6: 121 | I6: 2.4241953e+08 | J6: 2.4630395e+08 | K6: Lagos → Kano, Lagos → Ibadan, Lagos → Abuja
A7: 3 | B7: Lacasera | C7: 0.64565312 | D7: Well below peers | E7: 14209890 | F7: =IF($E$27=0,0,E7/$E$27) | G7: 14209890 | H7: 24 | I7: 28381995 | J7: 51736810 | K7: Lagos → Benin
A8: 4 | B8: JUBAILI AGROTEC | C8: 0.74606206 | D8: Well below peers | E8: 5694126.3 | F8: =IF($E$27=0,0,E8/$E$27) | G8: 6177712.4 | H8: 8 | I8: 13593464 | J8: 1.1060117e+08 | K8: Ibadan → Abuja, Ibadan → Ekpoma, Ibadan → Kaduna
A9: 5 | B9: VENDARA | C9: 0.93560814 | D9: Below peers | E9: 5627459.2 | F9: =IF($E$27=0,0,E9/$E$27) | G9: 6107459.2 | H9: 24 | I9: 88279070 | J9: 88279070 | K9: Lagos → Kano, Lagos → Onitsha
A10: 6 | B10: NIGER BISCUITS | C10: 0.91364002 | D10: Below peers | E10: 2599292 | F10: =IF($E$27=0,0,E10/$E$27) | G10: 4250000 | H10: 11 | I10: 26112791 | J10: 43323256 | K10: Lagos → Owerri, Lagos → Abuja, Lagos → PHC
A11: 7 | B11: NATURAL BEAUTY | C11: 0.98267631 | D11: Close to top | E11: 2506976.7 | F11: =IF($E$27=0,0,E11/$E$27) | G11: 16911628 | H11: 33 | I11: 1.2599767e+08 | J11: 1.2646279e+08 | K11: Lagos → Kano
A12: 8 | B12: KD & SONS | C12: 0.50900997 | D12: Well below peers | E12: 2007569.7 | F12: =IF($E$27=0,0,E12/$E$27) | G12: 2007569.7 | H12: 2 | I12: 2081250 | J12: 2081250 | K12: Kaduna (Kudenda) → Ibadan
A13: 9 | B13: GIVANAS | C13: 0.97345383 | D13: Close to top | E13: 1373058 | F13: =IF($E$27=0,0,E13/$E$27) | G13: 4396778.9 | H13: 23 | I13: 43741860 | J13: 43741860 | K13: Lagos → Onitsha
A14: 10 | B14: INTERSTYLE | C14: 0.93593162 | D14: Below peers | E14: 1227907 | F14: =IF($E$27=0,0,E14/$E$27) | G14: 1227907 | H14: 6 | I14: 17841860 | J14: 25655814 | K14: Lagos → Abuja, Lagos → PHC
A15: 11 | B15: B2B-ORCA DECO LIMITED(MR OTEGA) | C15: 0.67342174 | D15: Well below peers | E15: 1115393.2 | F15: =IF($E$27=0,0,E15/$E$27) | G15: 1115393.2 | H15: 1 | I15: 2300000 | J15: 2300000 | K15: Lagos → Asaba
A16: 12 | B16: NBL | C16: 0.93304459 | D16: Below peers | E16: 1058582.5 | F16: =IF($E$27=0,0,E16/$E$27) | G16: 5488758.1 | H16: 25 | I16: 44470130 | J16: 5.766846e+08 | K16: Lagos → Ibadan, Lagos → Ijebu Ode
... A26: 22 | B26: ORCA DECO LIMITED | C26: 1 | D26: At top rate | E26: 0 | F26: =IF($E$27=0,0,E26/$E$27) | G26: 0 | H26: 5 | I26: 14374086 | J26: 1.2501978e+08 | K26: —
B27: Total | E27: =SUM(E5:E26) | G27: =SUM(G5:G26) | H27: =SUM(H5:H26) | I27: =SUM(I5:I26) | J27: =SUM(J5:J26)

Sheet Rate Gaps by Route
A1: Where each client pays less than the best-paying client
A3: Quarter | B3: Route | C3: Vehicle | D3: Client (lower rate) | E3: Trips | F3: Their avg rate (₦) | G3: Best-paying client | H3: Best client trips | I3: Best avg rate (₦) | J3: Rate level | K3: Revenue lost (₦) | L3: Highest rate on route (₦) | M3: Lost if at highest (₦)
A4: Q1 | B4: Lagos → Benin | C4: Haulage | D4: Lacasera | E4: 18 | F4: 881463.21 | G4: NBL | H4: 2 | I4: 1670901.5 | J4: =F4/I4 | K4: =MAX(0,I4-F4)*E4 | L4: 1670901.5 | M4: 14209890
A5: Q3 | B5: Lagos → Abuja | C5: Haulage | D5: Jamara | E5: 22 | F5: 2692727.3 | G5: INTERSTYLE | H5: 3 | I5: 3162790.7 | J5: =F5/I5 | K5: =MAX(0,I5-F5)*E5 | L5: 3162790.7 | M5: 10341395
A6: Q2 | B6: Lagos → Abuja | C6: Haulage | D6: Jamara | E6: 12 | F6: 2794554.2 | G6: ORCA DECO LIMITED | H6: 1 | I6: 3627907 | J6: =F6/I6 | K6: =MAX(0,I6-F6)*E6 | L6: 3627907 | M6: 10000234
A7: Q3 | B7: Lagos → Kano | C7: Haulage | D7: Jamara | E7: 16 | F7: 3775000 | G7: SASO | H7: 10 | I7: 4400000 | J7: =F7/I7 | K7: =MAX(0,I7-F7)*E7 | L7: 4400000 | M7: 10000000
A8: Q3 | B8: Lagos → Kano | C8: Haulage | D8: MEGA MANU | E8: 11 | F8: 3771670.2 | G8: SASO | H8: 10 | I8: 4400000 | J8: =F8/I8 | K8: =MAX(0,I8-F8)*E8 | L8: 4400000 | M8: 6911627.9
A9: Q1 | B9: Lagos → PHC | C9: Haulage | D9: Jamara | E9: 17 | F9: 2035294.1 | G9: GIVANAS | H9: 1 | I9: 2325581.4 | J9: =F9/I9 | K9: =MAX(0,I9-F9)*E9 | L9: 2325581.4 | M9: 4934883.7
A10: Q2 | B10: Lagos → Kano | C10: Haulage | D10: Jamara | E10: 10 | F10: 3864820 | G10: SASO | H10: 8 | I10: 4340000 | J10: =F10/I10 | K10: =MAX(0,I10-F10)*E10 | L10: 4400000 | M10: 5351800
A11: Q1 | B11: Lagos → Benin | C11: Haulage | D11: Jamara | E11: 7 | F11: 1003543.3 | G11: NBL | H11: 2 | I11: 1670901.5 | J11: =F11/I11 | K11: =MAX(0,I11-F11)*E11 | L11: 1670901.5 | M11: 4671507.4
A12: Q2 | B12: Lagos → Ibadan | C12: Haulage | D12: MEGA MANU | E12: 28 | F12: 636943.52 | G12: MAMUDA BEVERAGES CO. LTD | H12: 5 | I12: 790697.67 | J12: =F12/I12 | K12: =MAX(0,I12-F12)*E12 | L12: 800000 | M12: 4565581.4
A13: Q2 | B13: Lagos → Kano | C13: Haulage | D13: MEGA MANU | E13: 13 | F13: 4089445.4 | G13: SASO | H13: 8 | I13: 4340000 | J13: =F13/I13 | K13: =MAX(0,I13-F13)*E13 | L13: 4400000 | M13: 4037209.3
A14: Q1 | B14: Lagos → Kano | C14: Haulage | D14: MEGA MANU | E14: 14 | F14: 3162790.7 | G14: NATURAL BEAUTY | H14: 14 | I14: 3386046.5 | J14: =F14/I14 | K14: =MAX(0,I14-F14)*E14 | L14: 4372093 | M14: 16930233
A15: Q3 | B15: Lagos → Kano | C15: Haulage | D15: VENDARA | E15: 11 | F15: 4139534.9 | G15: SASO | H15: 10 | I15: 4400000 | J15: =F15/I15 | K15: =MAX(0,I15-F15)*E15 | L15: 4400000 | M15: 2865116.3
... A65: Q1 | B65: Ibadan → Oyo | C65: Haulage | D65: JUBAILI AGROTEC | E65: 1 | F65: 279069.77 | G65: NBL | H65: 1 | I65: 283860 | J65: =F65/I65 | K65: =MAX(0,I65-F65)*E65 | L65: 283860 | M65: 4790.2326
D66: Total | K66: =SUM(K4:K65) | M66: =SUM(M4:M65)

Sheet Turnaround Table
A1: Turnaround time — one leg (drop point → loading bay)
A2: Your table. Edit any Days value (yellow) and the truck requirement recalculates. Add new routes at the bottom; the Key fills itself.
A4: From (drop point) | B4: To (loading bay) | C4: Days (one leg) | D4: Key
A5: Abuja | B5: APAPA | C5: 2 | D5: =UPPER(A5)&">"&UPPER(B5)
A6: Warri | B6: APAPA | C6: 1 | D6: =UPPER(A6)&">"&UPPER(B6)
A7: Abuja | B7: Abuja | C7: 1 | D7: =UPPER(A7)&">"&UPPER(B7)
A8: ABAJI | B8: IBADAN | C8: 2 | D8: =UPPER(A8)&">"&UPPER(B8)
A9: AYANGBA | B9: IBADAN | C9: 2 | D9: =UPPER(A9)&">"&UPPER(B9)
A10: Aba | B10: IBADAN | C10: 2 | D10: =UPPER(A10)&">"&UPPER(B10)
A11: Abakalike | B11: IBADAN | C11: 2 | D11: =UPPER(A11)&">"&UPPER(B11)
A12: Abuja | B12: IBADAN | C12: 2 | D12: =UPPER(A12)&">"&UPPER(B12)
A13: Agbor | B13: IBADAN | C13: 1 | D13: =UPPER(A13)&">"&UPPER(B13)
A14: Bauchi | B14: IBADAN | C14: 3 | D14: =UPPER(A14)&">"&UPPER(B14)
A15: Bida | B15: IBADAN | C15: 1 | D15: =UPPER(A15)&">"&UPPER(B15)
A16: Ekpoma | B16: IBADAN | C16: 1 | D16: =UPPER(A16)&">"&UPPER(B16)
... A201: Port Harcourt | B201: Benin | C201: 2 | D201: =UPPER(A201)&">"&UPPER(B201)
D202: =IF(A202="","",UPPER(A202)&">"&UPPER(B202))
D203: =IF(A203="","",UPPER(A203)&">"&UPPER(B203))
D204: =IF(A204="","",UPPER(A204)&">"&UPPER(B204))
D205: =IF(A205="","",UPPER(A205)&">"&UPPER(B205))
D206: =IF(A206="","",UPPER(A206)&">"&UPPER(B206))
D207: =IF(A207="","",UPPER(A207)&">"&UPPER(B207))
D208: =IF(A208="","",UPPER(A208)&">"&UPPER(B208))
D209: =IF(A209="","",UPPER(A209)&">"&UPPER(B209))
D210: =IF(A210="","",UPPER(A210)&">"&UPPER(B210))
D211: =IF(A211="","",UPPER(A211)&">"&UPPER(B211))
D212: =IF(A212="","",UPPER(A212)&">"&UPPER(B212))
D213: =IF(A213="","",UPPER(A213)&">"&UPPER(B213))
... D231: =IF(A231="","",UPPER(A231)&">"&UPPER(B231))

Sheet Truck Requirement
A1: Truck requirement per client — monthly rotation
A2: A truck rotates on its route through the month. Trips one truck can do per month = whole number of (operating days ÷ round-trip days). Example: 6-day round trip → 4 trips per truck per month (one a week), so 4 trips a month need 1 truck. Trucks needed = trips in the month ÷ trips per truck, added up across the client's routes and rounded up per client.
A4: Operating days per truck per month | B4: 26 | C4: Days a truck is available to run (26 allows for Sundays and maintenance; use 30 for every day).
A5: Default one-leg days for routes not in your table | B5: 2 | C5: Used only where a route has no match and no override (red rows on the route sheet).
A7: Trips one truck can do in a month:
A8: 2-day round trip (Lagos/Ibadan local) | B8: =MAX(1,INT('Truck Requirement'!$B$4/2)) | C8: trip(s) per truck per month
A9: 4-day round trip (e.g. PHC, Onitsha, Benin from Ibadan) | B9: =MAX(1,INT('Truck Requirement'!$B$4/4)) | C9: trip(s) per truck per month
A10: 6-day round trip (e.g. Abuja, Kaduna) | B10: =MAX(1,INT('Truck Requirement'!$B$4/6)) | C10: trip(s) per truck per month
A11: 8-day round trip (e.g. Kano from Lagos) | B11: =MAX(1,INT('Truck Requirement'!$B$4/8)) | C11: trip(s) per truck per month
A12: 10-day round trip (e.g. Yola, Maiduguri) | B12: =MAX(1,INT('Truck Requirement'!$B$4/10)) | C12: trip(s) per truck per month
B14: Trucks needed each month (trucks rotating on their routes)
A15: Client | B15: Jan | C15: Feb | D15: Mar | E15: Apr | F15: May | G15: Jun | H15: Jul | I15: Aug | J15: Sep | K15: Months with trips | L15: Avg trips per month | M15: Typical month (avg trucks) | N15: Peak month (trucks) | O15: Peak month Jul–Sep | P15: Avg round-trip days
A16: NBL | B16: =ROUNDUP(SUMIFS('Truck Req by Route'!$V$5:$V$320,'Truck Req by Route'!$A$5:$A$320,$A16),0) | C16: =ROUNDUP(SUMIFS('Truck Req by Route'!$W$5:$W$320,'Truck Req by Route'!$A$5:$A$320,$A16),0) | D16: =ROUNDUP(SUMIFS('Truck Req by Route'!$X$5:$X$320,'Truck Req by Route'!$A$5:$A$320,$A16),0) | E16: =ROUNDUP(SUMIFS('Truck Req by Route'!$Y$5:$Y$320,'Truck Req by Route'!$A$5:$A$320,$A16),0) | F16: =ROUNDUP(SUMIFS('Truck Req by Route'!$Z$5:$Z$320,'Truck Req by Route'!$A$5:$A$320,$A16),0) | G16: =ROUNDUP(SUMIFS('Truck Req by Route'!$AA$5:$AA$320,'Truck Req by Route'!$A$5:$A$320,$A16),0) | H16: =ROUNDUP(SUMIFS('Truck Req by Route'!$AB$5:$AB$320,'Truck Req by Route'!$A$5:$A$320,$A16),0) | I16: =ROUNDUP(SUMIFS('Truck Req by Route'!$AC$5:$AC$320,'Truck Req by Route'!$A$5:$A$320,$A16),0) | J16: =ROUNDUP(SUMIFS('Truck Req by Route'!$AD$5:$AD$320,'Truck Req by Route'!$A$5:$A$320,$A16),0) | K16: =COUNTIF(B16:J16,">0") | L16: =IF(K16=0,0,SUMIFS('Truck Req by Route'!$L$5:$L$320,'Truck Req by Route'!$A$5:$A$320,$A16)/K16) | M16: =IFERROR(AVERAGEIF(B16:J16,">0"),0) | N16: =MAX(B16:J16) | O16: =MAX(H16:J16) | P16: =IFERROR(SUMPRODUCT(('Truck Req by Route'!$A$5:$A$320=$A16)*'Truck Req by Route'!$L$5:$L$320*'Truck Req by Route'!$J$5:$J$320)/SUMIFS('Truck Req by Route'!$L$5:$L$320,'Truck Req by Route'!$A$5:$A$320,$A16),"")
A17: ORCA DECO LIMITED | B17: =ROUNDUP(SUMIFS('Truck Req by Route'!$V$5:$V$320,'Truck Req by Route'!$A$5:$A$320,$A17),0) | C17: =ROUNDUP(SUMIFS('Truck Req by Route'!$W$5:$W$320,'Truck Req by Route'!$A$5:$A$320,$A17),0) | D17: =ROUNDUP(SUMIFS('Truck Req by Route'!$X$5:$X$320,'Truck Req by Route'!$A$5:$A$320,$A17),0) | E17: =ROUNDUP(SUMIFS('Truck Req by Route'!$Y$5:$Y$320,'Truck Req by Route'!$A$5:$A$320,$A17),0) | F17: =ROUNDUP(SUMIFS('Truck Req by Route'!$Z$5:$Z$320,'Truck Req by Route'!$A$5:$A$320,$A17),0) | G17: =ROUNDUP(SUMIFS('Truck Req by Route'!$AA$5:$AA$320,'Truck Req by Route'!$A$5:$A$320,$A17),0) | H17: =ROUNDUP(SUMIFS('Truck Req by Route'!$AB$5:$AB$320,'Truck Req by Route'!$A$5:$A$320,$A17),0) | I17: =ROUNDUP(SUMIFS('Truck Req by Route'!$AC$5:$AC$320,'Truck Req by Route'!$A$5:$A$320,$A17),0) | J17: =ROUNDUP(SUMIFS('Truck Req by Route'!$AD$5:$AD$320,'Truck Req by Route'!$A$5:$A$320,$A17),0) | K17: =COUNTIF(B17:J17,">0") | L17: =IF(K17=0,0,SUMIFS('Truck Req by Route'!$L$5:$L$320,'Truck Req by Route'!$A$5:$A$320,$A17)/K17) | M17: =IFERROR(AVERAGEIF(B17:J17,">0"),0) | N17: =MAX(B17:J17) | O17: =MAX(H17:J17) | P17: =IFERROR(SUMPRODUCT(('Truck Req by Route'!$A$5:$A$320=$A17)*'Truck Req by Route'!$L$5:$L$320*'Truck Req by Route'!$J$5:$J$320)/SUMIFS('Truck Req by Route'!$L$5:$L$320,'Truck Req by Route'!$A$5:$A$320,$A17),"")
A18: Jamara | B18: =ROUNDUP(SUMIFS('Truck Req by Route'!$V$5:$V$320,'Truck Req by Route'!$A$5:$A$320,$A18),0) | C18: =ROUNDUP(SUMIFS('Truck Req by Route'!$W$5:$W$320,'Truck Req by Route'!$A$5:$A$320,$A18),0) | D18: =ROUNDUP(SUMIFS('Truck Req by Route'!$X$5:$X$320,'Truck Req by Route'!$A$5:$A$320,$A18),0) | E18: =ROUNDUP(SUMIFS('Truck Req by Route'!$Y$5:$Y$320,'Truck Req by Route'!$A$5:$A$320,$A18),0) | F18: =ROUNDUP(SUMIFS('Truck Req by Route'!$Z$5:$Z$320,'Truck Req by Route'!$A$5:$A$320,$A18),0) | G18: =ROUNDUP(SUMIFS('Truck Req by Route'!$AA$5:$AA$320,'Truck Req by Route'!$A$5:$A$320,$A18),0) | H18: =ROUNDUP(SUMIFS('Truck Req by Route'!$AB$5:$AB$320,'Truck Req by Route'!$A$5:$A$320,$A18),0) | I18: =ROUNDUP(SUMIFS('Truck Req by Route'!$AC$5:$AC$320,'Truck Req by Route'!$A$5:$A$320,$A18),0) | J18: =ROUNDUP(SUMIFS('Truck Req by Route'!$AD$5:$AD$320,'Truck Req by Route'!$A$5:$A$320,$A18),0) | K18: =COUNTIF(B18:J18,">0") | L18: =IF(K18=0,0,SUMIFS('Truck Req by Route'!$L$5:$L$320,'Truck Req by Route'!$A$5:$A$320,$A18)/K18) | M18: =IFERROR(AVERAGEIF(B18:J18,">0"),0) | N18: =MAX(B18:J18) | O18: =MAX(H18:J18) | P18: =IFERROR(SUMPRODUCT(('Truck Req by Route'!$A$5:$A$320=$A18)*'Truck Req by Route'!$L$5:$L$320*'Truck Req by Route'!$J$5:$J$320)/SUMIFS('Truck Req by Route'!$L$5:$L$320,'Truck Req by Route'!$A$5:$A$320,$A18),"")
A19: MEGA MANU | B19: =ROUNDUP(SUMIFS('Truck Req by Route'!$V$5:$V$320,'Truck Req by Route'!$A$5:$A$320,$A19),0) | C19: =ROUNDUP(SUMIFS('Truck Req by Route'!$W$5:$W$320,'Truck Req by Route'!$A$5:$A$320,$A19),0) | D19: =ROUNDUP(SUMIFS('Truck Req by Route'!$X$5:$X$320,'Truck Req by Route'!$A$5:$A$320,$A19),0) | E19: =ROUNDUP(SUMIFS('Truck Req by Route'!$Y$5:$Y$320,'Truck Req by Route'!$A$5:$A$320,$A19),0) | F19: =ROUNDUP(SUMIFS('Truck Req by Route'!$Z$5:$Z$320,'Truck Req by Route'!$A$5:$A$320,$A19),0) | G19: =ROUNDUP(SUMIFS('Truck Req by Route'!$AA$5:$AA$320,'Truck Req by Route'!$A$5:$A$320,$A19),0) | H19: =ROUNDUP(SUMIFS('Truck Req by Route'!$AB$5:$AB$320,'Truck Req by Route'!$A$5:$A$320,$A19),0) | I19: =ROUNDUP(SUMIFS('Truck Req by Route'!$AC$5:$AC$320,'Truck Req by Route'!$A$5:$A$320,$A19),0) | J19: =ROUNDUP(SUMIFS('Truck Req by Route'!$AD$5:$AD$320,'Truck Req by Route'!$A$5:$A$320,$A19),0) | K19: =COUNTIF(B19:J19,">0") | L19: =IF(K19=0,0,SUMIFS('Truck Req by Route'!$L$5:$L$320,'Truck Req by Route'!$A$5:$A$320,$A19)/K19) | M19: =IFERROR(AVERAGEIF(B19:J19,">0"),0) | N19: =MAX(B19:J19) | O19: =MAX(H19:J19) | P19: =IFERROR(SUMPRODUCT(('Truck Req by Route'!$A$5:$A$320=$A19)*'Truck Req by Route'!$L$5:$L$320*'Truck Req by Route'!$J$5:$J$320)/SUMIFS('Truck Req by Route'!$L$5:$L$320,'Truck Req by Route'!$A$5:$A$320,$A19),"")
A20: Lacasera | B20: =ROUNDUP(SUMIFS('Truck Req by Route'!$V$5:$V$320,'Truck Req by Route'!$A$5:$A$320,$A20),0) | C20: =ROUNDUP(SUMIFS('Truck Req by Route'!$W$5:$W$320,'Truck Req by Route'!$A$5:$A$320,$A20),0) | D20: =ROUNDUP(SUMIFS('Truck Req by Route'!$X$5:$X$320,'Truck Req by Route'!$A$5:$A$320,$A20),0) | E20: =ROUNDUP(SUMIFS('Truck Req by Route'!$Y$5:$Y$320,'Truck Req by Route'!$A$5:$A$320,$A20),0) | F20: =ROUNDUP(SUMIFS('Truck Req by Route'!$Z$5:$Z$320,'Truck Req by Route'!$A$5:$A$320,$A20),0) | G20: =ROUNDUP(SUMIFS('Truck Req by Route'!$AA$5:$AA$320,'Truck Req by Route'!$A$5:$A$320,$A20),0) | H20: =ROUNDUP(SUMIFS('Truck Req by Route'!$AB$5:$AB$320,'Truck Req by Route'!$A$5:$A$320,$A20),0) | I20: =ROUNDUP(SUMIFS('Truck Req by Route'!$AC$5:$AC$320,'Truck Req by Route'!$A$5:$A$320,$A20),0) | J20: =ROUNDUP(SUMIFS('Truck Req by Route'!$AD$5:$AD$320,'Truck Req by Route'!$A$5:$A$320,$A20),0) | K20: =COUNTIF(B20:J20,">0") | L20: =IF(K20=0,0,SUMIFS('Truck Req by Route'!$L$5:$L$320,'Truck Req by Route'!$A$5:$A$320,$A20)/K20) | M20: =IFERROR(AVERAGEIF(B20:J20,">0"),0) | N20: =MAX(B20:J20) | O20: =MAX(H20:J20) | P20: =IFERROR(SUMPRODUCT(('Truck Req by Route'!$A$5:$A$320=$A20)*'Truck Req by Route'!$L$5:$L$320*'Truck Req by Route'!$J$5:$J$320)/SUMIFS('Truck Req by Route'!$L$5:$L$320,'Truck Req by Route'!$A$5:$A$320,$A20),"")
A21: AB-INBEV | B21: =ROUNDUP(SUMIFS('Truck Req by Route'!$V$5:$V$320,'Truck Req by Route'!$A$5:$A$320,$A21),0) | C21: =ROUNDUP(SUMIFS('Truck Req by Route'!$W$5:$W$320,'Truck Req by Route'!$A$5:$A$320,$A21),0) | D21: =ROUNDUP(SUMIFS('Truck Req by Route'!$X$5:$X$320,'Truck Req by Route'!$A$5:$A$320,$A21),0) | E21: =ROUNDUP(SUMIFS('Truck Req by Route'!$Y$5:$Y$320,'Truck Req by Route'!$A$5:$A$320,$A21),0) | F21: =ROUNDUP(SUMIFS('Truck Req by Route'!$Z$5:$Z$320,'Truck Req by Route'!$A$5:$A$320,$A21),0) | G21: =ROUNDUP(SUMIFS('Truck Req by Route'!$AA$5:$AA$320,'Truck Req by Route'!$A$5:$A$320,$A21),0) | H21: =ROUNDUP(SUMIFS('Truck Req by Route'!$AB$5:$AB$320,'Truck Req by Route'!$A$5:$A$320,$A21),0) | I21: =ROUNDUP(SUMIFS('Truck Req by Route'!$AC$5:$AC$320,'Truck Req by Route'!$A$5:$A$320,$A21),0) | J21: =ROUNDUP(SUMIFS('Truck Req by Route'!$AD$5:$AD$320,'Truck Req by Route'!$A$5:$A$320,$A21),0) | K21: =COUNTIF(B21:J21,">0") | L21: =IF(K21=0,0,SUMIFS('Truck Req by Route'!$L$5:$L$320,'Truck Req by Route'!$A$5:$A$320,$A21)/K21) | M21: =IFERROR(AVERAGEIF(B21:J21,">0"),0) | N21: =MAX(B21:J21) | O21: =MAX(H21:J21) | P21: =IFERROR(SUMPRODUCT(('Truck Req by Route'!$A$5:$A$320=$A21)*'Truck Req by Route'!$L$5:$L$320*'Truck Req by Route'!$J$5:$J$320)/SUMIFS('Truck Req by Route'!$L$5:$L$320,'Truck Req by Route'!$A$5:$A$320,$A21),"")
A22: JUBAILI AGROTEC | B22: =ROUNDUP(SUMIFS('Truck Req by Route'!$V$5:$V$320,'Truck Req by Route'!$A$5:$A$320,$A22),0) | C22: =ROUNDUP(SUMIFS('Truck Req by Route'!$W$5:$W$320,'Truck Req by Route'!$A$5:$A$320,$A22),0) | D22: =ROUNDUP(SUMIFS('Truck Req by Route'!$X$5:$X$320,'Truck Req by Route'!$A$5:$A$320,$A22),0) | E22: =ROUNDUP(SUMIFS('Truck Req by Route'!$Y$5:$Y$320,'Truck Req by Route'!$A$5:$A$320,$A22),0) | F22: =ROUNDUP(SUMIFS('Truck Req by Route'!$Z$5:$Z$320,'Truck Req by Route'!$A$5:$A$320,$A22),0) | G22: =ROUNDUP(SUMIFS('Truck Req by Route'!$AA$5:$AA$320,'Truck Req by Route'!$A$5:$A$320,$A22),0) | H22: =ROUNDUP(SUMIFS('Truck Req by Route'!$AB$5:$AB$320,'Truck Req by Route'!$A$5:$A$320,$A22),0) | I22: =ROUNDUP(SUMIFS('Truck Req by Route'!$AC$5:$AC$320,'Truck Req by Route'!$A$5:$A$320,$A22),0) | J22: =ROUNDUP(SUMIFS('Truck Req by Route'!$AD$5:$AD$320,'Truck Req by Route'!$A$5:$A$320,$A22),0) | K22: =COUNTIF(B22:J22,">0") | L22: =IF(K22=0,0,SUMIFS('Truck Req by Route'!$L$5:$L$320,'Truck Req by Route'!$A$5:$A$320,$A22)/K22) | M22: =IFERROR(AVERAGEIF(B22:J22,">0"),0) | N22: =MAX(B22:J22) | O22: =MAX(H22:J22) | P22: =IFERROR(SUMPRODUCT(('Truck Req by Route'!$A$5:$A$320=$A22)*'Truck Req by Route'!$L$5:$L$320*'Truck Req by Route'!$J$5:$J$320)/SUMIFS('Truck Req by Route'!$L$5:$L$320,'Truck Req by Route'!$A$5:$A$320,$A22),"")
A23: SASO | B23: =ROUNDUP(SUMIFS('Truck Req by Route'!$V$5:$V$320,'Truck Req by Route'!$A$5:$A$320,$A23),0) | C23: =ROUNDUP(SUMIFS('Truck Req by Route'!$W$5:$W$320,'Truck Req by Route'!$A$5:$A$320,$A23),0) | D23: =ROUNDUP(SUMIFS('Truck Req by Route'!$X$5:$X$320,'Truck Req by Route'!$A$5:$A$320,$A23),0) | E23: =ROUNDUP(SUMIFS('Truck Req by Route'!$Y$5:$Y$320,'Truck Req by Route'!$A$5:$A$320,$A23),0) | F23: =ROUNDUP(SUMIFS('Truck Req by Route'!$Z$5:$Z$320,'Truck Req by Route'!$A$5:$A$320,$A23),0) | G23: =ROUNDUP(SUMIFS('Truck Req by Route'!$AA$5:$AA$320,'Truck Req by Route'!$A$5:$A$320,$A23),0) | H23: =ROUNDUP(SUMIFS('Truck Req by Route'!$AB$5:$AB$320,'Truck Req by Route'!$A$5:$A$320,$A23),0) | I23: =ROUNDUP(SUMIFS('Truck Req by Route'!$AC$5:$AC$320,'Truck Req by Route'!$A$5:$A$320,$A23),0) | J23: =ROUNDUP(SUMIFS('Truck Req by Route'!$AD$5:$AD$320,'Truck Req by Route'!$A$5:$A$320,$A23),0) | K23: =COUNTIF(B23:J23,">0") | L23: =IF(K23=0,0,SUMIFS('Truck Req by Route'!$L$5:$L$320,'Truck Req by Route'!$A$5:$A$320,$A23)/K23) | M23: =IFERROR(AVERAGEIF(B23:J23,">0"),0) | N23: =MAX(B23:J23) | O23: =MAX(H23:J23) | P23: =IFERROR(SUMPRODUCT(('Truck Req by Route'!$A$5:$A$320=$A23)*'Truck Req by Route'!$L$5:$L$320*'Truck Req by Route'!$J$5:$J$320)/SUMIFS('Truck Req by Route'!$L$5:$L$320,'Truck Req by Route'!$A$5:$A$320,$A23),"")
A24: NATURAL BEAUTY | B24: =ROUNDUP(SUMIFS('Truck Req by Route'!$V$5:$V$320,'Truck Req by Route'!$A$5:$A$320,$A24),0) | C24: =ROUNDUP(SUMIFS('Truck Req by Route'!$W$5:$W$320,'Truck Req by Route'!$A$5:$A$320,$A24),0) | D24: =ROUNDUP(SUMIFS('Truck Req by Route'!$X$5:$X$320,'Truck Req by Route'!$A$5:$A$320,$A24),0) | E24: =ROUNDUP(SUMIFS('Truck Req by Route'!$Y$5:$Y$320,'Truck Req by Route'!$A$5:$A$320,$A24),0) | F24: =ROUNDUP(SUMIFS('Truck Req by Route'!$Z$5:$Z$320,'Truck Req by Route'!$A$5:$A$320,$A24),0) | G24: =ROUNDUP(SUMIFS('Truck Req by Route'!$AA$5:$AA$320,'Truck Req by Route'!$A$5:$A$320,$A24),0) | H24: =ROUNDUP(SUMIFS('Truck Req by Route'!$AB$5:$AB$320,'Truck Req by Route'!$A$5:$A$320,$A24),0) | I24: =ROUNDUP(SUMIFS('Truck Req by Route'!$AC$5:$AC$320,'Truck Req by Route'!$A$5:$A$320,$A24),0) | J24: =ROUNDUP(SUMIFS('Truck Req by Route'!$AD$5:$AD$320,'Truck Req by Route'!$A$5:$A$320,$A24),0) | K24: =COUNTIF(B24:J24,">0") | L24: =IF(K24=0,0,SUMIFS('Truck Req by Route'!$L$5:$L$320,'Truck Req by Route'!$A$5:$A$320,$A24)/K24) | M24: =IFERROR(AVERAGEIF(B24:J24,">0"),0) | N24: =MAX(B24:J24) | O24: =MAX(H24:J24) | P24: =IFERROR(SUMPRODUCT(('Truck Req by Route'!$A$5:$A$320=$A24)*'Truck Req by Route'!$L$5:$L$320*'Truck Req by Route'!$J$5:$J$320)/SUMIFS('Truck Req by Route'!$L$5:$L$320,'Truck Req by Route'!$A$5:$A$320,$A24),"")
A25: ABBA ABASS | B25: =ROUNDUP(SUMIFS('Truck Req by Route'!$V$5:$V$320,'Truck Req by Route'!$A$5:$A$320,$A25),0) | C25: =ROUNDUP(SUMIFS('Truck Req by Route'!$W$5:$W$320,'Truck Req by Route'!$A$5:$A$320,$A25),0) | D25: =ROUNDUP(SUMIFS('Truck Req by Route'!$X$5:$X$320,'Truck Req by Route'!$A$5:$A$320,$A25),0) | E25: =ROUNDUP(SUMIFS('Truck Req by Route'!$Y$5:$Y$320,'Truck Req by Route'!$A$5:$A$320,$A25),0) | F25: =ROUNDUP(SUMIFS('Truck Req by Route'!$Z$5:$Z$320,'Truck Req by Route'!$A$5:$A$320,$A25),0) | G25: =ROUNDUP(SUMIFS('Truck Req by Route'!$AA$5:$AA$320,'Truck Req by Route'!$A$5:$A$320,$A25),0) | H25: =ROUNDUP(SUMIFS('Truck Req by Route'!$AB$5:$AB$320,'Truck Req by Route'!$A$5:$A$320,$A25),0) | I25: =ROUNDUP(SUMIFS('Truck Req by Route'!$AC$5:$AC$320,'Truck Req by Route'!$A$5:$A$320,$A25),0) | J25: =ROUNDUP(SUMIFS('Truck Req by Route'!$AD$5:$AD$320,'Truck Req by Route'!$A$5:$A$320,$A25),0) | K25: =COUNTIF(B25:J25,">0") | L25: =IF(K25=0,0,SUMIFS('Truck Req by Route'!$L$5:$L$320,'Truck Req by Route'!$A$5:$A$320,$A25)/K25) | M25: =IFERROR(AVERAGEIF(B25:J25,">0"),0) | N25: =MAX(B25:J25) | O25: =MAX(H25:J25) | P25: =IFERROR(SUMPRODUCT(('Truck Req by Route'!$A$5:$A$320=$A25)*'Truck Req by Route'!$L$5:$L$320*'Truck Req by Route'!$J$5:$J$320)/SUMIFS('Truck Req by Route'!$L$5:$L$320,'Truck Req by Route'!$A$5:$A$320,$A25),"")
A26: VENDARA | B26: =ROUNDUP(SUMIFS('Truck Req by Route'!$V$5:$V$320,'Truck Req by Route'!$A$5:$A$320,$A26),0) | C26: =ROUNDUP(SUMIFS('Truck Req by Route'!$W$5:$W$320,'Truck Req by Route'!$A$5:$A$320,$A26),0) | D26: =ROUNDUP(SUMIFS('Truck Req by Route'!$X$5:$X$320,'Truck Req by Route'!$A$5:$A$320,$A26),0) | E26: =ROUNDUP(SUMIFS('Truck Req by Route'!$Y$5:$Y$320,'Truck Req by Route'!$A$5:$A$320,$A26),0) | F26: =ROUNDUP(SUMIFS('Truck Req by Route'!$Z$5:$Z$320,'Truck Req by Route'!$A$5:$A$320,$A26),0) | G26: =ROUNDUP(SUMIFS('Truck Req by Route'!$AA$5:$AA$320,'Truck Req by Route'!$A$5:$A$320,$A26),0) | H26: =ROUNDUP(SUMIFS('Truck Req by Route'!$AB$5:$AB$320,'Truck Req by Route'!$A$5:$A$320,$A26),0) | I26: =ROUNDUP(SUMIFS('Truck Req by Route'!$AC$5:$AC$320,'Truck Req by Route'!$A$5:$A$320,$A26),0) | J26: =ROUNDUP(SUMIFS('Truck Req by Route'!$AD$5:$AD$320,'Truck Req by Route'!$A$5:$A$320,$A26),0) | K26: =COUNTIF(B26:J26,">0") | L26: =IF(K26=0,0,SUMIFS('Truck Req by Route'!$L$5:$L$320,'Truck Req by Route'!$A$5:$A$320,$A26)/K26) | M26: =IFERROR(AVERAGEIF(B26:J26,">0"),0) | N26: =MAX(B26:J26) | O26: =MAX(H26:J26) | P26: =IFERROR(SUMPRODUCT(('Truck Req by Route'!$A$5:$A$320=$A26)*'Truck Req by Route'!$L$5:$L$320*'Truck Req by Route'!$J$5:$J$320)/SUMIFS('Truck Req by Route'!$L$5:$L$320,'Truck Req by Route'!$A$5:$A$320,$A26),"")
A27: GIVANAS | B27: =ROUNDUP(SUMIFS('Truck Req by Route'!$V$5:$V$320,'Truck Req by Route'!$A$5:$A$320,$A27),0) | C27: =ROUNDUP(SUMIFS('Truck Req by Route'!$W$5:$W$320,'Truck Req by Route'!$A$5:$A$320,$A27),0) | D27: =ROUNDUP(SUMIFS('Truck Req by Route'!$X$5:$X$320,'Truck Req by Route'!$A$5:$A$320,$A27),0) | E27: =ROUNDUP(SUMIFS('Truck Req by Route'!$Y$5:$Y$320,'Truck Req by Route'!$A$5:$A$320,$A27),0) | F27: =ROUNDUP(SUMIFS('Truck Req by Route'!$Z$5:$Z$320,'Truck Req by Route'!$A$5:$A$320,$A27),0) | G27: =ROUNDUP(SUMIFS('Truck Req by Route'!$AA$5:$AA$320,'Truck Req by Route'!$A$5:$A$320,$A27),0) | H27: =ROUNDUP(SUMIFS('Truck Req by Route'!$AB$5:$AB$320,'Truck Req by Route'!$A$5:$A$320,$A27),0) | I27: =ROUNDUP(SUMIFS('Truck Req by Route'!$AC$5:$AC$320,'Truck Req by Route'!$A$5:$A$320,$A27),0) | J27: =ROUNDUP(SUMIFS('Truck Req by Route'!$AD$5:$AD$320,'Truck Req by Route'!$A$5:$A$320,$A27),0) | K27: =COUNTIF(B27:J27,">0") | L27: =IF(K27=0,0,SUMIFS('Truck Req by Route'!$L$5:$L$320,'Truck Req by Route'!$A$5:$A$320,$A27)/K27) | M27: =IFERROR(AVERAGEIF(B27:J27,">0"),0) | N27: =MAX(B27:J27) | O27: =MAX(H27:J27) | P27: =IFERROR(SUMPRODUCT(('Truck Req by Route'!$A$5:$A$320=$A27)*'Truck Req by Route'!$L$5:$L$320*'Truck Req by Route'!$J$5:$J$320)/SUMIFS('Truck Req by Route'!$L$5:$L$320,'Truck Req by Route'!$A$5:$A$320,$A27),"")
... A44: SASO-BACKLOAD | B44: =ROUNDUP(SUMIFS('Truck Req by Route'!$V$5:$V$320,'Truck Req by Route'!$A$5:$A$320,$A44),0) | C44: =ROUNDUP(SUMIFS('Truck Req by Route'!$W$5:$W$320,'Truck Req by Route'!$A$5:$A$320,$A44),0) | D44: =ROUNDUP(SUMIFS('Truck Req by Route'!$X$5:$X$320,'Truck Req by Route'!$A$5:$A$320,$A44),0) | E44: =ROUNDUP(SUMIFS('Truck Req by Route'!$Y$5:$Y$320,'Truck Req by Route'!$A$5:$A$320,$A44),0) | F44: =ROUNDUP(SUMIFS('Truck Req by Route'!$Z$5:$Z$320,'Truck Req by Route'!$A$5:$A$320,$A44),0) | G44: =ROUNDUP(SUMIFS('Truck Req by Route'!$AA$5:$AA$320,'Truck Req by Route'!$A$5:$A$320,$A44),0) | H44: =ROUNDUP(SUMIFS('Truck Req by Route'!$AB$5:$AB$320,'Truck Req by Route'!$A$5:$A$320,$A44),0) | I44: =ROUNDUP(SUMIFS('Truck Req by Route'!$AC$5:$AC$320,'Truck Req by Route'!$A$5:$A$320,$A44),0) | J44: =ROUNDUP(SUMIFS('Truck Req by Route'!$AD$5:$AD$320,'Truck Req by Route'!$A$5:$A$320,$A44),0) | K44: =COUNTIF(B44:J44,">0") | L44: =IF(K44=0,0,SUMIFS('Truck Req by Route'!$L$5:$L$320,'Truck Req by Route'!$A$5:$A$320,$A44)/K44) | M44: =IFERROR(AVERAGEIF(B44:J44,">0"),0) | N44: =MAX(B44:J44) | O44: =MAX(H44:J44) | P44: =IFERROR(SUMPRODUCT(('Truck Req by Route'!$A$5:$A$320=$A44)*'Truck Req by Route'!$L$5:$L$320*'Truck Req by Route'!$J$5:$J$320)/SUMIFS('Truck Req by Route'!$L$5:$L$320,'Truck Req by Route'!$A$5:$A$320,$A44),"")
A45: Total — each client has its own trucks (rounded up per client) | B45: =SUM(B16:B44) | C45: =SUM(C16:C44) | D45: =SUM(D16:D44) | E45: =SUM(E16:E44) | F45: =SUM(F16:F44) | G45: =SUM(G16:G44) | H45: =SUM(H16:H44) | I45: =SUM(I16:I44) | J45: =SUM(J16:J44) | M45: =AVERAGE(B45:J45) | N45: =MAX(B45:J45) | O45: =MAX(H45:J45)
A46: Total — trucks shared across clients (smallest fleet) | B46: =ROUNDUP(SUM('Truck Req by Route'!V5:V320),0) | C46: =ROUNDUP(SUM('Truck Req by Route'!W5:W320),0) | D46: =ROUNDUP(SUM('Truck Req by Route'!X5:X320),0) | E46: =ROUNDUP(SUM('Truck Req by Route'!Y5:Y320),0) | F46: =ROUNDUP(SUM('Truck Req by Route'!Z5:Z320),0) | G46: =ROUNDUP(SUM('Truck Req by Route'!AA5:AA320),0) | H46: =ROUNDUP(SUM('Truck Req by Route'!AB5:AB320),0) | I46: =ROUNDUP(SUM('Truck Req by Route'!AC5:AC320),0) | J46: =ROUNDUP(SUM('Truck Req by Route'!AD5:AD320),0) | M46: =AVERAGE(B46:J46) | N46: =MAX(B46:J46) | O46: =MAX(H46:J46)
A49: Own haulage/flat trucks actually used (distinct plate numbers, excl. 3rd party) | B49: 35 | C49: 36 | D49: 37 | E49: 40 | F49: 37 | G49: 37 | H49: 33 | I49: 36 | J49: 35 | M49: =AVERAGE(B49:J49) | N49: =MAX(B49:J49) | O49: =MAX(H49:J49)
A50: Own trucks minus shared-fleet need (positive = spare trucks) | B50: =B49-B46 | C50: =C49-C46 | D50: =D49-D46 | E50: =E49-E46 | F50: =F49-F46 | G50: =G49-G46 | H50: =H49-H46 | I50: =I49-I46 | J50: =J49-J46
A53: Notes
A54: Trips per month come from the 2026 trip log: haulage and flat trucks (treated as one), including 3rd-party trucks. Closed-body/canter and Hiab trips are excluded.
A55: Trucks rotate on their routes through the month: a 6-day round trip gives 4 trips per truck per month (weekly), an 8-day round trip gives 3, a 4-day round trip gives 6.
A56: The second total row shares trucks across clients (a truck that finishes one client’s work takes another’s), so it is the smallest fleet that covers the month on average.
A57: Loading/offloading waits beyond your turnaround days are not included; busy weeks inside a month may need more trucks than the monthly average shows.
A58: Lagos pickup points use the Lagos loading bay, Ibadan depots the Ibadan bay; nearby towns (Ilesa, Akure, Ijebu Ode, Ota, Agbara, Ogere) use the nearest bay; returns toward Lagos/Ibadan use your table in reverse.
A59: 76 trips (5.3%) have no route in your table — mostly NBL depot-to-depot moves (NGB4/NGB5/NGB8, Ama, Kudenda). They use the default days until you add the route or type an override.

Sheet Order Planner
A1: Order planner — trucks needed for a client’s monthly request
A2: Enter the client, pick the route (turnaround key from your table) and the trucks/trips requested per month. Operating days per month comes from the Truck Requirement sheet. Yellow cells are inputs.
A4: Client | B4: Route (turnaround key) | C4: Trips requested per month | D4: One-leg days | E4: Round-trip days | F4: Trips one truck can do per month | G4: Truck use (exact) | H4: Trucks needed for this route | J4: Totals by client
A5: Jamara | B5: ABUJA>LAGOS | C5: 4 | D5: =IF(B5="","",IFERROR(INDEX('Turnaround Table'!$C$5:$C$231,MATCH(B5,'Turnaround Table'!$D$5:$D$231,0)),"not in table")) | E5: =IF(ISNUMBER(D5),2*D5,"") | F5: =IF(ISNUMBER(E5),MAX(1,INT('Truck Requirement'!$B$4/E5)),"") | G5: =IF(AND(ISNUMBER(F5),C5<>""),C5/F5,"") | H5: =IF(ISNUMBER(G5),ROUNDUP(G5,0),"") | J5: Client | K5: Trips per month | L5: Trucks needed (shared across the client’s routes)
A6: Jamara | B6: PORT HARCOURT>LAGOS | C6: 6 | D6: =IF(B6="","",IFERROR(INDEX('Turnaround Table'!$C$5:$C$231,MATCH(B6,'Turnaround Table'!$D$5:$D$231,0)),"not in table")) | E6: =IF(ISNUMBER(D6),2*D6,"") | F6: =IF(ISNUMBER(E6),MAX(1,INT('Truck Requirement'!$B$4/E6)),"") | G6: =IF(AND(ISNUMBER(F6),C6<>""),C6/F6,"") | H6: =IF(ISNUMBER(G6),ROUNDUP(G6,0),"") | J6: Jamara | K6: =IF(J6="","",SUMIF($A$5:$A$34,J6,$C$5:$C$34)) | L6: =IF(J6="","",ROUNDUP(SUMIF($A$5:$A$34,J6,$G$5:$G$34),0))
A7: Jamara | B7: KANO>LAGOS | C7: 4 | D7: =IF(B7="","",IFERROR(INDEX('Turnaround Table'!$C$5:$C$231,MATCH(B7,'Turnaround Table'!$D$5:$D$231,0)),"not in table")) | E7: =IF(ISNUMBER(D7),2*D7,"") | F7: =IF(ISNUMBER(E7),MAX(1,INT('Truck Requirement'!$B$4/E7)),"") | G7: =IF(AND(ISNUMBER(F7),C7<>""),C7/F7,"") | H7: =IF(ISNUMBER(G7),ROUNDUP(G7,0),"") | K7: =IF(J7="","",SUMIF($A$5:$A$34,J7,$C$5:$C$34)) | L7: =IF(J7="","",ROUNDUP(SUMIF($A$5:$A$34,J7,$G$5:$G$34),0))
D8: =IF(B8="","",IFERROR(INDEX('Turnaround Table'!$C$5:$C$231,MATCH(B8,'Turnaround Table'!$D$5:$D$231,0)),"not in table")) | E8: =IF(ISNUMBER(D8),2*D8,"") | F8: =IF(ISNUMBER(E8),MAX(1,INT('Truck Requirement'!$B$4/E8)),"") | G8: =IF(AND(ISNUMBER(F8),C8<>""),C8/F8,"") | H8: =IF(ISNUMBER(G8),ROUNDUP(G8,0),"") | K8: =IF(J8="","",SUMIF($A$5:$A$34,J8,$C$5:$C$34)) | L8: =IF(J8="","",ROUNDUP(SUMIF($A$5:$A$34,J8,$G$5:$G$34),0))
D9: =IF(B9="","",IFERROR(INDEX('Turnaround Table'!$C$5:$C$231,MATCH(B9,'Turnaround Table'!$D$5:$D$231,0)),"not in table")) | E9: =IF(ISNUMBER(D9),2*D9,"") | F9: =IF(ISNUMBER(E9),MAX(1,INT('Truck Requirement'!$B$4/E9)),"") | G9: =IF(AND(ISNUMBER(F9),C9<>""),C9/F9,"") | H9: =IF(ISNUMBER(G9),ROUNDUP(G9,0),"") | K9: =IF(J9="","",SUMIF($A$5:$A$34,J9,$C$5:$C$34)) | L9: =IF(J9="","",ROUNDUP(SUMIF($A$5:$A$34,J9,$G$5:$G$34),0))
D10: =IF(B10="","",IFERROR(INDEX('Turnaround Table'!$C$5:$C$231,MATCH(B10,'Turnaround Table'!$D$5:$D$231,0)),"not in table")) | E10: =IF(ISNUMBER(D10),2*D10,"") | F10: =IF(ISNUMBER(E10),MAX(1,INT('Truck Requirement'!$B$4/E10)),"") | G10: =IF(AND(ISNUMBER(F10),C10<>""),C10/F10,"") | H10: =IF(ISNUMBER(G10),ROUNDUP(G10,0),"") | K10: =IF(J10="","",SUMIF($A$5:$A$34,J10,$C$5:$C$34)) | L10: =IF(J10="","",ROUNDUP(SUMIF($A$5:$A$34,J10,$G$5:$G$34),0))
D11: =IF(B11="","",IFERROR(INDEX('Turnaround Table'!$C$5:$C$231,MATCH(B11,'Turnaround Table'!$D$5:$D$231,0)),"not in table")) | E11: =IF(ISNUMBER(D11),2*D11,"") | F11: =IF(ISNUMBER(E11),MAX(1,INT('Truck Requirement'!$B$4/E11)),"") | G11: =IF(AND(ISNUMBER(F11),C11<>""),C11/F11,"") | H11: =IF(ISNUMBER(G11),ROUNDUP(G11,0),"") | K11: =IF(J11="","",SUMIF($A$5:$A$34,J11,$C$5:$C$34)) | L11: =IF(J11="","",ROUNDUP(SUMIF($A$5:$A$34,J11,$G$5:$G$34),0))
D12: =IF(B12="","",IFERROR(INDEX('Turnaround Table'!$C$5:$C$231,MATCH(B12,'Turnaround Table'!$D$5:$D$231,0)),"not in table")) | E12: =IF(ISNUMBER(D12),2*D12,"") | F12: =IF(ISNUMBER(E12),MAX(1,INT('Truck Requirement'!$B$4/E12)),"") | G12: =IF(AND(ISNUMBER(F12),C12<>""),C12/F12,"") | H12: =IF(ISNUMBER(G12),ROUNDUP(G12,0),"") | K12: =IF(J12="","",SUMIF($A$5:$A$34,J12,$C$5:$C$34)) | L12: =IF(J12="","",ROUNDUP(SUMIF($A$5:$A$34,J12,$G$5:$G$34),0))
D13: =IF(B13="","",IFERROR(INDEX('Turnaround Table'!$C$5:$C$231,MATCH(B13,'Turnaround Table'!$D$5:$D$231,0)),"not in table")) | E13: =IF(ISNUMBER(D13),2*D13,"") | F13: =IF(ISNUMBER(E13),MAX(1,INT('Truck Requirement'!$B$4/E13)),"") | G13: =IF(AND(ISNUMBER(F13),C13<>""),C13/F13,"") | H13: =IF(ISNUMBER(G13),ROUNDUP(G13,0),"") | K13: =IF(J13="","",SUMIF($A$5:$A$34,J13,$C$5:$C$34)) | L13: =IF(J13="","",ROUNDUP(SUMIF($A$5:$A$34,J13,$G$5:$G$34),0))
D14: =IF(B14="","",IFERROR(INDEX('Turnaround Table'!$C$5:$C$231,MATCH(B14,'Turnaround Table'!$D$5:$D$231,0)),"not in table")) | E14: =IF(ISNUMBER(D14),2*D14,"") | F14: =IF(ISNUMBER(E14),MAX(1,INT('Truck Requirement'!$B$4/E14)),"") | G14: =IF(AND(ISNUMBER(F14),C14<>""),C14/F14,"") | H14: =IF(ISNUMBER(G14),ROUNDUP(G14,0),"") | K14: =IF(J14="","",SUMIF($A$5:$A$34,J14,$C$5:$C$34)) | L14: =IF(J14="","",ROUNDUP(SUMIF($A$5:$A$34,J14,$G$5:$G$34),0))
D15: =IF(B15="","",IFERROR(INDEX('Turnaround Table'!$C$5:$C$231,MATCH(B15,'Turnaround Table'!$D$5:$D$231,0)),"not in table")) | E15: =IF(ISNUMBER(D15),2*D15,"") | F15: =IF(ISNUMBER(E15),MAX(1,INT('Truck Requirement'!$B$4/E15)),"") | G15: =IF(AND(ISNUMBER(F15),C15<>""),C15/F15,"") | H15: =IF(ISNUMBER(G15),ROUNDUP(G15,0),"") | K15: =IF(J15="","",SUMIF($A$5:$A$34,J15,$C$5:$C$34)) | L15: =IF(J15="","",ROUNDUP(SUMIF($A$5:$A$34,J15,$G$5:$G$34),0))
D16: =IF(B16="","",IFERROR(INDEX('Turnaround Table'!$C$5:$C$231,MATCH(B16,'Turnaround Table'!$D$5:$D$231,0)),"not in table")) | E16: =IF(ISNUMBER(D16),2*D16,"") | F16: =IF(ISNUMBER(E16),MAX(1,INT('Truck Requirement'!$B$4/E16)),"") | G16: =IF(AND(ISNUMBER(F16),C16<>""),C16/F16,"") | H16: =IF(ISNUMBER(G16),ROUNDUP(G16,0),"") | K16: =IF(J16="","",SUMIF($A$5:$A$34,J16,$C$5:$C$34)) | L16: =IF(J16="","",ROUNDUP(SUMIF($A$5:$A$34,J16,$G$5:$G$34),0))
D17: =IF(B17="","",IFERROR(INDEX('Turnaround Table'!$C$5:$C$231,MATCH(B17,'Turnaround Table'!$D$5:$D$231,0)),"not in table")) | E17: =IF(ISNUMBER(D17),2*D17,"") | F17: =IF(ISNUMBER(E17),MAX(1,INT('Truck Requirement'!$B$4/E17)),"") | G17: =IF(AND(ISNUMBER(F17),C17<>""),C17/F17,"") | H17: =IF(ISNUMBER(G17),ROUNDUP(G17,0),"") | K17: =IF(J17="","",SUMIF($A$5:$A$34,J17,$C$5:$C$34)) | L17: =IF(J17="","",ROUNDUP(SUMIF($A$5:$A$34,J17,$G$5:$G$34),0))
D18: =IF(B18="","",IFERROR(INDEX('Turnaround Table'!$C$5:$C$231,MATCH(B18,'Turnaround Table'!$D$5:$D$231,0)),"not in table")) | E18: =IF(ISNUMBER(D18),2*D18,"") | F18: =IF(ISNUMBER(E18),MAX(1,INT('Truck Requirement'!$B$4/E18)),"") | G18: =IF(AND(ISNUMBER(F18),C18<>""),C18/F18,"") | H18: =IF(ISNUMBER(G18),ROUNDUP(G18,0),"") | K18: =IF(J18="","",SUMIF($A$5:$A$34,J18,$C$5:$C$34)) | L18: =IF(J18="","",ROUNDUP(SUMIF($A$5:$A$34,J18,$G$5:$G$34),0))
D19: =IF(B19="","",IFERROR(INDEX('Turnaround Table'!$C$5:$C$231,MATCH(B19,'Turnaround Table'!$D$5:$D$231,0)),"not in table")) | E19: =IF(ISNUMBER(D19),2*D19,"") | F19: =IF(ISNUMBER(E19),MAX(1,INT('Truck Requirement'!$B$4/E19)),"") | G19: =IF(AND(ISNUMBER(F19),C19<>""),C19/F19,"") | H19: =IF(ISNUMBER(G19),ROUNDUP(G19,0),"") | K19: =IF(J19="","",SUMIF($A$5:$A$34,J19,$C$5:$C$34)) | L19: =IF(J19="","",ROUNDUP(SUMIF($A$5:$A$34,J19,$G$5:$G$34),0))
D20: =IF(B20="","",IFERROR(INDEX('Turnaround Table'!$C$5:$C$231,MATCH(B20,'Turnaround Table'!$D$5:$D$231,0)),"not in table")) | E20: =IF(ISNUMBER(D20),2*D20,"") | F20: =IF(ISNUMBER(E20),MAX(1,INT('Truck Requirement'!$B$4/E20)),"") | G20: =IF(AND(ISNUMBER(F20),C20<>""),C20/F20,"") | H20: =IF(ISNUMBER(G20),ROUNDUP(G20,0),"") | K20: =IF(J20="","",SUMIF($A$5:$A$34,J20,$C$5:$C$34)) | L20: =IF(J20="","",ROUNDUP(SUMIF($A$5:$A$34,J20,$G$5:$G$34),0))
D21: =IF(B21="","",IFERROR(INDEX('Turnaround Table'!$C$5:$C$231,MATCH(B21,'Turnaround Table'!$D$5:$D$231,0)),"not in table")) | E21: =IF(ISNUMBER(D21),2*D21,"") | F21: =IF(ISNUMBER(E21),MAX(1,INT('Truck Requirement'!$B$4/E21)),"") | G21: =IF(AND(ISNUMBER(F21),C21<>""),C21/F21,"") | H21: =IF(ISNUMBER(G21),ROUNDUP(G21,0),"")
D22: =IF(B22="","",IFERROR(INDEX('Turnaround Table'!$C$5:$C$231,MATCH(B22,'Turnaround Table'!$D$5:$D$231,0)),"not in table")) | E22: =IF(ISNUMBER(D22),2*D22,"") | F22: =IF(ISNUMBER(E22),MAX(1,INT('Truck Requirement'!$B$4/E22)),"") | G22: =IF(AND(ISNUMBER(F22),C22<>""),C22/F22,"") | H22: =IF(ISNUMBER(G22),ROUNDUP(G22,0),"")
D23: =IF(B23="","",IFERROR(INDEX('Turnaround Table'!$C$5:$C$231,MATCH(B23,'Turnaround Table'!$D$5:$D$231,0)),"not in table")) | E23: =IF(ISNUMBER(D23),2*D23,"") | F23: =IF(ISNUMBER(E23),MAX(1,INT('Truck Requirement'!$B$4/E23)),"") | G23: =IF(AND(ISNUMBER(F23),C23<>""),C23/F23,"") | H23: =IF(ISNUMBER(G23),ROUNDUP(G23,0),"")
D24: =IF(B24="","",IFERROR(INDEX('Turnaround Table'!$C$5:$C$231,MATCH(B24,'Turnaround Table'!$D$5:$D$231,0)),"not in table")) | E24: =IF(ISNUMBER(D24),2*D24,"") | F24: =IF(ISNUMBER(E24),MAX(1,INT('Truck Requirement'!$B$4/E24)),"") | G24: =IF(AND(ISNUMBER(F24),C24<>""),C24/F24,"") | H24: =IF(ISNUMBER(G24),ROUNDUP(G24,0),"")
D25: =IF(B25="","",IFERROR(INDEX('Turnaround Table'!$C$5:$C$231,MATCH(B25,'Turnaround Table'!$D$5:$D$231,0)),"not in table")) | E25: =IF(ISNUMBER(D25),2*D25,"") | F25: =IF(ISNUMBER(E25),MAX(1,INT('Truck Requirement'!$B$4/E25)),"") | G25: =IF(AND(ISNUMBER(F25),C25<>""),C25/F25,"") | H25: =IF(ISNUMBER(G25),ROUNDUP(G25,0),"")
D26: =IF(B26="","",IFERROR(INDEX('Turnaround Table'!$C$5:$C$231,MATCH(B26,'Turnaround Table'!$D$5:$D$231,0)),"not in table")) | E26: =IF(ISNUMBER(D26),2*D26,"") | F26: =IF(ISNUMBER(E26),MAX(1,INT('Truck Requirement'!$B$4/E26)),"") | G26: =IF(AND(ISNUMBER(F26),C26<>""),C26/F26,"") | H26: =IF(ISNUMBER(G26),ROUNDUP(G26,0),"")
D27: =IF(B27="","",IFERROR(INDEX('Turnaround Table'!$C$5:$C$231,MATCH(B27,'Turnaround Table'!$D$5:$D$231,0)),"not in table")) | E27: =IF(ISNUMBER(D27),2*D27,"") | F27: =IF(ISNUMBER(E27),MAX(1,INT('Truck Requirement'!$B$4/E27)),"") | G27: =IF(AND(ISNUMBER(F27),C27<>""),C27/F27,"") | H27: =IF(ISNUMBER(G27),ROUNDUP(G27,0),"")
D28: =IF(B28="","",IFERROR(INDEX('Turnaround Table'!$C$5:$C$231,MATCH(B28,'Turnaround Table'!$D$5:$D$231,0)),"not in table")) | E28: =IF(ISNUMBER(D28),2*D28,"") | F28: =IF(ISNUMBER(E28),MAX(1,INT('Truck Requirement'!$B$4/E28)),"") | G28: =IF(AND(ISNUMBER(F28),C28<>""),C28/F28,"") | H28: =IF(ISNUMBER(G28),ROUNDUP(G28,0),"")
D29: =IF(B29="","",IFERROR(INDEX('Turnaround Table'!$C$5:$C$231,MATCH(B29,'Turnaround Table'!$D$5:$D$231,0)),"not in table")) | E29: =IF(ISNUMBER(D29),2*D29,"") | F29: =IF(ISNUMBER(E29),MAX(1,INT('Truck Requirement'!$B$4/E29)),"") | G29: =IF(AND(ISNUMBER(F29),C29<>""),C29/F29,"") | H29: =IF(ISNUMBER(G29),ROUNDUP(G29,0),"")
D30: =IF(B30="","",IFERROR(INDEX('Turnaround Table'!$C$5:$C$231,MATCH(B30,'Turnaround Table'!$D$5:$D$231,0)),"not in table")) | E30: =IF(ISNUMBER(D30),2*D30,"") | F30: =IF(ISNUMBER(E30),MAX(1,INT('Truck Requirement'!$B$4/E30)),"") | G30: =IF(AND(ISNUMBER(F30),C30<>""),C30/F30,"") | H30: =IF(ISNUMBER(G30),ROUNDUP(G30,0),"")
D31: =IF(B31="","",IFERROR(INDEX('Turnaround Table'!$C$5:$C$231,MATCH(B31,'Turnaround Table'!$D$5:$D$231,0)),"not in table")) | E31: =IF(ISNUMBER(D31),2*D31,"") | F31: =IF(ISNUMBER(E31),MAX(1,INT('Truck Requirement'!$B$4/E31)),"") | G31: =IF(AND(ISNUMBER(F31),C31<>""),C31/F31,"") | H31: =IF(ISNUMBER(G31),ROUNDUP(G31,0),"")
D32: =IF(B32="","",IFERROR(INDEX('Turnaround Table'!$C$5:$C$231,MATCH(B32,'Turnaround Table'!$D$5:$D$231,0)),"not in table")) | E32: =IF(ISNUMBER(D32),2*D32,"") | F32: =IF(ISNUMBER(E32),MAX(1,INT('Truck Requirement'!$B$4/E32)),"") | G32: =IF(AND(ISNUMBER(F32),C32<>""),C32/F32,"") | H32: =IF(ISNUMBER(G32),ROUNDUP(G32,0),"")
... D34: =IF(B34="","",IFERROR(INDEX('Turnaround Table'!$C$5:$C$231,MATCH(B34,'Turnaround Table'!$D$5:$D$231,0)),"not in table")) | E34: =IF(ISNUMBER(D34),2*D34,"") | F34: =IF(ISNUMBER(E34),MAX(1,INT('Truck Requirement'!$B$4/E34)),"") | G34: =IF(AND(ISNUMBER(F34),C34<>""),C34/F34,"") | H34: =IF(ISNUMBER(G34),ROUNDUP(G34,0),"")
A35: Total | C35: =SUM(C5:C34) | G35: =SUM(G5:G34) | H35: =SUM(H5:H34)

Sheet Revenue Planner
A1: Revenue planner — what each route earns with the trucks allocated to it
A2: Pick the client and route, enter trips per month and your price per trip (yellow). Trucks follow the same rotation as the Order Planner. Revenue per truck-day lets you compare routes fairly: it is what one truck earns for each day it is tied up on that route.
A4: Client | B4: Route (turnaround key) | C4: Trips per month | D4: Price per trip (₦) | E4: One-leg days | F4: Round-trip days | G4: Trips one truck can do per month | H4: Truck use (exact) | I4: Trucks needed | J4: Monthly revenue (₦) | K4: Revenue per truck per month (₦) | L4: Revenue per truck-day (₦) | M4: Spare trips with these trucks | N4: Market avg price Jul–Sep (₦) | O4: Highest price Jul–Sep (₦) | P4: Your price vs market avg | R4: Totals by client
A5: Jamara | B5: ABUJA>LAGOS | C5: 4 | D5: 2693000 | E5: =IF(B5="","",IFERROR(INDEX('Turnaround Table'!$C$5:$C$231,MATCH(B5,'Turnaround Table'!$D$5:$D$231,0)),"not in table")) | F5: =IF(ISNUMBER(E5),2*E5,"") | G5: =IF(ISNUMBER(F5),MAX(1,INT('Truck Requirement'!$B$4/F5)),"") | H5: =IF(AND(ISNUMBER(G5),C5<>""),C5/G5,"") | I5: =IF(ISNUMBER(H5),ROUNDUP(H5,0),"") | J5: =IF(AND(C5<>"",D5<>""),C5*D5,"") | K5: =IF(AND(ISNUMBER(J5),ISNUMBER(I5)),IF(I5=0,"",J5/I5),"") | L5: =IF(AND(ISNUMBER(D5),ISNUMBER(F5)),D5/F5,"") | M5: =IF(ISNUMBER(I5),I5*G5-C5,"") | N5: =IF(B5="","",IFERROR(INDEX('Route Prices'!$F$5:$F$103,MATCH(B5,'Route Prices'!$A$5:$A$103,0)),"")) | O5: =IF(B5="","",IFERROR(INDEX('Route Prices'!$G$5:$G$103,MATCH(B5,'Route Prices'!$A$5:$A$103,0)),"")) | P5: =IF(AND(ISNUMBER(D5),ISNUMBER(N5)),IF(N5=0,"",D5/N5-1),"") | R5: Client | S5: Trips per month | T5: Trucks needed (shared across routes) | U5: Monthly revenue (₦) | V5: Revenue per truck per month (₦) | W5: Yearly revenue (₦)
A6: Jamara | B6: PORT HARCOURT>LAGOS | C6: 6 | D6: 2491000 | E6: =IF(B6="","",IFERROR(INDEX('Turnaround Table'!$C$5:$C$231,MATCH(B6,'Turnaround Table'!$D$5:$D$231,0)),"not in table")) | F6: =IF(ISNUMBER(E6),2*E6,"") | G6: =IF(ISNUMBER(F6),MAX(1,INT('Truck Requirement'!$B$4/F6)),"") | H6: =IF(AND(ISNUMBER(G6),C6<>""),C6/G6,"") | I6: =IF(ISNUMBER(H6),ROUNDUP(H6,0),"") | J6: =IF(AND(C6<>"",D6<>""),C6*D6,"") | K6: =IF(AND(ISNUMBER(J6),ISNUMBER(I6)),IF(I6=0,"",J6/I6),"") | L6: =IF(AND(ISNUMBER(D6),ISNUMBER(F6)),D6/F6,"") | M6: =IF(ISNUMBER(I6),I6*G6-C6,"") | N6: =IF(B6="","",IFERROR(INDEX('Route Prices'!$F$5:$F$103,MATCH(B6,'Route Prices'!$A$5:$A$103,0)),"")) | O6: =IF(B6="","",IFERROR(INDEX('Route Prices'!$G$5:$G$103,MATCH(B6,'Route Prices'!$A$5:$A$103,0)),"")) | P6: =IF(AND(ISNUMBER(D6),ISNUMBER(N6)),IF(N6=0,"",D6/N6-1),"") | R6: Jamara | S6: =IF(R6="","",SUMIF($A$5:$A$34,R6,$C$5:$C$34)) | T6: =IF(R6="","",ROUNDUP(SUMIF($A$5:$A$34,R6,$H$5:$H$34),0)) | U6: =IF(R6="","",SUMIF($A$5:$A$34,R6,$J$5:$J$34)) | V6: =IF(OR(R6="",T6=0),"",U6/T6) | W6: =IF(R6="","",U6*12)
A7: Jamara | B7: KANO>LAGOS | C7: 4 | D7: 3775000 | E7: =IF(B7="","",IFERROR(INDEX('Turnaround Table'!$C$5:$C$231,MATCH(B7,'Turnaround Table'!$D$5:$D$231,0)),"not in table")) | F7: =IF(ISNUMBER(E7),2*E7,"") | G7: =IF(ISNUMBER(F7),MAX(1,INT('Truck Requirement'!$B$4/F7)),"") | H7: =IF(AND(ISNUMBER(G7),C7<>""),C7/G7,"") | I7: =IF(ISNUMBER(H7),ROUNDUP(H7,0),"") | J7: =IF(AND(C7<>"",D7<>""),C7*D7,"") | K7: =IF(AND(ISNUMBER(J7),ISNUMBER(I7)),IF(I7=0,"",J7/I7),"") | L7: =IF(AND(ISNUMBER(D7),ISNUMBER(F7)),D7/F7,"") | M7: =IF(ISNUMBER(I7),I7*G7-C7,"") | N7: =IF(B7="","",IFERROR(INDEX('Route Prices'!$F$5:$F$103,MATCH(B7,'Route Prices'!$A$5:$A$103,0)),"")) | O7: =IF(B7="","",IFERROR(INDEX('Route Prices'!$G$5:$G$103,MATCH(B7,'Route Prices'!$A$5:$A$103,0)),"")) | P7: =IF(AND(ISNUMBER(D7),ISNUMBER(N7)),IF(N7=0,"",D7/N7-1),"") | S7: =IF(R7="","",SUMIF($A$5:$A$34,R7,$C$5:$C$34)) | T7: =IF(R7="","",ROUNDUP(SUMIF($A$5:$A$34,R7,$H$5:$H$34),0)) | U7: =IF(R7="","",SUMIF($A$5:$A$34,R7,$J$5:$J$34)) | V7: =IF(OR(R7="",T7=0),"",U7/T7) | W7: =IF(R7="","",U7*12)
E8: =IF(B8="","",IFERROR(INDEX('Turnaround Table'!$C$5:$C$231,MATCH(B8,'Turnaround Table'!$D$5:$D$231,0)),"not in table")) | F8: =IF(ISNUMBER(E8),2*E8,"") | G8: =IF(ISNUMBER(F8),MAX(1,INT('Truck Requirement'!$B$4/F8)),"") | H8: =IF(AND(ISNUMBER(G8),C8<>""),C8/G8,"") | I8: =IF(ISNUMBER(H8),ROUNDUP(H8,0),"") | J8: =IF(AND(C8<>"",D8<>""),C8*D8,"") | K8: =IF(AND(ISNUMBER(J8),ISNUMBER(I8)),IF(I8=0,"",J8/I8),"") | L8: =IF(AND(ISNUMBER(D8),ISNUMBER(F8)),D8/F8,"") | M8: =IF(ISNUMBER(I8),I8*G8-C8,"") | N8: =IF(B8="","",IFERROR(INDEX('Route Prices'!$F$5:$F$103,MATCH(B8,'Route Prices'!$A$5:$A$103,0)),"")) | O8: =IF(B8="","",IFERROR(INDEX('Route Prices'!$G$5:$G$103,MATCH(B8,'Route Prices'!$A$5:$A$103,0)),"")) | P8: =IF(AND(ISNUMBER(D8),ISNUMBER(N8)),IF(N8=0,"",D8/N8-1),"") | S8: =IF(R8="","",SUMIF($A$5:$A$34,R8,$C$5:$C$34)) | T8: =IF(R8="","",ROUNDUP(SUMIF($A$5:$A$34,R8,$H$5:$H$34),0)) | U8: =IF(R8="","",SUMIF($A$5:$A$34,R8,$J$5:$J$34)) | V8: =IF(OR(R8="",T8=0),"",U8/T8) | W8: =IF(R8="","",U8*12)
E9: =IF(B9="","",IFERROR(INDEX('Turnaround Table'!$C$5:$C$231,MATCH(B9,'Turnaround Table'!$D$5:$D$231,0)),"not in table")) | F9: =IF(ISNUMBER(E9),2*E9,"") | G9: =IF(ISNUMBER(F9),MAX(1,INT('Truck Requirement'!$B$4/F9)),"") | H9: =IF(AND(ISNUMBER(G9),C9<>""),C9/G9,"") | I9: =IF(ISNUMBER(H9),ROUNDUP(H9,0),"") | J9: =IF(AND(C9<>"",D9<>""),C9*D9,"") | K9: =IF(AND(ISNUMBER(J9),ISNUMBER(I9)),IF(I9=0,"",J9/I9),"") | L9: =IF(AND(ISNUMBER(D9),ISNUMBER(F9)),D9/F9,"") | M9: =IF(ISNUMBER(I9),I9*G9-C9,"") | N9: =IF(B9="","",IFERROR(INDEX('Route Prices'!$F$5:$F$103,MATCH(B9,'Route Prices'!$A$5:$A$103,0)),"")) | O9: =IF(B9="","",IFERROR(INDEX('Route Prices'!$G$5:$G$103,MATCH(B9,'Route Prices'!$A$5:$A$103,0)),"")) | P9: =IF(AND(ISNUMBER(D9),ISNUMBER(N9)),IF(N9=0,"",D9/N9-1),"") | S9: =IF(R9="","",SUMIF($A$5:$A$34,R9,$C$5:$C$34)) | T9: =IF(R9="","",ROUNDUP(SUMIF($A$5:$A$34,R9,$H$5:$H$34),0)) | U9: =IF(R9="","",SUMIF($A$5:$A$34,R9,$J$5:$J$34)) | V9: =IF(OR(R9="",T9=0),"",U9/T9) | W9: =IF(R9="","",U9*12)
E10: =IF(B10="","",IFERROR(INDEX('Turnaround Table'!$C$5:$C$231,MATCH(B10,'Turnaround Table'!$D$5:$D$231,0)),"not in table")) | F10: =IF(ISNUMBER(E10),2*E10,"") | G10: =IF(ISNUMBER(F10),MAX(1,INT('Truck Requirement'!$B$4/F10)),"") | H10: =IF(AND(ISNUMBER(G10),C10<>""),C10/G10,"") | I10: =IF(ISNUMBER(H10),ROUNDUP(H10,0),"") | J10: =IF(AND(C10<>"",D10<>""),C10*D10,"") | K10: =IF(AND(ISNUMBER(J10),ISNUMBER(I10)),IF(I10=0,"",J10/I10),"") | L10: =IF(AND(ISNUMBER(D10),ISNUMBER(F10)),D10/F10,"") | M10: =IF(ISNUMBER(I10),I10*G10-C10,"") | N10: =IF(B10="","",IFERROR(INDEX('Route Prices'!$F$5:$F$103,MATCH(B10,'Route Prices'!$A$5:$A$103,0)),"")) | O10: =IF(B10="","",IFERROR(INDEX('Route Prices'!$G$5:$G$103,MATCH(B10,'Route Prices'!$A$5:$A$103,0)),"")) | P10: =IF(AND(ISNUMBER(D10),ISNUMBER(N10)),IF(N10=0,"",D10/N10-1),"") | S10: =IF(R10="","",SUMIF($A$5:$A$34,R10,$C$5:$C$34)) | T10: =IF(R10="","",ROUNDUP(SUMIF($A$5:$A$34,R10,$H$5:$H$34),0)) | U10: =IF(R10="","",SUMIF($A$5:$A$34,R10,$J$5:$J$34)) | V10: =IF(OR(R10="",T10=0),"",U10/T10) | W10: =IF(R10="","",U10*12)
E11: =IF(B11="","",IFERROR(INDEX('Turnaround Table'!$C$5:$C$231,MATCH(B11,'Turnaround Table'!$D$5:$D$231,0)),"not in table")) | F11: =IF(ISNUMBER(E11),2*E11,"") | G11: =IF(ISNUMBER(F11),MAX(1,INT('Truck Requirement'!$B$4/F11)),"") | H11: =IF(AND(ISNUMBER(G11),C11<>""),C11/G11,"") | I11: =IF(ISNUMBER(H11),ROUNDUP(H11,0),"") | J11: =IF(AND(C11<>"",D11<>""),C11*D11,"") | K11: =IF(AND(ISNUMBER(J11),ISNUMBER(I11)),IF(I11=0,"",J11/I11),"") | L11: =IF(AND(ISNUMBER(D11),ISNUMBER(F11)),D11/F11,"") | M11: =IF(ISNUMBER(I11),I11*G11-C11,"") | N11: =IF(B11="","",IFERROR(INDEX('Route Prices'!$F$5:$F$103,MATCH(B11,'Route Prices'!$A$5:$A$103,0)),"")) | O11: =IF(B11="","",IFERROR(INDEX('Route Prices'!$G$5:$G$103,MATCH(B11,'Route Prices'!$A$5:$A$103,0)),"")) | P11: =IF(AND(ISNUMBER(D11),ISNUMBER(N11)),IF(N11=0,"",D11/N11-1),"") | S11: =IF(R11="","",SUMIF($A$5:$A$34,R11,$C$5:$C$34)) | T11: =IF(R11="","",ROUNDUP(SUMIF($A$5:$A$34,R11,$H$5:$H$34),0)) | U11: =IF(R11="","",SUMIF($A$5:$A$34,R11,$J$5:$J$34)) | V11: =IF(OR(R11="",T11=0),"",U11/T11) | W11: =IF(R11="","",U11*12)
E12: =IF(B12="","",IFERROR(INDEX('Turnaround Table'!$C$5:$C$231,MATCH(B12,'Turnaround Table'!$D$5:$D$231,0)),"not in table")) | F12: =IF(ISNUMBER(E12),2*E12,"") | G12: =IF(ISNUMBER(F12),MAX(1,INT('Truck Requirement'!$B$4/F12)),"") | H12: =IF(AND(ISNUMBER(G12),C12<>""),C12/G12,"") | I12: =IF(ISNUMBER(H12),ROUNDUP(H12,0),"") | J12: =IF(AND(C12<>"",D12<>""),C12*D12,"") | K12: =IF(AND(ISNUMBER(J12),ISNUMBER(I12)),IF(I12=0,"",J12/I12),"") | L12: =IF(AND(ISNUMBER(D12),ISNUMBER(F12)),D12/F12,"") | M12: =IF(ISNUMBER(I12),I12*G12-C12,"") | N12: =IF(B12="","",IFERROR(INDEX('Route Prices'!$F$5:$F$103,MATCH(B12,'Route Prices'!$A$5:$A$103,0)),"")) | O12: =IF(B12="","",IFERROR(INDEX('Route Prices'!$G$5:$G$103,MATCH(B12,'Route Prices'!$A$5:$A$103,0)),"")) | P12: =IF(AND(ISNUMBER(D12),ISNUMBER(N12)),IF(N12=0,"",D12/N12-1),"") | S12: =IF(R12="","",SUMIF($A$5:$A$34,R12,$C$5:$C$34)) | T12: =IF(R12="","",ROUNDUP(SUMIF($A$5:$A$34,R12,$H$5:$H$34),0)) | U12: =IF(R12="","",SUMIF($A$5:$A$34,R12,$J$5:$J$34)) | V12: =IF(OR(R12="",T12=0),"",U12/T12) | W12: =IF(R12="","",U12*12)
E13: =IF(B13="","",IFERROR(INDEX('Turnaround Table'!$C$5:$C$231,MATCH(B13,'Turnaround Table'!$D$5:$D$231,0)),"not in table")) | F13: =IF(ISNUMBER(E13),2*E13,"") | G13: =IF(ISNUMBER(F13),MAX(1,INT('Truck Requirement'!$B$4/F13)),"") | H13: =IF(AND(ISNUMBER(G13),C13<>""),C13/G13,"") | I13: =IF(ISNUMBER(H13),ROUNDUP(H13,0),"") | J13: =IF(AND(C13<>"",D13<>""),C13*D13,"") | K13: =IF(AND(ISNUMBER(J13),ISNUMBER(I13)),IF(I13=0,"",J13/I13),"") | L13: =IF(AND(ISNUMBER(D13),ISNUMBER(F13)),D13/F13,"") | M13: =IF(ISNUMBER(I13),I13*G13-C13,"") | N13: =IF(B13="","",IFERROR(INDEX('Route Prices'!$F$5:$F$103,MATCH(B13,'Route Prices'!$A$5:$A$103,0)),"")) | O13: =IF(B13="","",IFERROR(INDEX('Route Prices'!$G$5:$G$103,MATCH(B13,'Route Prices'!$A$5:$A$103,0)),"")) | P13: =IF(AND(ISNUMBER(D13),ISNUMBER(N13)),IF(N13=0,"",D13/N13-1),"") | S13: =IF(R13="","",SUMIF($A$5:$A$34,R13,$C$5:$C$34)) | T13: =IF(R13="","",ROUNDUP(SUMIF($A$5:$A$34,R13,$H$5:$H$34),0)) | U13: =IF(R13="","",SUMIF($A$5:$A$34,R13,$J$5:$J$34)) | V13: =IF(OR(R13="",T13=0),"",U13/T13) | W13: =IF(R13="","",U13*12)
E14: =IF(B14="","",IFERROR(INDEX('Turnaround Table'!$C$5:$C$231,MATCH(B14,'Turnaround Table'!$D$5:$D$231,0)),"not in table")) | F14: =IF(ISNUMBER(E14),2*E14,"") | G14: =IF(ISNUMBER(F14),MAX(1,INT('Truck Requirement'!$B$4/F14)),"") | H14: =IF(AND(ISNUMBER(G14),C14<>""),C14/G14,"") | I14: =IF(ISNUMBER(H14),ROUNDUP(H14,0),"") | J14: =IF(AND(C14<>"",D14<>""),C14*D14,"") | K14: =IF(AND(ISNUMBER(J14),ISNUMBER(I14)),IF(I14=0,"",J14/I14),"") | L14: =IF(AND(ISNUMBER(D14),ISNUMBER(F14)),D14/F14,"") | M14: =IF(ISNUMBER(I14),I14*G14-C14,"") | N14: =IF(B14="","",IFERROR(INDEX('Route Prices'!$F$5:$F$103,MATCH(B14,'Route Prices'!$A$5:$A$103,0)),"")) | O14: =IF(B14="","",IFERROR(INDEX('Route Prices'!$G$5:$G$103,MATCH(B14,'Route Prices'!$A$5:$A$103,0)),"")) | P14: =IF(AND(ISNUMBER(D14),ISNUMBER(N14)),IF(N14=0,"",D14/N14-1),"") | S14: =IF(R14="","",SUMIF($A$5:$A$34,R14,$C$5:$C$34)) | T14: =IF(R14="","",ROUNDUP(SUMIF($A$5:$A$34,R14,$H$5:$H$34),0)) | U14: =IF(R14="","",SUMIF($A$5:$A$34,R14,$J$5:$J$34)) | V14: =IF(OR(R14="",T14=0),"",U14/T14) | W14: =IF(R14="","",U14*12)
E15: =IF(B15="","",IFERROR(INDEX('Turnaround Table'!$C$5:$C$231,MATCH(B15,'Turnaround Table'!$D$5:$D$231,0)),"not in table")) | F15: =IF(ISNUMBER(E15),2*E15,"") | G15: =IF(ISNUMBER(F15),MAX(1,INT('Truck Requirement'!$B$4/F15)),"") | H15: =IF(AND(ISNUMBER(G15),C15<>""),C15/G15,"") | I15: =IF(ISNUMBER(H15),ROUNDUP(H15,0),"") | J15: =IF(AND(C15<>"",D15<>""),C15*D15,"") | K15: =IF(AND(ISNUMBER(J15),ISNUMBER(I15)),IF(I15=0,"",J15/I15),"") | L15: =IF(AND(ISNUMBER(D15),ISNUMBER(F15)),D15/F15,"") | M15: =IF(ISNUMBER(I15),I15*G15-C15,"") | N15: =IF(B15="","",IFERROR(INDEX('Route Prices'!$F$5:$F$103,MATCH(B15,'Route Prices'!$A$5:$A$103,0)),"")) | O15: =IF(B15="","",IFERROR(INDEX('Route Prices'!$G$5:$G$103,MATCH(B15,'Route Prices'!$A$5:$A$103,0)),"")) | P15: =IF(AND(ISNUMBER(D15),ISNUMBER(N15)),IF(N15=0,"",D15/N15-1),"") | S15: =IF(R15="","",SUMIF($A$5:$A$34,R15,$C$5:$C$34)) | T15: =IF(R15="","",ROUNDUP(SUMIF($A$5:$A$34,R15,$H$5:$H$34),0)) | U15: =IF(R15="","",SUMIF($A$5:$A$34,R15,$J$5:$J$34)) | V15: =IF(OR(R15="",T15=0),"",U15/T15) | W15: =IF(R15="","",U15*12)
E16: =IF(B16="","",IFERROR(INDEX('Turnaround Table'!$C$5:$C$231,MATCH(B16,'Turnaround Table'!$D$5:$D$231,0)),"not in table")) | F16: =IF(ISNUMBER(E16),2*E16,"") | G16: =IF(ISNUMBER(F16),MAX(1,INT('Truck Requirement'!$B$4/F16)),"") | H16: =IF(AND(ISNUMBER(G16),C16<>""),C16/G16,"") | I16: =IF(ISNUMBER(H16),ROUNDUP(H16,0),"") | J16: =IF(AND(C16<>"",D16<>""),C16*D16,"") | K16: =IF(AND(ISNUMBER(J16),ISNUMBER(I16)),IF(I16=0,"",J16/I16),"") | L16: =IF(AND(ISNUMBER(D16),ISNUMBER(F16)),D16/F16,"") | M16: =IF(ISNUMBER(I16),I16*G16-C16,"") | N16: =IF(B16="","",IFERROR(INDEX('Route Prices'!$F$5:$F$103,MATCH(B16,'Route Prices'!$A$5:$A$103,0)),"")) | O16: =IF(B16="","",IFERROR(INDEX('Route Prices'!$G$5:$G$103,MATCH(B16,'Route Prices'!$A$5:$A$103,0)),"")) | P16: =IF(AND(ISNUMBER(D16),ISNUMBER(N16)),IF(N16=0,"",D16/N16-1),"") | S16: =IF(R16="","",SUMIF($A$5:$A$34,R16,$C$5:$C$34)) | T16: =IF(R16="","",ROUNDUP(SUMIF($A$5:$A$34,R16,$H$5:$H$34),0)) | U16: =IF(R16="","",SUMIF($A$5:$A$34,R16,$J$5:$J$34)) | V16: =IF(OR(R16="",T16=0),"",U16/T16) | W16: =IF(R16="","",U16*12)
E17: =IF(B17="","",IFERROR(INDEX('Turnaround Table'!$C$5:$C$231,MATCH(B17,'Turnaround Table'!$D$5:$D$231,0)),"not in table")) | F17: =IF(ISNUMBER(E17),2*E17,"") | G17: =IF(ISNUMBER(F17),MAX(1,INT('Truck Requirement'!$B$4/F17)),"") | H17: =IF(AND(ISNUMBER(G17),C17<>""),C17/G17,"") | I17: =IF(ISNUMBER(H17),ROUNDUP(H17,0),"") | J17: =IF(AND(C17<>"",D17<>""),C17*D17,"") | K17: =IF(AND(ISNUMBER(J17),ISNUMBER(I17)),IF(I17=0,"",J17/I17),"") | L17: =IF(AND(ISNUMBER(D17),ISNUMBER(F17)),D17/F17,"") | M17: =IF(ISNUMBER(I17),I17*G17-C17,"") | N17: =IF(B17="","",IFERROR(INDEX('Route Prices'!$F$5:$F$103,MATCH(B17,'Route Prices'!$A$5:$A$103,0)),"")) | O17: =IF(B17="","",IFERROR(INDEX('Route Prices'!$G$5:$G$103,MATCH(B17,'Route Prices'!$A$5:$A$103,0)),"")) | P17: =IF(AND(ISNUMBER(D17),ISNUMBER(N17)),IF(N17=0,"",D17/N17-1),"") | S17: =IF(R17="","",SUMIF($A$5:$A$34,R17,$C$5:$C$34)) | T17: =IF(R17="","",ROUNDUP(SUMIF($A$5:$A$34,R17,$H$5:$H$34),0)) | U17: =IF(R17="","",SUMIF($A$5:$A$34,R17,$J$5:$J$34)) | V17: =IF(OR(R17="",T17=0),"",U17/T17) | W17: =IF(R17="","",U17*12)
E18: =IF(B18="","",IFERROR(INDEX('Turnaround Table'!$C$5:$C$231,MATCH(B18,'Turnaround Table'!$D$5:$D$231,0)),"not in table")) | F18: =IF(ISNUMBER(E18),2*E18,"") | G18: =IF(ISNUMBER(F18),MAX(1,INT('Truck Requirement'!$B$4/F18)),"") | H18: =IF(AND(ISNUMBER(G18),C18<>""),C18/G18,"") | I18: =IF(ISNUMBER(H18),ROUNDUP(H18,0),"") | J18: =IF(AND(C18<>"",D18<>""),C18*D18,"") | K18: =IF(AND(ISNUMBER(J18),ISNUMBER(I18)),IF(I18=0,"",J18/I18),"") | L18: =IF(AND(ISNUMBER(D18),ISNUMBER(F18)),D18/F18,"") | M18: =IF(ISNUMBER(I18),I18*G18-C18,"") | N18: =IF(B18="","",IFERROR(INDEX('Route Prices'!$F$5:$F$103,MATCH(B18,'Route Prices'!$A$5:$A$103,0)),"")) | O18: =IF(B18="","",IFERROR(INDEX('Route Prices'!$G$5:$G$103,MATCH(B18,'Route Prices'!$A$5:$A$103,0)),"")) | P18: =IF(AND(ISNUMBER(D18),ISNUMBER(N18)),IF(N18=0,"",D18/N18-1),"") | S18: =IF(R18="","",SUMIF($A$5:$A$34,R18,$C$5:$C$34)) | T18: =IF(R18="","",ROUNDUP(SUMIF($A$5:$A$34,R18,$H$5:$H$34),0)) | U18: =IF(R18="","",SUMIF($A$5:$A$34,R18,$J$5:$J$34)) | V18: =IF(OR(R18="",T18=0),"",U18/T18) | W18: =IF(R18="","",U18*12)
E19: =IF(B19="","",IFERROR(INDEX('Turnaround Table'!$C$5:$C$231,MATCH(B19,'Turnaround Table'!$D$5:$D$231,0)),"not in table")) | F19: =IF(ISNUMBER(E19),2*E19,"") | G19: =IF(ISNUMBER(F19),MAX(1,INT('Truck Requirement'!$B$4/F19)),"") | H19: =IF(AND(ISNUMBER(G19),C19<>""),C19/G19,"") | I19: =IF(ISNUMBER(H19),ROUNDUP(H19,0),"") | J19: =IF(AND(C19<>"",D19<>""),C19*D19,"") | K19: =IF(AND(ISNUMBER(J19),ISNUMBER(I19)),IF(I19=0,"",J19/I19),"") | L19: =IF(AND(ISNUMBER(D19),ISNUMBER(F19)),D19/F19,"") | M19: =IF(ISNUMBER(I19),I19*G19-C19,"") | N19: =IF(B19="","",IFERROR(INDEX('Route Prices'!$F$5:$F$103,MATCH(B19,'Route Prices'!$A$5:$A$103,0)),"")) | O19: =IF(B19="","",IFERROR(INDEX('Route Prices'!$G$5:$G$103,MATCH(B19,'Route Prices'!$A$5:$A$103,0)),"")) | P19: =IF(AND(ISNUMBER(D19),ISNUMBER(N19)),IF(N19=0,"",D19/N19-1),"") | S19: =IF(R19="","",SUMIF($A$5:$A$34,R19,$C$5:$C$34)) | T19: =IF(R19="","",ROUNDUP(SUMIF($A$5:$A$34,R19,$H$5:$H$34),0)) | U19: =IF(R19="","",SUMIF($A$5:$A$34,R19,$J$5:$J$34)) | V19: =IF(OR(R19="",T19=0),"",U19/T19) | W19: =IF(R19="","",U19*12)
E20: =IF(B20="","",IFERROR(INDEX('Turnaround Table'!$C$5:$C$231,MATCH(B20,'Turnaround Table'!$D$5:$D$231,0)),"not in table")) | F20: =IF(ISNUMBER(E20),2*E20,"") | G20: =IF(ISNUMBER(F20),MAX(1,INT('Truck Requirement'!$B$4/F20)),"") | H20: =IF(AND(ISNUMBER(G20),C20<>""),C20/G20,"") | I20: =IF(ISNUMBER(H20),ROUNDUP(H20,0),"") | J20: =IF(AND(C20<>"",D20<>""),C20*D20,"") | K20: =IF(AND(ISNUMBER(J20),ISNUMBER(I20)),IF(I20=0,"",J20/I20),"") | L20: =IF(AND(ISNUMBER(D20),ISNUMBER(F20)),D20/F20,"") | M20: =IF(ISNUMBER(I20),I20*G20-C20,"") | N20: =IF(B20="","",IFERROR(INDEX('Route Prices'!$F$5:$F$103,MATCH(B20,'Route Prices'!$A$5:$A$103,0)),"")) | O20: =IF(B20="","",IFERROR(INDEX('Route Prices'!$G$5:$G$103,MATCH(B20,'Route Prices'!$A$5:$A$103,0)),"")) | P20: =IF(AND(ISNUMBER(D20),ISNUMBER(N20)),IF(N20=0,"",D20/N20-1),"") | S20: =IF(R20="","",SUMIF($A$5:$A$34,R20,$C$5:$C$34)) | T20: =IF(R20="","",ROUNDUP(SUMIF($A$5:$A$34,R20,$H$5:$H$34),0)) | U20: =IF(R20="","",SUMIF($A$5:$A$34,R20,$J$5:$J$34)) | V20: =IF(OR(R20="",T20=0),"",U20/T20) | W20: =IF(R20="","",U20*12)
E21: =IF(B21="","",IFERROR(INDEX('Turnaround Table'!$C$5:$C$231,MATCH(B21,'Turnaround Table'!$D$5:$D$231,0)),"not in table")) | F21: =IF(ISNUMBER(E21),2*E21,"") | G21: =IF(ISNUMBER(F21),MAX(1,INT('Truck Requirement'!$B$4/F21)),"") | H21: =IF(AND(ISNUMBER(G21),C21<>""),C21/G21,"") | I21: =IF(ISNUMBER(H21),ROUNDUP(H21,0),"") | J21: =IF(AND(C21<>"",D21<>""),C21*D21,"") | K21: =IF(AND(ISNUMBER(J21),ISNUMBER(I21)),IF(I21=0,"",J21/I21),"") | L21: =IF(AND(ISNUMBER(D21),ISNUMBER(F21)),D21/F21,"") | M21: =IF(ISNUMBER(I21),I21*G21-C21,"") | N21: =IF(B21="","",IFERROR(INDEX('Route Prices'!$F$5:$F$103,MATCH(B21,'Route Prices'!$A$5:$A$103,0)),"")) | O21: =IF(B21="","",IFERROR(INDEX('Route Prices'!$G$5:$G$103,MATCH(B21,'Route Prices'!$A$5:$A$103,0)),"")) | P21: =IF(AND(ISNUMBER(D21),ISNUMBER(N21)),IF(N21=0,"",D21/N21-1),"")
E22: =IF(B22="","",IFERROR(INDEX('Turnaround Table'!$C$5:$C$231,MATCH(B22,'Turnaround Table'!$D$5:$D$231,0)),"not in table")) | F22: =IF(ISNUMBER(E22),2*E22,"") | G22: =IF(ISNUMBER(F22),MAX(1,INT('Truck Requirement'!$B$4/F22)),"") | H22: =IF(AND(ISNUMBER(G22),C22<>""),C22/G22,"") | I22: =IF(ISNUMBER(H22),ROUNDUP(H22,0),"") | J22: =IF(AND(C22<>"",D22<>""),C22*D22,"") | K22: =IF(AND(ISNUMBER(J22),ISNUMBER(I22)),IF(I22=0,"",J22/I22),"") | L22: =IF(AND(ISNUMBER(D22),ISNUMBER(F22)),D22/F22,"") | M22: =IF(ISNUMBER(I22),I22*G22-C22,"") | N22: =IF(B22="","",IFERROR(INDEX('Route Prices'!$F$5:$F$103,MATCH(B22,'Route Prices'!$A$5:$A$103,0)),"")) | O22: =IF(B22="","",IFERROR(INDEX('Route Prices'!$G$5:$G$103,MATCH(B22,'Route Prices'!$A$5:$A$103,0)),"")) | P22: =IF(AND(ISNUMBER(D22),ISNUMBER(N22)),IF(N22=0,"",D22/N22-1),"")
E23: =IF(B23="","",IFERROR(INDEX('Turnaround Table'!$C$5:$C$231,MATCH(B23,'Turnaround Table'!$D$5:$D$231,0)),"not in table")) | F23: =IF(ISNUMBER(E23),2*E23,"") | G23: =IF(ISNUMBER(F23),MAX(1,INT('Truck Requirement'!$B$4/F23)),"") | H23: =IF(AND(ISNUMBER(G23),C23<>""),C23/G23,"") | I23: =IF(ISNUMBER(H23),ROUNDUP(H23,0),"") | J23: =IF(AND(C23<>"",D23<>""),C23*D23,"") | K23: =IF(AND(ISNUMBER(J23),ISNUMBER(I23)),IF(I23=0,"",J23/I23),"") | L23: =IF(AND(ISNUMBER(D23),ISNUMBER(F23)),D23/F23,"") | M23: =IF(ISNUMBER(I23),I23*G23-C23,"") | N23: =IF(B23="","",IFERROR(INDEX('Route Prices'!$F$5:$F$103,MATCH(B23,'Route Prices'!$A$5:$A$103,0)),"")) | O23: =IF(B23="","",IFERROR(INDEX('Route Prices'!$G$5:$G$103,MATCH(B23,'Route Prices'!$A$5:$A$103,0)),"")) | P23: =IF(AND(ISNUMBER(D23),ISNUMBER(N23)),IF(N23=0,"",D23/N23-1),"")
E24: =IF(B24="","",IFERROR(INDEX('Turnaround Table'!$C$5:$C$231,MATCH(B24,'Turnaround Table'!$D$5:$D$231,0)),"not in table")) | F24: =IF(ISNUMBER(E24),2*E24,"") | G24: =IF(ISNUMBER(F24),MAX(1,INT('Truck Requirement'!$B$4/F24)),"") | H24: =IF(AND(ISNUMBER(G24),C24<>""),C24/G24,"") | I24: =IF(ISNUMBER(H24),ROUNDUP(H24,0),"") | J24: =IF(AND(C24<>"",D24<>""),C24*D24,"") | K24: =IF(AND(ISNUMBER(J24),ISNUMBER(I24)),IF(I24=0,"",J24/I24),"") | L24: =IF(AND(ISNUMBER(D24),ISNUMBER(F24)),D24/F24,"") | M24: =IF(ISNUMBER(I24),I24*G24-C24,"") | N24: =IF(B24="","",IFERROR(INDEX('Route Prices'!$F$5:$F$103,MATCH(B24,'Route Prices'!$A$5:$A$103,0)),"")) | O24: =IF(B24="","",IFERROR(INDEX('Route Prices'!$G$5:$G$103,MATCH(B24,'Route Prices'!$A$5:$A$103,0)),"")) | P24: =IF(AND(ISNUMBER(D24),ISNUMBER(N24)),IF(N24=0,"",D24/N24-1),"")
E25: =IF(B25="","",IFERROR(INDEX('Turnaround Table'!$C$5:$C$231,MATCH(B25,'Turnaround Table'!$D$5:$D$231,0)),"not in table")) | F25: =IF(ISNUMBER(E25),2*E25,"") | G25: =IF(ISNUMBER(F25),MAX(1,INT('Truck Requirement'!$B$4/F25)),"") | H25: =IF(AND(ISNUMBER(G25),C25<>""),C25/G25,"") | I25: =IF(ISNUMBER(H25),ROUNDUP(H25,0),"") | J25: =IF(AND(C25<>"",D25<>""),C25*D25,"") | K25: =IF(AND(ISNUMBER(J25),ISNUMBER(I25)),IF(I25=0,"",J25/I25),"") | L25: =IF(AND(ISNUMBER(D25),ISNUMBER(F25)),D25/F25,"") | M25: =IF(ISNUMBER(I25),I25*G25-C25,"") | N25: =IF(B25="","",IFERROR(INDEX('Route Prices'!$F$5:$F$103,MATCH(B25,'Route Prices'!$A$5:$A$103,0)),"")) | O25: =IF(B25="","",IFERROR(INDEX('Route Prices'!$G$5:$G$103,MATCH(B25,'Route Prices'!$A$5:$A$103,0)),"")) | P25: =IF(AND(ISNUMBER(D25),ISNUMBER(N25)),IF(N25=0,"",D25/N25-1),"")
E26: =IF(B26="","",IFERROR(INDEX('Turnaround Table'!$C$5:$C$231,MATCH(B26,'Turnaround Table'!$D$5:$D$231,0)),"not in table")) | F26: =IF(ISNUMBER(E26),2*E26,"") | G26: =IF(ISNUMBER(F26),MAX(1,INT('Truck Requirement'!$B$4/F26)),"") | H26: =IF(AND(ISNUMBER(G26),C26<>""),C26/G26,"") | I26: =IF(ISNUMBER(H26),ROUNDUP(H26,0),"") | J26: =IF(AND(C26<>"",D26<>""),C26*D26,"") | K26: =IF(AND(ISNUMBER(J26),ISNUMBER(I26)),IF(I26=0,"",J26/I26),"") | L26: =IF(AND(ISNUMBER(D26),ISNUMBER(F26)),D26/F26,"") | M26: =IF(ISNUMBER(I26),I26*G26-C26,"") | N26: =IF(B26="","",IFERROR(INDEX('Route Prices'!$F$5:$F$103,MATCH(B26,'Route Prices'!$A$5:$A$103,0)),"")) | O26: =IF(B26="","",IFERROR(INDEX('Route Prices'!$G$5:$G$103,MATCH(B26,'Route Prices'!$A$5:$A$103,0)),"")) | P26: =IF(AND(ISNUMBER(D26),ISNUMBER(N26)),IF(N26=0,"",D26/N26-1),"")
E27: =IF(B27="","",IFERROR(INDEX('Turnaround Table'!$C$5:$C$231,MATCH(B27,'Turnaround Table'!$D$5:$D$231,0)),"not in table")) | F27: =IF(ISNUMBER(E27),2*E27,"") | G27: =IF(ISNUMBER(F27),MAX(1,INT('Truck Requirement'!$B$4/F27)),"") | H27: =IF(AND(ISNUMBER(G27),C27<>""),C27/G27,"") | I27: =IF(ISNUMBER(H27),ROUNDUP(H27,0),"") | J27: =IF(AND(C27<>"",D27<>""),C27*D27,"") | K27: =IF(AND(ISNUMBER(J27),ISNUMBER(I27)),IF(I27=0,"",J27/I27),"") | L27: =IF(AND(ISNUMBER(D27),ISNUMBER(F27)),D27/F27,"") | M27: =IF(ISNUMBER(I27),I27*G27-C27,"") | N27: =IF(B27="","",IFERROR(INDEX('Route Prices'!$F$5:$F$103,MATCH(B27,'Route Prices'!$A$5:$A$103,0)),"")) | O27: =IF(B27="","",IFERROR(INDEX('Route Prices'!$G$5:$G$103,MATCH(B27,'Route Prices'!$A$5:$A$103,0)),"")) | P27: =IF(AND(ISNUMBER(D27),ISNUMBER(N27)),IF(N27=0,"",D27/N27-1),"")
E28: =IF(B28="","",IFERROR(INDEX('Turnaround Table'!$C$5:$C$231,MATCH(B28,'Turnaround Table'!$D$5:$D$231,0)),"not in table")) | F28: =IF(ISNUMBER(E28),2*E28,"") | G28: =IF(ISNUMBER(F28),MAX(1,INT('Truck Requirement'!$B$4/F28)),"") | H28: =IF(AND(ISNUMBER(G28),C28<>""),C28/G28,"") | I28: =IF(ISNUMBER(H28),ROUNDUP(H28,0),"") | J28: =IF(AND(C28<>"",D28<>""),C28*D28,"") | K28: =IF(AND(ISNUMBER(J28),ISNUMBER(I28)),IF(I28=0,"",J28/I28),"") | L28: =IF(AND(ISNUMBER(D28),ISNUMBER(F28)),D28/F28,"") | M28: =IF(ISNUMBER(I28),I28*G28-C28,"") | N28: =IF(B28="","",IFERROR(INDEX('Route Prices'!$F$5:$F$103,MATCH(B28,'Route Prices'!$A$5:$A$103,0)),"")) | O28: =IF(B28="","",IFERROR(INDEX('Route Prices'!$G$5:$G$103,MATCH(B28,'Route Prices'!$A$5:$A$103,0)),"")) | P28: =IF(AND(ISNUMBER(D28),ISNUMBER(N28)),IF(N28=0,"",D28/N28-1),"")
E29: =IF(B29="","",IFERROR(INDEX('Turnaround Table'!$C$5:$C$231,MATCH(B29,'Turnaround Table'!$D$5:$D$231,0)),"not in table")) | F29: =IF(ISNUMBER(E29),2*E29,"") | G29: =IF(ISNUMBER(F29),MAX(1,INT('Truck Requirement'!$B$4/F29)),"") | H29: =IF(AND(ISNUMBER(G29),C29<>""),C29/G29,"") | I29: =IF(ISNUMBER(H29),ROUNDUP(H29,0),"") | J29: =IF(AND(C29<>"",D29<>""),C29*D29,"") | K29: =IF(AND(ISNUMBER(J29),ISNUMBER(I29)),IF(I29=0,"",J29/I29),"") | L29: =IF(AND(ISNUMBER(D29),ISNUMBER(F29)),D29/F29,"") | M29: =IF(ISNUMBER(I29),I29*G29-C29,"") | N29: =IF(B29="","",IFERROR(INDEX('Route Prices'!$F$5:$F$103,MATCH(B29,'Route Prices'!$A$5:$A$103,0)),"")) | O29: =IF(B29="","",IFERROR(INDEX('Route Prices'!$G$5:$G$103,MATCH(B29,'Route Prices'!$A$5:$A$103,0)),"")) | P29: =IF(AND(ISNUMBER(D29),ISNUMBER(N29)),IF(N29=0,"",D29/N29-1),"")
E30: =IF(B30="","",IFERROR(INDEX('Turnaround Table'!$C$5:$C$231,MATCH(B30,'Turnaround Table'!$D$5:$D$231,0)),"not in table")) | F30: =IF(ISNUMBER(E30),2*E30,"") | G30: =IF(ISNUMBER(F30),MAX(1,INT('Truck Requirement'!$B$4/F30)),"") | H30: =IF(AND(ISNUMBER(G30),C30<>""),C30/G30,"") | I30: =IF(ISNUMBER(H30),ROUNDUP(H30,0),"") | J30: =IF(AND(C30<>"",D30<>""),C30*D30,"") | K30: =IF(AND(ISNUMBER(J30),ISNUMBER(I30)),IF(I30=0,"",J30/I30),"") | L30: =IF(AND(ISNUMBER(D30),ISNUMBER(F30)),D30/F30,"") | M30: =IF(ISNUMBER(I30),I30*G30-C30,"") | N30: =IF(B30="","",IFERROR(INDEX('Route Prices'!$F$5:$F$103,MATCH(B30,'Route Prices'!$A$5:$A$103,0)),"")) | O30: =IF(B30="","",IFERROR(INDEX('Route Prices'!$G$5:$G$103,MATCH(B30,'Route Prices'!$A$5:$A$103,0)),"")) | P30: =IF(AND(ISNUMBER(D30),ISNUMBER(N30)),IF(N30=0,"",D30/N30-1),"")
E31: =IF(B31="","",IFERROR(INDEX('Turnaround Table'!$C$5:$C$231,MATCH(B31,'Turnaround Table'!$D$5:$D$231,0)),"not in table")) | F31: =IF(ISNUMBER(E31),2*E31,"") | G31: =IF(ISNUMBER(F31),MAX(1,INT('Truck Requirement'!$B$4/F31)),"") | H31: =IF(AND(ISNUMBER(G31),C31<>""),C31/G31,"") | I31: =IF(ISNUMBER(H31),ROUNDUP(H31,0),"") | J31: =IF(AND(C31<>"",D31<>""),C31*D31,"") | K31: =IF(AND(ISNUMBER(J31),ISNUMBER(I31)),IF(I31=0,"",J31/I31),"") | L31: =IF(AND(ISNUMBER(D31),ISNUMBER(F31)),D31/F31,"") | M31: =IF(ISNUMBER(I31),I31*G31-C31,"") | N31: =IF(B31="","",IFERROR(INDEX('Route Prices'!$F$5:$F$103,MATCH(B31,'Route Prices'!$A$5:$A$103,0)),"")) | O31: =IF(B31="","",IFERROR(INDEX('Route Prices'!$G$5:$G$103,MATCH(B31,'Route Prices'!$A$5:$A$103,0)),"")) | P31: =IF(AND(ISNUMBER(D31),ISNUMBER(N31)),IF(N31=0,"",D31/N31-1),"")
E32: =IF(B32="","",IFERROR(INDEX('Turnaround Table'!$C$5:$C$231,MATCH(B32,'Turnaround Table'!$D$5:$D$231,0)),"not in table")) | F32: =IF(ISNUMBER(E32),2*E32,"") | G32: =IF(ISNUMBER(F32),MAX(1,INT('Truck Requirement'!$B$4/F32)),"") | H32: =IF(AND(ISNUMBER(G32),C32<>""),C32/G32,"") | I32: =IF(ISNUMBER(H32),ROUNDUP(H32,0),"") | J32: =IF(AND(C32<>"",D32<>""),C32*D32,"") | K32: =IF(AND(ISNUMBER(J32),ISNUMBER(I32)),IF(I32=0,"",J32/I32),"") | L32: =IF(AND(ISNUMBER(D32),ISNUMBER(F32)),D32/F32,"") | M32: =IF(ISNUMBER(I32),I32*G32-C32,"") | N32: =IF(B32="","",IFERROR(INDEX('Route Prices'!$F$5:$F$103,MATCH(B32,'Route Prices'!$A$5:$A$103,0)),"")) | O32: =IF(B32="","",IFERROR(INDEX('Route Prices'!$G$5:$G$103,MATCH(B32,'Route Prices'!$A$5:$A$103,0)),"")) | P32: =IF(AND(ISNUMBER(D32),ISNUMBER(N32)),IF(N32=0,"",D32/N32-1),"")
... E34: =IF(B34="","",IFERROR(INDEX('Turnaround Table'!$C$5:$C$231,MATCH(B34,'Turnaround Table'!$D$5:$D$231,0)),"not in table")) | F34: =IF(ISNUMBER(E34),2*E34,"") | G34: =IF(ISNUMBER(F34),MAX(1,INT('Truck Requirement'!$B$4/F34)),"") | H34: =IF(AND(ISNUMBER(G34),C34<>""),C34/G34,"") | I34: =IF(ISNUMBER(H34),ROUNDUP(H34,0),"") | J34: =IF(AND(C34<>"",D34<>""),C34*D34,"") | K34: =IF(AND(ISNUMBER(J34),ISNUMBER(I34)),IF(I34=0,"",J34/I34),"") | L34: =IF(AND(ISNUMBER(D34),ISNUMBER(F34)),D34/F34,"") | M34: =IF(ISNUMBER(I34),I34*G34-C34,"") | N34: =IF(B34="","",IFERROR(INDEX('Route Prices'!$F$5:$F$103,MATCH(B34,'Route Prices'!$A$5:$A$103,0)),"")) | O34: =IF(B34="","",IFERROR(INDEX('Route Prices'!$G$5:$G$103,MATCH(B34,'Route Prices'!$A$5:$A$103,0)),"")) | P34: =IF(AND(ISNUMBER(D34),ISNUMBER(N34)),IF(N34=0,"",D34/N34-1),"")
A35: Total | C35: =SUM(C5:C34) | H35: =SUM(H5:H34) | I35: =SUM(I5:I34) | J35: =SUM(J5:J34) | K35: =IF(I35=0,"",J35/I35) | M35: =SUM(M5:M34)
A36: Yearly revenue at this plan (× 12) | J36: =J35*12

Sheet Truck Req by Route
A1: Truck requirement by client and route — monthly rotation
A2: Days come from the Turnaround Table via the Key. Type a value in "Override days" to replace it for one route. Red rows have no match in your table and use the default; please check them.
A4: Client | B4: Vehicle type | C4: Loading from (area) | D4: Destination | E4: Turnaround key used | F4: How matched | G4: One-leg days (table) | H4: Override days | I4: One-leg days used | J4: Round-trip days | K4: Trips one truck can do per month | L4: Trips Jan–Sep | M4: Trips Jan | N4: Trips Feb | O4: Trips Mar | P4: Trips Apr | Q4: Trips May | R4: Trips Jun | S4: Trips Jul | T4: Trips Aug | U4: Trips Sep | V4: Trucks Jan | W4: Trucks Feb | X4: Trucks Mar | Y4: Trucks Apr | Z4: Trucks May | AA4: Trucks Jun | AB4: Trucks Jul | AC4: Trucks Aug | AD4: Trucks Sep
A5: AB-INBEV | B5: Haulage | C5: Ilesa | D5: Yola | E5: YOLA>IBADAN | F5: Nearest bay (Ibadan) | G5: =IFERROR(INDEX('Turnaround Table'!$C$5:$C$231,MATCH(E5,'Turnaround Table'!$D$5:$D$231,0)),"") | I5: =IF(H5<>"",H5,IF(G5<>"",G5,'Truck Requirement'!$B$5)) | J5: =2*I5 | K5: =MAX(1,INT('Truck Requirement'!$B$4/J5)) | L5: =SUM(M5:U5) | O5: 1 | P5: 1 | Q5: 4 | V5: =IF(M5="","",M5/$K5) | W5: =IF(N5="","",N5/$K5) | X5: =IF(O5="","",O5/$K5) | Y5: =IF(P5="","",P5/$K5) | Z5: =IF(Q5="","",Q5/$K5) | AA5: =IF(R5="","",R5/$K5) | AB5: =IF(S5="","",S5/$K5) | AC5: =IF(T5="","",T5/$K5) | AD5: =IF(U5="","",U5/$K5)
A6: AB-INBEV | B6: Haulage | C6: Ilesa | D6: Kaduna | E6: KADUNA>IBADAN | F6: Nearest bay (Ibadan) | G6: =IFERROR(INDEX('Turnaround Table'!$C$5:$C$231,MATCH(E6,'Turnaround Table'!$D$5:$D$231,0)),"") | I6: =IF(H6<>"",H6,IF(G6<>"",G6,'Truck Requirement'!$B$5)) | J6: =2*I6 | K6: =MAX(1,INT('Truck Requirement'!$B$4/J6)) | L6: =SUM(M6:U6) | O6: 1 | P6: 2 | Q6: 2 | V6: =IF(M6="","",M6/$K6) | W6: =IF(N6="","",N6/$K6) | X6: =IF(O6="","",O6/$K6) | Y6: =IF(P6="","",P6/$K6) | Z6: =IF(Q6="","",Q6/$K6) | AA6: =IF(R6="","",R6/$K6) | AB6: =IF(S6="","",S6/$K6) | AC6: =IF(T6="","",T6/$K6) | AD6: =IF(U6="","",U6/$K6)
A7: AB-INBEV | B7: Haulage | C7: Ilesa | D7: Maiduguri | E7: MAIDUGURI>IBADAN | F7: Nearest bay (Ibadan) | G7: =IFERROR(INDEX('Turnaround Table'!$C$5:$C$231,MATCH(E7,'Turnaround Table'!$D$5:$D$231,0)),"") | I7: =IF(H7<>"",H7,IF(G7<>"",G7,'Truck Requirement'!$B$5)) | J7: =2*I7 | K7: =MAX(1,INT('Truck Requirement'!$B$4/J7)) | L7: =SUM(M7:U7) | P7: 3 | Q7: 1 | V7: =IF(M7="","",M7/$K7) | W7: =IF(N7="","",N7/$K7) | X7: =IF(O7="","",O7/$K7) | Y7: =IF(P7="","",P7/$K7) | Z7: =IF(Q7="","",Q7/$K7) | AA7: =IF(R7="","",R7/$K7) | AB7: =IF(S7="","",S7/$K7) | AC7: =IF(T7="","",T7/$K7) | AD7: =IF(U7="","",U7/$K7)
A8: AB-INBEV | B8: Haulage | C8: Ilesa | D8: Bauchi | E8: BAUCHI>IBADAN | F8: Nearest bay (Ibadan) | G8: =IFERROR(INDEX('Turnaround Table'!$C$5:$C$231,MATCH(E8,'Turnaround Table'!$D$5:$D$231,0)),"") | I8: =IF(H8<>"",H8,IF(G8<>"",G8,'Truck Requirement'!$B$5)) | J8: =2*I8 | K8: =MAX(1,INT('Truck Requirement'!$B$4/J8)) | L8: =SUM(M8:U8) | O8: 1 | P8: 2 | V8: =IF(M8="","",M8/$K8) | W8: =IF(N8="","",N8/$K8) | X8: =IF(O8="","",O8/$K8) | Y8: =IF(P8="","",P8/$K8) | Z8: =IF(Q8="","",Q8/$K8) | AA8: =IF(R8="","",R8/$K8) | AB8: =IF(S8="","",S8/$K8) | AC8: =IF(T8="","",T8/$K8) | AD8: =IF(U8="","",U8/$K8)
A9: AB-INBEV | B9: Haulage | C9: Ilesa | D9: Gombe | E9: GOMBE>IBADAN | F9: Nearest bay (Ibadan) | G9: =IFERROR(INDEX('Turnaround Table'!$C$5:$C$231,MATCH(E9,'Turnaround Table'!$D$5:$D$231,0)),"") | I9: =IF(H9<>"",H9,IF(G9<>"",G9,'Truck Requirement'!$B$5)) | J9: =2*I9 | K9: =MAX(1,INT('Truck Requirement'!$B$4/J9)) | L9: =SUM(M9:U9) | P9: 3 | V9: =IF(M9="","",M9/$K9) | W9: =IF(N9="","",N9/$K9) | X9: =IF(O9="","",O9/$K9) | Y9: =IF(P9="","",P9/$K9) | Z9: =IF(Q9="","",Q9/$K9) | AA9: =IF(R9="","",R9/$K9) | AB9: =IF(S9="","",S9/$K9) | AC9: =IF(T9="","",T9/$K9) | AD9: =IF(U9="","",U9/$K9)
A10: AB-INBEV | B10: Haulage | C10: Ilesa | D10: Jos | E10: JOS>IBADAN | F10: Nearest bay (Ibadan) | G10: =IFERROR(INDEX('Turnaround Table'!$C$5:$C$231,MATCH(E10,'Turnaround Table'!$D$5:$D$231,0)),"") | I10: =IF(H10<>"",H10,IF(G10<>"",G10,'Truck Requirement'!$B$5)) | J10: =2*I10 | K10: =MAX(1,INT('Truck Requirement'!$B$4/J10)) | L10: =SUM(M10:U10) | O10: 2 | P10: 1 | V10: =IF(M10="","",M10/$K10) | W10: =IF(N10="","",N10/$K10) | X10: =IF(O10="","",O10/$K10) | Y10: =IF(P10="","",P10/$K10) | Z10: =IF(Q10="","",Q10/$K10) | AA10: =IF(R10="","",R10/$K10) | AB10: =IF(S10="","",S10/$K10) | AC10: =IF(T10="","",T10/$K10) | AD10: =IF(U10="","",U10/$K10)
A11: AB-INBEV | B11: Haulage | C11: Ilesa | D11: Abia | E11: UMUAHIA>LAGOS | F11: Lagos bay used | G11: =IFERROR(INDEX('Turnaround Table'!$C$5:$C$231,MATCH(E11,'Turnaround Table'!$D$5:$D$231,0)),"") | I11: =IF(H11<>"",H11,IF(G11<>"",G11,'Truck Requirement'!$B$5)) | J11: =2*I11 | K11: =MAX(1,INT('Truck Requirement'!$B$4/J11)) | L11: =SUM(M11:U11) | P11: 1 | Q11: 1 | V11: =IF(M11="","",M11/$K11) | W11: =IF(N11="","",N11/$K11) | X11: =IF(O11="","",O11/$K11) | Y11: =IF(P11="","",P11/$K11) | Z11: =IF(Q11="","",Q11/$K11) | AA11: =IF(R11="","",R11/$K11) | AB11: =IF(S11="","",S11/$K11) | AC11: =IF(T11="","",T11/$K11) | AD11: =IF(U11="","",U11/$K11)
A12: AB-INBEV | B12: Haulage | C12: Ilesa | D12: Minna | E12: MINNA>IBADAN | F12: Nearest bay (Ibadan) | G12: =IFERROR(INDEX('Turnaround Table'!$C$5:$C$231,MATCH(E12,'Turnaround Table'!$D$5:$D$231,0)),"") | I12: =IF(H12<>"",H12,IF(G12<>"",G12,'Truck Requirement'!$B$5)) | J12: =2*I12 | K12: =MAX(1,INT('Truck Requirement'!$B$4/J12)) | L12: =SUM(M12:U12) | P12: 2 | V12: =IF(M12="","",M12/$K12) | W12: =IF(N12="","",N12/$K12) | X12: =IF(O12="","",O12/$K12) | Y12: =IF(P12="","",P12/$K12) | Z12: =IF(Q12="","",Q12/$K12) | AA12: =IF(R12="","",R12/$K12) | AB12: =IF(S12="","",S12/$K12) | AC12: =IF(T12="","",T12/$K12) | AD12: =IF(U12="","",U12/$K12)
A13: AB-INBEV | B13: Haulage | C13: Ilesa | D13: Shendam | E13: SHENDAM>LAGOS | F13: Lagos bay used | G13: =IFERROR(INDEX('Turnaround Table'!$C$5:$C$231,MATCH(E13,'Turnaround Table'!$D$5:$D$231,0)),"") | I13: =IF(H13<>"",H13,IF(G13<>"",G13,'Truck Requirement'!$B$5)) | J13: =2*I13 | K13: =MAX(1,INT('Truck Requirement'!$B$4/J13)) | L13: =SUM(M13:U13) | O13: 1 | Q13: 1 | V13: =IF(M13="","",M13/$K13) | W13: =IF(N13="","",N13/$K13) | X13: =IF(O13="","",O13/$K13) | Y13: =IF(P13="","",P13/$K13) | Z13: =IF(Q13="","",Q13/$K13) | AA13: =IF(R13="","",R13/$K13) | AB13: =IF(S13="","",S13/$K13) | AC13: =IF(T13="","",T13/$K13) | AD13: =IF(U13="","",U13/$K13)
A14: AB-INBEV | B14: Haulage | C14: Ilesa | D14: Sokoto | E14: SOKOTO>IBADAN | F14: Nearest bay (Ibadan) | G14: =IFERROR(INDEX('Turnaround Table'!$C$5:$C$231,MATCH(E14,'Turnaround Table'!$D$5:$D$231,0)),"") | I14: =IF(H14<>"",H14,IF(G14<>"",G14,'Truck Requirement'!$B$5)) | J14: =2*I14 | K14: =MAX(1,INT('Truck Requirement'!$B$4/J14)) | L14: =SUM(M14:U14) | P14: 2 | V14: =IF(M14="","",M14/$K14) | W14: =IF(N14="","",N14/$K14) | X14: =IF(O14="","",O14/$K14) | Y14: =IF(P14="","",P14/$K14) | Z14: =IF(Q14="","",Q14/$K14) | AA14: =IF(R14="","",R14/$K14) | AB14: =IF(S14="","",S14/$K14) | AC14: =IF(T14="","",T14/$K14) | AD14: =IF(U14="","",U14/$K14)
A15: AB-INBEV | B15: Haulage | C15: Ilesa | D15: Abakaliki | E15: ABAKALIKI>LAGOS | F15: Lagos bay used | G15: =IFERROR(INDEX('Turnaround Table'!$C$5:$C$231,MATCH(E15,'Turnaround Table'!$D$5:$D$231,0)),"") | I15: =IF(H15<>"",H15,IF(G15<>"",G15,'Truck Requirement'!$B$5)) | J15: =2*I15 | K15: =MAX(1,INT('Truck Requirement'!$B$4/J15)) | L15: =SUM(M15:U15) | P15: 1 | V15: =IF(M15="","",M15/$K15) | W15: =IF(N15="","",N15/$K15) | X15: =IF(O15="","",O15/$K15) | Y15: =IF(P15="","",P15/$K15) | Z15: =IF(Q15="","",Q15/$K15) | AA15: =IF(R15="","",R15/$K15) | AB15: =IF(S15="","",S15/$K15) | AC15: =IF(T15="","",T15/$K15) | AD15: =IF(U15="","",U15/$K15)
A16: AB-INBEV | B16: Haulage | C16: Ilesa | D16: Abuja | E16: ABUJA>IBADAN | F16: Nearest bay (Ibadan) | G16: =IFERROR(INDEX('Turnaround Table'!$C$5:$C$231,MATCH(E16,'Turnaround Table'!$D$5:$D$231,0)),"") | I16: =IF(H16<>"",H16,IF(G16<>"",G16,'Truck Requirement'!$B$5)) | J16: =2*I16 | K16: =MAX(1,INT('Truck Requirement'!$B$4/J16)) | L16: =SUM(M16:U16) | O16: 1 | V16: =IF(M16="","",M16/$K16) | W16: =IF(N16="","",N16/$K16) | X16: =IF(O16="","",O16/$K16) | Y16: =IF(P16="","",P16/$K16) | Z16: =IF(Q16="","",Q16/$K16) | AA16: =IF(R16="","",R16/$K16) | AB16: =IF(S16="","",S16/$K16) | AC16: =IF(T16="","",T16/$K16) | AD16: =IF(U16="","",U16/$K16)
A17: AB-INBEV | B17: Haulage | C17: Ilesa | D17: Benue | E17: MAKURDI>IBADAN | F17: Nearest bay (Ibadan) | G17: =IFERROR(INDEX('Turnaround Table'!$C$5:$C$231,MATCH(E17,'Turnaround Table'!$D$5:$D$231,0)),"") | I17: =IF(H17<>"",H17,IF(G17<>"",G17,'Truck Requirement'!$B$5)) | J17: =2*I17 | K17: =MAX(1,INT('Truck Requirement'!$B$4/J17)) | L17: =SUM(M17:U17) | P17: 1 | V17: =IF(M17="","",M17/$K17) | W17: =IF(N17="","",N17/$K17) | X17: =IF(O17="","",O17/$K17) | Y17: =IF(P17="","",P17/$K17) | Z17: =IF(Q17="","",Q17/$K17) | AA17: =IF(R17="","",R17/$K17) | AB17: =IF(S17="","",S17/$K17) | AC17: =IF(T17="","",T17/$K17) | AD17: =IF(U17="","",U17/$K17)
A18: AB-INBEV | B18: Haulage | C18: Ilesa | D18: Gboko | E18: GBOKO>IBADAN | F18: Nearest bay (Ibadan) | G18: =IFERROR(INDEX('Turnaround Table'!$C$5:$C$231,MATCH(E18,'Turnaround Table'!$D$5:$D$231,0)),"") | I18: =IF(H18<>"",H18,IF(G18<>"",G18,'Truck Requirement'!$B$5)) | J18: =2*I18 | K18: =MAX(1,INT('Truck Requirement'!$B$4/J18)) | L18: =SUM(M18:U18) | P18: 1 | V18: =IF(M18="","",M18/$K18) | W18: =IF(N18="","",N18/$K18) | X18: =IF(O18="","",O18/$K18) | Y18: =IF(P18="","",P18/$K18) | Z18: =IF(Q18="","",Q18/$K18) | AA18: =IF(R18="","",R18/$K18) | AB18: =IF(S18="","",S18/$K18) | AC18: =IF(T18="","",T18/$K18) | AD18: =IF(U18="","",U18/$K18)
A19: AB-INBEV | B19: Haulage | C19: Ilesa | D19: Imo-Orlu | E19: OWERRI>LAGOS | F19: Lagos bay used | G19: =IFERROR(INDEX('Turnaround Table'!$C$5:$C$231,MATCH(E19,'Turnaround Table'!$D$5:$D$231,0)),"") | I19: =IF(H19<>"",H19,IF(G19<>"",G19,'Truck Requirement'!$B$5)) | J19: =2*I19 | K19: =MAX(1,INT('Truck Requirement'!$B$4/J19)) | L19: =SUM(M19:U19) | P19: 1 | V19: =IF(M19="","",M19/$K19) | W19: =IF(N19="","",N19/$K19) | X19: =IF(O19="","",O19/$K19) | Y19: =IF(P19="","",P19/$K19) | Z19: =IF(Q19="","",Q19/$K19) | AA19: =IF(R19="","",R19/$K19) | AB19: =IF(S19="","",S19/$K19) | AC19: =IF(T19="","",T19/$K19) | AD19: =IF(U19="","",U19/$K19)
A20: AB-INBEV | B20: Haulage | C20: Ilesa | D20: Kanfanchan, Kaduna | E20: KADUNA>IBADAN | F20: Nearest bay (Ibadan) | G20: =IFERROR(INDEX('Turnaround Table'!$C$5:$C$231,MATCH(E20,'Turnaround Table'!$D$5:$D$231,0)),"") | I20: =IF(H20<>"",H20,IF(G20<>"",G20,'Truck Requirement'!$B$5)) | J20: =2*I20 | K20: =MAX(1,INT('Truck Requirement'!$B$4/J20)) | L20: =SUM(M20:U20) | P20: 1 | V20: =IF(M20="","",M20/$K20) | W20: =IF(N20="","",N20/$K20) | X20: =IF(O20="","",O20/$K20) | Y20: =IF(P20="","",P20/$K20) | Z20: =IF(Q20="","",Q20/$K20) | AA20: =IF(R20="","",R20/$K20) | AB20: =IF(S20="","",S20/$K20) | AC20: =IF(T20="","",T20/$K20) | AD20: =IF(U20="","",U20/$K20)
A21: AB-INBEV | B21: Haulage | C21: Ilesa | D21: Katsina | E21: KATSINA>LAGOS | F21: Lagos bay used | G21: =IFERROR(INDEX('Turnaround Table'!$C$5:$C$231,MATCH(E21,'Turnaround Table'!$D$5:$D$231,0)),"") | I21: =IF(H21<>"",H21,IF(G21<>"",G21,'Truck Requirement'!$B$5)) | J21: =2*I21 | K21: =MAX(1,INT('Truck Requirement'!$B$4/J21)) | L21: =SUM(M21:U21) | Q21: 1 | V21: =IF(M21="","",M21/$K21) | W21: =IF(N21="","",N21/$K21) | X21: =IF(O21="","",O21/$K21) | Y21: =IF(P21="","",P21/$K21) | Z21: =IF(Q21="","",Q21/$K21) | AA21: =IF(R21="","",R21/$K21) | AB21: =IF(S21="","",S21/$K21) | AC21: =IF(T21="","",T21/$K21) | AD21: =IF(U21="","",U21/$K21)
A22: AB-INBEV | B22: Haulage | C22: Ilesa | D22: Lafia | E22: LAFIA>IBADAN | F22: Nearest bay (Ibadan) | G22: =IFERROR(INDEX('Turnaround Table'!$C$5:$C$231,MATCH(E22,'Turnaround Table'!$D$5:$D$231,0)),"") | I22: =IF(H22<>"",H22,IF(G22<>"",G22,'Truck Requirement'!$B$5)) | J22: =2*I22 | K22: =MAX(1,INT('Truck Requirement'!$B$4/J22)) | L22: =SUM(M22:U22) | Q22: 1 | V22: =IF(M22="","",M22/$K22) | W22: =IF(N22="","",N22/$K22) | X22: =IF(O22="","",O22/$K22) | Y22: =IF(P22="","",P22/$K22) | Z22: =IF(Q22="","",Q22/$K22) | AA22: =IF(R22="","",R22/$K22) | AB22: =IF(S22="","",S22/$K22) | AC22: =IF(T22="","",T22/$K22) | AD22: =IF(U22="","",U22/$K22)
A23: AB-INBEV | B23: Haulage | C23: Ilesa | D23: Lantang, Plateau | E23: SHENDAM>LAGOS | F23: Lagos bay used | G23: =IFERROR(INDEX('Turnaround Table'!$C$5:$C$231,MATCH(E23,'Turnaround Table'!$D$5:$D$231,0)),"") | I23: =IF(H23<>"",H23,IF(G23<>"",G23,'Truck Requirement'!$B$5)) | J23: =2*I23 | K23: =MAX(1,INT('Truck Requirement'!$B$4/J23)) | L23: =SUM(M23:U23) | P23: 1 | V23: =IF(M23="","",M23/$K23) | W23: =IF(N23="","",N23/$K23) | X23: =IF(O23="","",O23/$K23) | Y23: =IF(P23="","",P23/$K23) | Z23: =IF(Q23="","",Q23/$K23) | AA23: =IF(R23="","",R23/$K23) | AB23: =IF(S23="","",S23/$K23) | AC23: =IF(T23="","",T23/$K23) | AD23: =IF(U23="","",U23/$K23)
A24: AB-INBEV | B24: Haulage | C24: Ilesa | D24: Mangu | E24: JOS>IBADAN | F24: Nearest bay (Ibadan) | G24: =IFERROR(INDEX('Turnaround Table'!$C$5:$C$231,MATCH(E24,'Turnaround Table'!$D$5:$D$231,0)),"") | I24: =IF(H24<>"",H24,IF(G24<>"",G24,'Truck Requirement'!$B$5)) | J24: =2*I24 | K24: =MAX(1,INT('Truck Requirement'!$B$4/J24)) | L24: =SUM(M24:U24) | P24: 1 | V24: =IF(M24="","",M24/$K24) | W24: =IF(N24="","",N24/$K24) | X24: =IF(O24="","",O24/$K24) | Y24: =IF(P24="","",P24/$K24) | Z24: =IF(Q24="","",Q24/$K24) | AA24: =IF(R24="","",R24/$K24) | AB24: =IF(S24="","",S24/$K24) | AC24: =IF(T24="","",T24/$K24) | AD24: =IF(U24="","",U24/$K24)
A25: AB-INBEV | B25: Haulage | C25: Ilesa | D25: Nasarawa | E25: LAFIA>IBADAN | F25: Nearest bay (Ibadan) | G25: =IFERROR(INDEX('Turnaround Table'!$C$5:$C$231,MATCH(E25,'Turnaround Table'!$D$5:$D$231,0)),"") | I25: =IF(H25<>"",H25,IF(G25<>"",G25,'Truck Requirement'!$B$5)) | J25: =2*I25 | K25: =MAX(1,INT('Truck Requirement'!$B$4/J25)) | L25: =SUM(M25:U25) | P25: 1 | V25: =IF(M25="","",M25/$K25) | W25: =IF(N25="","",N25/$K25) | X25: =IF(O25="","",O25/$K25) | Y25: =IF(P25="","",P25/$K25) | Z25: =IF(Q25="","",Q25/$K25) | AA25: =IF(R25="","",R25/$K25) | AB25: =IF(S25="","",S25/$K25) | AC25: =IF(T25="","",T25/$K25) | AD25: =IF(U25="","",U25/$K25)
A26: AB-INBEV | B26: Haulage | C26: Ilesa | D26: Rivers State | F26: Not in table | G26: =IFERROR(INDEX('Turnaround Table'!$C$5:$C$231,MATCH(E26,'Turnaround Table'!$D$5:$D$231,0)),"") | I26: =IF(H26<>"",H26,IF(G26<>"",G26,'Truck Requirement'!$B$5)) | J26: =2*I26 | K26: =MAX(1,INT('Truck Requirement'!$B$4/J26)) | L26: =SUM(M26:U26) | P26: 1 | V26: =IF(M26="","",M26/$K26) | W26: =IF(N26="","",N26/$K26) | X26: =IF(O26="","",O26/$K26) | Y26: =IF(P26="","",P26/$K26) | Z26: =IF(Q26="","",Q26/$K26) | AA26: =IF(R26="","",R26/$K26) | AB26: =IF(S26="","",S26/$K26) | AC26: =IF(T26="","",T26/$K26) | AD26: =IF(U26="","",U26/$K26)
A27: AB-INBEV | B27: Haulage | C27: Ilesa | D27: Tundun Wada, Plateau | E27: SHENDAM>LAGOS | F27: Lagos bay used | G27: =IFERROR(INDEX('Turnaround Table'!$C$5:$C$231,MATCH(E27,'Turnaround Table'!$D$5:$D$231,0)),"") | I27: =IF(H27<>"",H27,IF(G27<>"",G27,'Truck Requirement'!$B$5)) | J27: =2*I27 | K27: =MAX(1,INT('Truck Requirement'!$B$4/J27)) | L27: =SUM(M27:U27) | P27: 1 | V27: =IF(M27="","",M27/$K27) | W27: =IF(N27="","",N27/$K27) | X27: =IF(O27="","",O27/$K27) | Y27: =IF(P27="","",P27/$K27) | Z27: =IF(Q27="","",Q27/$K27) | AA27: =IF(R27="","",R27/$K27) | AB27: =IF(S27="","",S27/$K27) | AC27: =IF(T27="","",T27/$K27) | AD27: =IF(U27="","",U27/$K27)
A28: AB-INBEV | B28: Haulage | C28: Ilesa | D28: Uli | E28: ONITSHA>IBADAN | F28: Nearest bay (Ibadan) | G28: =IFERROR(INDEX('Turnaround Table'!$C$5:$C$231,MATCH(E28,'Turnaround Table'!$D$5:$D$231,0)),"") | I28: =IF(H28<>"",H28,IF(G28<>"",G28,'Truck Requirement'!$B$5)) | J28: =2*I28 | K28: =MAX(1,INT('Truck Requirement'!$B$4/J28)) | L28: =SUM(M28:U28) | P28: 1 | V28: =IF(M28="","",M28/$K28) | W28: =IF(N28="","",N28/$K28) | X28: =IF(O28="","",O28/$K28) | Y28: =IF(P28="","",P28/$K28) | Z28: =IF(Q28="","",Q28/$K28) | AA28: =IF(R28="","",R28/$K28) | AB28: =IF(S28="","",S28/$K28) | AC28: =IF(T28="","",T28/$K28) | AD28: =IF(U28="","",U28/$K28)
A29: ABBA ABASS | B29: Haulage | C29: Nasarawa | D29: Ogere | E29: LAFIA>LAGOS | F29: Reverse | G29: =IFERROR(INDEX('Turnaround Table'!$C$5:$C$231,MATCH(E29,'Turnaround Table'!$D$5:$D$231,0)),"") | I29: =IF(H29<>"",H29,IF(G29<>"",G29,'Truck Requirement'!$B$5)) | J29: =2*I29 | K29: =MAX(1,INT('Truck Requirement'!$B$4/J29)) | L29: =SUM(M29:U29) | R29: 8 | S29: 9 | T29: 3 | U29: 11 | V29: =IF(M29="","",M29/$K29) | W29: =IF(N29="","",N29/$K29) | X29: =IF(O29="","",O29/$K29) | Y29: =IF(P29="","",P29/$K29) | Z29: =IF(Q29="","",Q29/$K29) | AA29: =IF(R29="","",R29/$K29) | AB29: =IF(S29="","",S29/$K29) | AC29: =IF(T29="","",T29/$K29) | AD29: =IF(U29="","",U29/$K29)
A30: ABBA ABASS | B30: Haulage | C30: Ogere | D30: Nasarawa | E30: LAFIA>LAGOS | F30: Nearest bay (Lagos) | G30: =IFERROR(INDEX('Turnaround Table'!$C$5:$C$231,MATCH(E30,'Turnaround Table'!$D$5:$D$231,0)),"") | I30: =IF(H30<>"",H30,IF(G30<>"",G30,'Truck Requirement'!$B$5)) | J30: =2*I30 | K30: =MAX(1,INT('Truck Requirement'!$B$4/J30)) | L30: =SUM(M30:U30) | T30: 2 | U30: 1 | V30: =IF(M30="","",M30/$K30) | W30: =IF(N30="","",N30/$K30) | X30: =IF(O30="","",O30/$K30) | Y30: =IF(P30="","",P30/$K30) | Z30: =IF(Q30="","",Q30/$K30) | AA30: =IF(R30="","",R30/$K30) | AB30: =IF(S30="","",S30/$K30) | AC30: =IF(T30="","",T30/$K30) | AD30: =IF(U30="","",U30/$K30)
A31: B2B-ORCA DECO LIMITED (MR LEKAN) | B31: Haulage | C31: Lagos | D31: Lekki | E31: LEKKI>LAGOS | F31: Exact | G31: =IFERROR(INDEX('Turnaround Table'!$C$5:$C$231,MATCH(E31,'Turnaround Table'!$D$5:$D$231,0)),"") | I31: =IF(H31<>"",H31,IF(G31<>"",G31,'Truck Requirement'!$B$5)) | J31: =2*I31 | K31: =MAX(1,INT('Truck Requirement'!$B$4/J31)) | L31: =SUM(M31:U31) | P31: 1 | V31: =IF(M31="","",M31/$K31) | W31: =IF(N31="","",N31/$K31) | X31: =IF(O31="","",O31/$K31) | Y31: =IF(P31="","",P31/$K31) | Z31: =IF(Q31="","",Q31/$K31) | AA31: =IF(R31="","",R31/$K31) | AB31: =IF(S31="","",S31/$K31) | AC31: =IF(T31="","",T31/$K31) | AD31: =IF(U31="","",U31/$K31)
A32: B2B-ORCA DECO LIMITED(MR OTEGA) | B32: Haulage | C32: Lagos | D32: Asaba | E32: ASABA>LAGOS | F32: Exact | G32: =IFERROR(INDEX('Turnaround Table'!$C$5:$C$231,MATCH(E32,'Turnaround Table'!$D$5:$D$231,0)),"") | I32: =IF(H32<>"",H32,IF(G32<>"",G32,'Truck Requirement'!$B$5)) | J32: =2*I32 | K32: =MAX(1,INT('Truck Requirement'!$B$4/J32)) | L32: =SUM(M32:U32) | P32: 1 | V32: =IF(M32="","",M32/$K32) | W32: =IF(N32="","",N32/$K32) | X32: =IF(O32="","",O32/$K32) | Y32: =IF(P32="","",P32/$K32) | Z32: =IF(Q32="","",Q32/$K32) | AA32: =IF(R32="","",R32/$K32) | AB32: =IF(S32="","",S32/$K32) | AC32: =IF(T32="","",T32/$K32) | AD32: =IF(U32="","",U32/$K32)
A33: B2B-ORCA DECO LIMITED(ULOMA) | B33: Haulage | C33: Lagos | D33: Abuja | E33: ABUJA>LAGOS | F33: Exact | G33: =IFERROR(INDEX('Turnaround Table'!$C$5:$C$231,MATCH(E33,'Turnaround Table'!$D$5:$D$231,0)),"") | I33: =IF(H33<>"",H33,IF(G33<>"",G33,'Truck Requirement'!$B$5)) | J33: =2*I33 | K33: =MAX(1,INT('Truck Requirement'!$B$4/J33)) | L33: =SUM(M33:U33) | R33: 1 | V33: =IF(M33="","",M33/$K33) | W33: =IF(N33="","",N33/$K33) | X33: =IF(O33="","",O33/$K33) | Y33: =IF(P33="","",P33/$K33) | Z33: =IF(Q33="","",Q33/$K33) | AA33: =IF(R33="","",R33/$K33) | AB33: =IF(S33="","",S33/$K33) | AC33: =IF(T33="","",T33/$K33) | AD33: =IF(U33="","",U33/$K33)
A34: B2B-ORCA DECO LIMITED-AGR | B34: Haulage | C34: Lagos | D34: Abuja | E34: ABUJA>LAGOS | F34: Exact | G34: =IFERROR(INDEX('Turnaround Table'!$C$5:$C$231,MATCH(E34,'Turnaround Table'!$D$5:$D$231,0)),"") | I34: =IF(H34<>"",H34,IF(G34<>"",G34,'Truck Requirement'!$B$5)) | J34: =2*I34 | K34: =MAX(1,INT('Truck Requirement'!$B$4/J34)) | L34: =SUM(M34:U34) | Q34: 1 | V34: =IF(M34="","",M34/$K34) | W34: =IF(N34="","",N34/$K34) | X34: =IF(O34="","",O34/$K34) | Y34: =IF(P34="","",P34/$K34) | Z34: =IF(Q34="","",Q34/$K34) | AA34: =IF(R34="","",R34/$K34) | AB34: =IF(S34="","",S34/$K34) | AC34: =IF(T34="","",T34/$K34) | AD34: =IF(U34="","",U34/$K34)
A35: CRESEADA | B35: Haulage | C35: Lagos | D35: Lokoja | E35: LOKOJA>LAGOS | F35: Exact | G35: =IFERROR(INDEX('Turnaround Table'!$C$5:$C$231,MATCH(E35,'Turnaround Table'!$D$5:$D$231,0)),"") | I35: =IF(H35<>"",H35,IF(G35<>"",G35,'Truck Requirement'!$B$5)) | J35: =2*I35 | K35: =MAX(1,INT('Truck Requirement'!$B$4/J35)) | L35: =SUM(M35:U35) | U35: 6 | V35: =IF(M35="","",M35/$K35) | W35: =IF(N35="","",N35/$K35) | X35: =IF(O35="","",O35/$K35) | Y35: =IF(P35="","",P35/$K35) | Z35: =IF(Q35="","",Q35/$K35) | AA35: =IF(R35="","",R35/$K35) | AB35: =IF(S35="","",S35/$K35) | AC35: =IF(T35="","",T35/$K35) | AD35: =IF(U35="","",U35/$K35)
A36: GIVANAS | B36: Haulage | C36: Lagos | D36: Onitsha | E36: ONITSHA>LAGOS | F36: Exact | G36: =IFERROR(INDEX('Turnaround Table'!$C$5:$C$231,MATCH(E36,'Turnaround Table'!$D$5:$D$231,0)),"") | I36: =IF(H36<>"",H36,IF(G36<>"",G36,'Truck Requirement'!$B$5)) | J36: =2*I36 | K36: =MAX(1,INT('Truck Requirement'!$B$4/J36)) | L36: =SUM(M36:U36) | M36: 3 | N36: 2 | O36: 4 | P36: 3 | Q36: 3 | R36: 1 | S36: 1 | T36: 3 | U36: 2 | V36: =IF(M36="","",M36/$K36) | W36: =IF(N36="","",N36/$K36) | X36: =IF(O36="","",O36/$K36) | Y36: =IF(P36="","",P36/$K36) | Z36: =IF(Q36="","",Q36/$K36) | AA36: =IF(R36="","",R36/$K36) | AB36: =IF(S36="","",S36/$K36) | AC36: =IF(T36="","",T36/$K36) | AD36: =IF(U36="","",U36/$K36)
A37: GIVANAS | B37: Haulage | C37: Lagos | D37: Phc | E37: PORT HARCOURT>LAGOS | F37: Exact | G37: =IFERROR(INDEX('Turnaround Table'!$C$5:$C$231,MATCH(E37,'Turnaround Table'!$D$5:$D$231,0)),"") | I37: =IF(H37<>"",H37,IF(G37<>"",G37,'Truck Requirement'!$B$5)) | J37: =2*I37 | K37: =MAX(1,INT('Truck Requirement'!$B$4/J37)) | L37: =SUM(M37:U37) | O37: 1 | V37: =IF(M37="","",M37/$K37) | W37: =IF(N37="","",N37/$K37) | X37: =IF(O37="","",O37/$K37) | Y37: =IF(P37="","",P37/$K37) | Z37: =IF(Q37="","",Q37/$K37) | AA37: =IF(R37="","",R37/$K37) | AB37: =IF(S37="","",S37/$K37) | AC37: =IF(T37="","",T37/$K37) | AD37: =IF(U37="","",U37/$K37)
A38: INTERSTYLE | B38: Haulage | C38: Abuja | D38: Apapa | E38: ABUJA>LAGOS | F38: Reverse | G38: =IFERROR(INDEX('Turnaround Table'!$C$5:$C$231,MATCH(E38,'Turnaround Table'!$D$5:$D$231,0)),"") | I38: =IF(H38<>"",H38,IF(G38<>"",G38,'Truck Requirement'!$B$5)) | J38: =2*I38 | K38: =MAX(1,INT('Truck Requirement'!$B$4/J38)) | L38: =SUM(M38:U38) | M38: 1 | O38: 1 | Q38: 1 | R38: 1 | S38: 1 | T38: 1 | V38: =IF(M38="","",M38/$K38) | W38: =IF(N38="","",N38/$K38) | X38: =IF(O38="","",O38/$K38) | Y38: =IF(P38="","",P38/$K38) | Z38: =IF(Q38="","",Q38/$K38) | AA38: =IF(R38="","",R38/$K38) | AB38: =IF(S38="","",S38/$K38) | AC38: =IF(T38="","",T38/$K38) | AD38: =IF(U38="","",U38/$K38)
A39: INTERSTYLE | B39: Haulage | C39: Lagos | D39: Abuja | E39: ABUJA>APAPA | F39: Exact | G39: =IFERROR(INDEX('Turnaround Table'!$C$5:$C$231,MATCH(E39,'Turnaround Table'!$D$5:$D$231,0)),"") | I39: =IF(H39<>"",H39,IF(G39<>"",G39,'Truck Requirement'!$B$5)) | J39: =2*I39 | K39: =MAX(1,INT('Truck Requirement'!$B$4/J39)) | L39: =SUM(M39:U39) | Q39: 1 | R39: 1 | S39: 1 | T39: 1 | U39: 1 | V39: =IF(M39="","",M39/$K39) | W39: =IF(N39="","",N39/$K39) | X39: =IF(O39="","",O39/$K39) | Y39: =IF(P39="","",P39/$K39) | Z39: =IF(Q39="","",Q39/$K39) | AA39: =IF(R39="","",R39/$K39) | AB39: =IF(S39="","",S39/$K39) | AC39: =IF(T39="","",T39/$K39) | AD39: =IF(U39="","",U39/$K39)
A40: INTERSTYLE | B40: Haulage | C40: Lagos | D40: Phc | E40: PORT HARCOURT>LAGOS | F40: Exact | G40: =IFERROR(INDEX('Turnaround Table'!$C$5:$C$231,MATCH(E40,'Turnaround Table'!$D$5:$D$231,0)),"") | I40: =IF(H40<>"",H40,IF(G40<>"",G40,'Truck Requirement'!$B$5)) | J40: =2*I40 | K40: =MAX(1,INT('Truck Requirement'!$B$4/J40)) | L40: =SUM(M40:U40) | N40: 1 | V40: =IF(M40="","",M40/$K40) | W40: =IF(N40="","",N40/$K40) | X40: =IF(O40="","",O40/$K40) | Y40: =IF(P40="","",P40/$K40) | Z40: =IF(Q40="","",Q40/$K40) | AA40: =IF(R40="","",R40/$K40) | AB40: =IF(S40="","",S40/$K40) | AC40: =IF(T40="","",T40/$K40) | AD40: =IF(U40="","",U40/$K40)
A41: Illera Agro | B41: Haulage | C41: Kaduna (Kudenda) | D41: Ikorodu | E41: KADUNA>LAGOS | F41: Reverse | G41: =IFERROR(INDEX('Turnaround Table'!$C$5:$C$231,MATCH(E41,'Turnaround Table'!$D$5:$D$231,0)),"") | I41: =IF(H41<>"",H41,IF(G41<>"",G41,'Truck Requirement'!$B$5)) | J41: =2*I41 | K41: =MAX(1,INT('Truck Requirement'!$B$4/J41)) | L41: =SUM(M41:U41) | S41: 2 | V41: =IF(M41="","",M41/$K41) | W41: =IF(N41="","",N41/$K41) | X41: =IF(O41="","",O41/$K41) | Y41: =IF(P41="","",P41/$K41) | Z41: =IF(Q41="","",Q41/$K41) | AA41: =IF(R41="","",R41/$K41) | AB41: =IF(S41="","",S41/$K41) | AC41: =IF(T41="","",T41/$K41) | AD41: =IF(U41="","",U41/$K41)
A42: JMG | B42: Haulage | C42: Lagos | D42: Abuja | E42: ABUJA>LAGOS | F42: Exact | G42: =IFERROR(INDEX('Turnaround Table'!$C$5:$C$231,MATCH(E42,'Turnaround Table'!$D$5:$D$231,0)),"") | I42: =IF(H42<>"",H42,IF(G42<>"",G42,'Truck Requirement'!$B$5)) | J42: =2*I42 | K42: =MAX(1,INT('Truck Requirement'!$B$4/J42)) | L42: =SUM(M42:U42) | Q42: 1 | V42: =IF(M42="","",M42/$K42) | W42: =IF(N42="","",N42/$K42) | X42: =IF(O42="","",O42/$K42) | Y42: =IF(P42="","",P42/$K42) | Z42: =IF(Q42="","",Q42/$K42) | AA42: =IF(R42="","",R42/$K42) | AB42: =IF(S42="","",S42/$K42) | AC42: =IF(T42="","",T42/$K42) | AD42: =IF(U42="","",U42/$K42)
A43: JUBAILI AGROTEC | B43: Haulage | C43: Ibadan | D43: Kabba | E43: KABBA>IBADAN | F43: Exact | G43: =IFERROR(INDEX('Turnaround Table'!$C$5:$C$231,MATCH(E43,'Turnaround Table'!$D$5:$D$231,0)),"") | I43: =IF(H43<>"",H43,IF(G43<>"",G43,'Truck Requirement'!$B$5)) | J43: =2*I43 | K43: =MAX(1,INT('Truck Requirement'!$B$4/J43)) | L43: =SUM(M43:U43) | O43: 1 | P43: 3 | Q43: 1 | R43: 1 | V43: =IF(M43="","",M43/$K43) | W43: =IF(N43="","",N43/$K43) | X43: =IF(O43="","",O43/$K43) | Y43: =IF(P43="","",P43/$K43) | Z43: =IF(Q43="","",Q43/$K43) | AA43: =IF(R43="","",R43/$K43) | AB43: =IF(S43="","",S43/$K43) | AC43: =IF(T43="","",T43/$K43) | AD43: =IF(U43="","",U43/$K43)
A44: JUBAILI AGROTEC | B44: Haulage | C44: Ibadan | D44: Keffi | E44: KEFFI>IBADAN | F44: Exact | G44: =IFERROR(INDEX('Turnaround Table'!$C$5:$C$231,MATCH(E44,'Turnaround Table'!$D$5:$D$231,0)),"") | I44: =IF(H44<>"",H44,IF(G44<>"",G44,'Truck Requirement'!$B$5)) | J44: =2*I44 | K44: =MAX(1,INT('Truck Requirement'!$B$4/J44)) | L44: =SUM(M44:U44) | N44: 1 | O44: 1 | P44: 1 | R44: 2 | U44: 1 | V44: =IF(M44="","",M44/$K44) | W44: =IF(N44="","",N44/$K44) | X44: =IF(O44="","",O44/$K44) | Y44: =IF(P44="","",P44/$K44) | Z44: =IF(Q44="","",Q44/$K44) | AA44: =IF(R44="","",R44/$K44) | AB44: =IF(S44="","",S44/$K44) | AC44: =IF(T44="","",T44/$K44) | AD44: =IF(U44="","",U44/$K44)
A45: JUBAILI AGROTEC | B45: Haulage | C45: Ibadan | D45: Kano | E45: KANO>IBADAN | F45: Exact | G45: =IFERROR(INDEX('Turnaround Table'!$C$5:$C$231,MATCH(E45,'Turnaround Table'!$D$5:$D$231,0)),"") | I45: =IF(H45<>"",H45,IF(G45<>"",G45,'Truck Requirement'!$B$5)) | J45: =2*I45 | K45: =MAX(1,INT('Truck Requirement'!$B$4/J45)) | L45: =SUM(M45:U45) | S45: 3 | V45: =IF(M45="","",M45/$K45) | W45: =IF(N45="","",N45/$K45) | X45: =IF(O45="","",O45/$K45) | Y45: =IF(P45="","",P45/$K45) | Z45: =IF(Q45="","",Q45/$K45) | AA45: =IF(R45="","",R45/$K45) | AB45: =IF(S45="","",S45/$K45) | AC45: =IF(T45="","",T45/$K45) | AD45: =IF(U45="","",U45/$K45)
A46: JUBAILI AGROTEC | B46: Haulage | C46: Ibadan | D46: Minna | E46: MINNA>IBADAN | F46: Exact | G46: =IFERROR(INDEX('Turnaround Table'!$C$5:$C$231,MATCH(E46,'Turnaround Table'!$D$5:$D$231,0)),"") | I46: =IF(H46<>"",H46,IF(G46<>"",G46,'Truck Requirement'!$B$5)) | J46: =2*I46 | K46: =MAX(1,INT('Truck Requirement'!$B$4/J46)) | L46: =SUM(M46:U46) | U46: 3 | V46: =IF(M46="","",M46/$K46) | W46: =IF(N46="","",N46/$K46) | X46: =IF(O46="","",O46/$K46) | Y46: =IF(P46="","",P46/$K46) | Z46: =IF(Q46="","",Q46/$K46) | AA46: =IF(R46="","",R46/$K46) | AB46: =IF(S46="","",S46/$K46) | AC46: =IF(T46="","",T46/$K46) | AD46: =IF(U46="","",U46/$K46)
A47: JUBAILI AGROTEC | B47: Haulage | C47: Ibadan | D47: Sokoto | E47: SOKOTO>IBADAN | F47: Exact | G47: =IFERROR(INDEX('Turnaround Table'!$C$5:$C$231,MATCH(E47,'Turnaround Table'!$D$5:$D$231,0)),"") | I47: =IF(H47<>"",H47,IF(G47<>"",G47,'Truck Requirement'!$B$5)) | J47: =2*I47 | K47: =MAX(1,INT('Truck Requirement'!$B$4/J47)) | L47: =SUM(M47:U47) | U47: 3 | V47: =IF(M47="","",M47/$K47) | W47: =IF(N47="","",N47/$K47) | X47: =IF(O47="","",O47/$K47) | Y47: =IF(P47="","",P47/$K47) | Z47: =IF(Q47="","",Q47/$K47) | AA47: =IF(R47="","",R47/$K47) | AB47: =IF(S47="","",S47/$K47) | AC47: =IF(T47="","",T47/$K47) | AD47: =IF(U47="","",U47/$K47)
A48: JUBAILI AGROTEC | B48: Haulage | C48: Ibadan | D48: Abakaliki | E48: ABAKALIKI>LAGOS | F48: Lagos bay used | G48: =IFERROR(INDEX('Turnaround Table'!$C$5:$C$231,MATCH(E48,'Turnaround Table'!$D$5:$D$231,0)),"") | I48: =IF(H48<>"",H48,IF(G48<>"",G48,'Truck Requirement'!$B$5)) | J48: =2*I48 | K48: =MAX(1,INT('Truck Requirement'!$B$4/J48)) | L48: =SUM(M48:U48) | M48: 1 | O48: 1 | V48: =IF(M48="","",M48/$K48) | W48: =IF(N48="","",N48/$K48) | X48: =IF(O48="","",O48/$K48) | Y48: =IF(P48="","",P48/$K48) | Z48: =IF(Q48="","",Q48/$K48) | AA48: =IF(R48="","",R48/$K48) | AB48: =IF(S48="","",S48/$K48) | AC48: =IF(T48="","",T48/$K48) | AD48: =IF(U48="","",U48/$K48)
A49: JUBAILI AGROTEC | B49: Haulage | C49: Ibadan | D49: Abuja | E49: ABUJA>IBADAN | F49: Exact | G49: =IFERROR(INDEX('Turnaround Table'!$C$5:$C$231,MATCH(E49,'Turnaround Table'!$D$5:$D$231,0)),"") | I49: =IF(H49<>"",H49,IF(G49<>"",G49,'Truck Requirement'!$B$5)) | J49: =2*I49 | K49: =MAX(1,INT('Truck Requirement'!$B$4/J49)) | L49: =SUM(M49:U49) | U49: 2 | V49: =IF(M49="","",M49/$K49) | W49: =IF(N49="","",N49/$K49) | X49: =IF(O49="","",O49/$K49) | Y49: =IF(P49="","",P49/$K49) | Z49: =IF(Q49="","",Q49/$K49) | AA49: =IF(R49="","",R49/$K49) | AB49: =IF(S49="","",S49/$K49) | AC49: =IF(T49="","",T49/$K49) | AD49: =IF(U49="","",U49/$K49)
A50: JUBAILI AGROTEC | B50: Haulage | C50: Ibadan | D50: Ekpoma | E50: UROMI>LAGOS | F50: Lagos bay used | G50: =IFERROR(INDEX('Turnaround Table'!$C$5:$C$231,MATCH(E50,'Turnaround Table'!$D$5:$D$231,0)),"") | I50: =IF(H50<>"",H50,IF(G50<>"",G50,'Truck Requirement'!$B$5)) | J50: =2*I50 | K50: =MAX(1,INT('Truck Requirement'!$B$4/J50)) | L50: =SUM(M50:U50) | N50: 1 | O50: 1 | V50: =IF(M50="","",M50/$K50) | W50: =IF(N50="","",N50/$K50) | X50: =IF(O50="","",O50/$K50) | Y50: =IF(P50="","",P50/$K50) | Z50: =IF(Q50="","",Q50/$K50) | AA50: =IF(R50="","",R50/$K50) | AB50: =IF(S50="","",S50/$K50) | AC50: =IF(T50="","",T50/$K50) | AD50: =IF(U50="","",U50/$K50)
A51: JUBAILI AGROTEC | B51: Haulage | C51: Ibadan | D51: Enugu | E51: ENUGU>LAGOS | F51: Lagos bay used | G51: =IFERROR(INDEX('Turnaround Table'!$C$5:$C$231,MATCH(E51,'Turnaround Table'!$D$5:$D$231,0)),"") | I51: =IF(H51<>"",H51,IF(G51<>"",G51,'Truck Requirement'!$B$5)) | J51: =2*I51 | K51: =MAX(1,INT('Truck Requirement'!$B$4/J51)) | L51: =SUM(M51:U51) | O51: 2 | V51: =IF(M51="","",M51/$K51) | W51: =IF(N51="","",N51/$K51) | X51: =IF(O51="","",O51/$K51) | Y51: =IF(P51="","",P51/$K51) | Z51: =IF(Q51="","",Q51/$K51) | AA51: =IF(R51="","",R51/$K51) | AB51: =IF(S51="","",S51/$K51) | AC51: =IF(T51="","",T51/$K51) | AD51: =IF(U51="","",U51/$K51)
A52: JUBAILI AGROTEC | B52: Haulage | C52: Ibadan | D52: Jalingo | E52: JALINGO>IBADAN | F52: Exact | G52: =IFERROR(INDEX('Turnaround Table'!$C$5:$C$231,MATCH(E52,'Turnaround Table'!$D$5:$D$231,0)),"") | I52: =IF(H52<>"",H52,IF(G52<>"",G52,'Truck Requirement'!$B$5)) | J52: =2*I52 | K52: =MAX(1,INT('Truck Requirement'!$B$4/J52)) | L52: =SUM(M52:U52) | U52: 2 | V52: =IF(M52="","",M52/$K52) | W52: =IF(N52="","",N52/$K52) | X52: =IF(O52="","",O52/$K52) | Y52: =IF(P52="","",P52/$K52) | Z52: =IF(Q52="","",Q52/$K52) | AA52: =IF(R52="","",R52/$K52) | AB52: =IF(S52="","",S52/$K52) | AC52: =IF(T52="","",T52/$K52) | AD52: =IF(U52="","",U52/$K52)
A53: JUBAILI AGROTEC | B53: Haulage | C53: Ibadan | D53: Lafia | E53: LAFIA>IBADAN | F53: Exact | G53: =IFERROR(INDEX('Turnaround Table'!$C$5:$C$231,MATCH(E53,'Turnaround Table'!$D$5:$D$231,0)),"") | I53: =IF(H53<>"",H53,IF(G53<>"",G53,'Truck Requirement'!$B$5)) | J53: =2*I53 | K53: =MAX(1,INT('Truck Requirement'!$B$4/J53)) | L53: =SUM(M53:U53) | O53: 1 | U53: 1 | V53: =IF(M53="","",M53/$K53) | W53: =IF(N53="","",N53/$K53) | X53: =IF(O53="","",O53/$K53) | Y53: =IF(P53="","",P53/$K53) | Z53: =IF(Q53="","",Q53/$K53) | AA53: =IF(R53="","",R53/$K53) | AB53: =IF(S53="","",S53/$K53) | AC53: =IF(T53="","",T53/$K53) | AD53: =IF(U53="","",U53/$K53)
A54: JUBAILI AGROTEC | B54: Haulage | C54: Ibadan | D54: Maiduguri | E54: MAIDUGURI>IBADAN | F54: Exact | G54: =IFERROR(INDEX('Turnaround Table'!$C$5:$C$231,MATCH(E54,'Turnaround Table'!$D$5:$D$231,0)),"") | I54: =IF(H54<>"",H54,IF(G54<>"",G54,'Truck Requirement'!$B$5)) | J54: =2*I54 | K54: =MAX(1,INT('Truck Requirement'!$B$4/J54)) | L54: =SUM(M54:U54) | U54: 2 | V54: =IF(M54="","",M54/$K54) | W54: =IF(N54="","",N54/$K54) | X54: =IF(O54="","",O54/$K54) | Y54: =IF(P54="","",P54/$K54) | Z54: =IF(Q54="","",Q54/$K54) | AA54: =IF(R54="","",R54/$K54) | AB54: =IF(S54="","",S54/$K54) | AC54: =IF(T54="","",T54/$K54) | AD54: =IF(U54="","",U54/$K54)
A55: JUBAILI AGROTEC | B55: Haulage | C55: Ibadan | D55: Aba | E55: ABA>IBADAN | F55: Exact | G55: =IFERROR(INDEX('Turnaround Table'!$C$5:$C$231,MATCH(E55,'Turnaround Table'!$D$5:$D$231,0)),"") | I55: =IF(H55<>"",H55,IF(G55<>"",G55,'Truck Requirement'!$B$5)) | J55: =2*I55 | K55: =MAX(1,INT('Truck Requirement'!$B$4/J55)) | L55: =SUM(M55:U55) | M55: 1 | V55: =IF(M55="","",M55/$K55) | W55: =IF(N55="","",N55/$K55) | X55: =IF(O55="","",O55/$K55) | Y55: =IF(P55="","",P55/$K55) | Z55: =IF(Q55="","",Q55/$K55) | AA55: =IF(R55="","",R55/$K55) | AB55: =IF(S55="","",S55/$K55) | AC55: =IF(T55="","",T55/$K55) | AD55: =IF(U55="","",U55/$K55)
A56: JUBAILI AGROTEC | B56: Haulage | C56: Ibadan | D56: Abaji | E56: ABUJA>IBADAN | F56: Exact | G56: =IFERROR(INDEX('Turnaround Table'!$C$5:$C$231,MATCH(E56,'Turnaround Table'!$D$5:$D$231,0)),"") | I56: =IF(H56<>"",H56,IF(G56<>"",G56,'Truck Requirement'!$B$5)) | J56: =2*I56 | K56: =MAX(1,INT('Truck Requirement'!$B$4/J56)) | L56: =SUM(M56:U56) | N56: 1 | V56: =IF(M56="","",M56/$K56) | W56: =IF(N56="","",N56/$K56) | X56: =IF(O56="","",O56/$K56) | Y56: =IF(P56="","",P56/$K56) | Z56: =IF(Q56="","",Q56/$K56) | AA56: =IF(R56="","",R56/$K56) | AB56: =IF(S56="","",S56/$K56) | AC56: =IF(T56="","",T56/$K56) | AD56: =IF(U56="","",U56/$K56)
A57: JUBAILI AGROTEC | B57: Haulage | C57: Ibadan | D57: Abeokuta | E57: ABEOKUTA>LAGOS | F57: Lagos bay used | G57: =IFERROR(INDEX('Turnaround Table'!$C$5:$C$231,MATCH(E57,'Turnaround Table'!$D$5:$D$231,0)),"") | I57: =IF(H57<>"",H57,IF(G57<>"",G57,'Truck Requirement'!$B$5)) | J57: =2*I57 | K57: =MAX(1,INT('Truck Requirement'!$B$4/J57)) | L57: =SUM(M57:U57) | N57: 1 | V57: =IF(M57="","",M57/$K57) | W57: =IF(N57="","",N57/$K57) | X57: =IF(O57="","",O57/$K57) | Y57: =IF(P57="","",P57/$K57) | Z57: =IF(Q57="","",Q57/$K57) | AA57: =IF(R57="","",R57/$K57) | AB57: =IF(S57="","",S57/$K57) | AC57: =IF(T57="","",T57/$K57) | AD57: =IF(U57="","",U57/$K57)
A58: JUBAILI AGROTEC | B58: Haulage | C58: Ibadan | D58: Bida | E58: BIDA>IBADAN | F58: Exact | G58: =IFERROR(INDEX('Turnaround Table'!$C$5:$C$231,MATCH(E58,'Turnaround Table'!$D$5:$D$231,0)),"") | I58: =IF(H58<>"",H58,IF(G58<>"",G58,'Truck Requirement'!$B$5)) | J58: =2*I58 | K58: =MAX(1,INT('Truck Requirement'!$B$4/J58)) | L58: =SUM(M58:U58) | U58: 1 | V58: =IF(M58="","",M58/$K58) | W58: =IF(N58="","",N58/$K58) | X58: =IF(O58="","",O58/$K58) | Y58: =IF(P58="","",P58/$K58) | Z58: =IF(Q58="","",Q58/$K58) | AA58: =IF(R58="","",R58/$K58) | AB58: =IF(S58="","",S58/$K58) | AC58: =IF(T58="","",T58/$K58) | AD58: =IF(U58="","",U58/$K58)
A59: JUBAILI AGROTEC | B59: Haulage | C59: Ibadan | D59: Kaduna | E59: KADUNA>IBADAN | F59: Exact | G59: =IFERROR(INDEX('Turnaround Table'!$C$5:$C$231,MATCH(E59,'Turnaround Table'!$D$5:$D$231,0)),"") | I59: =IF(H59<>"",H59,IF(G59<>"",G59,'Truck Requirement'!$B$5)) | J59: =2*I59 | K59: =MAX(1,INT('Truck Requirement'!$B$4/J59)) | L59: =SUM(M59:U59) | Q59: 1 | V59: =IF(M59="","",M59/$K59) | W59: =IF(N59="","",N59/$K59) | X59: =IF(O59="","",O59/$K59) | Y59: =IF(P59="","",P59/$K59) | Z59: =IF(Q59="","",Q59/$K59) | AA59: =IF(R59="","",R59/$K59) | AB59: =IF(S59="","",S59/$K59) | AC59: =IF(T59="","",T59/$K59) | AD59: =IF(U59="","",U59/$K59)
A60: JUBAILI AGROTEC | B60: Haulage | C60: Ibadan | D60: Kotangora | E60: KONTAGORA>LAGOS | F60: Lagos bay used | G60: =IFERROR(INDEX('Turnaround Table'!$C$5:$C$231,MATCH(E60,'Turnaround Table'!$D$5:$D$231,0)),"") | I60: =IF(H60<>"",H60,IF(G60<>"",G60,'Truck Requirement'!$B$5)) | J60: =2*I60 | K60: =MAX(1,INT('Truck Requirement'!$B$4/J60)) | L60: =SUM(M60:U60) | R60: 1 | V60: =IF(M60="","",M60/$K60) | W60: =IF(N60="","",N60/$K60) | X60: =IF(O60="","",O60/$K60) | Y60: =IF(P60="","",P60/$K60) | Z60: =IF(Q60="","",Q60/$K60) | AA60: =IF(R60="","",R60/$K60) | AB60: =IF(S60="","",S60/$K60) | AC60: =IF(T60="","",T60/$K60) | AD60: =IF(U60="","",U60/$K60)
A61: JUBAILI AGROTEC | B61: Haulage | C61: Ibadan | D61: Oyo | E61: OYO>LAGOS | F61: Lagos bay used | G61: =IFERROR(INDEX('Turnaround Table'!$C$5:$C$231,MATCH(E61,'Turnaround Table'!$D$5:$D$231,0)),"") | I61: =IF(H61<>"",H61,IF(G61<>"",G61,'Truck Requirement'!$B$5)) | J61: =2*I61 | K61: =MAX(1,INT('Truck Requirement'!$B$4/J61)) | L61: =SUM(M61:U61) | N61: 1 | V61: =IF(M61="","",M61/$K61) | W61: =IF(N61="","",N61/$K61) | X61: =IF(O61="","",O61/$K61) | Y61: =IF(P61="","",P61/$K61) | Z61: =IF(Q61="","",Q61/$K61) | AA61: =IF(R61="","",R61/$K61) | AB61: =IF(S61="","",S61/$K61) | AC61: =IF(T61="","",T61/$K61) | AD61: =IF(U61="","",U61/$K61)
A62: JUBAILI AGROTEC | B62: Haulage | C62: Ibadan | D62: Suleja | E62: ABUJA>IBADAN | F62: Exact | G62: =IFERROR(INDEX('Turnaround Table'!$C$5:$C$231,MATCH(E62,'Turnaround Table'!$D$5:$D$231,0)),"") | I62: =IF(H62<>"",H62,IF(G62<>"",G62,'Truck Requirement'!$B$5)) | J62: =2*I62 | K62: =MAX(1,INT('Truck Requirement'!$B$4/J62)) | L62: =SUM(M62:U62) | P62: 1 | V62: =IF(M62="","",M62/$K62) | W62: =IF(N62="","",N62/$K62) | X62: =IF(O62="","",O62/$K62) | Y62: =IF(P62="","",P62/$K62) | Z62: =IF(Q62="","",Q62/$K62) | AA62: =IF(R62="","",R62/$K62) | AB62: =IF(S62="","",S62/$K62) | AC62: =IF(T62="","",T62/$K62) | AD62: =IF(U62="","",U62/$K62)
A63: JUBAILI AGROTEC | B63: Haulage | C63: Ibadan | D63: Zaria | E63: ZARIA>IBADAN | F63: Exact | G63: =IFERROR(INDEX('Turnaround Table'!$C$5:$C$231,MATCH(E63,'Turnaround Table'!$D$5:$D$231,0)),"") | I63: =IF(H63<>"",H63,IF(G63<>"",G63,'Truck Requirement'!$B$5)) | J63: =2*I63 | K63: =MAX(1,INT('Truck Requirement'!$B$4/J63)) | L63: =SUM(M63:U63) | U63: 1 | V63: =IF(M63="","",M63/$K63) | W63: =IF(N63="","",N63/$K63) | X63: =IF(O63="","",O63/$K63) | Y63: =IF(P63="","",P63/$K63) | Z63: =IF(Q63="","",Q63/$K63) | AA63: =IF(R63="","",R63/$K63) | AB63: =IF(S63="","",S63/$K63) | AC63: =IF(T63="","",T63/$K63) | AD63: =IF(U63="","",U63/$K63)
A64: Jamara | B64: Haulage | C64: Lagos | D64: Phc | E64: PORT HARCOURT>LAGOS | F64: Exact | G64: =IFERROR(INDEX('Turnaround Table'!$C$5:$C$231,MATCH(E64,'Turnaround Table'!$D$5:$D$231,0)),"") | I64: =IF(H64<>"",H64,IF(G64<>"",G64,'Truck Requirement'!$B$5)) | J64: =2*I64 | K64: =MAX(1,INT('Truck Requirement'!$B$4/J64)) | L64: =SUM(M64:U64) | M64: 7 | N64: 6 | O64: 4 | P64: 6 | Q64: 4 | R64: 8 | S64: 7 | T64: 14 | U64: 6 | V64: =IF(M64="","",M64/$K64) | W64: =IF(N64="","",N64/$K64) | X64: =IF(O64="","",O64/$K64) | Y64: =IF(P64="","",P64/$K64) | Z64: =IF(Q64="","",Q64/$K64) | AA64: =IF(R64="","",R64/$K64) | AB64: =IF(S64="","",S64/$K64) | AC64: =IF(T64="","",T64/$K64) | AD64: =IF(U64="","",U64/$K64)
A65: Jamara | B65: Haulage | C65: Lagos | D65: Abuja | E65: ABUJA>LAGOS | F65: Exact | G65: =IFERROR(INDEX('Turnaround Table'!$C$5:$C$231,MATCH(E65,'Turnaround Table'!$D$5:$D$231,0)),"") | I65: =IF(H65<>"",H65,IF(G65<>"",G65,'Truck Requirement'!$B$5)) | J65: =2*I65 | K65: =MAX(1,INT('Truck Requirement'!$B$4/J65)) | L65: =SUM(M65:U65) | M65: 6 | N65: 5 | O65: 3 | P65: 4 | Q65: 3 | R65: 5 | S65: 8 | T65: 7 | U65: 7 | V65: =IF(M65="","",M65/$K65) | W65: =IF(N65="","",N65/$K65) | X65: =IF(O65="","",O65/$K65) | Y65: =IF(P65="","",P65/$K65) | Z65: =IF(Q65="","",Q65/$K65) | AA65: =IF(R65="","",R65/$K65) | AB65: =IF(S65="","",S65/$K65) | AC65: =IF(T65="","",T65/$K65) | AD65: =IF(U65="","",U65/$K65)
A66: Jamara | B66: Haulage | C66: Lagos | D66: Kano | E66: KANO>LAGOS | F66: Exact | G66: =IFERROR(INDEX('Turnaround Table'!$C$5:$C$231,MATCH(E66,'Turnaround Table'!$D$5:$D$231,0)),"") | I66: =IF(H66<>"",H66,IF(G66<>"",G66,'Truck Requirement'!$B$5)) | J66: =2*I66 | K66: =MAX(1,INT('Truck Requirement'!$B$4/J66)) | L66: =SUM(M66:U66) | M66: 3 | N66: 5 | O66: 2 | P66: 3 | Q66: 2 | R66: 5 | S66: 5 | T66: 6 | U66: 5 | V66: =IF(M66="","",M66/$K66) | W66: =IF(N66="","",N66/$K66) | X66: =IF(O66="","",O66/$K66) | Y66: =IF(P66="","",P66/$K66) | Z66: =IF(Q66="","",Q66/$K66) | AA66: =IF(R66="","",R66/$K66) | AB66: =IF(S66="","",S66/$K66) | AC66: =IF(T66="","",T66/$K66) | AD66: =IF(U66="","",U66/$K66)
A67: Jamara | B67: Haulage | C67: Lagos | D67: Ibadan | E67: IBADAN>LAGOS | F67: Exact | G67: =IFERROR(INDEX('Turnaround Table'!$C$5:$C$231,MATCH(E67,'Turnaround Table'!$D$5:$D$231,0)),"") | I67: =IF(H67<>"",H67,IF(G67<>"",G67,'Truck Requirement'!$B$5)) | J67: =2*I67 | K67: =MAX(1,INT('Truck Requirement'!$B$4/J67)) | L67: =SUM(M67:U67) | M67: 6 | N67: 1 | O67: 5 | P67: 2 | Q67: 2 | R67: 2 | U67: 9 | V67: =IF(M67="","",M67/$K67) | W67: =IF(N67="","",N67/$K67) | X67: =IF(O67="","",O67/$K67) | Y67: =IF(P67="","",P67/$K67) | Z67: =IF(Q67="","",Q67/$K67) | AA67: =IF(R67="","",R67/$K67) | AB67: =IF(S67="","",S67/$K67) | AC67: =IF(T67="","",T67/$K67) | AD67: =IF(U67="","",U67/$K67)
A68: Jamara | B68: Haulage | C68: Lagos | D68: Isolo | E68: ISOLO>LAGOS | F68: Exact | G68: =IFERROR(INDEX('Turnaround Table'!$C$5:$C$231,MATCH(E68,'Turnaround Table'!$D$5:$D$231,0)),"") | I68: =IF(H68<>"",H68,IF(G68<>"",G68,'Truck Requirement'!$B$5)) | J68: =2*I68 | K68: =MAX(1,INT('Truck Requirement'!$B$4/J68)) | L68: =SUM(M68:U68) | M68: 1 | N68: 1 | O68: 3 | P68: 6 | Q68: 3 | R68: 1 | S68: 3 | V68: =IF(M68="","",M68/$K68) | W68: =IF(N68="","",N68/$K68) | X68: =IF(O68="","",O68/$K68) | Y68: =IF(P68="","",P68/$K68) | Z68: =IF(Q68="","",Q68/$K68) | AA68: =IF(R68="","",R68/$K68) | AB68: =IF(S68="","",S68/$K68) | AC68: =IF(T68="","",T68/$K68) | AD68: =IF(U68="","",U68/$K68)
A69: Jamara | B69: Haulage | C69: Lagos | D69: Ikotun | E69: IKM-SHAGARI-EGIGBO-IPAJA-AYOBO-OKOKOMAIKO-OSHODI-ISOLO>LAGOS | F69: Exact | G69: =IFERROR(INDEX('Turnaround Table'!$C$5:$C$231,MATCH(E69,'Turnaround Table'!$D$5:$D$231,0)),"") | I69: =IF(H69<>"",H69,IF(G69<>"",G69,'Truck Requirement'!$B$5)) | J69: =2*I69 | K69: =MAX(1,INT('Truck Requirement'!$B$4/J69)) | L69: =SUM(M69:U69) | S69: 6 | T69: 1 | U69: 10 | V69: =IF(M69="","",M69/$K69) | W69: =IF(N69="","",N69/$K69) | X69: =IF(O69="","",O69/$K69) | Y69: =IF(P69="","",P69/$K69) | Z69: =IF(Q69="","",Q69/$K69) | AA69: =IF(R69="","",R69/$K69) | AB69: =IF(S69="","",S69/$K69) | AC69: =IF(T69="","",T69/$K69) | AD69: =IF(U69="","",U69/$K69)
A70: Jamara | B70: Haulage | C70: Lagos | D70: Osogbo | E70: OSOGBO>LAGOS | F70: Exact | G70: =IFERROR(INDEX('Turnaround Table'!$C$5:$C$231,MATCH(E70,'Turnaround Table'!$D$5:$D$231,0)),"") | I70: =IF(H70<>"",H70,IF(G70<>"",G70,'Truck Requirement'!$B$5)) | J70: =2*I70 | K70: =MAX(1,INT('Truck Requirement'!$B$4/J70)) | L70: =SUM(M70:U70) | M70: 5 | N70: 1 | P70: 1 | Q70: 1 | R70: 1 | U70: 5 | V70: =IF(M70="","",M70/$K70) | W70: =IF(N70="","",N70/$K70) | X70: =IF(O70="","",O70/$K70) | Y70: =IF(P70="","",P70/$K70) | Z70: =IF(Q70="","",Q70/$K70) | AA70: =IF(R70="","",R70/$K70) | AB70: =IF(S70="","",S70/$K70) | AC70: =IF(T70="","",T70/$K70) | AD70: =IF(U70="","",U70/$K70)
A71: Jamara | B71: Haulage | C71: Lagos | D71: Benin | E71: BENIN>LAGOS | F71: Exact | G71: =IFERROR(INDEX('Turnaround Table'!$C$5:$C$231,MATCH(E71,'Turnaround Table'!$D$5:$D$231,0)),"") | I71: =IF(H71<>"",H71,IF(G71<>"",G71,'Truck Requirement'!$B$5)) | J71: =2*I71 | K71: =MAX(1,INT('Truck Requirement'!$B$4/J71)) | L71: =SUM(M71:U71) | M71: 3 | N71: 3 | O71: 1 | P71: 2 | R71: 1 | S71: 2 | T71: 1 | V71: =IF(M71="","",M71/$K71) | W71: =IF(N71="","",N71/$K71) | X71: =IF(O71="","",O71/$K71) | Y71: =IF(P71="","",P71/$K71) | Z71: =IF(Q71="","",Q71/$K71) | AA71: =IF(R71="","",R71/$K71) | AB71: =IF(S71="","",S71/$K71) | AC71: =IF(T71="","",T71/$K71) | AD71: =IF(U71="","",U71/$K71)
A72: Jamara | B72: Haulage | C72: Lagos | D72: Akure | E72: AKURE>LAGOS | F72: Exact | G72: =IFERROR(INDEX('Turnaround Table'!$C$5:$C$231,MATCH(E72,'Turnaround Table'!$D$5:$D$231,0)),"") | I72: =IF(H72<>"",H72,IF(G72<>"",G72,'Truck Requirement'!$B$5)) | J72: =2*I72 | K72: =MAX(1,INT('Truck Requirement'!$B$4/J72)) | L72: =SUM(M72:U72) | N72: 1 | P72: 1 | R72: 1 | T72: 1 | V72: =IF(M72="","",M72/$K72) | W72: =IF(N72="","",N72/$K72) | X72: =IF(O72="","",O72/$K72) | Y72: =IF(P72="","",P72/$K72) | Z72: =IF(Q72="","",Q72/$K72) | AA72: =IF(R72="","",R72/$K72) | AB72: =IF(S72="","",S72/$K72) | AC72: =IF(T72="","",T72/$K72) | AD72: =IF(U72="","",U72/$K72)
A73: Jamara | B73: Haulage | C73: Lagos | D73: Gbagada | E73: ILUPEJU-GBD-APAPA-MUSHIN-OKOTA-FADEYI>LAGOS | F73: Exact | G73: =IFERROR(INDEX('Turnaround Table'!$C$5:$C$231,MATCH(E73,'Turnaround Table'!$D$5:$D$231,0)),"") | I73: =IF(H73<>"",H73,IF(G73<>"",G73,'Truck Requirement'!$B$5)) | J73: =2*I73 | K73: =MAX(1,INT('Truck Requirement'!$B$4/J73)) | L73: =SUM(M73:U73) | U73: 3 | V73: =IF(M73="","",M73/$K73) | W73: =IF(N73="","",N73/$K73) | X73: =IF(O73="","",O73/$K73) | Y73: =IF(P73="","",P73/$K73) | Z73: =IF(Q73="","",Q73/$K73) | AA73: =IF(R73="","",R73/$K73) | AB73: =IF(S73="","",S73/$K73) | AC73: =IF(T73="","",T73/$K73) | AD73: =IF(U73="","",U73/$K73)
A74: Jamara | B74: Haulage | C74: Lagos | D74: Abeokuta | E74: ABEOKUTA>LAGOS | F74: Exact | G74: =IFERROR(INDEX('Turnaround Table'!$C$5:$C$231,MATCH(E74,'Turnaround Table'!$D$5:$D$231,0)),"") | I74: =IF(H74<>"",H74,IF(G74<>"",G74,'Truck Requirement'!$B$5)) | J74: =2*I74 | K74: =MAX(1,INT('Truck Requirement'!$B$4/J74)) | L74: =SUM(M74:U74) | S74: 1 | U74: 1 | V74: =IF(M74="","",M74/$K74) | W74: =IF(N74="","",N74/$K74) | X74: =IF(O74="","",O74/$K74) | Y74: =IF(P74="","",P74/$K74) | Z74: =IF(Q74="","",Q74/$K74) | AA74: =IF(R74="","",R74/$K74) | AB74: =IF(S74="","",S74/$K74) | AC74: =IF(T74="","",T74/$K74) | AD74: =IF(U74="","",U74/$K74)
A75: Jamara | B75: Haulage | C75: Lagos | D75: Ilorin | E75: ILORIN>LAGOS | F75: Exact | G75: =IFERROR(INDEX('Turnaround Table'!$C$5:$C$231,MATCH(E75,'Turnaround Table'!$D$5:$D$231,0)),"") | I75: =IF(H75<>"",H75,IF(G75<>"",G75,'Truck Requirement'!$B$5)) | J75: =2*I75 | K75: =MAX(1,INT('Truck Requirement'!$B$4/J75)) | L75: =SUM(M75:U75) | R75: 1 | U75: 1 | V75: =IF(M75="","",M75/$K75) | W75: =IF(N75="","",N75/$K75) | X75: =IF(O75="","",O75/$K75) | Y75: =IF(P75="","",P75/$K75) | Z75: =IF(Q75="","",Q75/$K75) | AA75: =IF(R75="","",R75/$K75) | AB75: =IF(S75="","",S75/$K75) | AC75: =IF(T75="","",T75/$K75) | AD75: =IF(U75="","",U75/$K75)
A76: Jamara | B76: Haulage | C76: Lagos | D76: Ilorin/Omu-Aran | E76: OMU-ARAN>LAGOS | F76: Exact | G76: =IFERROR(INDEX('Turnaround Table'!$C$5:$C$231,MATCH(E76,'Turnaround Table'!$D$5:$D$231,0)),"") | I76: =IF(H76<>"",H76,IF(G76<>"",G76,'Truck Requirement'!$B$5)) | J76: =2*I76 | K76: =MAX(1,INT('Truck Requirement'!$B$4/J76)) | L76: =SUM(M76:U76) | M76: 1 | O76: 1 | V76: =IF(M76="","",M76/$K76) | W76: =IF(N76="","",N76/$K76) | X76: =IF(O76="","",O76/$K76) | Y76: =IF(P76="","",P76/$K76) | Z76: =IF(Q76="","",Q76/$K76) | AA76: =IF(R76="","",R76/$K76) | AB76: =IF(S76="","",S76/$K76) | AC76: =IF(T76="","",T76/$K76) | AD76: =IF(U76="","",U76/$K76)
A77: Jamara | B77: Haulage | C77: Lagos | D77: Alaba | E77: ALABA>LAGOS | F77: Exact | G77: =IFERROR(INDEX('Turnaround Table'!$C$5:$C$231,MATCH(E77,'Turnaround Table'!$D$5:$D$231,0)),"") | I77: =IF(H77<>"",H77,IF(G77<>"",G77,'Truck Requirement'!$B$5)) | J77: =2*I77 | K77: =MAX(1,INT('Truck Requirement'!$B$4/J77)) | L77: =SUM(M77:U77) | N77: 1 | V77: =IF(M77="","",M77/$K77) | W77: =IF(N77="","",N77/$K77) | X77: =IF(O77="","",O77/$K77) | Y77: =IF(P77="","",P77/$K77) | Z77: =IF(Q77="","",Q77/$K77) | AA77: =IF(R77="","",R77/$K77) | AB77: =IF(S77="","",S77/$K77) | AC77: =IF(T77="","",T77/$K77) | AD77: =IF(U77="","",U77/$K77)
A78: Jamara | B78: Haulage | C78: Lagos | D78: Ilesha & Oshogbo | E78: OSOGBO>LAGOS | F78: Exact | G78: =IFERROR(INDEX('Turnaround Table'!$C$5:$C$231,MATCH(E78,'Turnaround Table'!$D$5:$D$231,0)),"") | I78: =IF(H78<>"",H78,IF(G78<>"",G78,'Truck Requirement'!$B$5)) | J78: =2*I78 | K78: =MAX(1,INT('Truck Requirement'!$B$4/J78)) | L78: =SUM(M78:U78) | R78: 1 | V78: =IF(M78="","",M78/$K78) | W78: =IF(N78="","",N78/$K78) | X78: =IF(O78="","",O78/$K78) | Y78: =IF(P78="","",P78/$K78) | Z78: =IF(Q78="","",Q78/$K78) | AA78: =IF(R78="","",R78/$K78) | AB78: =IF(S78="","",S78/$K78) | AC78: =IF(T78="","",T78/$K78) | AD78: =IF(U78="","",U78/$K78)
A79: Jamara | B79: Haulage | C79: Lagos | D79: Lafia | E79: LAFIA>LAGOS | F79: Exact | G79: =IFERROR(INDEX('Turnaround Table'!$C$5:$C$231,MATCH(E79,'Turnaround Table'!$D$5:$D$231,0)),"") | I79: =IF(H79<>"",H79,IF(G79<>"",G79,'Truck Requirement'!$B$5)) | J79: =2*I79 | K79: =MAX(1,INT('Truck Requirement'!$B$4/J79)) | L79: =SUM(M79:U79) | T79: 1 | V79: =IF(M79="","",M79/$K79) | W79: =IF(N79="","",N79/$K79) | X79: =IF(O79="","",O79/$K79) | Y79: =IF(P79="","",P79/$K79) | Z79: =IF(Q79="","",Q79/$K79) | AA79: =IF(R79="","",R79/$K79) | AB79: =IF(S79="","",S79/$K79) | AC79: =IF(T79="","",T79/$K79) | AD79: =IF(U79="","",U79/$K79)
A80: Jamara | B80: Haulage | C80: Lagos | D80: Minna | E80: MINNA>LAGOS | F80: Exact | G80: =IFERROR(INDEX('Turnaround Table'!$C$5:$C$231,MATCH(E80,'Turnaround Table'!$D$5:$D$231,0)),"") | I80: =IF(H80<>"",H80,IF(G80<>"",G80,'Truck Requirement'!$B$5)) | J80: =2*I80 | K80: =MAX(1,INT('Truck Requirement'!$B$4/J80)) | L80: =SUM(M80:U80) | T80: 1 | V80: =IF(M80="","",M80/$K80) | W80: =IF(N80="","",N80/$K80) | X80: =IF(O80="","",O80/$K80) | Y80: =IF(P80="","",P80/$K80) | Z80: =IF(Q80="","",Q80/$K80) | AA80: =IF(R80="","",R80/$K80) | AB80: =IF(S80="","",S80/$K80) | AC80: =IF(T80="","",T80/$K80) | AD80: =IF(U80="","",U80/$K80)
A81: Jamara | B81: Haulage | C81: Lagos | D81: Ondo | E81: ONDO>LAGOS | F81: Exact | G81: =IFERROR(INDEX('Turnaround Table'!$C$5:$C$231,MATCH(E81,'Turnaround Table'!$D$5:$D$231,0)),"") | I81: =IF(H81<>"",H81,IF(G81<>"",G81,'Truck Requirement'!$B$5)) | J81: =2*I81 | K81: =MAX(1,INT('Truck Requirement'!$B$4/J81)) | L81: =SUM(M81:U81) | M81: 1 | V81: =IF(M81="","",M81/$K81) | W81: =IF(N81="","",N81/$K81) | X81: =IF(O81="","",O81/$K81) | Y81: =IF(P81="","",P81/$K81) | Z81: =IF(Q81="","",Q81/$K81) | AA81: =IF(R81="","",R81/$K81) | AB81: =IF(S81="","",S81/$K81) | AC81: =IF(T81="","",T81/$K81) | AD81: =IF(U81="","",U81/$K81)
A82: Jamara | B82: Haulage | C82: Lagos | D82: Osun | E82: OSUN>LAGOS | F82: Exact | G82: =IFERROR(INDEX('Turnaround Table'!$C$5:$C$231,MATCH(E82,'Turnaround Table'!$D$5:$D$231,0)),"") | I82: =IF(H82<>"",H82,IF(G82<>"",G82,'Truck Requirement'!$B$5)) | J82: =2*I82 | K82: =MAX(1,INT('Truck Requirement'!$B$4/J82)) | L82: =SUM(M82:U82) | P82: 1 | V82: =IF(M82="","",M82/$K82) | W82: =IF(N82="","",N82/$K82) | X82: =IF(O82="","",O82/$K82) | Y82: =IF(P82="","",P82/$K82) | Z82: =IF(Q82="","",Q82/$K82) | AA82: =IF(R82="","",R82/$K82) | AB82: =IF(S82="","",S82/$K82) | AC82: =IF(T82="","",T82/$K82) | AD82: =IF(U82="","",U82/$K82)
A83: Jamara | B83: Haulage | C83: Lagos | D83: Owerri | E83: OWERRI>LAGOS | F83: Exact | G83: =IFERROR(INDEX('Turnaround Table'!$C$5:$C$231,MATCH(E83,'Turnaround Table'!$D$5:$D$231,0)),"") | I83: =IF(H83<>"",H83,IF(G83<>"",G83,'Truck Requirement'!$B$5)) | J83: =2*I83 | K83: =MAX(1,INT('Truck Requirement'!$B$4/J83)) | L83: =SUM(M83:U83) | T83: 1 | V83: =IF(M83="","",M83/$K83) | W83: =IF(N83="","",N83/$K83) | X83: =IF(O83="","",O83/$K83) | Y83: =IF(P83="","",P83/$K83) | Z83: =IF(Q83="","",Q83/$K83) | AA83: =IF(R83="","",R83/$K83) | AB83: =IF(S83="","",S83/$K83) | AC83: =IF(T83="","",T83/$K83) | AD83: =IF(U83="","",U83/$K83)
A84: KD & SONS | B84: Haulage | C84: Kaduna (Kudenda) | D84: Ibadan | E84: KADUNA>IBADAN | F84: Reverse | G84: =IFERROR(INDEX('Turnaround Table'!$C$5:$C$231,MATCH(E84,'Turnaround Table'!$D$5:$D$231,0)),"") | I84: =IF(H84<>"",H84,IF(G84<>"",G84,'Truck Requirement'!$B$5)) | J84: =2*I84 | K84: =MAX(1,INT('Truck Requirement'!$B$4/J84)) | L84: =SUM(M84:U84) | S84: 2 | V84: =IF(M84="","",M84/$K84) | W84: =IF(N84="","",N84/$K84) | X84: =IF(O84="","",O84/$K84) | Y84: =IF(P84="","",P84/$K84) | Z84: =IF(Q84="","",Q84/$K84) | AA84: =IF(R84="","",R84/$K84) | AB84: =IF(S84="","",S84/$K84) | AC84: =IF(T84="","",T84/$K84) | AD84: =IF(U84="","",U84/$K84)
A85: LEBRUNI AGRO LTD | B85: Haulage | C85: Lagos | D85: Ibadan | E85: IBADAN>LAGOS | F85: Exact | G85: =IFERROR(INDEX('Turnaround Table'!$C$5:$C$231,MATCH(E85,'Turnaround Table'!$D$5:$D$231,0)),"") | I85: =IF(H85<>"",H85,IF(G85<>"",G85,'Truck Requirement'!$B$5)) | J85: =2*I85 | K85: =MAX(1,INT('Truck Requirement'!$B$4/J85)) | L85: =SUM(M85:U85) | O85: 2 | U85: 1 | V85: =IF(M85="","",M85/$K85) | W85: =IF(N85="","",N85/$K85) | X85: =IF(O85="","",O85/$K85) | Y85: =IF(P85="","",P85/$K85) | Z85: =IF(Q85="","",Q85/$K85) | AA85: =IF(R85="","",R85/$K85) | AB85: =IF(S85="","",S85/$K85) | AC85: =IF(T85="","",T85/$K85) | AD85: =IF(U85="","",U85/$K85)
A86: LEBRUNI AGRO LTD | B86: Haulage | C86: Ibadan | D86: Abuja | E86: ABUJA>IBADAN | F86: Exact | G86: =IFERROR(INDEX('Turnaround Table'!$C$5:$C$231,MATCH(E86,'Turnaround Table'!$D$5:$D$231,0)),"") | I86: =IF(H86<>"",H86,IF(G86<>"",G86,'Truck Requirement'!$B$5)) | J86: =2*I86 | K86: =MAX(1,INT('Truck Requirement'!$B$4/J86)) | L86: =SUM(M86:U86) | U86: 2 | V86: =IF(M86="","",M86/$K86) | W86: =IF(N86="","",N86/$K86) | X86: =IF(O86="","",O86/$K86) | Y86: =IF(P86="","",P86/$K86) | Z86: =IF(Q86="","",Q86/$K86) | AA86: =IF(R86="","",R86/$K86) | AB86: =IF(S86="","",S86/$K86) | AC86: =IF(T86="","",T86/$K86) | AD86: =IF(U86="","",U86/$K86)
A87: LEBRUNI AGRO LTD | B87: Haulage | C87: Ibadan | D87: Warri | E87: WARRI>LAGOS | F87: Lagos bay used | G87: =IFERROR(INDEX('Turnaround Table'!$C$5:$C$231,MATCH(E87,'Turnaround Table'!$D$5:$D$231,0)),"") | I87: =IF(H87<>"",H87,IF(G87<>"",G87,'Truck Requirement'!$B$5)) | J87: =2*I87 | K87: =MAX(1,INT('Truck Requirement'!$B$4/J87)) | L87: =SUM(M87:U87) | U87: 2 | V87: =IF(M87="","",M87/$K87) | W87: =IF(N87="","",N87/$K87) | X87: =IF(O87="","",O87/$K87) | Y87: =IF(P87="","",P87/$K87) | Z87: =IF(Q87="","",Q87/$K87) | AA87: =IF(R87="","",R87/$K87) | AB87: =IF(S87="","",S87/$K87) | AC87: =IF(T87="","",T87/$K87) | AD87: =IF(U87="","",U87/$K87)
A88: LEBRUNI AGRO LTD | B88: Haulage | C88: Kano | D88: Ibadan | E88: KANO>IBADAN | F88: Reverse | G88: =IFERROR(INDEX('Turnaround Table'!$C$5:$C$231,MATCH(E88,'Turnaround Table'!$D$5:$D$231,0)),"") | I88: =IF(H88<>"",H88,IF(G88<>"",G88,'Truck Requirement'!$B$5)) | J88: =2*I88 | K88: =MAX(1,INT('Truck Requirement'!$B$4/J88)) | L88: =SUM(M88:U88) | P88: 1 | V88: =IF(M88="","",M88/$K88) | W88: =IF(N88="","",N88/$K88) | X88: =IF(O88="","",O88/$K88) | Y88: =IF(P88="","",P88/$K88) | Z88: =IF(Q88="","",Q88/$K88) | AA88: =IF(R88="","",R88/$K88) | AB88: =IF(S88="","",S88/$K88) | AC88: =IF(T88="","",T88/$K88) | AD88: =IF(U88="","",U88/$K88)
A89: Lacasera | B89: Haulage | C89: Lagos | D89: Mowe | E89: MOWE>LAGOS | F89: Exact | G89: =IFERROR(INDEX('Turnaround Table'!$C$5:$C$231,MATCH(E89,'Turnaround Table'!$D$5:$D$231,0)),"") | I89: =IF(H89<>"",H89,IF(G89<>"",G89,'Truck Requirement'!$B$5)) | J89: =2*I89 | K89: =MAX(1,INT('Truck Requirement'!$B$4/J89)) | L89: =SUM(M89:U89) | N89: 26 | O89: 11 | V89: =IF(M89="","",M89/$K89) | W89: =IF(N89="","",N89/$K89) | X89: =IF(O89="","",O89/$K89) | Y89: =IF(P89="","",P89/$K89) | Z89: =IF(Q89="","",Q89/$K89) | AA89: =IF(R89="","",R89/$K89) | AB89: =IF(S89="","",S89/$K89) | AC89: =IF(T89="","",T89/$K89) | AD89: =IF(U89="","",U89/$K89)
A90: Lacasera | B90: Haulage | C90: Lagos | D90: Benin | E90: BENIN>LAGOS | F90: Exact | G90: =IFERROR(INDEX('Turnaround Table'!$C$5:$C$231,MATCH(E90,'Turnaround Table'!$D$5:$D$231,0)),"") | I90: =IF(H90<>"",H90,IF(G90<>"",G90,'Truck Requirement'!$B$5)) | J90: =2*I90 | K90: =MAX(1,INT('Truck Requirement'!$B$4/J90)) | L90: =SUM(M90:U90) | N90: 15 | O90: 3 | T90: 2 | V90: =IF(M90="","",M90/$K90) | W90: =IF(N90="","",N90/$K90) | X90: =IF(O90="","",O90/$K90) | Y90: =IF(P90="","",P90/$K90) | Z90: =IF(Q90="","",Q90/$K90) | AA90: =IF(R90="","",R90/$K90) | AB90: =IF(S90="","",S90/$K90) | AC90: =IF(T90="","",T90/$K90) | AD90: =IF(U90="","",U90/$K90)
A91: Lacasera | B91: Haulage | C91: Lagos | D91: Lokoja | E91: LOKOJA>LAGOS | F91: Exact | G91: =IFERROR(INDEX('Turnaround Table'!$C$5:$C$231,MATCH(E91,'Turnaround Table'!$D$5:$D$231,0)),"") | I91: =IF(H91<>"",H91,IF(G91<>"",G91,'Truck Requirement'!$B$5)) | J91: =2*I91 | K91: =MAX(1,INT('Truck Requirement'!$B$4/J91)) | L91: =SUM(M91:U91) | Q91: 1 | R91: 2 | V91: =IF(M91="","",M91/$K91) | W91: =IF(N91="","",N91/$K91) | X91: =IF(O91="","",O91/$K91) | Y91: =IF(P91="","",P91/$K91) | Z91: =IF(Q91="","",Q91/$K91) | AA91: =IF(R91="","",R91/$K91) | AB91: =IF(S91="","",S91/$K91) | AC91: =IF(T91="","",T91/$K91) | AD91: =IF(U91="","",U91/$K91)
A92: Lacasera | B92: Haulage | C92: Lagos | D92: Onitsha | E92: ONITSHA>LAGOS | F92: Exact | G92: =IFERROR(INDEX('Turnaround Table'!$C$5:$C$231,MATCH(E92,'Turnaround Table'!$D$5:$D$231,0)),"") | I92: =IF(H92<>"",H92,IF(G92<>"",G92,'Truck Requirement'!$B$5)) | J92: =2*I92 | K92: =MAX(1,INT('Truck Requirement'!$B$4/J92)) | L92: =SUM(M92:U92) | T92: 1 | U92: 2 | V92: =IF(M92="","",M92/$K92) | W92: =IF(N92="","",N92/$K92) | X92: =IF(O92="","",O92/$K92) | Y92: =IF(P92="","",P92/$K92) | Z92: =IF(Q92="","",Q92/$K92) | AA92: =IF(R92="","",R92/$K92) | AB92: =IF(S92="","",S92/$K92) | AC92: =IF(T92="","",T92/$K92) | AD92: =IF(U92="","",U92/$K92)
A93: Lacasera | B93: Haulage | C93: Lagos | D93: Anyigba | E93: AYANGBA>LAGOS | F93: Exact | G93: =IFERROR(INDEX('Turnaround Table'!$C$5:$C$231,MATCH(E93,'Turnaround Table'!$D$5:$D$231,0)),"") | I93: =IF(H93<>"",H93,IF(G93<>"",G93,'Truck Requirement'!$B$5)) | J93: =2*I93 | K93: =MAX(1,INT('Truck Requirement'!$B$4/J93)) | L93: =SUM(M93:U93) | Q93: 2 | V93: =IF(M93="","",M93/$K93) | W93: =IF(N93="","",N93/$K93) | X93: =IF(O93="","",O93/$K93) | Y93: =IF(P93="","",P93/$K93) | Z93: =IF(Q93="","",Q93/$K93) | AA93: =IF(R93="","",R93/$K93) | AB93: =IF(S93="","",S93/$K93) | AC93: =IF(T93="","",T93/$K93) | AD93: =IF(U93="","",U93/$K93)
A94: Lacasera | B94: Haulage | C94: Lagos | D94: (Not Recorded) | F94: Not in table | G94: =IFERROR(INDEX('Turnaround Table'!$C$5:$C$231,MATCH(E94,'Turnaround Table'!$D$5:$D$231,0)),"") | I94: =IF(H94<>"",H94,IF(G94<>"",G94,'Truck Requirement'!$B$5)) | J94: =2*I94 | K94: =MAX(1,INT('Truck Requirement'!$B$4/J94)) | L94: =SUM(M94:U94) | U94: 1 | V94: =IF(M94="","",M94/$K94) | W94: =IF(N94="","",N94/$K94) | X94: =IF(O94="","",O94/$K94) | Y94: =IF(P94="","",P94/$K94) | Z94: =IF(Q94="","",Q94/$K94) | AA94: =IF(R94="","",R94/$K94) | AB94: =IF(S94="","",S94/$K94) | AC94: =IF(T94="","",T94/$K94) | AD94: =IF(U94="","",U94/$K94)
A95: Lacasera | B95: Haulage | C95: Lagos | D95: Abakaliki | E95: ABAKALIKI>LAGOS | F95: Exact | G95: =IFERROR(INDEX('Turnaround Table'!$C$5:$C$231,MATCH(E95,'Turnaround Table'!$D$5:$D$231,0)),"") | I95: =IF(H95<>"",H95,IF(G95<>"",G95,'Truck Requirement'!$B$5)) | J95: =2*I95 | K95: =MAX(1,INT('Truck Requirement'!$B$4/J95)) | L95: =SUM(M95:U95) | N95: 1 | V95: =IF(M95="","",M95/$K95) | W95: =IF(N95="","",N95/$K95) | X95: =IF(O95="","",O95/$K95) | Y95: =IF(P95="","",P95/$K95) | Z95: =IF(Q95="","",Q95/$K95) | AA95: =IF(R95="","",R95/$K95) | AB95: =IF(S95="","",S95/$K95) | AC95: =IF(T95="","",T95/$K95) | AD95: =IF(U95="","",U95/$K95)
A96: Lacasera | B96: Haulage | C96: Lagos | D96: Idah | E96: AYANGBA>LAGOS | F96: Exact | G96: =IFERROR(INDEX('Turnaround Table'!$C$5:$C$231,MATCH(E96,'Turnaround Table'!$D$5:$D$231,0)),"") | I96: =IF(H96<>"",H96,IF(G96<>"",G96,'Truck Requirement'!$B$5)) | J96: =2*I96 | K96: =MAX(1,INT('Truck Requirement'!$B$4/J96)) | L96: =SUM(M96:U96) | R96: 1 | V96: =IF(M96="","",M96/$K96) | W96: =IF(N96="","",N96/$K96) | X96: =IF(O96="","",O96/$K96) | Y96: =IF(P96="","",P96/$K96) | Z96: =IF(Q96="","",Q96/$K96) | AA96: =IF(R96="","",R96/$K96) | AB96: =IF(S96="","",S96/$K96) | AC96: =IF(T96="","",T96/$K96) | AD96: =IF(U96="","",U96/$K96)
A97: Lacasera | B97: Haulage | C97: Lagos | D97: Okene | E97: OKENE>LAGOS | F97: Exact | G97: =IFERROR(INDEX('Turnaround Table'!$C$5:$C$231,MATCH(E97,'Turnaround Table'!$D$5:$D$231,0)),"") | I97: =IF(H97<>"",H97,IF(G97<>"",G97,'Truck Requirement'!$B$5)) | J97: =2*I97 | K97: =MAX(1,INT('Truck Requirement'!$B$4/J97)) | L97: =SUM(M97:U97) | T97: 1 | V97: =IF(M97="","",M97/$K97) | W97: =IF(N97="","",N97/$K97) | X97: =IF(O97="","",O97/$K97) | Y97: =IF(P97="","",P97/$K97) | Z97: =IF(Q97="","",Q97/$K97) | AA97: =IF(R97="","",R97/$K97) | AB97: =IF(S97="","",S97/$K97) | AC97: =IF(T97="","",T97/$K97) | AD97: =IF(U97="","",U97/$K97)
A98: MAMUDA BEVERAGES CO. LTD | B98: Haulage | C98: Kano | D98: Ikeja | E98: KANO>LAGOS | F98: Reverse | G98: =IFERROR(INDEX('Turnaround Table'!$C$5:$C$231,MATCH(E98,'Turnaround Table'!$D$5:$D$231,0)),"") | I98: =IF(H98<>"",H98,IF(G98<>"",G98,'Truck Requirement'!$B$5)) | J98: =2*I98 | K98: =MAX(1,INT('Truck Requirement'!$B$4/J98)) | L98: =SUM(M98:U98) | N98: 2 | O98: 1 | P98: 4 | V98: =IF(M98="","",M98/$K98) | W98: =IF(N98="","",N98/$K98) | X98: =IF(O98="","",O98/$K98) | Y98: =IF(P98="","",P98/$K98) | Z98: =IF(Q98="","",Q98/$K98) | AA98: =IF(R98="","",R98/$K98) | AB98: =IF(S98="","",S98/$K98) | AC98: =IF(T98="","",T98/$K98) | AD98: =IF(U98="","",U98/$K98)
A99: MAMUDA BEVERAGES CO. LTD | B99: Haulage | C99: Lagos | D99: Ibadan | E99: IBADAN>LAGOS | F99: Exact | G99: =IFERROR(INDEX('Turnaround Table'!$C$5:$C$231,MATCH(E99,'Turnaround Table'!$D$5:$D$231,0)),"") | I99: =IF(H99<>"",H99,IF(G99<>"",G99,'Truck Requirement'!$B$5)) | J99: =2*I99 | K99: =MAX(1,INT('Truck Requirement'!$B$4/J99)) | L99: =SUM(M99:U99) | Q99: 5 | V99: =IF(M99="","",M99/$K99) | W99: =IF(N99="","",N99/$K99) | X99: =IF(O99="","",O99/$K99) | Y99: =IF(P99="","",P99/$K99) | Z99: =IF(Q99="","",Q99/$K99) | AA99: =IF(R99="","",R99/$K99) | AB99: =IF(S99="","",S99/$K99) | AC99: =IF(T99="","",T99/$K99) | AD99: =IF(U99="","",U99/$K99)
A100: MAMUDA BEVERAGES CO. LTD | B100: Haulage | C100: Lagos | D100: Lekki | E100: LEKKI>LAGOS | F100: Exact | G100: =IFERROR(INDEX('Turnaround Table'!$C$5:$C$231,MATCH(E100,'Turnaround Table'!$D$5:$D$231,0)),"") | I100: =IF(H100<>"",H100,IF(G100<>"",G100,'Truck Requirement'!$B$5)) | J100: =2*I100 | K100: =MAX(1,INT('Truck Requirement'!$B$4/J100)) | L100: =SUM(M100:U100) | P100: 1 | Q100: 2 | V100: =IF(M100="","",M100/$K100) | W100: =IF(N100="","",N100/$K100) | X100: =IF(O100="","",O100/$K100) | Y100: =IF(P100="","",P100/$K100) | Z100: =IF(Q100="","",Q100/$K100) | AA100: =IF(R100="","",R100/$K100) | AB100: =IF(S100="","",S100/$K100) | AC100: =IF(T100="","",T100/$K100) | AD100: =IF(U100="","",U100/$K100)
A101: MAMUDA BEVERAGES CO. LTD | B101: Haulage | C101: Kano | D101: Ibadan | E101: KANO>IBADAN | F101: Reverse | G101: =IFERROR(INDEX('Turnaround Table'!$C$5:$C$231,MATCH(E101,'Turnaround Table'!$D$5:$D$231,0)),"") | I101: =IF(H101<>"",H101,IF(G101<>"",G101,'Truck Requirement'!$B$5)) | J101: =2*I101 | K101: =MAX(1,INT('Truck Requirement'!$B$4/J101)) | L101: =SUM(M101:U101) | M101: 1 | V101: =IF(M101="","",M101/$K101) | W101: =IF(N101="","",N101/$K101) | X101: =IF(O101="","",O101/$K101) | Y101: =IF(P101="","",P101/$K101) | Z101: =IF(Q101="","",Q101/$K101) | AA101: =IF(R101="","",R101/$K101) | AB101: =IF(S101="","",S101/$K101) | AC101: =IF(T101="","",T101/$K101) | AD101: =IF(U101="","",U101/$K101)
...

Sheet Client List
A1: Clients (used by the Order Planner dropdowns). Add new clients in the blank rows.
A3: Client
A4: AB-INBEV
A5: ABBA ABASS
A6: B2B-ORCA DECO LIMITED (MR LEKAN)
A7: B2B-ORCA DECO LIMITED(MR OTEGA)
A8: B2B-ORCA DECO LIMITED(ULOMA)
A9: B2B-ORCA DECO LIMITED-AGR
A10: CRESEADA
A11: GIVANAS
A12: Illera Agro
A13: INTERSTYLE
... A32: WALTER & HIFY RESOURCES

Sheet Route Prices
A1: Route price reference — 2026 haulage trips (excl. VAT, one-off special jobs excluded)
A2: Used by the Revenue Planner to show the market rate next to your price. Each turnaround key is linked to the trip route it covers.
A4: Turnaround key | B4: Route in trip log | C4: Trips 2026 | D4: Avg price 2026 (₦) | E4: Trips Jul–Sep | F4: Avg price Jul–Sep (₦) | G4: Highest price Jul–Sep (₦)
A5: VI-LEKKI-AJAH>LAGOS | B5: Lagos → VI | C5: 276 | D5: 388532.61 | E5: 3 | F5: 495000 | G5: 685000
A6: KANO>LAGOS | B6: Lagos → Kano | C6: 147 | D6: 3849733 | E6: 59 | F6: 4022546.3 | G6: 4400000
A7: IBADAN>LAGOS | B7: Lagos → Ibadan | C7: 89 | D7: 629765.62 | E7: 33 | F7: 630904.97 | G7: 680000
A8: ABUJA>APAPA | B8: Lagos → Abuja | C8: 76 | D8: 2647226.6 | E8: 35 | F8: 2823202.7 | G8: 3162790.7
A9: ABUJA>LAGOS | B9: Lagos → Abuja | C9: 76 | D9: 2647226.6 | E9: 35 | F9: 2823202.7 | G9: 3162790.7
A10: PORT HARCOURT>LAGOS | B10: Lagos → PHC | C10: 68 | D10: 2359995.6 | E10: 31 | F10: 2470393.8 | G10: 2550000
A11: ONITSHA>LAGOS | B11: Lagos → Onitsha | C11: 39 | D11: 1896124.5 | E11: 14 | F11: 2035316.9 | G11: 2248843
A12: MOWE>LAGOS | B12: Lagos → Mowe | C12: 37 | D12: 245000
A13: BENIN>LAGOS | B13: Lagos → Benin | C13: 35 | D13: 1018630.6 | E13: 5 | F13: 1293825.6 | G13: 1634564
A14: LAFIA>LAGOS | B14: Nasarawa → Ogere | C14: 31 | D14: 1353278.3 | E14: 23 | F14: 1401334.7 | G14: 1534883.7
A15: ABA>IBADAN | B15: Ibadan → ABA | C15: 21 | D15: 2172268.3 | E15: 1 | F15: 3322166 | G15: 3322166
A16: ISOLO>LAGOS | B16: Lagos → Isolo | C16: 18 | D16: 406790.54 | E16: 3 | F16: 418000 | G16: 418000
A17: IBADAN>IBADAN | B17: Ibadan → Ibadan | C17: 18 | D17: 56020.585 | E17: 7 | F17: 47865.152 | G17: 130615.07
A18: IKM-SHAGARI-EGIGBO-IPAJA-AYOBO-OKOKOMAIKO-OSHODI-ISOLO>LAGOS | B18: Lagos → Ikotun | C18: 17 | D18: 431058.82 | E18: 17 | F18: 431058.82 | G18: 520000
A19: OSOGBO>LAGOS | B19: Lagos → Osogbo | C19: 15 | D19: 920911.38 | E19: 5 | F19: 1100000 | G19: 1100000
A20: ABUJA>IBADAN | B20: Ibadan → Abuja | C20: 13 | D20: 3228121.4 | E20: 4 | F20: 3161327.5 | G20: 3788400
A21: AKURE>LAGOS | B21: Ibadan → Akure | C21: 11 | D21: 906301.78 | E21: 4 | F21: 988131.43 | G21: 988131.43
A22: AUCHI>LAGOS | B22: Ibadan → Auchi | C22: 9 | D22: 2223151.5 | E22: 1 | F22: 2265887.6 | G22: 2265887.6
A23: LOKOJA>LAGOS | B23: Lagos → Lokoja | C23: 9 | D23: 2563503.9 | E23: 6 | F23: 3000000 | G23: 3000000
A24: KATSINA>LAGOS | B24: Lagos → Katsina | C24: 9 | D24: 3745736.4 | E24: 6 | F24: 3900000 | G24: 3900000
... A29: KEFFI>IBADAN | B29: Ibadan → Keffi | C29: 6 | D29: 2685028.2 | E29: 1 | F29: 2815839.1 | G29: 2815839.1
A30: YOLA>IBADAN | B30: Ilesa → Yola | C30: 6 | D30: 3466281.3
A31: KABBA>IBADAN | B31: Ibadan → Kabba | C31: 6 | D31: 1436622.6
A32: ONDO>LAGOS | B32: Ibadan → Ondo | C32: 5 | D32: 833962.48 | E32: 4 | F32: 846158.53 | G32: 1078994.1
A33: OFFA>LAGOS | B33: Ibadan → Ijagbo-Offa | C33: 5 | D33: 785334.58 | E33: 2 | F33: 806406.11 | G33: 806406.11
A34: IKEJA>LAGOS | B34: Ibadan → Lagos | C34: 5 | D34: 545359.32 | E34: 2 | F34: 831961.24 | G34: 868874.19
A35: AYANGBA>IBADAN | B35: Ibadan → Anyigba | C35: 4 | D35: 2385230.2
A36: ASABA>LAGOS | B36: Lagos → Asaba | C36: 4 | D36: 3136544.9
A37: IJEBU-ODE>LAGOS | B37: Ibadan → Ijebu ODE | C37: 4 | D37: 272750.1
A38: ABA>LAGOS | B38: Lagos → ABA | C38: 4 | D38: 2306395.3 | E38: 3 | F38: 2532558.1 | G38: 2900000
A39: MINNA>IBADAN | B39: Ibadan → Minna | C39: 4 | D39: 2628785.6 | E39: 3 | F39: 2675047.4 | G39: 2675047.4
A40: MAKURDI>IBADAN | B40: Ibadan → Otukpa | C40: 4 | D40: 1389914.8
A41: LEKKI>LAGOS | B41: Lagos → Lekki | C41: 4 | D41: 471220.93
A42: KADUNA>LAGOS | B42: Lagos → Kaduna | C42: 4 | D42: 3831976.7 | E42: 3 | F42: 3806976.7 | G42: 3850000
A43: OWERRI>LAGOS | B43: Lagos → Owerri | C43: 4 | D43: 2340104.7 | E43: 4 | F43: 2340104.7 | G43: 2900000
A44: WARRI>LAGOS | B44: Ibadan → Warri | C44: 4 | D44: 2078741.6 | E44: 2 | F44: 2079000 | G44: 2310000
A45: OGBA>LAGOS | B45: Ibadan → Ogba | C45: 4 | D45: 725074.57
A46: ONITSHA>IBADAN | B46: Ibadan → Onitsha | C46: 4 | D46: 2084453.1
A47: JOS>IBADAN | B47: Ibadan → JOS | C47: 4 | D47: 4793250
A48: MAIDUGURI>IBADAN | B48: Ilesa → Maiduguri | C48: 4 | D48: 3660172.8
A49: SAKI>LAGOS | B49: Ibadan → Saki | C49: 3 | D49: 1120500
A50: KANO>IBADAN | B50: Ibadan → Kano | C50: 3 | D50: 3441860.5 | E50: 3 | F50: 3441860.5 | G50: 3441860.5
A51: OYO>LAGOS | B51: Ibadan → OYO | C51: 3 | D51: 303171.58
A52: SOKOTO>IBADAN | B52: Ibadan → Sokoto | C52: 3 | D52: 3472134.9 | E52: 3 | F52: 3472134.9 | G52: 3660590.8
A53: JALINGO>IBADAN | B53: Ibadan → Jalingo | C53: 3 | D53: 4827199.4 | E53: 2 | F53: 4930232.6 | G53: 4930232.6
A54: FUNTUA>LAGOS | B54: Lagos → Funtua | C54: 3 | D54: 3833410.9 | E54: 1 | F54: 4170000 | G54: 4170000
A55: GOMBE>IBADAN | B55: Ilesa → Gombe | C55: 3 | D55: 2928719.6
A56: ABAKALIKI>LAGOS | B56: Ibadan → Abakaliki | C56: 3 | D56: 2218801.5
A57: BAUCHI>IBADAN | B57: Ilesa → Bauchi | C57: 3 | D57: 2676660.7
A58: CALABAR>LAGOS | B58: Ibadan → Calabar | C58: 3 | D58: 3871717.2
A59: ENUGU>LAGOS | B59: AMA → OTA | C59: 3 | D59: 1556023.1
A60: SAGAMU>LAGOS | B60: Lagos → Sagamu | C60: 3 | D60: 588139.53 | E60: 3 | F60: 588139.53 | G60: 650000
A61: OGUN>LAGOS | B61: Ibadan → Idiroko | C61: 3 | D61: 1042594.4 | E61: 1 | F61: 1135783.3 | G61: 1135783.3
A62: UROMI>LAGOS | B62: Ibadan → Ekpoma | C62: 3 | D62: 1565362.2
A63: IKEJA-AGEGE-DOPEMU-MAGODO>LAGOS | B63: Ibadan → Shasha | C63: 3 | D63: 697200
A64: ILE-IFE>LAGOS | B64: Ibadan → Ile-Ife | C64: 2 | D64: 389050.44
A65: ADO-EKITI>LAGOS | B65: Ijebu ODE → Ado-Ekiti | C65: 2 | D65: 1517587.8
A66: LAFIA>IBADAN | B66: Ibadan → Lafia | C66: 2 | D66: 2956618.5 | E66: 1 | F66: 3097423 | G66: 3097423
A67: FESTAC-MILE2 --AMOWO-OKOTA>LAGOS | B67: Ibadan → Festac | C67: 2 | D67: 737040
A68: AYANGBA>LAGOS | B68: Lagos → Anyigba | C68: 2 | D68: 1790139.5
A69: ABEOKUTA>LAGOS | B69: Ibadan → Abeokuta | C69: 2 | D69: 538828.14
A70: GBOKO>LAGOS | B70: Ijebu ODE → Gboko | C70: 2 | D70: 3440091.4
A71: SHENDAM>LAGOS | B71: Ilesa → Shendam | C71: 2 | D71: 2139098.9
A72: UMUAHIA>LAGOS | B72: Ibadan → Okigwe | C72: 2 | D72: 1552715.4
A73: OMU-ARAN>LAGOS | B73: Lagos → Ilorin/Omu-Aran | C73: 2 | D73: 1153098.6
A74: SANGO OTTA>LAGOS | B74: Ibadan → Sango | C74: 2 | D74: 74700
A75: UYO>LAGOS | B75: Lagos → UYO | C75: 2 | D75: 2232558.1 | E75: 2 | F75: 2232558.1 | G75: 2232558.1
A76: GBOKO>IBADAN | B76: Ilesa → Gboko | C76: 1 | D76: 1615591.9
A77: IFON>LAGOS | B77: Ibadan → Ifon Osun | C77: 1 | D77: 559373.25
A78: AWKA>LAGOS | B78: Lagos → Anambra | C78: 1 | D78: 2500000 | E78: 1 | F78: 2500000 | G78: 2500000
A79: AGBARA-BADAGRI>LAGOS | B79: Ibadan → Badagry | C79: 1 | D79: 1147141.1
A80: ADIKPO>LAGOS | B80: Ibadan → Adikpo/Gboko | C80: 1 | D80: 4332600
A81: BIDA>IBADAN | B81: Ibadan → Bida | C81: 1 | D81: 1759899.5 | E81: 1 | F81: 1759899.5 | G81: 1759899.5
A82: AGBARA>LAGOS | B82: Ibadan → Agbara | C82: 1 | D82: 199200
A83: ALABA>LAGOS | B83: Lagos → Alaba | C83: 1 | D83: 385000
A84: AJAO ESTATE>LAGOS | B84: Lagos → Ajao Estate | C84: 1 | D84: 485000 | E84: 1 | F84: 485000 | G84: 485000
A85: APAPA>LAGOS | B85: Lagos → Kirikiri | C85: 1 | D85: 790697.67 | E85: 1 | F85: 790697.67 | G85: 790697.67
A86: ILESA>LAGOS | B86: Ibadan → Ilesa | C86: 1 | D86: 576410
A87: MINNA>LAGOS | B87: Lagos → Minna | C87: 1 | D87: 2500000 | E87: 1 | F87: 2500000 | G87: 2500000
A88: MARABA>LAGOS | B88: Ibadan → Mararaba | C88: 1 | D88: 3046938.1
A89: MAIDUGURI>LAGOS | B89: Lagos → Maiduguri | C89: 1 | D89: 6000000 | E89: 1 | F89: 6000000 | G89: 6000000
A90: MAKURDI>LAGOS | B90: Ijebu ODE → Makurdi | C90: 1 | D90: 2007496.9
A91: KONTAGORA>LAGOS | B91: Ibadan → Kotangora | C91: 1 | D91: 2534254.9
A92: ISEYIN>LAGOS | B92: Ibadan → Igboora | C92: 1 | D92: 1044783.3
A93: IKARE>LAGOS | B93: Ibadan → Ikare Akoko | C93: 1 | D93: 1294800
A94: OKENE>LAGOS | B94: Lagos → Okene | C94: 1 | D94: 2453579 | E94: 1 | F94: 2453579 | G94: 2453579
A95: OTUKPO>IBADAN | B95: Otukpa → Ibadan | C95: 1 | D95: 900108.23
A96: OSUN>LAGOS | B96: Lagos → Osun | C96: 1 | D96: 650000
A97: ORON>LAGOS | B97: Ibadan → Oron | C97: 1 | D97: 4162645.6 | E97: 1 | F97: 4162645.6 | G97: 4162645.6
A98: ORE>LAGOS | B98: Ibadan → ORE | C98: 1 | D98: 946200
A99: NSUKKA>LAGOS | B99: Ibadan → Nsukka / Orba | C99: 1 | D99: 3339202.8
A100: OBUBRA>LAGOS | B100: Ibadan → Afikpo | C100: 1 | D100: 1837129.4
A101: OGBOMOSHO>LAGOS | B101: Ibadan → Ogbomosho | C101: 1 | D101: 616162.42
A102: ZARIA>IBADAN | B102: Ibadan → Zaria | C102: 1 | D102: 2956631 | E102: 1 | F102: 2956631 | G102: 2956631
A103: ILUPEJU-GBD-APAPA-MUSHIN-OKOTA-FADEYI>LAGOS | B103: Lagos → Gbagada
