Workbook
Name \0: #REF!
Name \X: #REF!
Name _311_H: #REF!
Name _BOM2: #REF!
Name _COL1: #REF!
Name _DAT1: #REF!
Name _DAT2: #REF!
Name _DAT3: #REF!
Name _DAT4: #REF!
Name _DAT5: #REF!
Name _DAT6: #REF!
Name _DAT7: #REF!
Name _DAT8: #REF!
Name _DAT9: #REF!
Name _hdr1: #REF!
Name _hdr2: #REF!
Name _hdr22: #REF!
Name _MAK1: #REF!
Name _MAK2: #REF!
Name _MAK3: #REF!
Name _MAK4: #REF!
Name _ONE1: #REF!
Name _ROW1: #REF!
Name _SIX1: #REF!
Name _TEN1: #REF!
Name _TWO1: #REF!
Name ○: #REF!
Name a: #REF!
Name A11A: #REF!
Name A11B: #REF!
Name A12A: #REF!
Name A12B: #REF!
Name A13A: #REF!
Name A13B: #REF!
Name A14A: #REF!
Name A14B: #REF!
Name A15A: #REF!
Name A15B: #REF!
Name A16A: #REF!
Name A16B: #REF!
Name A17A: #REF!
Name A17B: #REF!
Name A18A: #REF!
Name A18B: #REF!
Name A19A: #REF!
Name A19B: #REF!
Name A20A: #REF!
Name A20B: #REF!
Name A21A: #REF!
Name A21B: #REF!
Name A22A: #REF!
Name A22B: #REF!
Name A23A: #REF!
Name A23B: #REF!
Name A24A: #REF!
Name A24B: #REF!
Name A25A: #REF!
Name A25B: #REF!
Name AA: #REF!
Name aaaa: #REF!

Sheet Asset Code
A1: Asset code | B1: Plate Number | C1: Asset Name | D1: Tonnage | E1: Body Size | F1: Type | G1: Cost Center | H1: Cost Center Name
A2: MVEH-000266 | B2: T2404LA | C2: Volswagen Titan Tractor 18-310 Head | D2: 25T | E2: FLAT | F2: Tractor Head | G2: =_xlfn.XLOOKUP(A2,'[3]Budgets 2027'!I$3:I$759,'[3]Budgets 2027'!Q$3:Q$759) -> CC046 | H2: =_xlfn.XLOOKUP(A2,'[3]Budgets 2027'!I$3:I$759,'[3]Budgets 2027'!R$3:R$759) -> Flat Trucks Logistics
A3: MVEH-000267 | B3: T2486LA | C3: Volswagen Titan Tractor 18-310 Head | D3: 25T | E3: FLAT | F3: Tractor Head | G3: =_xlfn.XLOOKUP(A3,'[3]Budgets 2027'!I$3:I$759,'[3]Budgets 2027'!Q$3:Q$759) -> CC046 | H3: =_xlfn.XLOOKUP(A3,'[3]Budgets 2027'!I$3:I$759,'[3]Budgets 2027'!R$3:R$759) -> Flat Trucks Logistics
A4: MVEH-000269 | B4: T2490LA | C4: Volswagen Titan Tractor 18-310 Head | D4: 25T | E4: FLAT | F4: Tractor Head | G4: =_xlfn.XLOOKUP(A4,'[3]Budgets 2027'!I$3:I$759,'[3]Budgets 2027'!Q$3:Q$759) -> CC046 | H4: =_xlfn.XLOOKUP(A4,'[3]Budgets 2027'!I$3:I$759,'[3]Budgets 2027'!R$3:R$759) -> Flat Trucks Logistics
A5: MVEH-000271 | B5: T2407LA | C5: Volswagen Titan Tractor 18-310 Head | D5: 25T | E5: FLAT | F5: Tractor Head | G5: =_xlfn.XLOOKUP(A5,'[3]Budgets 2027'!I$3:I$759,'[3]Budgets 2027'!Q$3:Q$759) -> CC046 | H5: =_xlfn.XLOOKUP(A5,'[3]Budgets 2027'!I$3:I$759,'[3]Budgets 2027'!R$3:R$759) -> Flat Trucks Logistics
A6: MVEH-000273 | B6: T2485LA | C6: Volswagen Titan Tractor 18-310 Head | D6: 30T | E6: FLAT | F6: Tractor Head | G6: =_xlfn.XLOOKUP(A6,'[3]Budgets 2027'!I$3:I$759,'[3]Budgets 2027'!Q$3:Q$759) -> CC046 | H6: =_xlfn.XLOOKUP(A6,'[3]Budgets 2027'!I$3:I$759,'[3]Budgets 2027'!R$3:R$759) -> Flat Trucks Logistics
A7: MVEH-000276 | B7: T2412LA | C7: Volswagen Titan Tractor 18-310 Head | D7: 25T | E7: FLAT | F7: Tractor Head | G7: =_xlfn.XLOOKUP(A7,'[3]Budgets 2027'!I$3:I$759,'[3]Budgets 2027'!Q$3:Q$759) -> CC046 | H7: =_xlfn.XLOOKUP(A7,'[3]Budgets 2027'!I$3:I$759,'[3]Budgets 2027'!R$3:R$759) -> Flat Trucks Logistics
A8: MVEH-000283 | B8: T2420LA | C8: Volswagen Titan Tractor 18-310 Head | D8: 25T | E8: FLAT | F8: Tractor Head | G8: =_xlfn.XLOOKUP(A8,'[3]Budgets 2027'!I$3:I$759,'[3]Budgets 2027'!Q$3:Q$759) -> CC046 | H8: =_xlfn.XLOOKUP(A8,'[3]Budgets 2027'!I$3:I$759,'[3]Budgets 2027'!R$3:R$759) -> Flat Trucks Logistics
A9: MVEH-000326 | B9: EPE531YD | C9: Mercedes Benz Diesel Truck | D9: 15T | E9: TANKER | F9: Tractor Head | G9: =_xlfn.XLOOKUP(A9,'[3]Budgets 2027'!I$3:I$759,'[3]Budgets 2027'!Q$3:Q$759) -> CC037 | H9: =_xlfn.XLOOKUP(A9,'[3]Budgets 2027'!I$3:I$759,'[3]Budgets 2027'!R$3:R$759) -> General Overhead
A10: MVEH-000130 | B10: T2418LA | C10: Volswagen Titan Tractor 18-310 Head | D10: 25T | E10: FLAT | F10: Tractor Head | G10: =_xlfn.XLOOKUP(A10,'[3]Budgets 2027'!I$3:I$759,'[3]Budgets 2027'!Q$3:Q$759) -> CC046 | H10: =_xlfn.XLOOKUP(A10,'[3]Budgets 2027'!I$3:I$759,'[3]Budgets 2027'!R$3:R$759) -> Flat Trucks Logistics
A11: MVEH-000131 | B11: T2489LA | C11: Volswagen Titan Tractor 18-310 Head | D11: 25T | E11: FLAT | F11: Tractor Head | G11: =_xlfn.XLOOKUP(A11,'[3]Budgets 2027'!I$3:I$759,'[3]Budgets 2027'!Q$3:Q$759) -> CC046 | H11: =_xlfn.XLOOKUP(A11,'[3]Budgets 2027'!I$3:I$759,'[3]Budgets 2027'!R$3:R$759) -> Flat Trucks Logistics
A12: MVEH-000132 | B12: T2421LA | C12: Volswagen Titan Tractor 18-310 Head | D12: 25T | E12: FLAT | F12: Tractor Head | G12: =_xlfn.XLOOKUP(A12,'[3]Budgets 2027'!I$3:I$759,'[3]Budgets 2027'!Q$3:Q$759) -> CC046 | H12: =_xlfn.XLOOKUP(A12,'[3]Budgets 2027'!I$3:I$759,'[3]Budgets 2027'!R$3:R$759) -> Flat Trucks Logistics
A13: MVEH-000142 | B13: T2419LA | C13: Volswagen Titan Tractor 18-310 | D13: 25T | E13: FLAT | F13: Tractor Head | G13: =_xlfn.XLOOKUP(A13,'[3]Budgets 2027'!I$3:I$759,'[3]Budgets 2027'!Q$3:Q$759) -> CC046 | H13: =_xlfn.XLOOKUP(A13,'[3]Budgets 2027'!I$3:I$759,'[3]Budgets 2027'!R$3:R$759) -> Flat Trucks Logistics
... A68: MVEH-000146 | B68: T2413LA | C68: T 2413 LA 4*2Cargo Truck | D68: 8T | E68: 25FT | F68: Canter | G68: =_xlfn.XLOOKUP(A68,'[3]Budgets 2027'!I$3:I$759,'[3]Budgets 2027'!Q$3:Q$759) -> CC047 | H68: =_xlfn.XLOOKUP(A68,'[3]Budgets 2027'!I$3:I$759,'[3]Budgets 2027'!R$3:R$759) -> Closed Body Logistics
A69: MVEH-000134 | B69: 0 | C69: Flat Trailer single Axel - 30T | D69: =_xlfn.XLOOKUP(A69,'[4]Fleet Master'!D$3:D$52,'[4]Fleet Master'!F$3:F$52) -> 30T | E69: 102-45T | F69: BOX BODY | G69: =_xlfn.XLOOKUP(A69,'[3]Budgets 2027'!I$3:I$759,'[3]Budgets 2027'!Q$3:Q$759) -> CC046 | H69: =_xlfn.XLOOKUP(A69,'[3]Budgets 2027'!I$3:I$759,'[3]Budgets 2027'!R$3:R$759) -> Flat Trucks Logistics
A70: MVEH-000135 | B70: 0 | C70: Flat Trailer single Axel - 30T (double not yet acquired) | D70: =_xlfn.XLOOKUP(A70,'[4]Fleet Master'!D$3:D$52,'[4]Fleet Master'!F$3:F$52) -> 30T | E70: 102-30T | F70: BOX BODY | G70: =_xlfn.XLOOKUP(A70,'[3]Budgets 2027'!I$3:I$759,'[3]Budgets 2027'!Q$3:Q$759) -> CC046 | H70: =_xlfn.XLOOKUP(A70,'[3]Budgets 2027'!I$3:I$759,'[3]Budgets 2027'!R$3:R$759) -> Flat Trucks Logistics
A71: MVEH-000265 | B71: 0 | C71: FLAT TRAILER SINGLE AXEL-30T | D71: 30T | E71: FLAT | F71: Flat Trailer | G71: =_xlfn.XLOOKUP(A71,'[3]Budgets 2027'!I$3:I$759,'[3]Budgets 2027'!Q$3:Q$759) -> CC046 | H71: =_xlfn.XLOOKUP(A71,'[3]Budgets 2027'!I$3:I$759,'[3]Budgets 2027'!R$3:R$759) -> Flat Trucks Logistics
A72: MVEH-000268 | B72: 0 | C72: Flat Trailer single Axel - 30T | D72: 30T | E72: FLAT | F72: Flat Trailer | G72: =_xlfn.XLOOKUP(A72,'[3]Budgets 2027'!I$3:I$759,'[3]Budgets 2027'!Q$3:Q$759) -> CC046 | H72: =_xlfn.XLOOKUP(A72,'[3]Budgets 2027'!I$3:I$759,'[3]Budgets 2027'!R$3:R$759) -> Flat Trucks Logistics
A73: MVEH-000279 | B73: 0 | C73: Flat Trailer single Axel - 30T | D73: =_xlfn.XLOOKUP(A73,'[4]Fleet Master'!D$3:D$52,'[4]Fleet Master'!F$3:F$52) -> 30T | E73: FLAT | F73: Flat Trailer | G73: =_xlfn.XLOOKUP(A73,'[3]Budgets 2027'!I$3:I$759,'[3]Budgets 2027'!Q$3:Q$759) -> CC046 | H73: =_xlfn.XLOOKUP(A73,'[3]Budgets 2027'!I$3:I$759,'[3]Budgets 2027'!R$3:R$759) -> Flat Trucks Logistics
A74: MVEH-000292 | B74: 0 | C74: FLAT TRAILER SINGLE AXEL-30T | D74: =_xlfn.XLOOKUP(A74,'[4]Fleet Master'!D$3:D$52,'[4]Fleet Master'!F$3:F$52) -> 30T | E74: FLAT | F74: Flat Trailer | G74: =_xlfn.XLOOKUP(A74,'[3]Budgets 2027'!I$3:I$759,'[3]Budgets 2027'!Q$3:Q$759) -> CC046 | H74: =_xlfn.XLOOKUP(A74,'[3]Budgets 2027'!I$3:I$759,'[3]Budgets 2027'!R$3:R$759) -> Flat Trucks Logistics
A75: MVEH-000293 | B75: 0 | C75: FLAT TRAILER SINGLE AXEL-30T | D75: =_xlfn.XLOOKUP(A75,'[4]Fleet Master'!D$3:D$52,'[4]Fleet Master'!F$3:F$52) -> 30T | E75: 102-30T | F75: BOX BODY | G75: =_xlfn.XLOOKUP(A75,'[3]Budgets 2027'!I$3:I$759,'[3]Budgets 2027'!Q$3:Q$759) -> CC046 | H75: =_xlfn.XLOOKUP(A75,'[3]Budgets 2027'!I$3:I$759,'[3]Budgets 2027'!R$3:R$759) -> Flat Trucks Logistics
A76: MVEH-000303 | B76: 0 | C76: Flat Trailer single Axel - 30T | D76: =_xlfn.XLOOKUP(A76,'[4]Fleet Master'!D$3:D$52,'[4]Fleet Master'!F$3:F$52) -> 30T | E76: 102-45T | F76: BOX BODY | G76: =_xlfn.XLOOKUP(A76,'[3]Budgets 2027'!I$3:I$759,'[3]Budgets 2027'!Q$3:Q$759) -> CC046 | H76: =_xlfn.XLOOKUP(A76,'[3]Budgets 2027'!I$3:I$759,'[3]Budgets 2027'!R$3:R$759) -> Flat Trucks Logistics
A77: MVEH-000362 | B77: 0 | C77: Flat Trailer single Axel - 30T | D77: =_xlfn.XLOOKUP(A77,'[4]Fleet Master'!D$3:D$52,'[4]Fleet Master'!F$3:F$52) -> 30T | E77: FLAT | F77: Flat Trailer | G77: =_xlfn.XLOOKUP(A77,'[3]Budgets 2027'!I$3:I$759,'[3]Budgets 2027'!Q$3:Q$759) -> CC046 | H77: =_xlfn.XLOOKUP(A77,'[3]Budgets 2027'!I$3:I$759,'[3]Budgets 2027'!R$3:R$759) -> Flat Trucks Logistics
A78: MVEH-000133 | B78: 0 | C78: Flat Trailer single Axel - 30T | D78: =_xlfn.XLOOKUP(A78,'[4]Fleet Master'!D$3:D$52,'[4]Fleet Master'!F$3:F$52) -> 30T | E78: 102-30T | F78: BOX BODY | G78: =_xlfn.XLOOKUP(A78,'[3]Budgets 2027'!I$3:I$759,'[3]Budgets 2027'!Q$3:Q$759) -> CC046 | H78: =_xlfn.XLOOKUP(A78,'[3]Budgets 2027'!I$3:I$759,'[3]Budgets 2027'!R$3:R$759) -> Flat Trucks Logistics
A79: MVEH-000138 | B79: 0 | C79: Flat Trailer single Axel - 30T | D79: =_xlfn.XLOOKUP(A79,'[4]Fleet Master'!D$3:D$52,'[4]Fleet Master'!F$3:F$52) -> 30T | E79: FLAT | F79: Flat Trailer | G79: =_xlfn.XLOOKUP(A79,'[3]Budgets 2027'!I$3:I$759,'[3]Budgets 2027'!Q$3:Q$759) -> CC046 | H79: =_xlfn.XLOOKUP(A79,'[3]Budgets 2027'!I$3:I$759,'[3]Budgets 2027'!R$3:R$759) -> Flat Trucks Logistics
A80: MVEH-000139 | B80: 0 | C80: Flat Trailer single Axel - 30T (double not yet acquired) | D80: =_xlfn.XLOOKUP(A80,'[4]Fleet Master'!D$3:D$52,'[4]Fleet Master'!F$3:F$52) -> 30T | E80: FLAT | F80: Flat Trailer | G80: =_xlfn.XLOOKUP(A80,'[3]Budgets 2027'!I$3:I$759,'[3]Budgets 2027'!Q$3:Q$759) -> CC046 | H80: =_xlfn.XLOOKUP(A80,'[3]Budgets 2027'!I$3:I$759,'[3]Budgets 2027'!R$3:R$759) -> Flat Trucks Logistics
A81: MVEH-000140 | B81: 0 | C81: Flat Trailer single Axel - 30T | D81: =_xlfn.XLOOKUP(A81,'[4]Fleet Master'!D$3:D$52,'[4]Fleet Master'!F$3:F$52) -> 35T | E81: 102-30T | F81: BOX BODY | G81: =_xlfn.XLOOKUP(A81,'[3]Budgets 2027'!I$3:I$759,'[3]Budgets 2027'!Q$3:Q$759) -> CC046 | H81: =_xlfn.XLOOKUP(A81,'[3]Budgets 2027'!I$3:I$759,'[3]Budgets 2027'!R$3:R$759) -> Flat Trucks Logistics
A82: MVEH-000270 | B82: 0 | C82: Flat Trailer single Axel - 30T | D82: =_xlfn.XLOOKUP(A82,'[4]Fleet Master'!D$3:D$52,'[4]Fleet Master'!F$3:F$52) -> 30T | E82: FLAT | F82: Flat Trailer | G82: =_xlfn.XLOOKUP(A82,'[3]Budgets 2027'!I$3:I$759,'[3]Budgets 2027'!Q$3:Q$759) -> CC046 | H82: =_xlfn.XLOOKUP(A82,'[3]Budgets 2027'!I$3:I$759,'[3]Budgets 2027'!R$3:R$759) -> Flat Trucks Logistics
A83: MVEH-000272 | B83: 0 | C83: Flat Trailer single Axel - 30T | D83: 30T | E83: FLAT | F83: Flat Trailer | G83: =_xlfn.XLOOKUP(A83,'[3]Budgets 2027'!I$3:I$759,'[3]Budgets 2027'!Q$3:Q$759) -> CC046 | H83: =_xlfn.XLOOKUP(A83,'[3]Budgets 2027'!I$3:I$759,'[3]Budgets 2027'!R$3:R$759) -> Flat Trucks Logistics
A84: MVEH-000277 | B84: 0 | C84: Flat Trailer single Axel - 30T | D84: =_xlfn.XLOOKUP(A84,'[4]Fleet Master'!D$3:D$52,'[4]Fleet Master'!F$3:F$52) -> 35T | E84: 102-45T | F84: BOX BODY | G84: =_xlfn.XLOOKUP(A84,'[3]Budgets 2027'!I$3:I$759,'[3]Budgets 2027'!Q$3:Q$759) -> CC046 | H84: =_xlfn.XLOOKUP(A84,'[3]Budgets 2027'!I$3:I$759,'[3]Budgets 2027'!R$3:R$759) -> Flat Trucks Logistics
A85: MVEH-000290 | B85: 0 | C85: IPI FLAT TRAILER SINGLE AXEL-30T | D85: =_xlfn.XLOOKUP(A85,'[4]Fleet Master'!D$3:D$52,'[4]Fleet Master'!F$3:F$52) -> 30T | E85: FLAT | F85: Flat Trailer | G85: =_xlfn.XLOOKUP(A85,'[3]Budgets 2027'!I$3:I$759,'[3]Budgets 2027'!Q$3:Q$759) -> CC046 | H85: =_xlfn.XLOOKUP(A85,'[3]Budgets 2027'!I$3:I$759,'[3]Budgets 2027'!R$3:R$759) -> Flat Trucks Logistics
A86: MVEH-000302 | B86: 0 | C86: Flat Trailer single Axel - 30T | D86: 30T | E86: FLAT | F86: Flat Trailer | G86: =_xlfn.XLOOKUP(A86,'[3]Budgets 2027'!I$3:I$759,'[3]Budgets 2027'!Q$3:Q$759) -> CC046 | H86: =_xlfn.XLOOKUP(A86,'[3]Budgets 2027'!I$3:I$759,'[3]Budgets 2027'!R$3:R$759) -> Flat Trucks Logistics
A87: MVEH-000328 | B87: 0 | C87: Flat Body(15200x2650x2600 Tri AXLE | D87: =_xlfn.XLOOKUP(A87,'[4]Fleet Master'!D$3:D$52,'[4]Fleet Master'!F$3:F$52) -> 45T | E87: 102-45T | F87: BOX BODY | G87: =_xlfn.XLOOKUP(A87,'[3]Budgets 2027'!I$3:I$759,'[3]Budgets 2027'!Q$3:Q$759) -> CC059 | H87: =_xlfn.XLOOKUP(A87,'[3]Budgets 2027'!I$3:I$759,'[3]Budgets 2027'!R$3:R$759) -> Haulage
A88: MVEH-000330 | B88: 0 | C88: Flat Body(15200x2650x2600 Tri AXLE | D88: =_xlfn.XLOOKUP(A88,'[4]Fleet Master'!D$3:D$52,'[4]Fleet Master'!F$3:F$52) -> 30T | E88: SIDED-45T | F88: Sided | G88: =_xlfn.XLOOKUP(A88,'[3]Budgets 2027'!I$3:I$759,'[3]Budgets 2027'!Q$3:Q$759) -> CC059 | H88: =_xlfn.XLOOKUP(A88,'[3]Budgets 2027'!I$3:I$759,'[3]Budgets 2027'!R$3:R$759) -> Haulage
A89: MVEH-000332 | B89: 0 | C89: Flat Body(15200x2650x2600 Tri AXLE | D89: =_xlfn.XLOOKUP(A89,'[4]Fleet Master'!D$3:D$52,'[4]Fleet Master'!F$3:F$52) -> 30T | E89: 102-45T | F89: BOX BODY | G89: =_xlfn.XLOOKUP(A89,'[3]Budgets 2027'!I$3:I$759,'[3]Budgets 2027'!Q$3:Q$759) -> CC059 | H89: =_xlfn.XLOOKUP(A89,'[3]Budgets 2027'!I$3:I$759,'[3]Budgets 2027'!R$3:R$759) -> Haulage
A90: MVEH-000341 | B90: 0 | C90: Flat Body 12500x2500 Bogie Axle | D90: =_xlfn.XLOOKUP(A90,'[4]Fleet Master'!D$3:D$52,'[4]Fleet Master'!F$3:F$52) -> 45T | E90: 102-45T | F90: BOX BODY | G90: =_xlfn.XLOOKUP(A90,'[3]Budgets 2027'!I$3:I$759,'[3]Budgets 2027'!Q$3:Q$759) -> CC059 | H90: =_xlfn.XLOOKUP(A90,'[3]Budgets 2027'!I$3:I$759,'[3]Budgets 2027'!R$3:R$759) -> Haulage
A91: MVEH-000343 | B91: 0 | C91: Flat Body 12500x2500 Bogie Axle | D91: =_xlfn.XLOOKUP(A91,'[4]Fleet Master'!D$3:D$52,'[4]Fleet Master'!F$3:F$52) -> 30T | E91: FLAT | F91: Flat Trailer | G91: =_xlfn.XLOOKUP(A91,'[3]Budgets 2027'!I$3:I$759,'[3]Budgets 2027'!Q$3:Q$759) -> CC059 | H91: =_xlfn.XLOOKUP(A91,'[3]Budgets 2027'!I$3:I$759,'[3]Budgets 2027'!R$3:R$759) -> Haulage
A92: MVEH-000345 | B92: 0 | C92: Flat Body 12500x2500 Bogie Axle | D92: =_xlfn.XLOOKUP(A92,'[4]Fleet Master'!D$3:D$52,'[4]Fleet Master'!F$3:F$52) -> 45T | E92: 102-45T | F92: BOX BODY | G92: =_xlfn.XLOOKUP(A92,'[3]Budgets 2027'!I$3:I$759,'[3]Budgets 2027'!Q$3:Q$759) -> CC059 | H92: =_xlfn.XLOOKUP(A92,'[3]Budgets 2027'!I$3:I$759,'[3]Budgets 2027'!R$3:R$759) -> Haulage
A93: MVEH-000354 | B93: 0 | C93: JUMBO BOX BODY(15200 X 2650 X 2600)-TRI-AXLE, EPOXY PAINT | D93: =_xlfn.XLOOKUP(A93,'[4]Fleet Master'!D$3:D$52,'[4]Fleet Master'!F$3:F$52) -> 45T | E93: 102-45T | F93: BOX BODY | G93: =_xlfn.XLOOKUP(A93,'[3]Budgets 2027'!I$3:I$759,'[3]Budgets 2027'!Q$3:Q$759) -> CC059 | H93: =_xlfn.XLOOKUP(A93,'[3]Budgets 2027'!I$3:I$759,'[3]Budgets 2027'!R$3:R$759) -> Haulage
A94: MVEH-000355 | B94: 0 | C94: JUMBO BOX BODY(15200 X 2650 X 2600)-TRI-AXLE, EPOXY PAINT | D94: =_xlfn.XLOOKUP(A94,'[4]Fleet Master'!D$3:D$52,'[4]Fleet Master'!F$3:F$52) -> 45T | E94: 102-45T | F94: BOX BODY | G94: CC059 | H94: Haulage
A95: MVEH-000360 | B95: 0 | C95: JUMBO BOX BODY(15200 X 2650 X 2600)-TRI-AXLE, EPOXY PAINT | D95: =_xlfn.XLOOKUP(A95,'[4]Fleet Master'!D$3:D$52,'[4]Fleet Master'!F$3:F$52) -> 45T | E95: 102-45T | F95: BOX BODY | G95: =_xlfn.XLOOKUP(A95,'[3]Budgets 2027'!I$3:I$759,'[3]Budgets 2027'!Q$3:Q$759) -> CC059 | H95: =_xlfn.XLOOKUP(A95,'[3]Budgets 2027'!I$3:I$759,'[3]Budgets 2027'!R$3:R$759) -> Haulage
A96: MVEH-000361 | B96: 0 | C96: JUMBO BOX BODY(15200 X 2650 X 2600)-TRI-AXLE, EPOXY PAINT | D96: =_xlfn.XLOOKUP(A96,'[4]Fleet Master'!D$3:D$52,'[4]Fleet Master'!F$3:F$52) -> 45T | E96: 102-45T | F96: BOX BODY | G96: =_xlfn.XLOOKUP(A96,'[3]Budgets 2027'!I$3:I$759,'[3]Budgets 2027'!Q$3:Q$759) -> CC059 | H96: =_xlfn.XLOOKUP(A96,'[3]Budgets 2027'!I$3:I$759,'[3]Budgets 2027'!R$3:R$759) -> Haulage
A97: MVEH-000385 | B97: 0 | C97: JUMBO BOX BODY(15200 X 2650 X 2600)-BOGIEI-AXLE, EPOXY PAINT | D97: =_xlfn.XLOOKUP(A97,'[4]Fleet Master'!D$3:D$52,'[4]Fleet Master'!F$3:F$52) -> 45T | E97: 102-45T | F97: BOX BODY | G97: =_xlfn.XLOOKUP(A97,'[3]Budgets 2027'!I$3:I$759,'[3]Budgets 2027'!Q$3:Q$759) -> CC059 | H97: =_xlfn.XLOOKUP(A97,'[3]Budgets 2027'!I$3:I$759,'[3]Budgets 2027'!R$3:R$759) -> Haulage
A98: MVEH-000386 | B98: 0 | C98: JUMBO BOX BODY(15200 X 2650 X 2600)-BOGIEI-AXLE, EPOXY PAINT | D98: =_xlfn.XLOOKUP(A98,'[4]Fleet Master'!D$3:D$52,'[4]Fleet Master'!F$3:F$52) -> 45T | E98: 102-45T | F98: BOX BODY | G98: CC059 | H98: Haulage
A99: MVEH-000387 | B99: 0 | C99: JUMBO BOX BODY(15200 X 2650 X 2600)-BOGIEI-AXLE, EPOXY PAINT | D99: =_xlfn.XLOOKUP(A99,'[4]Fleet Master'!D$3:D$52,'[4]Fleet Master'!F$3:F$52) -> 45T | E99: 102-45T | F99: BOX BODY | G99: =_xlfn.XLOOKUP(A99,'[3]Budgets 2027'!I$3:I$759,'[3]Budgets 2027'!Q$3:Q$759) -> CC059 | H99: =_xlfn.XLOOKUP(A99,'[3]Budgets 2027'!I$3:I$759,'[3]Budgets 2027'!R$3:R$759) -> Haulage
A100: MVEH-000286 | B100: 0 | C100: Flat Trailer single Axel - 30T | D100: =_xlfn.XLOOKUP(A100,'[4]Fleet Master'!D$3:D$52,'[4]Fleet Master'!F$3:F$52) -> 30T | E100: FLAT | F100: Flat Trailer | G100: =_xlfn.XLOOKUP(A100,'[3]Budgets 2027'!I$3:I$759,'[3]Budgets 2027'!Q$3:Q$759) -> CC059 | H100: =_xlfn.XLOOKUP(A100,'[3]Budgets 2027'!I$3:I$759,'[3]Budgets 2027'!R$3:R$759) -> Haulage
A101: MVEH-000291 | B101: 0 | C101: IPI FLAT TRAILER DOUBLE AXEL-48T | D101: =_xlfn.XLOOKUP(A101,'[4]Fleet Master'!D$3:D$52,'[4]Fleet Master'!F$3:F$52) -> 30T | E101: FLAT | F101: Flat Trailer | G101: =_xlfn.XLOOKUP(A101,'[3]Budgets 2027'!I$3:I$759,'[3]Budgets 2027'!Q$3:Q$759) -> CC059 | H101: =_xlfn.XLOOKUP(A101,'[3]Budgets 2027'!I$3:I$759,'[3]Budgets 2027'!R$3:R$759) -> Haulage
A102: MVEH-000294 | B102: 0 | C102: FLAT TRAILER SINGLE AXEL-30T | D102: 30T | E102: FLAT | F102: Flat Trailer | G102: =_xlfn.XLOOKUP(A102,'[3]Budgets 2027'!I$3:I$759,'[3]Budgets 2027'!Q$3:Q$759) -> CC059 | H102: =_xlfn.XLOOKUP(A102,'[3]Budgets 2027'!I$3:I$759,'[3]Budgets 2027'!R$3:R$759) -> Haulage
A103: MVEH-000295 | B103: 0 | C103: Flat Trailer Closed Body - 40T | D103: 40T | E103: 102-40T | F103: BOX BODY | G103: =_xlfn.XLOOKUP(A103,'[3]Budgets 2027'!I$3:I$759,'[3]Budgets 2027'!Q$3:Q$759) -> CC059 | H103: =_xlfn.XLOOKUP(A103,'[3]Budgets 2027'!I$3:I$759,'[3]Budgets 2027'!R$3:R$759) -> Haulage
A104: MVEH-000337 | B104: 0 | C104: Flat Body 12500x2500 Bogie Axle | D104: =_xlfn.XLOOKUP(A104,'[4]Fleet Master'!D$3:D$52,'[4]Fleet Master'!F$3:F$52) -> 30T | E104: FLAT | F104: Flat Trailer | G104: =_xlfn.XLOOKUP(A104,'[3]Budgets 2027'!I$3:I$759,'[3]Budgets 2027'!Q$3:Q$759) -> CC059 | H104: =_xlfn.XLOOKUP(A104,'[3]Budgets 2027'!I$3:I$759,'[3]Budgets 2027'!R$3:R$759) -> Haulage
A105: MVEH-000339 | B105: 0 | C105: Flat Body 12500x2500 Bogie Axle | D105: =_xlfn.XLOOKUP(A105,'[4]Fleet Master'!D$3:D$52,'[4]Fleet Master'!F$3:F$52) -> 30T | E105: FLAT | F105: Flat Trailer | G105: =_xlfn.XLOOKUP(A105,'[3]Budgets 2027'!I$3:I$759,'[3]Budgets 2027'!Q$3:Q$759) -> CC059 | H105: =_xlfn.XLOOKUP(A105,'[3]Budgets 2027'!I$3:I$759,'[3]Budgets 2027'!R$3:R$759) -> Haulage
A106: MVEH-000453 | B106: 0 | C106: 24 Pallet Trailer (15800x2700x2100) With Traixale | D106: =_xlfn.XLOOKUP(A106,'[4]Fleet Master'!D$3:D$52,'[4]Fleet Master'!F$3:F$52) -> 45T | E106: 102-45T | F106: BOX BODY | G106: =_xlfn.XLOOKUP(A106,'[3]Budgets 2027'!I$3:I$759,'[3]Budgets 2027'!Q$3:Q$759) -> CC059 | H106: =_xlfn.XLOOKUP(A106,'[3]Budgets 2027'!I$3:I$759,'[3]Budgets 2027'!R$3:R$759) -> Haulage
A107: MVEH-000454 | B107: 0 | C107: 24 Pallet Trailer (15800x2700x2100) With Traixale | D107: =_xlfn.XLOOKUP(A107,'[4]Fleet Master'!D$3:D$52,'[4]Fleet Master'!F$3:F$52) -> 45T | E107: 102-45T | F107: BOX BODY | G107: =_xlfn.XLOOKUP(A107,'[3]Budgets 2027'!I$3:I$759,'[3]Budgets 2027'!Q$3:Q$759) -> CC059 | H107: =_xlfn.XLOOKUP(A107,'[3]Budgets 2027'!I$3:I$759,'[3]Budgets 2027'!R$3:R$759) -> Haulage
A108: MVEH-000455 | B108: 0 | C108: 24 Pallet Trailer (15800x2700x2100) With Traixale | D108: =_xlfn.XLOOKUP(A108,'[4]Fleet Master'!D$3:D$52,'[4]Fleet Master'!F$3:F$52) -> 45T | E108: 102-45T | F108: BOX BODY | G108: =_xlfn.XLOOKUP(A108,'[3]Budgets 2027'!I$3:I$759,'[3]Budgets 2027'!Q$3:Q$759) -> CC059 | H108: =_xlfn.XLOOKUP(A108,'[3]Budgets 2027'!I$3:I$759,'[3]Budgets 2027'!R$3:R$759) -> Haulage
A109: MVEH-000456 | B109: 0 | C109: 24 Pallet Trailer (15800x2700x2100) With Traixale | D109: =_xlfn.XLOOKUP(A109,'[4]Fleet Master'!D$3:D$52,'[4]Fleet Master'!F$3:F$52) -> 45T | E109: 102-45T | F109: BOX BODY | G109: =_xlfn.XLOOKUP(A109,'[3]Budgets 2027'!I$3:I$759,'[3]Budgets 2027'!Q$3:Q$759) -> CC059 | H109: =_xlfn.XLOOKUP(A109,'[3]Budgets 2027'!I$3:I$759,'[3]Budgets 2027'!R$3:R$759) -> Haulage
A110: MVEH-000457 | B110: 0 | C110: 24 Pallet Trailer (15800x2700x2100) With Traixale | D110: =_xlfn.XLOOKUP(A110,'[4]Fleet Master'!D$3:D$52,'[4]Fleet Master'!F$3:F$52) -> 45T | E110: 102-45T | F110: BOX BODY | G110: =_xlfn.XLOOKUP(A110,'[3]Budgets 2027'!I$3:I$759,'[3]Budgets 2027'!Q$3:Q$759) -> CC059 | H110: =_xlfn.XLOOKUP(A110,'[3]Budgets 2027'!I$3:I$759,'[3]Budgets 2027'!R$3:R$759) -> Haulage
A111: MVEH-000458 | B111: 0 | C111: 24 Pallet Trailer (15800x2700x2100) With Traixale | D111: =_xlfn.XLOOKUP(A111,'[4]Fleet Master'!D$3:D$52,'[4]Fleet Master'!F$3:F$52) -> 45T | E111: 102-45T | F111: BOX BODY | G111: =_xlfn.XLOOKUP(A111,'[3]Budgets 2027'!I$3:I$759,'[3]Budgets 2027'!Q$3:Q$759) -> CC059 | H111: =_xlfn.XLOOKUP(A111,'[3]Budgets 2027'!I$3:I$759,'[3]Budgets 2027'!R$3:R$759) -> Haulage
A112: MVEH-000459 | B112: 0 | C112: 24 Pallet Trailer (15800x2700x2100) With Traixale | D112: 45T | E112: 102-45T | F112: BOX BODY | G112: =_xlfn.XLOOKUP(A112,'[3]Budgets 2027'!I$3:I$759,'[3]Budgets 2027'!Q$3:Q$759) -> CC059 | H112: =_xlfn.XLOOKUP(A112,'[3]Budgets 2027'!I$3:I$759,'[3]Budgets 2027'!R$3:R$759) -> Haulage
A113: MVEH-000460 | B113: 0 | C113: 24 Pallet Trailer (15800x2700x2100) With Traixale | D113: =_xlfn.XLOOKUP(A113,'[4]Fleet Master'!D$3:D$52,'[4]Fleet Master'!F$3:F$52) -> 45T | E113: 102-45T | F113: BOX BODY | G113: =_xlfn.XLOOKUP(A113,'[3]Budgets 2027'!I$3:I$759,'[3]Budgets 2027'!Q$3:Q$759) -> CC059 | H113: =_xlfn.XLOOKUP(A113,'[3]Budgets 2027'!I$3:I$759,'[3]Budgets 2027'!R$3:R$759) -> Haulage
A114: MVEH-000461 | B114: 0 | C114: 24 Pallet Trailer (15800x2700x2100) With Traixale | D114: =_xlfn.XLOOKUP(A114,'[4]Fleet Master'!D$3:D$52,'[4]Fleet Master'!F$3:F$52) -> 45T | E114: 102-45T | F114: BOX BODY | G114: =_xlfn.XLOOKUP(A114,'[3]Budgets 2027'!I$3:I$759,'[3]Budgets 2027'!Q$3:Q$759) -> CC059 | H114: =_xlfn.XLOOKUP(A114,'[3]Budgets 2027'!I$3:I$759,'[3]Budgets 2027'!R$3:R$759) -> Haulage
A115: MVEH-000462 | B115: 0 | C115: 24 Pallet Trailer (15800x2700x2100) With Traixale | D115: 45T | E115: 102-45T | F115: BOX BODY | G115: =_xlfn.XLOOKUP(A115,'[3]Budgets 2027'!I$3:I$759,'[3]Budgets 2027'!Q$3:Q$759) -> CC059 | H115: =_xlfn.XLOOKUP(A115,'[3]Budgets 2027'!I$3:I$759,'[3]Budgets 2027'!R$3:R$759) -> Haulage
A116: MVEH-000463 | B116: 0 | C116: 24 Pallet Trailer (15800x2700x2100) With Traixale | D116: =_xlfn.XLOOKUP(A116,'[4]Fleet Master'!D$3:D$52,'[4]Fleet Master'!F$3:F$52) -> 45T | E116: 102-45T | F116: BOX BODY | G116: =_xlfn.XLOOKUP(A116,'[3]Budgets 2027'!I$3:I$759,'[3]Budgets 2027'!Q$3:Q$759) -> CC059 | H116: =_xlfn.XLOOKUP(A116,'[3]Budgets 2027'!I$3:I$759,'[3]Budgets 2027'!R$3:R$759) -> Haulage
A117: MVEH-000464 | B117: 0 | C117: 24 Pallet Trailer (15800x2700x2100) With Traixale | D117: 45T | E117: 102-45T | F117: BOX BODY | G117: =_xlfn.XLOOKUP(A117,'[3]Budgets 2027'!I$3:I$759,'[3]Budgets 2027'!Q$3:Q$759) -> CC059 | H117: =_xlfn.XLOOKUP(A117,'[3]Budgets 2027'!I$3:I$759,'[3]Budgets 2027'!R$3:R$759) -> Haulage
A118: MVEH-000465 | B118: 0 | C118: 24 Pallet Trailer (15800x2700x2100) With Traixale | D118: =_xlfn.XLOOKUP(A118,'[4]Fleet Master'!D$3:D$52,'[4]Fleet Master'!F$3:F$52) -> 45T | E118: 102-45T | F118: BOX BODY | G118: =_xlfn.XLOOKUP(A118,'[3]Budgets 2027'!I$3:I$759,'[3]Budgets 2027'!Q$3:Q$759) -> CC059 | H118: =_xlfn.XLOOKUP(A118,'[3]Budgets 2027'!I$3:I$759,'[3]Budgets 2027'!R$3:R$759) -> Haulage
A119: MVEH-000466 | B119: 0 | C119: 24 Pallet Trailer (15800x2700x2100) With Traixale | D119: =_xlfn.XLOOKUP(A119,'[4]Fleet Master'!D$3:D$52,'[4]Fleet Master'!F$3:F$52) -> 45T | E119: 102-45T | F119: BOX BODY | G119: =_xlfn.XLOOKUP(A119,'[3]Budgets 2027'!I$3:I$759,'[3]Budgets 2027'!Q$3:Q$759) -> CC059 | H119: =_xlfn.XLOOKUP(A119,'[3]Budgets 2027'!I$3:I$759,'[3]Budgets 2027'!R$3:R$759) -> Haulage
A120: MVEH-000467 | B120: 0 | C120: 24 Pallet Trailer (15800x2700x2100) With Traixale | D120: 45T | E120: 102-45T | F120: BOX BODY | G120: =_xlfn.XLOOKUP(A120,'[3]Budgets 2027'!I$3:I$759,'[3]Budgets 2027'!Q$3:Q$759) -> CC059 | H120: =_xlfn.XLOOKUP(A120,'[3]Budgets 2027'!I$3:I$759,'[3]Budgets 2027'!R$3:R$759) -> Haulage
A121: MVEH-000468 | B121: 0 | C121: 24 Pallet Trailer (15800x2700x2100) With Traixale | D121: 45T | E121: 102-45T | F121: BOX BODY | G121: =_xlfn.XLOOKUP(A121,'[3]Budgets 2027'!I$3:I$759,'[3]Budgets 2027'!Q$3:Q$759) -> CC059 | H121: =_xlfn.XLOOKUP(A121,'[3]Budgets 2027'!I$3:I$759,'[3]Budgets 2027'!R$3:R$759) -> Haulage
A122: MVEH-000469 | B122: 0 | C122: 24 Pallet Trailer (15800x2700x2100) With Traixale | D122: 45T | E122: 102-45T | F122: BOX BODY | G122: =_xlfn.XLOOKUP(A122,'[3]Budgets 2027'!I$3:I$759,'[3]Budgets 2027'!Q$3:Q$759) -> CC059 | H122: =_xlfn.XLOOKUP(A122,'[3]Budgets 2027'!I$3:I$759,'[3]Budgets 2027'!R$3:R$759) -> Haulage
A123: MVEH-000470 | B123: 0 | C123: 24 Pallet Trailer (15800x2700x2100) With Traixale | D123: 45T | E123: 102-45T | F123: BOX BODY | G123: =_xlfn.XLOOKUP(A123,'[3]Budgets 2027'!I$3:I$759,'[3]Budgets 2027'!Q$3:Q$759) -> CC059 | H123: =_xlfn.XLOOKUP(A123,'[3]Budgets 2027'!I$3:I$759,'[3]Budgets 2027'!R$3:R$759) -> Haulage
A124: MVEH-000471 | B124: 0 | C124: 24 Pallet Trailer (15800x2700x2100) With Traixale | D124: 45T | E124: 102-45T | F124: BOX BODY | G124: =_xlfn.XLOOKUP(A124,'[3]Budgets 2027'!I$3:I$759,'[3]Budgets 2027'!Q$3:Q$759) -> CC059 | H124: =_xlfn.XLOOKUP(A124,'[3]Budgets 2027'!I$3:I$759,'[3]Budgets 2027'!R$3:R$759) -> Haulage
A125: MVEH-000472 | B125: 0 | C125: 24 Pallet Trailer (15800x2700x2100) With Traixale | D125: 45T | E125: 102-45T | F125: BOX BODY | G125: =_xlfn.XLOOKUP(A125,'[3]Budgets 2027'!I$3:I$759,'[3]Budgets 2027'!Q$3:Q$759) -> CC059 | H125: =_xlfn.XLOOKUP(A125,'[3]Budgets 2027'!I$3:I$759,'[3]Budgets 2027'!R$3:R$759) -> Haulage

Sheet Item List
A1: Item Number | B1: Vehicle Model | C1: Original Description | D1: Part Name | E1: Vehicle Type | F1: Make | G1: Original Category | H1: Category | I1: Group | J1: Subgroup | K1: Suggested Class | L1: Cost
A2: WS1460226 | B2: VOLKWAGEN | C2: Truck/VW/18310/Air Compressor | D2: Air Compressor | E2: Truck | F2: Volkswagen | G2: Mechanical | H2: Air Brake System | I2: Air Compressor | J2: Air Compressor Assembly | K2: Mechanical | L2: 320000
A3: WS1461310 | B3: — | C3: Truck/Foton/Hiab/Air Compressor | D3: Air Compressor | E3: Truck | F3: Foton | G3: Mechanical | H3: Air Brake System | I3: Air Compressor | J3: Air Compressor Assembly | K3: Mechanical | L3: 24000
A4: WS1460849 | B4: HOWO 371 6X4 DANGOTE | C4: Truck/Sino/6x4D/Air compressor assembly | D4: Air compressor assembly | E4: Truck | F4: Sinotruk HOWO | G4: Mechanical | H4: Air Brake System | I4: Air Compressor | J4: Air Compressor Assembly | K4: Mechanical | L4: 200000
A5: WS1460854 | B5: HOWO E7G371 6X4 (COVID) | C5: Truck/Sino/6x4C/AIR COMPRESSOR COVID19 | D5: AIR COMPRESSOR COVID19 | E5: Truck | F5: Sinotruk HOWO | G5: Mechanical | H5: Air Brake System | I5: Air Compressor | J5: Air Compressor Assembly | K5: Mechanical | L5: 240000
A6: WS1460219 | B6: HOWO E7G371 6X4 (COVID) | C6: Truck/Sino/All/Air Compressure Kit | D6: Air Compressure Kit | E6: Truck | F6: Sinotruk HOWO | G6: Mechanical | H6: Air Brake System | I6: Air Compressor | J6: Compressor Repair Kits & Gaskets | K6: Mechanical | L6: 0
A7: WS1460253 | B7: VOLKWAGEN | C7: Truck/VW/18310/Compressor Head Gasket | D7: Compressor Head Gasket | E7: Truck | F7: Volkswagen | G7: Mechanical | H7: Air Brake System | I7: Air Compressor | J7: Compressor Repair Kits & Gaskets | K7: Mechanical | L7: 18000
A8: SINO-6x4-COMPR-KIT | B8: HOWO E7G371 6X4 (COVID) | C8: Compressor kit | D8: Compressor kit | E8: Truck | F8: Sinotruk HOWO | G8: Mechanical | H8: Air Brake System | I8: Air Compressor | J8: Compressor Repair Kits & Gaskets | K8: Mechanical | L8: 0
A9: WS1460460 | B9: HOWO E7G371 6X4 (COVID) | C9: Truck/All/All/12Mm Air Hose Black | D9: 12Mm Air Hose Black | E9: Truck | F9: Universal | G9: Mechanical | H9: Air Brake System | I9: Air Lines & Fittings | J9: Air / Brake Hoses & Connectors | K9: Mechanical | L9: 1000
A10: WS1460288 | B10: VOLKWAGEN | C10: Truck/VW/18310/Air Coulper | D10: Air Coulper | E10: Truck | F10: Volkswagen | G10: Mechanical | H10: Air Brake System | I10: Air Lines & Fittings | J10: Air / Brake Hoses & Connectors | K10: Mechanical | L10: 0
A11: VW-18310-AIR-HOSE | B11: VOLKWAGEN | C11: Air hose | D11: Air hose | E11: Truck | F11: Volkswagen | G11: Mechanical | H11: Air Brake System | I11: Air Lines & Fittings | J11: Air / Brake Hoses & Connectors | K11: Mechanical | L11: 0
A12: WS1461202 | B12: HOWO E7G371 6X4 (COVID) | C12: All/All/All/Air Hose Quick Fix 12MM | D12: Air Hose Quick Fix 12MM | E12: All | F12: Universal | G12: Mechanical | H12: Air Brake System | I12: Air Lines & Fittings | J12: Air / Brake Hoses & Connectors | K12: Mechanical | L12: 1000
A13: WS1460461 | B13: HOWO E7G371 6X4 (COVID) | C13: All/All/All/Air Hose Quick Fix 6Mm | D13: Air Hose Quick Fix 6Mm | E13: All | F13: Universal | G13: Mechanical | H13: Air Brake System | I13: Air Lines & Fittings | J13: Air / Brake Hoses & Connectors | K13: Mechanical | L13: 1000
... A727: WS1460787 | B727: HOWO E7G371 6X4 (COVID) | C727: Truck/VW/18310/Threading Tape | D727: Threading Tape | E727: Truck | F727: Volkswagen | G727: Mechanical | H727: Workshop Consumables | I727: Tapes | J727: Thread Seal Tape | K727: Mechanical | L727: 300

Sheet Staffs List
A1: S/No | B1: Employee staff number | C1: NAME | D1: Position Name | E1: Company | F1: JOINING DATE | G1: Employee category | H1: Staff Group (Local/Expatriate/3rd Party | I1: Branch Code | J1: Branch Name | K1: costcenter | L1: CC Name | M1: Dept Code | N1: Dept Name | O1: Type | P1: Job Function | Q1: Division | R1: Business Unit | S1: Intercompany functions | T1: Within JMG function | U1: Reporting line Manager's Name | V1: Section | W1: Country of Resident
A2: 1 | B2: 000033 | C2: ADAH Joseph | D2: Bike Mechanic | E2: JMG | F2: 38341 | G2: Labour | H2: Local | I2: BRH002 | J2: Gbagada | K2: CC025 | L2: Vehicle Workshop | M2: DPT023 | N2: Vehicle Workshop | O2: Direct | P2: Logistics Support | Q2: Overhead | R2: Shared Services | S2: Dedicated Service | T2: Shared service | U2: GHASSAN El Saifi | V2: Vehicle Workshop | W2: Nigeria
A3: 2 | B3: 000083 | C3: ADESANYA Oluwatosin Oluwaseun | D3: HIAB Operator | E3: JMG | F3: 41191 | G3: Labour | H3: Local | I3: BRH002 | J3: Gbagada | K3: CC039 | L3: Hiabs Logistics | M3: DPT026 | N3: Logistics | O3: Direct | P3: Logistics | Q3: Logistics | R3: Transport | S3: Dedicated Service | T3: Dedicated service | U3: YEKEEN Oyetunde Bolarinwa | V3: Logistics | W3: Nigeria
A4: =A3+1 -> 3 | B4: 000089 | C4: ADEWUNMI Adetayo Joseph | D4: HIAB Operator | E4: JMG | F4: 42066 | G4: Labour | H4: Local | I4: BRH001 | J4: Abuja | K4: CC039 | L4: Hiabs Logistics | M4: DPT026 | N4: Logistics | O4: Direct | P4: Logistics | Q4: Logistics | R4: Transport | S4: Dedicated Service | T4: Dedicated service | U4: YEKEEN Oyetunde Bolarinwa | V4: Logistics | W4: Nigeria
A5: =A4+1 -> 4 | B5: 000105 | C5: AFOLABI Ayodeji | D5: HIAB Operator | E5: JMG | F5: 42887 | G5: Labour | H5: Local | I5: BRH002 | J5: Gbagada | K5: CC039 | L5: Hiabs Logistics | M5: DPT026 | N5: Logistics | O5: Direct | P5: Logistics | Q5: Logistics | R5: Transport | S5: Dedicated Service | T5: Dedicated service | U5: YEKEEN Oyetunde Bolarinwa | V5: Logistics | W5: Nigeria
A6: =A5+1 -> 5 | B6: 000133 | C6: AJIBADE Afeez Adeyemi | D6: Logistics Supervisor Heavy Duty | E6: JMG | F6: 41715 | G6: Admin | H6: Local | I6: BRH002 | J6: Gbagada | K6: CC024 | L6: Logistics And Transportation Ovh | M6: DPT026 | N6: Logistics | O6: Direct | P6: Logistics Support | Q6: Logistics | R6: Transport | S6: Dedicated Service | T6: Dedicated service | U6: DAYEKH Mohamad | V6: Logistics | W6: Nigeria
A7: =A6+1 -> 6 | B7: 000156 | C7: AKINDEJI Alfred Temidayo | D7: Light Duty Driver | E7: JMG | F7: 41438 | G7: Labour | H7: Local | I7: BRH002 | J7: Gbagada | K7: CC047 | L7: Closed Body Logistics | M7: DPT026 | N7: Logistics | O7: Direct | P7: Logistics | Q7: Logistics | R7: Transport | S7: Dedicated Service | T7: Dedicated service | U7: YEKEEN Oyetunde Bolarinwa | V7: Logistics | W7: Nigeria
A8: =A7+1 -> 7 | B8: 000163 | C8: AKINOLA Kehinde John | D8: Heavy Duty Driver | E8: JMG | F8: 41353 | G8: Labour | H8: Local | I8: BRH002 | J8: Gbagada | K8: CC059 | L8: HAULAGE | M8: DPT026 | N8: Logistics | O8: Direct | P8: Logistics | Q8: Logistics | R8: Transport | S8: Dedicated Service | T8: Dedicated service | U8: DAODU Timileyin Monday | V8: Logistics | W8: Nigeria
A9: =A8+1 -> 8 | B9: 000164 | C9: AKINOLA Oluwaseun Samson | D9: Heavy Duty Driver | E9: JMG | F9: 41344 | G9: Labour | H9: Local | I9: BRH002 | J9: Gbagada | K9: CC046 | L9: Flat Trucks Logistics | M9: DPT026 | N9: Logistics | O9: Direct | P9: Logistics | Q9: Logistics | R9: Transport | S9: Dedicated Service | T9: Dedicated service | U9: AJIBADE Afeez Adeyemi | V9: Logistics | W9: Nigeria
A10: =A9+1 -> 9 | B10: 000181 | C10: ALAMEZIE Denis Ndubuisi | D10: HIAB Operator | E10: JMG | F10: 42072 | G10: Labour | H10: Local | I10: BRH002 | J10: Gbagada | K10: CC039 | L10: Hiabs Logistics | M10: DPT026 | N10: Logistics | O10: Direct | P10: Logistics | Q10: Logistics | R10: Transport | S10: Dedicated Service | T10: Dedicated service | U10: YEKEEN Oyetunde Bolarinwa | V10: Logistics | W10: Nigeria
A11: =A10+1 -> 10 | B11: 000189 | C11: ALIYU Lawal | D11: Heavy Duty Driver | E11: JMG | F11: 42149 | G11: Labour | H11: Local | I11: BRH002 | J11: Gbagada | K11: CC059 | L11: HAULAGE | M11: DPT026 | N11: Logistics | O11: Direct | P11: Logistics | Q11: Logistics | R11: Transport | S11: Dedicated Service | T11: Dedicated service | U11: AJIBADE Afeez Adeyemi | V11: Logistics | W11: Nigeria
A12: =A11+1 -> 11 | B12: 000220 | C12: ASINI Ogwhonigho | D12: Logisitics Officer | E12: JMG | F12: 44830 | G12: Admin | H12: Local | I12: BRH009 | J12: PH | K12: CC066 | L12: Stores Operations | M12: DPT026 | N12: Logistics | O12: Indirect | P12: Logistics Support | Q12: Overhead | R12: Transport | S12: Dedicated Service | T12: Dedicated service | U12: DAYEKH Mohamad | V12: Logistics | W12: Nigeria
A13: =A12+1 -> 12 | B13: 000303 | C13: BANYE Franklin Asuamaka | D13: Trailer Motor Boy | E13: JMG | F13: 40882 | G13: Labour | H13: Local | I13: BRH002 | J13: Gbagada | K13: CC046 | L13: Flat Trucks Logistics | M13: DPT026 | N13: Logistics | O13: Direct | P13: Logistics | Q13: Logistics | R13: Transport | S13: Dedicated Service | T13: Dedicated service | U13: AJIBADE Afeez Adeyemi | V13: Logistics | W13: Nigeria
A14: =A13+1 -> 13 | B14: 000425 | C14: ESSIEN Micah Emmanuel | D14: Light Duty Driver | E14: JMG | F14: 40330 | G14: Labour | H14: Local | I14: BRH002 | J14: Gbagada | K14: CC047 | L14: Closed Body Logistics | M14: DPT026 | N14: Logistics | O14: Direct | P14: Logistics | Q14: Logistics | R14: Transport | S14: Dedicated Service | T14: Dedicated service | U14: YEKEEN Oyetunde Bolarinwa | V14: Logistics | W14: Nigeria
A15: =A14+1 -> 14 | B15: 000450 | C15: EZRA Mallam | D15: HIAB Operator | E15: JMG | F15: 42887 | G15: Labour | H15: Local | I15: BRH001 | J15: Abuja | K15: CC024 | L15: Logistics And Transportation Ovh | M15: DPT026 | N15: Logistics | O15: Direct | P15: Logistics | Q15: Logistics | R15: Transport | S15: Dedicated Service | T15: Dedicated service | U15: YEKEEN Oyetunde Bolarinwa | V15: Logistics | W15: Nigeria
... A132: =A131+1 -> 131 | B132: 003119 | C132: OGUNLEYE Abiodun Amos | D132: Auto Electrician | E132: JMG | F132: 45432 | G132: Labour | H132: Local | I132: BRH002 | J132: Gbagada | K132: CC024 | L132: Logistics And Transportation Ovh | M132: DPT023 | N132: Vehicle Workshop | O132: Direct | P132: Logistics Support | Q132: Overhead | R132: Transport | S132: Dedicated Service | T132: Shared service | U132: ADEGOKE Ademola Abdulkareem | V132: Vehicle Workshop | W132: Nigeria

Sheet Supplier
F2: Scope | G2: Equipment Providor | H2: Equipment Providor | I2: Equipment Providor | J2: Equipment Providor | K2: Equipment Providor | L2: Equipment Providor | M2: Equipment Providor | N2: Travels Upcountry | O2: Delivery Local within State | P2: Equipment Providor | Q2: Sell Equiment | R2: Sell Equiment | S2: Spare Parts | T2: External Workshop | U2: Tracking Company | V2: Diesel Supplier | W2: Tyre Supplier
F3: Expenses Type | G3: Opex | H3: Opex | I3: Opex | J3: Opex | K3: Opex | L3: Opex | M3: Opex | N3: Operation Type | O3: Operation Type | P3: Opex | Q3: Capex | R3: Capex | S3: Opex | T3: Opex | U3: Opex | V3: Opx | W3: Opex
A4: Supplier account | B4: Name | C4: Supplier hold | D4: Proposed | E4: Type Of Expenses | F4: Used by Division | G4: HAIB | H4: Crane | I4: FLATBED | J4: Low-bed | K4: 20FT | L4: 25FT | M4: 40FT | N4: Upcountry | O4: Local | P4: Forklift | Q4: Trucks | R4: Trailers | S4: Spare Parts | T4: External Workshop | U4: Tracking Company | V4: Diesel Supplier | W4: Tyre Supplier
A5: V00001019 | B5: IRON PRODUCTS INDUSTRIES LTD | C5: No | D5: 30D | E5: Non Stock | F5: Transport Division | G5: NO | H5: NO | I5: NO | J5: NO | K5: NO | L5: NO | M5: NO | N5: NO | O5: NO | P5: NO | Q5: Yes | R5: Yes | S5: Yes | T5: Yes | U5: NO | V5: NO | W5: NO
A6: V00001429 | B6: ONE STOP AFRICA INDUSTRIES LIMITED | C6: No | D6: 30D | E6: Stock Item | F6: Vehicle Workshop | G6: NO | H6: NO | I6: NO | J6: NO | K6: NO | L6: NO | M6: NO | N6: NO | O6: NO | P6: NO | Q6: NO | R6: NO | S6: Yes | T6: Yes | U6: NO | V6: NO | W6: NO
A7: V00001514 | B7: C.WOERMANN(NIGERIA)LIMITED | C7: No | D7: 30D | E7: Stock Item | F7: Vehicle Workshop | G7: NO | H7: NO | I7: NO | J7: NO | K7: NO | L7: NO | M7: NO | N7: NO | O7: NO | P7: NO | Q7: NO | R7: NO | S7: Yes | T7: NO | U7: NO | V7: NO | W7: NO
A8: V00000042 | B8: HAYYLUCK NIG LTD | C8: No | D8: Payment on Invoice | E8: Non Stock | F8: 3rd party Logistics | G8: YES | H8: YES | I8: YES | J8: YES | K8: NO | L8: NO | M8: NO | N8: YES | O8: YES | P8: YES | Q8: NO | R8: NO | S8: NO | T8: Yes | U8: NO | V8: NO | W8: NO
A9: V00001279 | B9: QT CONCEPTS LTD | C9: No | D9: 30D | E9: Stock Item | F9: Vehicle Workshop | G9: NO | H9: NO | I9: NO | J9: NO | K9: NO | L9: NO | M9: NO | N9: NO | O9: NO | P9: NO | Q9: NO | R9: NO | S9: Yes | T9: NO | U9: NO | V9: NO | W9: NO
A10: V00000699 | B10: PAT-ELLENZ INTERNATIONAL NIG. | C10: No | D10: Payment on Invoice | E10: Non Stock | F10: 3rd party Logistics | G10: YES | H10: YES | I10: YES | J10: YES | K10: YES | L10: YES | M10: YES | N10: YES | O10: YES | P10: YES | Q10: NO | R10: NO | S10: NO | T10: Yes | U10: NO | V10: NO | W10: NO
A11: V00001297 | B11: MAM IMPEX CONCEPT LTD | C11: No | D11: 30D | E11: Stock Item | F11: Vehicle Workshop | G11: NO | H11: NO | I11: NO | J11: NO | K11: NO | L11: NO | M11: NO | N11: NO | O11: NO | P11: NO | Q11: NO | R11: NO | S11: Yes | T11: NO | U11: NO | V11: NO | W11: NO
A12: V00000802 | B12: OMOS AND SONS NIGERIA LIMITED | C12: No | D12: Payment on Invoice | E12: Non Stock | F12: 3rd party Logistics | G12: YES | H12: YES | I12: YES | J12: YES | K12: YES | L12: YES | M12: YES | N12: YES | O12: YES | P12: YES | Q12: NO | R12: NO | S12: NO | T12: Yes | U12: NO | V12: NO | W12: NO
A13: V00000185 | B13: CHRISTMAN AUTO. SUPPLY | C13: No | D13: 30D | E13: Stock Item | F13: Vehicle Workshop | G13: NO | H13: NO | I13: NO | J13: NO | K13: NO | L13: NO | M13: NO | N13: NO | O13: NO | P13: NO | Q13: NO | R13: NO | S13: Yes | T13: NO | U13: NO | V13: NO | W13: NO
A14: V00001231 | B14: ANIBIRE ANIS & SONS NIGERIA ENTERPRIES | C14: No | D14: Payment on Invoice | E14: Non Stock | F14: 3rd party Logistics | G14: YES | H14: YES | I14: YES | J14: NO | K14: NO | L14: NO | M14: NO | N14: NO | O14: NO | P14: NO | Q14: NO | R14: NO | S14: NO | T14: NO | U14: NO | V14: NO | W14: NO
A15: V00000941 | B15: MOJEED OSUOLALE ENTERPRISES | C15: No | D15: 30D | E15: Stock Item | F15: Vehicle Workshop | G15: NO | H15: NO | I15: NO | J15: NO | K15: NO | L15: NO | M15: NO | N15: NO | O15: NO | P15: NO | Q15: NO | R15: NO | S15: Yes | T15: NO | U15: NO | V15: NO | W15: NO
... A59: V00000328 | B59: OPTIMAS OE SOLUTIONS LTD | C59: No | D59: 30D | E59: Stock Item | F59: Diesel | G59: NO | H59: NO | I59: NO | J59: NO | K59: NO | L59: NO | M59: NO | N59: NO | O59: NO | P59: NO | Q59: NO | R59: NO | S59: NO | T59: NO | U59: NO | V59: YES | W59: NO

Sheet LOB
B2: Haulage
B3: Port Operations
B4: Hiab
B5: Vans
B6: Crane & Heavy Lifts
B7: 3PL

Sheet Rate Card for costing 
A2: DIVISION | B2: OLD PLATE NO | C2: NEW PLATE NO | D2: ASSET ID | E2: Consumption | F2: Mentaiance Budget | G2: Montly Trip | H2: KM | I2: Project Number of Day | J2: Planned | K2: Actual Fixed Cost | L2: MTC Cost Per KM | M2: Tyre Cost Per KM | N2: Road Expenses Per KM | O2: Selling Fixed
A3: Closed Body Logistics | B3: AAA822XS | C3: AAA822XS | D3: MVEH-000202 | E3: 0.15 | F3: 7800 | G3: 16 | H3: 650 | I3: 236 | J3: 236 | K3: 57798.9 | L3: 83.333333 | M3: 2.7692308 | N3: 38 | O3: 75138.57
A4: Closed Body Logistics | B4: KSF352YC | C4: KSF352YC | D4: MVEH-000304 | E4: 0.2 | F4: 7800 | G4: 16 | H4: 650 | I4: 236 | J4: 236 | K4: 42975.81 | L4: 55.128205 | M4: 4.6153846 | N4: 38 | O4: 55868.553
A5: Closed Body Logistics | B5: T-1589LA | C5: T-1589LA | D5: MVEH-000289 | E5: 0.25 | F5: 12000 | G5: 16 | H5: 1000 | I5: 236 | J5: 236 | K5: 53846.91 | L5: 66.666667 | M5: 13.846154 | N5: 49 | O5: 70000.983
A6: Closed Body Logistics | B6: T-1590LA | C6: T-1590LA | D6: MVEH-000288 | E6: 0.25 | F6: 12000 | G6: 16 | H6: 1000 | I6: 236 | J6: 236 | K6: 51668.075 | L6: 66.666667 | M6: 13.846154 | N6: 49 | O6: 67168.497
A7: Closed Body Logistics | B7: T-1678LA | C7: T-1678LA | D7: MVEH-000287 | E7: 0.25 | F7: 12000 | G7: 16 | H7: 1000 | I7: 236 | J7: 236 | K7: 51744.759 | L7: 66.666667 | M7: 13.846154 | N7: 49 | O7: 67268.186
A8: Closed Body Logistics | B8: GGE28XU | C8: KRD640YF | D8: MVEH-000363 | E8: 0.25 | F8: 12000 | G8: 16 | H8: 1000 | I8: 236 | J8: 236 | K8: 54975.303 | L8: 66.666667 | M8: 13.846154 | N8: 49 | O8: 71467.893
A9: Closed Body Logistics | B9: KTU69XP | C9: T-2413LA | D9: MVEH-000146 | E9: 0.35 | F9: 21600 | G9: 16 | H9: 1800 | I9: 236 | J9: 236 | K9: 82650.804 | L9: 94.907407 | M9: 23.076923 | N9: 59 | O9: 107446.05
A10: Closed Body Logistics | B10: KTU68XP | C10: T-2417LA | D10: MVEH-000145 | E10: 0.35 | F10: 21600 | G10: 16 | H10: 1800 | I10: 236 | J10: 236 | K10: 86200.454 | L10: 94.907407 | M10: 23.076923 | N10: 59 | O10: 112060.59
A11: Hiabs Logistics | B11: KTU74XP | C11: KTU74XP | D11: MVEH-000103 | E11: 0.42 | F11: 21600 | G11: 16 | H11: 1800 | I11: 284 | J11: 284 | K11: 98036.085 | L11: 145.83333 | M11: 24.615385 | N11: 80 | O11: 127446.91
A12: Hiabs Logistics | B12: KTU76XP | C12: KTU76XP | D12: MVEH-000101 | E12: 0.42 | F12: 21600 | G12: 16 | H12: 1800 | I12: 284 | J12: 284 | K12: 96572.173 | L12: 145.83333 | M12: 24.615385 | N12: 80 | O12: 125543.82
A13: Hiabs Logistics | B13: KTU77XP | C13: KTU77XP | D13: MVEH-000102 | E13: 0.42 | F13: 21600 | G13: 16 | H13: 1800 | I13: 284 | J13: 284 | K13: 89136.641 | L13: 145.83333 | M13: 30.769231 | N13: 80 | O13: 115877.63
A14: Hiabs Logistics | B14: KTU79XP | C14: T-2405LA | D14: MVEH-000105 | E14: 0.42 | F14: 21600 | G14: 16 | H14: 1800 | I14: 284 | J14: 284 | K14: 94395.326 | L14: 145.83333 | M14: 24.615385 | N14: 80 | O14: 122713.92
... A42: HAULAGE | B42: T20358LA | C42: T20358LA | D42: MVEH-000334 | E42: 0.5 | F42: 66000 | G42: 3 | H42: 5500 | I42: 260 | J42: 260 | K42: 145036.61 | L42: 81.439394 | M42: 143.84615 | N42: 25 | O42: 210303.08
A43: NBL-DSL | B43: =_xlfn.XLOOKUP(D43,'Asset Code'!$A:$A,'Asset Code'!$B:$B) -> T33405LA | C43: =B43 -> T33405LA | D43: MVEH-000443 | E43: 0.5 | F43: 66000 | G43: 3 | H43: 5500 | I43: 293 | J43: 293 | K43: 187900.17 | L43: 99.621212 | M43: 143.84615 | N43: 36 | O43: 244270.22
A44: NBL-DSL | B44: =_xlfn.XLOOKUP(D44,'Asset Code'!$A:$A,'Asset Code'!$B:$B) -> T33404LA | C44: =B44 -> T33404LA | D44: MVEH-000444 | E44: 0.5 | F44: 66000 | G44: 3 | H44: 5500 | I44: 293 | J44: 293 | K44: 187900.17 | L44: 99.621212 | M44: 143.84615 | N44: 36 | O44: 244270.22
A45: NBL-DSL | B45: =_xlfn.XLOOKUP(D45,'Asset Code'!$A:$A,'Asset Code'!$B:$B) -> T33403LA | C45: =B45 -> T33403LA | D45: MVEH-000445 | E45: 0.5 | F45: 66000 | G45: 3 | H45: 5500 | I45: 293 | J45: 293 | K45: 187900.17 | L45: 99.621212 | M45: 143.84615 | N45: 36 | O45: 244270.22
A46: NBL-DSL | B46: =_xlfn.XLOOKUP(D46,'Asset Code'!$A:$A,'Asset Code'!$B:$B) -> T33402LA | C46: =B46 -> T33402LA | D46: MVEH-000446 | E46: 0.5 | F46: 66000 | G46: 3 | H46: 5500 | I46: 293 | J46: 293 | K46: 187900.17 | L46: 99.621212 | M46: 143.84615 | N46: 36 | O46: 244270.22
A47: NBL-DSL | B47: =_xlfn.XLOOKUP(D47,'Asset Code'!$A:$A,'Asset Code'!$B:$B) -> T33401LA | C47: =B47 -> T33401LA | D47: MVEH-000447 | E47: 0.5 | F47: 66000 | G47: 3 | H47: 5500 | I47: 293 | J47: 293 | K47: 187900.17 | L47: 99.621212 | M47: 143.84615 | N47: 36 | O47: 244270.22
A48: NBL-DSL | B48: =_xlfn.XLOOKUP(D48,'Asset Code'!$A:$A,'Asset Code'!$B:$B) -> T33213LA | C48: =B48 -> T33213LA | D48: MVEH-000448 | E48: 0.5 | F48: 66000 | G48: 3 | H48: 5500 | I48: 293 | J48: 293 | K48: 187900.17 | L48: 99.621212 | M48: 143.84615 | N48: 36 | O48: 244270.22
A49: NBL-DSL | B49: =_xlfn.XLOOKUP(D49,'Asset Code'!$A:$A,'Asset Code'!$B:$B) -> T33076LA | C49: =B49 -> T33076LA | D49: MVEH-000449 | E49: 0.5 | F49: 66000 | G49: 3 | H49: 5500 | I49: 293 | J49: 293 | K49: 187900.17 | L49: 99.621212 | M49: 143.84615 | N49: 36 | O49: 244270.22
A50: NBL-DSL | B50: =_xlfn.XLOOKUP(D50,'Asset Code'!$A:$A,'Asset Code'!$B:$B) -> T33075LA | C50: =B50 -> T33075LA | D50: MVEH-000450 | E50: 0.5 | F50: 66000 | G50: 3 | H50: 5500 | I50: 293 | J50: 293 | K50: 187900.17 | L50: 99.621212 | M50: 143.84615 | N50: 36 | O50: 244270.22
A51: NBL-DSL | B51: =_xlfn.XLOOKUP(D51,'Asset Code'!$A:$A,'Asset Code'!$B:$B) -> T33074LA | C51: =B51 -> T33074LA | D51: MVEH-000451 | E51: 0.5 | F51: 66000 | G51: 3 | H51: 5500 | I51: 293 | J51: 293 | K51: 187900.17 | L51: 99.621212 | M51: 143.84615 | N51: 36 | O51: 244270.22
A52: NBL-DSL | B52: =_xlfn.XLOOKUP(D52,'Asset Code'!$A:$A,'Asset Code'!$B:$B) -> T33073LA | C52: =B52 -> T33073LA | D52: MVEH-000452 | E52: 0.5 | F52: 66000 | G52: 3 | H52: 5500 | I52: 293 | J52: 293 | K52: 187900.17 | L52: 99.621212 | M52: 143.84615 | N52: 36 | O52: 244270.22
A53: NBL-CNG | B53: NBL11 | C53: NBL11 | D53: MVEH-000433 | E53: 0.7 | F53: 66000 | G53: 3 | H53: 5500 | I53: 293 | J53: 293 | K53: 204282.42 | L53: 99.621212 | M53: 143.84615 | N53: 36 | O53: 265567.15
A54: NBL-CNG | B54: NBL12 | C54: NBL12 | D54: MVEH-000434 | E54: 0.7 | F54: 66000 | G54: 3 | H54: 5500 | I54: 293 | J54: 293 | K54: 204282.42 | L54: 99.621212 | M54: 143.84615 | N54: 36 | O54: 265567.15
A55: NBL-CNG | B55: NBL13 | C55: NBL13 | D55: MVEH-000435 | E55: 0.7 | F55: 66000 | G55: 3 | H55: 5500 | I55: 293 | J55: 293 | K55: 204282.42 | L55: 99.621212 | M55: 143.84615 | N55: 36 | O55: 265567.15
A56: NBL-CNG | B56: NBL14 | C56: NBL14 | D56: MVEH-000436 | E56: 0.7 | F56: 66000 | G56: 3 | H56: 5500 | I56: 293 | J56: 293 | K56: 204282.42 | L56: 99.621212 | M56: 143.84615 | N56: 36 | O56: 265567.15
A57: NBL-CNG | B57: NBL15 | C57: NBL15 | D57: MVEH-000437 | E57: 0.7 | F57: 66000 | G57: 3 | H57: 5500 | I57: 293 | J57: 293 | K57: 204282.42 | L57: 99.621212 | M57: 143.84615 | N57: 36 | O57: 265567.15
A58: NBL-CNG | B58: NBL16 | C58: NBL16 | D58: MVEH-000438 | E58: 0.7 | F58: 66000 | G58: 3 | H58: 5500 | I58: 293 | J58: 293 | K58: 204282.42 | L58: 99.621212 | M58: 143.84615 | N58: 36 | O58: 265567.15
A59: NBL-CNG | B59: NBL17 | C59: NBL17 | D59: MVEH-000439 | E59: 0.7 | F59: 66000 | G59: 3 | H59: 5500 | I59: 293 | J59: 293 | K59: 204282.42 | L59: 99.621212 | M59: 143.84615 | N59: 36 | O59: 265567.15
A60: NBL-CNG | B60: NBL18 | C60: NBL18 | D60: MVEH-000440 | E60: 0.7 | F60: 66000 | G60: 3 | H60: 5500 | I60: 293 | J60: 293 | K60: 204282.42 | L60: 99.621212 | M60: 143.84615 | N60: 36 | O60: 265567.15
A61: NBL-CNG | B61: NBL19 | C61: NBL19 | D61: MVEH-000441 | E61: 0.7 | F61: 66000 | G61: 3 | H61: 5500 | I61: 293 | J61: 293 | K61: 204282.42 | L61: 99.621212 | M61: 143.84615 | N61: 36 | O61: 265567.15
A62: NBL-CNG | B62: NBL20 | C62: NBL20 | D62: MVEH-000442 | E62: 0.7 | F62: 66000 | G62: 3 | H62: 5500 | I62: 293 | J62: 293 | K62: 204282.42 | L62: 99.621212 | M62: 143.84615 | N62: 36 | O62: 265567.15
A63: Flat Trucks Logistics- | B63: KJA44XZ | C63: T-2404LA | D63: MVEH-000266 | E63: 0.42 | F63: 11700 | G63: 6.5 | H63: 975 | I63: 260 | J63: 260 | K63: 113224.05 | L63: 382.47863 | M63: 53.846154 | N63: 25 | O63: 271737.72
A64: Flat Trucks Logistics- | B64: LSD698XZ | C64: T-2407LA | D64: MVEH-000271 | E64: 0.42 | F64: 11700 | G64: 6.5 | H64: 975 | I64: 260 | J64: 260 | K64: 114569.74 | L64: 382.47863 | M64: 53.846154 | N64: 25 | O64: 274967.36
... A69: Flat Trucks Logistics- | B69: KJA47XZ | C69: T-2490LA | D69: MVEH-000269 | E69: 0.42 | F69: 11700 | G69: 6.5 | H69: 975 | I69: 260 | J69: 260 | K69: 113614.43 | L69: 382.47863 | M69: 53.846154 | N69: 25 | O69: 272674.64

Sheet KPI
A2: KPI
A3: Driving KM Per Day for All Upcountry trucks | B3: 300KM
A4: Offloading and offloading for all deliveries should be 1 day | B4: 1 Day
A5: Diesel Hiab | B5: 0.42
A6: Flat Bed Diesel needed | B6: 0.42
A7: Haulage truck 30T -102 | B7: 0.42
A8: Haulage Truck 45T 102 | B8: 0.5
A9: CNG Truck consumption | B9: 0.75
A10: 16CBM Truck | B10: 0.15
A11: 30CBM Truck | B11: 0.35
A15: Logistics Port Expenses | B15: Driver Road Expenses | C15: Additional Diesel | D15: Passing Truck Express | E15: Dropping Empty
A16: APMT-MSC | B16: 114000 | C16: 40000 | D16: 300000 | E16: 80000
A17: APMT-CMA | B17: 114000 | C17: 40000 | D17: 300000 | E17: 39000
A18: ESS-Libra-CMA | B18: 114000 | C18: 40000 | D18: 40000 | E18: 39000
A19: ESS-Libra-MSC | B19: 114000 | C19: 40000 | D19: 40000 | E19: 80000
A20: Ikorudo-CMA | B20: 114000 | C20: 40000 | D20: 40000 | E20: 39000
A21: Ikorudo-MSC | B21: 114000 | C21: 40000 | D21: 40000 | E21: 80000

Sheet Expense Account 
A1: Type | B1: Account number | C1: Account Name | D1: Expense Type | E1: KPI
A2: Operational Expenses | B2: 6101027 | C2: Logistics Allowances | D2: Drivers Trip Expenses | E2: 25 Naira Per KM
B3: 6103008 | C3: Diesel for Hiabs | D3: Diesel from Internal Fuel Dump | E3: Use KPI Sheet
B4: 6103009 | C4: Diesel for Lorries | D4: Diesel from Internal Fuel Dump | E4: Use KPI Sheet
B5: 6103013 | C5: Fuel and Diesel Logistics Allowances | D5: Cash Allowance to buy Diesel | E5: Additional Expense on Created Trip
B6: New Account | C6: CNG Expense | D6: Cash Allowance for CNG | E6: Use KPI Sheet
B7: 6105047 | C7: Logistics Misc Expenses | D7: Tickets and Sticker Payments | E7: Additional Expense on Created Trip
B8: 6105051 | C8: Logistics Port Expenses | D8: Port Operation Expenses | E8: Use KPI Sheet
B9: 6102028 | C9: Truck Tyre Expenses | D9: Tyre Expenses | E9: MTC Module
B10: 6102010 | C10: Lorries Maintenance Expenses | D10: Tractor and Trailer Repairs | E10: MTC Module
B11: 6102009 | C11: Hiabs Maintenance Expenses | D11: Hiab | E11: MTC Module
B12: 6101030 | C12: Logistics Positioning-Pushing Allowances | D12: Manual Pushing | E12: Additional Expense on Created Trip
B13: 6105061 | C13: Delivery Allowance Misc | D13: Community Settlement | E13: Additional Expense on Created Trip
B14: 6105040 | C14: Towing/Other Vehicle Breakdown Expenses | D14: Towing | E14: Expense Module Request
B15: 6105001 | C15: Transportation And Offloading Of Finished Goods | D15: 3rd Party contracted Trucks | E15: 3PL PO
B16: 6105002 | C16: Crane & Heavy Lifts | D16: Crane & Heavy Lifts | E16: 3PL PO
B17: 6105003 | C17: Staff Transportation | D17: Transport for Operational Staffs | E17: 3PL PO
B18: New Account | C18: Tracking System | D18: For subscription of Tracking | E18: PO Level should all be posted on the asset
A19: Non-Operational Expenses | C19: Insurance | D19: Vehicle Insurance | E19: Entries on Asset
C20: GIT | D20: Good in Transit
C21: License and Permit | D21: License and Permit | E21: Entries on Asset
C22: Salaries Local and Expat
C23: Rent | D23: House rents offices and Yard
C24: Depreciation | D24: Vehicle Depreciation

Sheet All Routes
A1: Contract Name | B1: Truck Size | C1: Division | D1: Truck Tonnage | E1: Client | F1: Client Main Location | G1: Loading Point | H1: Loading State | I1: Destination (corrected) | J1: Destination State | K1: Region (geopolitical zone) | L1: Delivery Type | M1: Internal Zone | N1: Stops (in drive order) | O1: Leg Breakdown (km) | P1: Leg 1 - Outbound KM | Q1: Leg 2 - Return KM | R1: Total Round Trip KM | S1: KM Source | T1: Notes
A2: JAT-45T-NBL-DSL-JUMBO | B2: JUMBO | C2: NBL-DSL | D2: 45T | E2: JAT | F2: Ibadan | G2: Ibadan | H2: Oyo | I2: Kano | J2: Kano | K2: North West | L2: Interstate | N2: Kano | O2: Ibadan > Kano: 876 | Return Kano > Ibadan: 876 | P2: 876 | Q2: 876 | R2: =IF(P2="","",P2+Q2) -> 1752 | S2: Estimated (calibrated)
A3: ABBA SALEH-45T-NBL-DSL-JUMBO | B3: JUMBO | C3: NBL-DSL | D3: 45T | E3: ABBA SALEH | F3: Keffi | G3: Keffi | H3: Nasarawa | I3: Ogere | J3: Ogun | K3: South West | L3: Interstate | N3: Ogere | O3: Keffi > Ogere: 728 | Return Ogere > Keffi: 728 | P3: 728 | Q3: 728 | R3: =IF(P3="","",P3+Q3) -> 1456 | S3: Road-routed (OpenStreetMap)
A4: ABBA SALEH-30T-NBL-DSL-JUMBO | B4: JUMBO | C4: NBL-DSL | D4: 30T | E4: ABBA SALEH | F4: Keffi | G4: Keffi | H4: Nasarawa | I4: Ogere | J4: Ogun | K4: South West | L4: Interstate | N4: Ogere | O4: Keffi > Ogere: 728 | Return Ogere > Keffi: 728 | P4: 728 | Q4: 728 | R4: =IF(P4="","",P4+Q4) -> 1456 | S4: Road-routed (OpenStreetMap)
A5: JAT-45T-NBL-DSL-JUMBO | B5: JUMBO | C5: NBL-DSL | D5: 45T | E5: JAT | F5: Ibadan | G5: Ibadan | H5: Oyo | I5: Abuja | J5: FCT | K5: North Central | L5: Interstate | N5: Abuja | O5: Ibadan > Abuja: 612 | Return Abuja > Ibadan: 612 | P5: 612 | Q5: 612 | R5: =IF(P5="","",P5+Q5) -> 1224 | S5: Estimated (calibrated)
A6: JAT-45T-NBL-DSL-JUMBO | B6: JUMBO | C6: NBL-DSL | D6: 45T | E6: JAT | F6: Ibadan | G6: Ibadan | H6: Oyo | I6: Suleja | J6: Niger | K6: North Central | L6: Interstate | N6: Suleja | O6: Ibadan > Suleja: 578 | Return Suleja > Ibadan: 578 | P6: 578 | Q6: 578 | R6: =IF(P6="","",P6+Q6) -> 1156 | S6: Estimated (calibrated)
A7: JAT-45T-NBL-DSL-JUMBO | B7: JUMBO | C7: NBL-DSL | D7: 45T | E7: JAT | F7: Ibadan | G7: Ibadan | H7: Oyo | I7: Sokoto | J7: Sokoto | K7: North West | L7: Interstate | N7: Sokoto | O7: Ibadan > Sokoto: 787 | Return Sokoto > Ibadan: 787 | P7: 787 | Q7: 787 | R7: =IF(P7="","",P7+Q7) -> 1574 | S7: Estimated (calibrated)
A8: JAT-45T-NBL-DSL-JUMBO | B8: JUMBO | C8: NBL-DSL | D8: 45T | E8: JAT | F8: Ibadan | G8: Ibadan | H8: Oyo | I8: Wukari | J8: Taraba | K8: North East | L8: Interstate | N8: Wukari | O8: Ibadan > Wukari: 846 | Return Wukari > Ibadan: 846 | P8: 846 | Q8: 846 | R8: =IF(P8="","",P8+Q8) -> 1692 | S8: Estimated (calibrated)
A9: JAT-45T-NBL-DSL-JUMBO | B9: JUMBO | C9: NBL-DSL | D9: 45T | E9: JAT | F9: Ibadan | G9: Ibadan | H9: Oyo | I9: Jalingo | J9: Taraba | K9: North East | L9: Interstate | N9: Jalingo | O9: Ibadan > Jalingo: 1090 | Return Jalingo > Ibadan: 1090 | P9: 1090 | Q9: 1090 | R9: =IF(P9="","",P9+Q9) -> 2180 | S9: Estimated (calibrated)
A10: JAT-45T-NBL-DSL-JUMBO | B10: JUMBO | C10: NBL-DSL | D10: 45T | E10: JAT | F10: Ibadan | G10: Ibadan | H10: Oyo | I10: Kontagora | J10: Niger | K10: North Central | L10: Interstate | N10: Kontagora | O10: Ibadan > Kontagora: 527 | Return Kontagora > Ibadan: 527 | P10: 527 | Q10: 527 | R10: =IF(P10="","",P10+Q10) -> 1054 | S10: Estimated (calibrated)
A11: JAT-45T-NBL-DSL-JUMBO | B11: JUMBO | C11: NBL-DSL | D11: 45T | E11: JAT | F11: Ibadan | G11: Ibadan | H11: Oyo | I11: Gombe | J11: Gombe | K11: North East | L11: Interstate | N11: Gombe | O11: Ibadan > Gombe: 1120 | Return Gombe > Ibadan: 1120 | P11: 1120 | Q11: 1120 | R11: =IF(P11="","",P11+Q11) -> 2240 | S11: Estimated (calibrated)
A12: JAT-45T-NBL-DSL-JUMBO | B12: JUMBO | C12: NBL-DSL | D12: 45T | E12: JAT | F12: Ibadan | G12: Ibadan | H12: Oyo | I12: Minna | J12: Niger | K12: North Central | L12: Interstate | N12: Minna | O12: Ibadan > Minna: 535 | Return Minna > Ibadan: 535 | P12: 535 | Q12: 535 | R12: =IF(P12="","",P12+Q12) -> 1070 | S12: Estimated (calibrated)
A13: JAT-45T-NBL-DSL-JUMBO | B13: JUMBO | C13: NBL-DSL | D13: 45T | E13: JAT | F13: Ibadan | G13: Ibadan | H13: Oyo | I13: Zaria | J13: Kaduna | K13: North West | L13: Interstate | N13: Zaria | O13: Ibadan > Zaria: 713 | Return Zaria > Ibadan: 713 | P13: 713 | Q13: 713 | R13: =IF(P13="","",P13+Q13) -> 1426 | S13: Estimated (calibrated)
... A39: JAT-45T-NBL-DSL-JUMBO | B39: JUMBO | C39: NBL-DSL | D39: 45T | E39: JAT | F39: Ibadan | G39: Ibadan | H39: Oyo | I39: Koko (Kebbi) | J39: Kebbi | K39: North West | L39: Interstate | N39: Koko | O39: Ibadan > Koko: 553 | Return Koko > Ibadan: 553 | P39: 553 | Q39: 553 | R39: =IF(P39="","",P39+Q39) -> 1106 | S39: Estimated (calibrated)
A40: JAT-45T-NBL-DSL-JUMBO | B40: JUMBO | C40: NBL-DSL | D40: 45T | E40: JAT | F40: Ibadan | G40: Ibadan | H40: Oyo | I40: Ibadan | J40: Oyo | K40: South West | L40: Internal (within state) | M40: Outside listed zones | N40: Ibadan | O40: Ibadan > Ibadan: 10 | Return Ibadan > Ibadan: 10 | P40: 10 | Q40: 10 | R40: =IF(P40="","",P40+Q40) -> 20 | S40: Estimated (calibrated) | T40: Delivery inside the loading town - 10 km allowance each way
A41: JAT-45T-NBL-DSL-JUMBO | B41: JUMBO | C41: NBL-DSL | D41: 45T | E41: JAT | F41: Ibadan | G41: Ibadan | H41: Oyo | I41: Ekpoma | J41: Edo | K41: South South | L41: Interstate | N41: Ekpoma | O41: Ibadan > Ekpoma: 315 | Return Ekpoma > Ibadan: 315 | P41: 315 | Q41: 315 | R41: =IF(P41="","",P41+Q41) -> 630 | S41: Estimated (calibrated)
A42: JAT-45T-NBL-DSL-JUMBO | B42: JUMBO | C42: NBL-DSL | D42: 45T | E42: JAT | F42: Ibadan | G42: Ibadan | H42: Oyo | I42: Aba | J42: Abia | K42: South East | L42: Interstate | N42: Aba | O42: Ibadan > Aba: 580 | Return Aba > Ibadan: 580 | P42: 580 | Q42: 580 | R42: =IF(P42="","",P42+Q42) -> 1160 | S42: Estimated (calibrated)
A43: JAT-45T-NBL-DSL-JUMBO | B43: JUMBO | C43: NBL-DSL | D43: 45T | E43: JAT | F43: Ibadan | G43: Ibadan | H43: Oyo | I43: Agbor | J43: Delta | K43: South South | L43: Interstate | N43: Agbor | O43: Ibadan > Agbor: 357 | Return Agbor > Ibadan: 357 | P43: 357 | Q43: 357 | R43: =IF(P43="","",P43+Q43) -> 714 | S43: Estimated (calibrated)
A44: JAT-45T-NBL-DSL-JUMBO | B44: JUMBO | C44: NBL-DSL | D44: 45T | E44: JAT | F44: Ibadan | G44: Ibadan | H44: Oyo | I44: Onitsha | J44: Anambra | K44: South East | L44: Interstate | N44: Onitsha | O44: Ibadan > Onitsha: 442 | Return Onitsha > Ibadan: 442 | P44: 442 | Q44: 442 | R44: =IF(P44="","",P44+Q44) -> 884 | S44: Estimated (calibrated)
A45: JAT-45T-NBL-DSL-JUMBO | B45: JUMBO | C45: NBL-DSL | D45: 45T | E45: JAT | F45: Ibadan | G45: Ibadan | H45: Oyo | I45: Abakaliki | J45: Ebonyi | K45: South East | L45: Interstate | N45: Abakaliki | O45: Ibadan > Abakaliki: 631 | Return Abakaliki > Ibadan: 631 | P45: 631 | Q45: 631 | R45: =IF(P45="","",P45+Q45) -> 1262 | S45: Estimated (calibrated)
A46: JAT-45T-NBL-DSL-JUMBO | B46: JUMBO | C46: NBL-DSL | D46: 45T | E46: JAT | F46: Ibadan | G46: Ibadan | H46: Oyo | I46: Otukpo | J46: Benue | K46: North Central | L46: Interstate | N46: Otukpo | O46: Ibadan > Otukpo: 655 | Return Otukpo > Ibadan: 655 | P46: 655 | Q46: 655 | R46: =IF(P46="","",P46+Q46) -> 1310 | S46: Estimated (calibrated)
A47: Givanas-45T-NBL-DSL-JUMBO | B47: JUMBO | C47: NBL-DSL | D47: 45T | E47: Givanas | F47: Lagos | G47: Amuwo Odofin | H47: Lagos | I47: Onitsha | J47: Anambra | K47: South East | L47: Interstate | N47: Onitsha | O47: Amuwo Odofin > Onitsha: 483 | Return Onitsha > Amuwo Odofin: 483 | P47: 483 | Q47: 483 | R47: =IF(P47="","",P47+Q47) -> 966 | S47: Estimated (calibrated)
A48: Givanas-45T-NBL-DSL-JUMBO | B48: JUMBO | C48: NBL-DSL | D48: 45T | E48: Givanas | F48: Lagos | G48: Amuwo Odofin | H48: Lagos | I48: Kano | J48: Kano | K48: North West | L48: Interstate | N48: Kano | O48: Amuwo Odofin > Kano: 1021 | Return Kano > Amuwo Odofin: 1021 | P48: 1021 | Q48: 1021 | R48: =IF(P48="","",P48+Q48) -> 2042 | S48: Estimated (calibrated)
A49: Givanas-45T-NBL-DSL-JUMBO | B49: JUMBO | C49: NBL-DSL | D49: 45T | E49: Givanas | F49: Lagos | G49: Amuwo Odofin | H49: Lagos | I49: Sokoto | J49: Sokoto | K49: North West | L49: Interstate | N49: Sokoto | O49: Amuwo Odofin > Sokoto: 928 | Return Sokoto > Amuwo Odofin: 928 | P49: 928 | Q49: 928 | R49: =IF(P49="","",P49+Q49) -> 1856 | S49: Estimated (calibrated)
A50: JAMARA-30T-NBL-DSL-JUMBO | B50: JUMBO | C50: NBL-DSL | D50: 30T | E50: JAMARA | F50: Lagos | G50: JMG Gbagada | H50: Lagos | I50: Port Harcourt | J50: Rivers | K50: South South | L50: Interstate | N50: Port Harcourt | O50: JMG Gbagada > Port Harcourt: 603 | Return Port Harcourt > JMG Gbagada: 603 | P50: 603 | Q50: 603 | R50: =IF(P50="","",P50+Q50) -> 1206 | S50: Estimated (calibrated)
A51: JAMARA-30T-NBL-DSL-JUMBO | B51: JUMBO | C51: NBL-DSL | D51: 30T | E51: JAMARA | F51: Lagos | G51: JMG Gbagada | H51: Lagos | I51: Abuja | J51: FCT | K51: North Central | L51: Interstate | N51: Abuja | O51: JMG Gbagada > Abuja: 740 | Return Abuja > JMG Gbagada: 740 | P51: 740 | Q51: 740 | R51: =IF(P51="","",P51+Q51) -> 1480 | S51: Road-routed (OpenStreetMap)
A52: JAMARA-30T-NBL-DSL-JUMBO | B52: JUMBO | C52: NBL-DSL | D52: 30T | E52: JAMARA | F52: Lagos | G52: JMG Gbagada | H52: Lagos | I52: Kano | J52: Kano | K52: North West | L52: Interstate | N52: Kano | O52: JMG Gbagada > Kano: 984 | Return Kano > JMG Gbagada: 984 | P52: 984 | Q52: 984 | R52: =IF(P52="","",P52+Q52) -> 1968 | S52: Road-routed (OpenStreetMap)
... A67: Mega Manu-45T-NBL-DSL-JUMBO | B67: JUMBO | C67: NBL-DSL | D67: 45T | E67: Mega Manu | F67: Lagos | G67: Apapa | H67: Lagos | I67: Kaduna | J67: Kaduna | K67: North West | L67: Interstate | N67: Kaduna | O67: Apapa > Kaduna: 774 | Return Kaduna > Apapa: 774 | P67: 774 | Q67: 774 | R67: =IF(P67="","",P67+Q67) -> 1548 | S67: Estimated (calibrated)
A68: Mega Manu-Local-30T-NBL-DSL-JUMBO | B68: JUMBO | C68: NBL-DSL | D68: 30T | E68: Mega Manu-Local | F68: Lagos | G68: Apapa | H68: Lagos | I68: Agbara | J68: Ogun | K68: South West | L68: Interstate | M68: Ojo–Badagry | N68: Agbara | O68: Apapa > Agbara: 43 | Return Agbara > Apapa: 43 | P68: 43 | Q68: 43 | R68: =IF(P68="","",P68+Q68) -> 86 | S68: Estimated (calibrated)
A69: Mega Manu-Local-30T-NBL-DSL-JUMBO | B69: JUMBO | C69: NBL-DSL | D69: 30T | E69: Mega Manu-Local | F69: Lagos | G69: Apapa | H69: Lagos | I69: Amuwo Odofin | J69: Lagos | K69: South West | L69: Internal (within state) | M69: Mainland | N69: Amuwo Odofin | O69: Apapa > Amuwo Odofin: 10 | Return Amuwo Odofin > Apapa: 10 | P69: 10 | Q69: 10 | R69: =IF(P69="","",P69+Q69) -> 20 | S69: Estimated (calibrated)
A70: Mega Manu-Local-30T-NBL-DSL-JUMBO | B70: JUMBO | C70: NBL-DSL | D70: 30T | E70: Mega Manu-Local | F70: Lagos | G70: Apapa | H70: Lagos | I70: Isolo | J70: Lagos | K70: South West | L70: Internal (within state) | M70: Mainland | N70: Isolo | O70: Apapa > Isolo: 15 | Return Isolo > Apapa: 15 | P70: 15 | Q70: 15 | R70: =IF(P70="","",P70+Q70) -> 30 | S70: Estimated (calibrated)
A71: Mega Manu-Local-30T-NBL-DSL-JUMBO | B71: JUMBO | C71: NBL-DSL | D71: 30T | E71: Mega Manu-Local | F71: Lagos | G71: Apapa | H71: Lagos | I71: Ibadan | J71: Oyo | K71: South West | L71: Interstate | N71: Ibadan | O71: Apapa > Ibadan: 156 | Return Ibadan > Apapa: 156 | P71: 156 | Q71: 156 | R71: =IF(P71="","",P71+Q71) -> 312 | S71: Estimated (calibrated)
A72: Mega Manu-Local-30T-NBL-DSL-JUMBO | B72: JUMBO | C72: NBL-DSL | D72: 30T | E72: Mega Manu-Local | F72: Lagos | G72: Apapa | H72: Lagos | I72: Sango Ota | J72: Ogun | K72: South West | L72: Interstate | N72: Sango Ota | O72: Apapa > Sango Ota: 42 | Return Sango Ota > Apapa: 42 | P72: 42 | Q72: 42 | R72: =IF(P72="","",P72+Q72) -> 84 | S72: Estimated (calibrated)
A73: Mega Manu-Local-30T-NBL-DSL-JUMBO | B73: JUMBO | C73: NBL-DSL | D73: 30T | E73: Mega Manu-Local | F73: Lagos | G73: Apapa | H73: Lagos | I73: Matori | J73: Lagos | K73: South West | L73: Internal (within state) | M73: Mainland | N73: Matori | O73: Apapa > Matori: 15 | Return Matori > Apapa: 15 | P73: 15 | Q73: 15 | R73: =IF(P73="","",P73+Q73) -> 30 | S73: Estimated (calibrated)
A74: Mega Manu-Local-30T-NBL-DSL-JUMBO | B74: JUMBO | C74: NBL-DSL | D74: 30T | E74: Mega Manu-Local | F74: Lagos | G74: Apapa | H74: Lagos | I74: Fatai Atere | J74: Lagos | K74: South West | L74: Internal (within state) | M74: Mainland | N74: Fatai Atere | O74: Apapa > Fatai Atere: 12 | Return Fatai Atere > Apapa: 12 | P74: 12 | Q74: 12 | R74: =IF(P74="","",P74+Q74) -> 24 | S74: Estimated (calibrated)
A75: Mega Manu-Local-30T-NBL-DSL-JUMBO | B75: JUMBO | C75: NBL-DSL | D75: 30T | E75: Mega Manu-Local | F75: Lagos | G75: Apapa | H75: Lagos | I75: Igbesa | J75: Ogun | K75: South West | L75: Interstate | N75: Igbesa | O75: Apapa > Igbesa: 39 | Return Igbesa > Apapa: 39 | P75: 39 | Q75: 39 | R75: =IF(P75="","",P75+Q75) -> 78 | S75: Estimated (calibrated)
A76: Mega Manu-Local-30T-NBL-DSL-JUMBO | B76: JUMBO | C76: NBL-DSL | D76: 30T | E76: Mega Manu-Local | F76: Lagos | G76: Apapa | H76: Lagos | I76: Ikeja | J76: Lagos | K76: South West | L76: Internal (within state) | M76: Mainland | N76: Ikeja | O76: Apapa > Ikeja: 23 | Return Ikeja > Apapa: 23 | P76: 23 | Q76: 23 | R76: =IF(P76="","",P76+Q76) -> 46 | S76: Estimated (calibrated)
A77: Mega Manu-Local-30T-NBL-DSL-JUMBO | B77: JUMBO | C77: NBL-DSL | D77: 30T | E77: Mega Manu-Local | F77: Lagos | G77: Apapa | H77: Lagos | I77: Dopemu | J77: Lagos | K77: South West | L77: Internal (within state) | M77: Mainland | N77: Dopemu | O77: Apapa > Dopemu: 27 | Return Dopemu > Apapa: 27 | P77: 27 | Q77: 27 | R77: =IF(P77="","",P77+Q77) -> 54 | S77: Estimated (calibrated)
A78: Mega Manu-Local-30T-NBL-DSL-JUMBO | B78: JUMBO | C78: NBL-DSL | D78: 30T | E78: Mega Manu-Local | F78: Lagos | G78: Apapa | H78: Lagos | I78: Sagamu | J78: Ogun | K78: South West | L78: Interstate | N78: Sagamu | O78: Apapa > Sagamu: 70 | Return Sagamu > Apapa: 70 | P78: 70 | Q78: 70 | R78: =IF(P78="","",P78+Q78) -> 140 | S78: Estimated (calibrated)
A79: Mega Manu-Local-30T-NBL-DSL-JUMBO | B79: JUMBO | C79: NBL-DSL | D79: 30T | E79: Mega Manu-Local | F79: Lagos | G79: Apapa | H79: Lagos | I79: Mowe | J79: Ogun | K79: South West | L79: Interstate | N79: Mowe | O79: Apapa > Mowe: 53 | Return Mowe > Apapa: 53 | P79: 53 | Q79: 53 | R79: =IF(P79="","",P79+Q79) -> 106 | S79: Estimated (calibrated)
A80: Mega Manu-Local-30T-NBL-DSL-JUMBO | B80: JUMBO | C80: NBL-DSL | D80: 30T | E80: Mega Manu-Local | F80: Lagos | G80: Apapa | H80: Lagos | I80: Ijebu Ososa | J80: Ogun | K80: South West | L80: Interstate | N80: Ijebu Ososa | O80: Apapa > Ijebu Ososa: 81 | Return Ijebu Ososa > Apapa: 81 | P80: 81 | Q80: 81 | R80: =IF(P80="","",P80+Q80) -> 162 | S80: Estimated (calibrated)
A81: Mega Manu-Local-30T-NBL-DSL-JUMBO | B81: JUMBO | C81: NBL-DSL | D81: 30T | E81: Mega Manu-Local | F81: Lagos | G81: Apapa | H81: Lagos | I81: Ojota | J81: Lagos | K81: South West | L81: Internal (within state) | M81: Mainland | N81: Ojota | O81: Apapa > Ojota: 21 | Return Ojota > Apapa: 21 | P81: 21 | Q81: 21 | R81: =IF(P81="","",P81+Q81) -> 42 | S81: Estimated (calibrated)
A82: Mega Manu-Local-30T-NBL-DSL-JUMBO | B82: JUMBO | C82: NBL-DSL | D82: 30T | E82: Mega Manu-Local | F82: Lagos | G82: Apapa | H82: Lagos | I82: Ijebu Ode | J82: Ogun | K82: South West | L82: Interstate | N82: Ijebu Ode | O82: Apapa > Ijebu Ode: 96 | Return Ijebu Ode > Apapa: 96 | P82: 96 | Q82: 96 | R82: =IF(P82="","",P82+Q82) -> 192 | S82: Estimated (calibrated)
A83: Mega Manu-Local-30T-NBL-DSL-JUMBO | B83: JUMBO | C83: NBL-DSL | D83: 30T | E83: Mega Manu-Local | F83: Lagos | G83: Apapa | H83: Lagos | I83: Apapa | J83: Lagos | K83: South West | L83: Internal (within state) | M83: Mainland | N83: Apapa | O83: Apapa > Apapa: 10 | Return Apapa > Apapa: 10 | P83: 10 | Q83: 10 | R83: =IF(P83="","",P83+Q83) -> 20 | S83: Estimated (calibrated) | T83: Delivery inside the loading town - 10 km allowance each way
A84: Mega Manu-Local-30T-NBL-DSL-JUMBO | B84: JUMBO | C84: NBL-DSL | D84: 30T | E84: Mega Manu-Local | F84: Lagos | G84: Apapa | H84: Lagos | I84: Ilupeju | J84: Lagos | K84: South West | L84: Internal (within state) | M84: Mainland | N84: Ilupeju | O84: Apapa > Ilupeju: 16 | Return Ilupeju > Apapa: 16 | P84: 16 | Q84: 16 | R84: =IF(P84="","",P84+Q84) -> 32 | S84: Estimated (calibrated)
A85: Mega Manu-Local-30T-NBL-DSL-JUMBO | B85: JUMBO | C85: NBL-DSL | D85: 30T | E85: Mega Manu-Local | F85: Lagos | G85: Apapa | H85: Lagos | I85: Ajao Estate | J85: Lagos | K85: South West | L85: Internal (within state) | M85: Mainland | N85: Ajao Estate | O85: Apapa > Ajao Estate: 16 | Return Ajao Estate > Apapa: 16 | P85: 16 | Q85: 16 | R85: =IF(P85="","",P85+Q85) -> 32 | S85: Estimated (calibrated)
A86: Mega Manu-Local-30T-NBL-DSL-JUMBO | B86: JUMBO | C86: NBL-DSL | D86: 30T | E86: Mega Manu-Local | F86: Lagos | G86: Apapa | H86: Lagos | I86: Okota | J86: Lagos | K86: South West | L86: Internal (within state) | M86: Mainland | N86: Okota | O86: Apapa > Okota: 12 | Return Okota > Apapa: 12 | P86: 12 | Q86: 12 | R86: =IF(P86="","",P86+Q86) -> 24 | S86: Estimated (calibrated)
A87: Mega Manu-Local-30T-NBL-DSL-JUMBO | B87: JUMBO | C87: NBL-DSL | D87: 30T | E87: Mega Manu-Local | F87: Lagos | G87: Apapa | H87: Lagos | I87: Oshodi | J87: Lagos | K87: South West | L87: Internal (within state) | M87: Mainland | N87: Oshodi | O87: Apapa > Oshodi: 17 | Return Oshodi > Apapa: 17 | P87: 17 | Q87: 17 | R87: =IF(P87="","",P87+Q87) -> 34 | S87: Estimated (calibrated)
A88: Mega Manu-Local-30T-NBL-DSL-JUMBO | B88: JUMBO | C88: NBL-DSL | D88: 30T | E88: Mega Manu-Local | F88: Lagos | G88: Apapa | H88: Lagos | I88: Ogere | J88: Ogun | K88: South West | L88: Interstate | N88: Ogere | O88: Apapa > Ogere: 83 | Return Ogere > Apapa: 83 | P88: 83 | Q88: 83 | R88: =IF(P88="","",P88+Q88) -> 166 | S88: Estimated (calibrated)
A89: Mega Manu-Local-30T-NBL-DSL-JUMBO | B89: JUMBO | C89: NBL-DSL | D89: 30T | E89: Mega Manu-Local | F89: Lagos | G89: Apapa | H89: Lagos | I89: Lekki | J89: Lagos | K89: South West | L89: Internal (within state) | M89: Island | N89: Lekki | O89: Apapa > Lekki: 17 | Return Lekki > Apapa: 17 | P89: 17 | Q89: 17 | R89: =IF(P89="","",P89+Q89) -> 34 | S89: Estimated (calibrated)
A90: Mega Manu-Local-30T-NBL-DSL-JUMBO | B90: JUMBO | C90: NBL-DSL | D90: 30T | E90: Mega Manu-Local | F90: Lagos | G90: Apapa | H90: Lagos | I90: Ogba | J90: Lagos | K90: South West | L90: Internal (within state) | M90: Mainland | N90: Ogba | O90: Apapa > Ogba: 28 | Return Ogba > Apapa: 28 | P90: 28 | Q90: 28 | R90: =IF(P90="","",P90+Q90) -> 56 | S90: Estimated (calibrated)
A91: Mega Manu-Local-30T-NBL-DSL-JUMBO | B91: JUMBO | C91: NBL-DSL | D91: 30T | E91: Mega Manu-Local | F91: Lagos | G91: Apapa | H91: Lagos | I91: Ilorin | J91: Kwara | K91: North Central | L91: Interstate | N91: Ilorin | O91: Apapa > Ilorin: 367 | Return Ilorin > Apapa: 367 | P91: 367 | Q91: 367 | R91: =IF(P91="","",P91+Q91) -> 734 | S91: Estimated (calibrated)
A92: Mega Manu-Local-45T-NBL-DSL-JUMBO | B92: JUMBO | C92: NBL-DSL | D92: 45T | E92: Mega Manu-Local | F92: Lagos | G92: Apapa | H92: Lagos | I92: Agbara | J92: Ogun | K92: South West | L92: Interstate | M92: Ojo–Badagry | N92: Agbara | O92: Apapa > Agbara: 43 | Return Agbara > Apapa: 43 | P92: 43 | Q92: 43 | R92: =IF(P92="","",P92+Q92) -> 86 | S92: Estimated (calibrated)
A93: Mega Manu-Local-45T-NBL-DSL-JUMBO | B93: JUMBO | C93: NBL-DSL | D93: 45T | E93: Mega Manu-Local | F93: Lagos | G93: Apapa | H93: Lagos | I93: Amuwo Odofin | J93: Lagos | K93: South West | L93: Internal (within state) | M93: Mainland | N93: Amuwo Odofin | O93: Apapa > Amuwo Odofin: 10 | Return Amuwo Odofin > Apapa: 10 | P93: 10 | Q93: 10 | R93: =IF(P93="","",P93+Q93) -> 20 | S93: Estimated (calibrated)
A94: Mega Manu-Local-45T-NBL-DSL-JUMBO | B94: JUMBO | C94: NBL-DSL | D94: 45T | E94: Mega Manu-Local | F94: Lagos | G94: Apapa | H94: Lagos | I94: Isolo | J94: Lagos | K94: South West | L94: Internal (within state) | M94: Mainland | N94: Isolo | O94: Apapa > Isolo: 15 | Return Isolo > Apapa: 15 | P94: 15 | Q94: 15 | R94: =IF(P94="","",P94+Q94) -> 30 | S94: Estimated (calibrated)
A95: Mega Manu-Local-45T-NBL-DSL-JUMBO | B95: JUMBO | C95: NBL-DSL | D95: 45T | E95: Mega Manu-Local | F95: Lagos | G95: Apapa | H95: Lagos | I95: Ibadan | J95: Oyo | K95: South West | L95: Interstate | N95: Ibadan | O95: Apapa > Ibadan: 156 | Return Ibadan > Apapa: 156 | P95: 156 | Q95: 156 | R95: =IF(P95="","",P95+Q95) -> 312 | S95: Estimated (calibrated)
A96: Mega Manu-Local-45T-NBL-DSL-JUMBO | B96: JUMBO | C96: NBL-DSL | D96: 45T | E96: Mega Manu-Local | F96: Lagos | G96: Apapa | H96: Lagos | I96: Sango Ota | J96: Ogun | K96: South West | L96: Interstate | N96: Sango Ota | O96: Apapa > Sango Ota: 42 | Return Sango Ota > Apapa: 42 | P96: 42 | Q96: 42 | R96: =IF(P96="","",P96+Q96) -> 84 | S96: Estimated (calibrated)
A97: Mega Manu-Local-45T-NBL-DSL-JUMBO | B97: JUMBO | C97: NBL-DSL | D97: 45T | E97: Mega Manu-Local | F97: Lagos | G97: Apapa | H97: Lagos | I97: Matori | J97: Lagos | K97: South West | L97: Internal (within state) | M97: Mainland | N97: Matori | O97: Apapa > Matori: 15 | Return Matori > Apapa: 15 | P97: 15 | Q97: 15 | R97: =IF(P97="","",P97+Q97) -> 30 | S97: Estimated (calibrated)
A98: Mega Manu-Local-45T-NBL-DSL-JUMBO | B98: JUMBO | C98: NBL-DSL | D98: 45T | E98: Mega Manu-Local | F98: Lagos | G98: Apapa | H98: Lagos | I98: Fatai Atere | J98: Lagos | K98: South West | L98: Internal (within state) | M98: Mainland | N98: Fatai Atere | O98: Apapa > Fatai Atere: 12 | Return Fatai Atere > Apapa: 12 | P98: 12 | Q98: 12 | R98: =IF(P98="","",P98+Q98) -> 24 | S98: Estimated (calibrated)
A99: Mega Manu-Local-45T-NBL-DSL-JUMBO | B99: JUMBO | C99: NBL-DSL | D99: 45T | E99: Mega Manu-Local | F99: Lagos | G99: Apapa | H99: Lagos | I99: Igbesa | J99: Ogun | K99: South West | L99: Interstate | N99: Igbesa | O99: Apapa > Igbesa: 39 | Return Igbesa > Apapa: 39 | P99: 39 | Q99: 39 | R99: =IF(P99="","",P99+Q99) -> 78 | S99: Estimated (calibrated)
A100: Mega Manu-Local-45T-NBL-DSL-JUMBO | B100: JUMBO | C100: NBL-DSL | D100: 45T | E100: Mega Manu-Local | F100: Lagos | G100: Apapa | H100: Lagos | I100: Ikeja | J100: Lagos | K100: South West | L100: Internal (within state) | M100: Mainland | N100: Ikeja | O100: Apapa > Ikeja: 23 | Return Ikeja > Apapa: 23 | P100: 23 | Q100: 23 | R100: =IF(P100="","",P100+Q100) -> 46 | S100: Estimated (calibrated)
A101: Mega Manu-Local-45T-NBL-DSL-JUMBO | B101: JUMBO | C101: NBL-DSL | D101: 45T | E101: Mega Manu-Local | F101: Lagos | G101: Apapa | H101: Lagos | I101: Dopemu | J101: Lagos | K101: South West | L101: Internal (within state) | M101: Mainland | N101: Dopemu | O101: Apapa > Dopemu: 27 | Return Dopemu > Apapa: 27 | P101: 27 | Q101: 27 | R101: =IF(P101="","",P101+Q101) -> 54 | S101: Estimated (calibrated)
A102: Mega Manu-Local-45T-NBL-DSL-JUMBO | B102: JUMBO | C102: NBL-DSL | D102: 45T | E102: Mega Manu-Local | F102: Lagos | G102: Apapa | H102: Lagos | I102: Sagamu | J102: Ogun | K102: South West | L102: Interstate | N102: Sagamu | O102: Apapa > Sagamu: 70 | Return Sagamu > Apapa: 70 | P102: 70 | Q102: 70 | R102: =IF(P102="","",P102+Q102) -> 140 | S102: Estimated (calibrated)
A103: Mega Manu-Local-45T-NBL-DSL-JUMBO | B103: JUMBO | C103: NBL-DSL | D103: 45T | E103: Mega Manu-Local | F103: Lagos | G103: Apapa | H103: Lagos | I103: Mowe | J103: Ogun | K103: South West | L103: Interstate | N103: Mowe | O103: Apapa > Mowe: 53 | Return Mowe > Apapa: 53 | P103: 53 | Q103: 53 | R103: =IF(P103="","",P103+Q103) -> 106 | S103: Estimated (calibrated)
A104: Mega Manu-Local-45T-NBL-DSL-JUMBO | B104: JUMBO | C104: NBL-DSL | D104: 45T | E104: Mega Manu-Local | F104: Lagos | G104: Apapa | H104: Lagos | I104: Ijebu Ososa | J104: Ogun | K104: South West | L104: Interstate | N104: Ijebu Ososa | O104: Apapa > Ijebu Ososa: 81 | Return Ijebu Ososa > Apapa: 81 | P104: 81 | Q104: 81 | R104: =IF(P104="","",P104+Q104) -> 162 | S104: Estimated (calibrated)
A105: Mega Manu-Local-45T-NBL-DSL-JUMBO | B105: JUMBO | C105: NBL-DSL | D105: 45T | E105: Mega Manu-Local | F105: Lagos | G105: Apapa | H105: Lagos | I105: Ojota | J105: Lagos | K105: South West | L105: Internal (within state) | M105: Mainland | N105: Ojota | O105: Apapa > Ojota: 21 | Return Ojota > Apapa: 21 | P105: 21 | Q105: 21 | R105: =IF(P105="","",P105+Q105) -> 42 | S105: Estimated (calibrated)
A106: Mega Manu-Local-45T-NBL-DSL-JUMBO | B106: JUMBO | C106: NBL-DSL | D106: 45T | E106: Mega Manu-Local | F106: Lagos | G106: Apapa | H106: Lagos | I106: Ijebu Ode | J106: Ogun | K106: South West | L106: Interstate | N106: Ijebu Ode | O106: Apapa > Ijebu Ode: 96 | Return Ijebu Ode > Apapa: 96 | P106: 96 | Q106: 96 | R106: =IF(P106="","",P106+Q106) -> 192 | S106: Estimated (calibrated)
A107: Mega Manu-Local-45T-NBL-DSL-JUMBO | B107: JUMBO | C107: NBL-DSL | D107: 45T | E107: Mega Manu-Local | F107: Lagos | G107: Apapa | H107: Lagos | I107: Apapa | J107: Lagos | K107: South West | L107: Internal (within state) | M107: Mainland | N107: Apapa | O107: Apapa > Apapa: 10 | Return Apapa > Apapa: 10 | P107: 10 | Q107: 10 | R107: =IF(P107="","",P107+Q107) -> 20 | S107: Estimated (calibrated) | T107: Delivery inside the loading town - 10 km allowance each way
A108: Mega Manu-Local-45T-NBL-DSL-JUMBO | B108: JUMBO | C108: NBL-DSL | D108: 45T | E108: Mega Manu-Local | F108: Lagos | G108: Apapa | H108: Lagos | I108: Ilupeju | J108: Lagos | K108: South West | L108: Internal (within state) | M108: Mainland | N108: Ilupeju | O108: Apapa > Ilupeju: 16 | Return Ilupeju > Apapa: 16 | P108: 16 | Q108: 16 | R108: =IF(P108="","",P108+Q108) -> 32 | S108: Estimated (calibrated)
A109: Mega Manu-Local-45T-NBL-DSL-JUMBO | B109: JUMBO | C109: NBL-DSL | D109: 45T | E109: Mega Manu-Local | F109: Lagos | G109: Apapa | H109: Lagos | I109: Ajao Estate | J109: Lagos | K109: South West | L109: Internal (within state) | M109: Mainland | N109: Ajao Estate | O109: Apapa > Ajao Estate: 16 | Return Ajao Estate > Apapa: 16 | P109: 16 | Q109: 16 | R109: =IF(P109="","",P109+Q109) -> 32 | S109: Estimated (calibrated)
A110: Mega Manu-Local-45T-NBL-DSL-JUMBO | B110: JUMBO | C110: NBL-DSL | D110: 45T | E110: Mega Manu-Local | F110: Lagos | G110: Apapa | H110: Lagos | I110: Okota | J110: Lagos | K110: South West | L110: Internal (within state) | M110: Mainland | N110: Okota | O110: Apapa > Okota: 12 | Return Okota > Apapa: 12 | P110: 12 | Q110: 12 | R110: =IF(P110="","",P110+Q110) -> 24 | S110: Estimated (calibrated)
A111: Mega Manu-Local-45T-NBL-DSL-JUMBO | B111: JUMBO | C111: NBL-DSL | D111: 45T | E111: Mega Manu-Local | F111: Lagos | G111: Apapa | H111: Lagos | I111: Oshodi | J111: Lagos | K111: South West | L111: Internal (within state) | M111: Mainland | N111: Oshodi | O111: Apapa > Oshodi: 17 | Return Oshodi > Apapa: 17 | P111: 17 | Q111: 17 | R111: =IF(P111="","",P111+Q111) -> 34 | S111: Estimated (calibrated)
A112: Mega Manu-Local-45T-NBL-DSL-JUMBO | B112: JUMBO | C112: NBL-DSL | D112: 45T | E112: Mega Manu-Local | F112: Lagos | G112: Apapa | H112: Lagos | I112: Ogba | J112: Lagos | K112: South West | L112: Internal (within state) | M112: Mainland | N112: Ogba | O112: Apapa > Ogba: 28 | Return Ogba > Apapa: 28 | P112: 28 | Q112: 28 | R112: =IF(P112="","",P112+Q112) -> 56 | S112: Estimated (calibrated)
A113: VANDERA-45T-NBL-DSL-JUMBO | B113: JUMBO | C113: NBL-DSL | D113: 45T | E113: VANDERA | F113: Lagos | G113: Apapa | H113: Lagos | I113: Onitsha | J113: Anambra | K113: South East | L113: Interstate | N113: Onitsha | O113: Apapa > Onitsha: 475 | Return Onitsha > Apapa: 475 | P113: 475 | Q113: 475 | R113: =IF(P113="","",P113+Q113) -> 950 | S113: Estimated (calibrated)
A114: VANDERA-45T-NBL-DSL-JUMBO | B114: JUMBO | C114: NBL-DSL | D114: 45T | E114: VANDERA | F114: Lagos | G114: Apapa | H114: Lagos | I114: Kano | J114: Kano | K114: North West | L114: Interstate | N114: Kano | O114: Apapa > Kano: 1017 | Return Kano > Apapa: 1017 | P114: 1017 | Q114: 1017 | R114: =IF(P114="","",P114+Q114) -> 2034 | S114: Estimated (calibrated)
A115: VANDERA-45T-NBL-DSL-JUMBO | B115: JUMBO | C115: NBL-DSL | D115: 45T | E115: VANDERA | F115: Lagos | G115: Apapa | H115: Lagos | I115: Calabar | J115: Cross River | K115: South South | L115: Interstate | N115: Calabar | O115: Apapa > Calabar: 742 | Return Calabar > Apapa: 742 | P115: 742 | Q115: 742 | R115: =IF(P115="","",P115+Q115) -> 1484 | S115: Estimated (calibrated)
A116: Lacasera-45T-NBL-DSL-JUMBO | B116: JUMBO | C116: NBL-DSL | D116: 45T | E116: Lacasera | F116: Lagos | G116: Mile 2 | H116: Lagos | I116: Aba | J116: Abia | K116: South East | L116: Interstate | N116: Aba | O116: Mile 2 > Aba: 619 | Return Aba > Mile 2: 619 | P116: 619 | Q116: 619 | R116: =IF(P116="","",P116+Q116) -> 1238 | S116: Estimated (calibrated)
A117: Lacasera-45T-NBL-DSL-JUMBO | B117: JUMBO | C117: NBL-DSL | D117: 45T | E117: Lacasera | F117: Lagos | G117: Mile 2 | H117: Lagos | I117: Port Harcourt | J117: Rivers | K117: South South | L117: Interstate | N117: Port Harcourt | O117: Mile 2 > Port Harcourt: 612 | Return Port Harcourt > Mile 2: 612 | P117: 612 | Q117: 612 | R117: =IF(P117="","",P117+Q117) -> 1224 | S117: Estimated (calibrated)
A118: Lacasera-45T-NBL-DSL-JUMBO | B118: JUMBO | C118: NBL-DSL | D118: 45T | E118: Lacasera | F118: Lagos | G118: Mile 2 | H118: Lagos | I118: Abuja | J118: FCT | K118: North Central | L118: Interstate | N118: Abuja | O118: Mile 2 > Abuja: 761 | Return Abuja > Mile 2: 761 | P118: 761 | Q118: 761 | R118: =IF(P118="","",P118+Q118) -> 1522 | S118: Estimated (calibrated)
A119: Lacasera-45T-NBL-DSL-JUMBO | B119: JUMBO | C119: NBL-DSL | D119: 45T | E119: Lacasera | F119: Lagos | G119: Mile 2 | H119: Lagos | I119: Kano | J119: Kano | K119: North West | L119: Interstate | N119: Kano | O119: Mile 2 > Kano: 1020 | Return Kano > Mile 2: 1020 | P119: 1020 | Q119: 1020 | R119: =IF(P119="","",P119+Q119) -> 2040 | S119: Estimated (calibrated)
A120: Lacasera-45T-NBL-DSL-JUMBO | B120: JUMBO | C120: NBL-DSL | D120: 45T | E120: Lacasera | F120: Lagos | G120: Mile 2 | H120: Lagos | I120: Ibadan | J120: Oyo | K120: South West | L120: Interstate | N120: Ibadan | O120: Mile 2 > Ibadan: 157 | Return Ibadan > Mile 2: 157 | P120: 157 | Q120: 157 | R120: =IF(P120="","",P120+Q120) -> 314 | S120: Estimated (calibrated)
A121: Lacasera-45T-NBL-DSL-JUMBO | B121: JUMBO | C121: NBL-DSL | D121: 45T | E121: Lacasera | F121: Lagos | G121: Mile 2 | H121: Lagos | I121: Benin City | J121: Edo | K121: South South | L121: Interstate | N121: Benin City | O121: Mile 2 > Benin City: 312 | Return Benin City > Mile 2: 312 | P121: 312 | Q121: 312 | R121: =IF(P121="","",P121+Q121) -> 624 | S121: Estimated (calibrated)
A122: Lacasera-45T-NBL-DSL-JUMBO | B122: JUMBO | C122: NBL-DSL | D122: 45T | E122: Lacasera | F122: Lagos | G122: Mile 2 | H122: Lagos | I122: Onitsha | J122: Anambra | K122: South East | L122: Interstate | N122: Onitsha | O122: Mile 2 > Onitsha: 481 | Return Onitsha > Mile 2: 481 | P122: 481 | Q122: 481 | R122: =IF(P122="","",P122+Q122) -> 962 | S122: Estimated (calibrated)
A123: NATURAL BEAUTY-45T-NBL-DSL-JUMBO | B123: JUMBO | C123: NBL-DSL | D123: 45T | E123: NATURAL BEAUTY | F123: Lagos | G123: Isolo | H123: Lagos | I123: Kano | J123: Kano | K123: North West | L123: Interstate | N123: Kano | O123: Isolo > Kano: 990 | Return Kano > Isolo: 990 | P123: 990 | Q123: 990 | R123: =IF(P123="","",P123+Q123) -> 1980 | S123: Road-routed (OpenStreetMap)
A124: NATURAL BEAUTY-45T-NBL-DSL-JUMBO | B124: JUMBO | C124: NBL-DSL | D124: 45T | E124: NATURAL BEAUTY | F124: Lagos | G124: Isolo | H124: Lagos | I124: Maiduguri | J124: Borno | K124: North East | L124: Interstate | N124: Maiduguri | O124: Isolo > Maiduguri: 1557 | Return Maiduguri > Isolo: 1557 | P124: 1557 | Q124: 1557 | R124: =IF(P124="","",P124+Q124) -> 3114 | S124: Road-routed (OpenStreetMap)
... A139: I'HS-30T-NBL-DSL-FLATBED | B139: FLATBED | C139: NBL-DSL | D139: 30T | E139: I'HS | F139: Lagos | G139: JMG Gbagada | H139: Lagos | I139: Ibadan | J139: Oyo | K139: South West | L139: Interstate | N139: Ibadan | O139: JMG Gbagada > Ibadan: 124 | Return Ibadan > JMG Gbagada: 124 | P139: 124 | Q139: 124 | R139: =IF(P139="","",P139+Q139) -> 248 | S139: Road-routed (OpenStreetMap)
A140: I'HS-30T-NBL-DSL-FLATBED | B140: FLATBED | C140: NBL-DSL | D140: 30T | E140: I'HS | F140: Lagos | G140: JMG Gbagada | H140: Lagos | I140: IKM | N140: LOCATION NOT FOUND | R140: =IF(P140="","",P140+Q140) | T140: Place not recognised - send the exact location/address and it will be filled in
A141: I'HS-30T-NBL-DSL-FLATBED | B141: FLATBED | C141: NBL-DSL | D141: 30T | E141: I'HS | F141: Lagos | G141: JMG Gbagada | H141: Lagos | I141: Epe | J141: Lagos | K141: South West | L141: Internal (within state) | M141: Epe & Ibeju-Lekki | N141: Epe | O141: JMG Gbagada > Epe: 85 | Return Epe > JMG Gbagada: 85 | P141: 85 | Q141: 85 | R141: =IF(P141="","",P141+Q141) -> 170 | S141: Estimated (calibrated)
A142: I'HS-30T-NBL-DSL-FLATBED | B142: FLATBED | C142: NBL-DSL | D142: 30T | E142: I'HS | F142: Lagos | G142: JMG Gbagada | H142: Lagos | I142: Kaduna | J142: Kaduna | K142: North West | L142: Interstate | N142: Kaduna | O142: JMG Gbagada > Kaduna: 762 | Return Kaduna > JMG Gbagada: 762 | P142: 762 | Q142: 762 | R142: =IF(P142="","",P142+Q142) -> 1524 | S142: Estimated (calibrated)
A143: JAMARA-30T-NBL-DSL-CONTAINARIZED | B143: CONTAINERIZED | C143: NBL-DSL | D143: 30T | E143: JAMARA | F143: Lagos | G143: JMG Gbagada | H143: Lagos | I143: Ibadan | J143: Oyo | K143: South West | L143: Interstate | N143: Ibadan | O143: JMG Gbagada > Ibadan: 124 | Return Ibadan > JMG Gbagada: 124 | P143: 124 | Q143: 124 | R143: =IF(P143="","",P143+Q143) -> 248 | S143: Road-routed (OpenStreetMap)
A144: JAMARA-30T-NBL-DSL-CONTAINARIZED | B144: CONTAINERIZED | C144: NBL-DSL | D144: 30T | E144: JAMARA | F144: Lagos | G144: JMG Gbagada | H144: Lagos | I144: Ekiti (Ado Ekiti) | J144: Ekiti | K144: South West | L144: Interstate | N144: Ado Ekiti | O144: JMG Gbagada > Ado Ekiti: 305 | Return Ado Ekiti > JMG Gbagada: 305 | P144: 305 | Q144: 305 | R144: =IF(P144="","",P144+Q144) -> 610 | S144: Estimated (calibrated)
A145: JAMARA-30T-NBL-DSL-CONTAINARIZED | B145: CONTAINERIZED | C145: NBL-DSL | D145: 30T | E145: JAMARA | F145: Lagos | G145: JMG Gbagada | H145: Lagos | I145: Ondo State (Akure) | J145: Ondo | K145: South West | L145: Interstate | N145: Akure | O145: JMG Gbagada > Akure: 278 | Return Akure > JMG Gbagada: 278 | P145: 278 | Q145: 278 | R145: =IF(P145="","",P145+Q145) -> 556 | S145: Estimated (calibrated)
A146: JAMARA-30T-NBL-DSL-CONTAINARIZED | B146: CONTAINERIZED | C146: NBL-DSL | D146: 30T | E146: JAMARA | F146: Lagos | G146: JMG Gbagada | H146: Lagos | I146: Osun (Osogbo) | J146: Osun | K146: South West | L146: Interstate | N146: Osogbo | O146: JMG Gbagada > Osogbo: 243 | Return Osogbo > JMG Gbagada: 243 | P146: 243 | Q146: 243 | R146: =IF(P146="","",P146+Q146) -> 486 | S146: Estimated (calibrated)
A147: JAMARA-30T-NBL-DSL-CONTAINARIZED | B147: CONTAINERIZED | C147: NBL-DSL | D147: 30T | E147: JAMARA | F147: Lagos | G147: JMG Gbagada | H147: Lagos | I147: Kwara (Ilorin) | J147: Kwara | K147: North Central | L147: Interstate | N147: Ilorin | O147: JMG Gbagada > Ilorin: 351 | Return Ilorin > JMG Gbagada: 351 | P147: 351 | Q147: 351 | R147: =IF(P147="","",P147+Q147) -> 702 | S147: Estimated (calibrated)
A148: JAMARA-30T-NBL-DSL-CONTAINARIZED | B148: CONTAINERIZED | C148: NBL-DSL | D148: 30T | E148: JAMARA | F148: Lagos | G148: JMG Gbagada | H148: Lagos | I148: Omu Aran | J148: Kwara | K148: North Central | L148: Interstate | N148: Omu Aran | O148: JMG Gbagada > Omu Aran: 361 | Return Omu Aran > JMG Gbagada: 361 | P148: 361 | Q148: 361 | R148: =IF(P148="","",P148+Q148) -> 722 | S148: Estimated (calibrated)
A149: JAMARA-30T-NBL-DSL-CONTAINARIZED | B149: CONTAINERIZED | C149: NBL-DSL | D149: 30T | E149: JAMARA | F149: Lagos | G149: JMG Gbagada | H149: Lagos | I149: Abeokuta | J149: Ogun | K149: South West | L149: Interstate | N149: Abeokuta | O149: JMG Gbagada > Abeokuta: 85 | Return Abeokuta > JMG Gbagada: 85 | P149: 85 | Q149: 85 | R149: =IF(P149="","",P149+Q149) -> 170 | S149: Estimated (calibrated)
A150: JAMARA-30T-NBL-DSL-CONTAINARIZED | B150: CONTAINERIZED | C150: NBL-DSL | D150: 30T | E150: JAMARA | F150: Lagos | G150: JMG Gbagada | H150: Lagos | I150: Benin City | J150: Edo | K150: South South | L150: Interstate | N150: Benin City | O150: JMG Gbagada > Benin City: 303 | Return Benin City > JMG Gbagada: 303 | P150: 303 | Q150: 303 | R150: =IF(P150="","",P150+Q150) -> 606 | S150: Estimated (calibrated)
A151: JAMARA-30T-NBL-DSL-CONTAINARIZED | B151: CONTAINERIZED | C151: NBL-DSL | D151: 30T | E151: JAMARA | F151: Lagos | G151: JMG Gbagada | H151: Lagos | I151: Abule Egba - Ijaiye - Moshalashi - Kola - Sango Ota | J151: Ogun | K151: South West | L151: Interstate | N151: Abule Egba > Sango Ota > Kola > Moshalashi > Ijaiye | O151: JMG Gbagada > Abule Egba: 19 | Abule Egba > Sango Ota: 12 | Sango Ota > Kola: 4 | Kola > Moshalashi: 8 | Moshalashi > Ijaiye: 3 | Return Ijaiye > JMG Gbagada: 17 | P151: 46 | Q151: 17 | R151: =IF(P151="","",P151+Q151) -> 63 | S151: Estimated (calibrated) | T151: Drop order re-sequenced for the shortest loop (written order would be 69 km round trip); Multi-drop: Leg 1 = sum of drop-to-drop legs
A152: JAMARA-30T-NBL-DSL-CONTAINARIZED | B152: CONTAINERIZED | C152: NBL-DSL | D152: 30T | E152: JAMARA | F152: Lagos | G152: JMG Gbagada | H152: Lagos | I152: Abule Egba - Ijaiye - Moshalashi - Kola - Sango Ota | J152: Ogun | K152: South West | L152: Interstate | N152: Abule Egba > Sango Ota > Kola > Moshalashi > Ijaiye | O152: JMG Gbagada > Abule Egba: 19 | Abule Egba > Sango Ota: 12 | Sango Ota > Kola: 4 | Kola > Moshalashi: 8 | Moshalashi > Ijaiye: 3 | Return Ijaiye > JMG Gbagada: 17 | P152: 46 | Q152: 17 | R152: =IF(P152="","",P152+Q152) -> 63 | S152: Estimated (calibrated) | T152: Drop order re-sequenced for the shortest loop (written order would be 69 km round trip); Multi-drop: Leg 1 = sum of drop-to-drop legs
A153: JAMARA-30T-NBL-DSL-CONTAINARIZED | B153: CONTAINERIZED | C153: NBL-DSL | D153: 30T | E153: JAMARA | F153: Lagos | G153: JMG Gbagada | H153: Lagos | I153: Abule Egba - Ijaiye - Moshalashi - Kola - Sango Ota | J153: Ogun | K153: South West | L153: Interstate | N153: Abule Egba > Sango Ota > Kola > Moshalashi > Ijaiye | O153: JMG Gbagada > Abule Egba: 19 | Abule Egba > Sango Ota: 12 | Sango Ota > Kola: 4 | Kola > Moshalashi: 8 | Moshalashi > Ijaiye: 3 | Return Ijaiye > JMG Gbagada: 17 | P153: 46 | Q153: 17 | R153: =IF(P153="","",P153+Q153) -> 63 | S153: Estimated (calibrated) | T153: Drop order re-sequenced for the shortest loop (written order would be 69 km round trip); Multi-drop: Leg 1 = sum of drop-to-drop legs
...

Sheet Driver Mapping On Each Vehicle 
A1: Asset code | B1: Plate Number | C1: Asset Name | D1: Tonnage | E1: Body Size | F1: HR Registered name | G1: Camanda Driver Name | H1: Staff ID no | I1: Station Officer | J1: Station Officer | K1: Operation Manager
A2: MVEH-000266 | B2: T2404LA | C2: Volswagen Titan Tractor 18-310 Head | D2: 25T | E2: FLAT | F2: ABDULSALAM Adams Araga | G2: Adams Araga | H2: 003455 | I2: AYENI Ebenezer Akintunde | J2: DAODU Timileyin Monday | K2: AJIBADE Afeez Adeyemi
A3: MVEH-000267 | B3: T2486LA | C3: Volswagen Titan Tractor 18-310 Head | D3: 25T | E3: FLAT | F3: ADEMOLA Marcus Adedayo | G3: Ademola Marcus Adedayo | H3: 002752 | I3: AYENI Ebenezer Akintunde | J3: DAODU Timileyin Monday | K3: AJIBADE Afeez Adeyemi
A4: MVEH-000269 | B4: T2490LA | C4: Volswagen Titan Tractor 18-310 Head | D4: 25T | E4: FLAT | F4: OLADOYINBO Olusoji Opeyemi | G4: Opeyemi Soji | H4: 002335 | I4: AYENI Ebenezer Akintunde | J4: DAODU Timileyin Monday | K4: AJIBADE Afeez Adeyemi
A5: MVEH-000271 | B5: T2407LA | C5: Volswagen Titan Tractor 18-310 Head | D5: 25T | E5: FLAT | F5: POPOOLA Akeem Olalekan | G5: Akeem Popoola | H5: 001983 | I5: AYENI Ebenezer Akintunde | J5: DAODU Timileyin Monday | K5: AJIBADE Afeez Adeyemi
A6: MVEH-000273 | B6: T2485LA | C6: Volswagen Titan Tractor 18-310 Head | D6: 30T | E6: FLAT | F6: ABUBAKAR Kamal | G6: Kamal Abubakar | H6: 002344 | I6: AYENI Ebenezer Akintunde | J6: DAODU Timileyin Monday | K6: AJIBADE Afeez Adeyemi
A7: MVEH-000276 | B7: T2412LA | C7: Volswagen Titan Tractor 18-310 Head | D7: 25T | E7: FLAT | F7: Hussien Nemadi | G7: Hussien Nemadi | H7: 002200 | I7: AYENI Ebenezer Akintunde | J7: DAODU Timileyin Monday | K7: AJIBADE Afeez Adeyemi
A8: MVEH-000283 | B8: T2420LA | C8: Volswagen Titan Tractor 18-310 Head | D8: 25T | E8: FLAT | F8: ALI Suleiman Nasiru | G8: Naslr Ali | I8: AYENI Ebenezer Akintunde | J8: DAODU Timileyin Monday | K8: AJIBADE Afeez Adeyemi
A9: MVEH-000326 | B9: EPE531YD | C9: Mercedes Benz Diesel Truck | D9: 15T | E9: TANKER | I9: AYENI Ebenezer Akintunde
A10: MVEH-000130 | B10: T2418LA | C10: Volswagen Titan Tractor 18-310 Head | D10: 25T | E10: FLAT | F10: IHINEGBU Lucky Uche | G10: Lucky Ihinegbu | H10: 000556 | I10: AYENI Ebenezer Akintunde | J10: DAODU Timileyin Monday | K10: AJIBADE Afeez Adeyemi
A11: MVEH-000131 | B11: T2489LA | C11: Volswagen Titan Tractor 18-310 Head | D11: 25T | E11: FLAT | F11: OLASUNKANMI Kabiru Ademola | G11: Ademola Marcus Adedayo | H11: 000828 | I11: AYENI Ebenezer Akintunde | J11: DAODU Timileyin Monday | K11: AJIBADE Afeez Adeyemi
A12: MVEH-000132 | B12: T2421LA | C12: Volswagen Titan Tractor 18-310 Head | D12: 25T | E12: FLAT | F12: AZEEZ Kamoru | G12: Azeez Kamorudeen | H12: 001590 | I12: AYENI Ebenezer Akintunde | J12: DAODU Timileyin Monday | K12: AJIBADE Afeez Adeyemi
A13: MVEH-000142 | B13: T2419LA | C13: Volswagen Titan Tractor 18-310 | D13: 25T | E13: FLAT | F13: OLADOYINBO Olusoji Opeyemi | G13: Opeyemi Soji | H13: 002335 | I13: AYENI Ebenezer Akintunde | J13: DAODU Timileyin Monday | K13: AJIBADE Afeez Adeyemi
A14: MVEH-000143 | B14: T2415LA | C14: Volswagen titan Tractor 18-310 Head (double not yet acquired) | D14: 25T | E14: FLAT | F14: OWOLO James Folorunsho | G14: Owolo James | H14: 000914 | I14: AYENI Ebenezer Akintunde | J14: DAODU Timileyin Monday | K14: AJIBADE Afeez Adeyemi
A15: MVEH-000144 | B15: T2414LA | C15: Volswagen Titan Tractor 18-310 Head | D15: 25T | E15: FLAT | F15: AKINOLA Oluwaseun Samson | G15: Seun Akinola | H15: 000164 | I15: AYENI Ebenezer Akintunde | J15: DAODU Timileyin Monday | K15: AJIBADE Afeez Adeyemi
A16: MVEH-000318 | B16: T5526LA | C16: SINOTRUCK HOWO E7 6X4 TRACTOR .STERLING BANK LEASE | D16: 30T | E16: FLAT | F16: IGWALAH Christopher Maxwell | G16: Maxwell Christopher | H16: 000512 | I16: AYENI Ebenezer Akintunde | J16: DAODU Timileyin Monday | K16: AJIBADE Afeez Adeyemi
A17: MVEH-000320 | B17: T5524LA | C17: SINOTRUCK HOWO 4X2 TRACTOR LHD STERLING BANK LEASE | D17: 30T | E17: 102-30T | F17: ARUWAJOYE Kolawole Tilo | G17: Aruwajoye Tilo | H17: 003254 | I17: AYENI Ebenezer Akintunde | J17: DAODU Timileyin Monday | K17: AJIBADE Afeez Adeyemi
A18: MVEH-000327 | B18: T9943LA | C18: Sino Truck Howo 6x4 | D18: 45T | E18: 102-45T | F18: IBRAHIM Alhaji | G18: Alhaji Ibrahim | H18: 000497 | I18: AYENI Ebenezer Akintunde | J18: DAODU Timileyin Monday | K18: AJIBADE Afeez Adeyemi
A19: MVEH-000329 | B19: T10265LA | C19: Sino Truck Howo 6x4 | D19: 45T | E19: 102-45T | F19: BENSON Peter Matto | G19: Benson Peter Mallo | H19: 003515 | I19: AYENI Ebenezer Akintunde | J19: DAODU Timileyin Monday | K19: AJIBADE Afeez Adeyemi
A20: MVEH-000331 | B20: T8116LA | C20: Sino Truck Howo 6x4 | D20: 45T | E20: 102-45T | F20: ABUBAKAR Kamal | G20: Kamal Abubakar | H20: 002344 | I20: AYENI Ebenezer Akintunde | J20: DAODU Timileyin Monday | K20: AJIBADE Afeez Adeyemi
A21: MVEH-000335 | B21: T15333LA | C21: Sino Truck Howo 6X4 | D21: 45T | E21: 102-45T | F21: ALIYU Lawal | G21: Aliyu Lawal | H21: 000189 | I21: AYENI Ebenezer Akintunde | J21: DAODU Timileyin Monday | K21: AJIBADE Afeez Adeyemi
... A60: MVEH-000145 | B60: T2417LA | C60: SIno 4*2 Cargo Truck | D60: 8T | E60: 25FT | F60: OWOYEMI Isa Babatunde | G60: Isa Owoyemi | H60: 000917 | I60: AYENI Ebenezer Akintunde | J60: DAODU Timileyin Monday | K60: YEKEEN Oyetunde Bolarinwa
A61: MVEH-000202 | B61: AAA822XS | C61: Hyundai Hi P Van 3 | D61: 2T | E61: BUS | I61: AYENI Ebenezer Akintunde | J61: DAODU Timileyin Monday | K61: YEKEEN Oyetunde Bolarinwa
A62: MVEH-000289 | B62: T1589LA | C62: Isuzu Truck Model : QKR 55H | D62: 30T | E62: 15T | F62: ADELEKE Seun Oluwasegun | G62: Seun Adeleke | H62: 003284 | I62: AYENI Ebenezer Akintunde | J62: DAODU Timileyin Monday | K62: YEKEEN Oyetunde Bolarinwa
A63: MVEH-000304 | B63: KSF352YC | C63: Foton L/D Truck (+body BJ1020) | D63: 1T | E63: 10FT | F63: ADEDEJI Aderemi Adetunji | G63: Adedeji Aderemi | H63: 003560 | I63: AYENI Ebenezer Akintunde | J63: DAODU Timileyin Monday | K63: YEKEEN Oyetunde Bolarinwa
A64: MVEH-000363 | B64: KRD640YF | C64: MK1 3T Truck 2.8L Isuzu Manual | D64: 3T | E64: 15T | F64: ESSIEN Micah Emmanuel | G64: Essien Emmanuel | H64: 000425 | I64: AYENI Ebenezer Akintunde | J64: DAODU Timileyin Monday | K64: YEKEEN Oyetunde Bolarinwa
A65: MVEH-000287 | B65: T1678LA | C65: Isuzu Truck Model : T 1678 LA | D65: 3T | E65: 15T | F65: ADEKOBA Toluwase Alex | G65: Adekoba Toluwalase Alex | H65: 003186 | I65: AYENI Ebenezer Akintunde | J65: DAODU Timileyin Monday | K65: YEKEEN Oyetunde Bolarinwa
A66: MVEH-000103 | B66: KTU74XP | C66: Sino 4x2 Hiab Truck | D66: 10T | E66: SELF-LOADER | F66: ADAMU Mohammed | G66: Mohammed Adamu | H66: 003160 | I66: AYENI Ebenezer Akintunde | J66: DAODU Timileyin Monday | K66: YEKEEN Oyetunde Bolarinwa
A67: MVEH-000288 | B67: T1590LA | C67: Isuzu Truck Model : QKR 55H | D67: 3T | E67: 15T | F67: ADEGBENRO Abayomi Meshack | G67: Adegbenro Abayomi | H67: 003271 | I67: AYENI Ebenezer Akintunde | J67: DAODU Timileyin Monday | K67: YEKEEN Oyetunde Bolarinwa
A68: MVEH-000146 | B68: T2413LA | C68: T 2413 LA 4*2Cargo Truck | D68: 8T | E68: 25FT | F68: OKOJIE Lucky Araze | G68: Okojie Lucky | H68: 000785 | I68: AYENI Ebenezer Akintunde | J68: DAODU Timileyin Monday | K68: YEKEEN Oyetunde Bolarinwa

Sheet KM from Lagos
A1: Loading Point | B1: Destination | C1: Destination State | D1: Region | E1: Delivery Type | F1: Internal Zone | G1: Stops (in drive order) | H1: Leg Breakdown (km) | I1: Leg 1 - Outbound KM | J1: Leg 2 - Return KM | K1: Total Round Trip KM | L1: KM Source | M1: Clients on this lane | N1: Notes
A2: Amuwo Odofin | B2: Onitsha | C2: Anambra | D2: South East | E2: Interstate | G2: Onitsha | H2: Amuwo Odofin > Onitsha: 483 | Return Onitsha > Amuwo Odofin: 483 | I2: 483 | J2: 483 | K2: =IF(I2="","",I2+J2) -> 966 | L2: Estimated (calibrated) | M2: Givanas
A3: Amuwo Odofin | B3: Abuja | C3: FCT | D3: North Central | E3: Interstate | G3: Abuja | H3: Amuwo Odofin > Abuja: 763 | Return Abuja > Amuwo Odofin: 763 | I3: 763 | J3: 763 | K3: =IF(I3="","",I3+J3) -> 1526 | L3: Estimated (calibrated) | M3: SASO
A4: Amuwo Odofin | B4: Mubi | C4: Adamawa | D4: North East | E4: Interstate | G4: Mubi | H4: Amuwo Odofin > Mubi: 1527 | Return Mubi > Amuwo Odofin: 1527 | I4: 1527 | J4: 1527 | K4: =IF(I4="","",I4+J4) -> 3054 | L4: Estimated (calibrated) | M4: SASO
A5: Amuwo Odofin | B5: Yola | C5: Adamawa | D5: North East | E5: Interstate | G5: Yola | H5: Amuwo Odofin > Yola: 1375 | Return Yola > Amuwo Odofin: 1375 | I5: 1375 | J5: 1375 | K5: =IF(I5="","",I5+J5) -> 2750 | L5: Estimated (calibrated) | M5: SASO
A6: Amuwo Odofin | B6: Gombe | C6: Gombe | D6: North East | E6: Interstate | G6: Gombe | H6: Amuwo Odofin > Gombe: 1253 | Return Gombe > Amuwo Odofin: 1253 | I6: 1253 | J6: 1253 | K6: =IF(I6="","",I6+J6) -> 2506 | L6: Estimated (calibrated) | M6: SASO
A7: Amuwo Odofin | B7: Jalingo | C7: Taraba | D7: North East | E7: Interstate | G7: Jalingo | H7: Amuwo Odofin > Jalingo: 1207 | Return Jalingo > Amuwo Odofin: 1207 | I7: 1207 | J7: 1207 | K7: =IF(I7="","",I7+J7) -> 2414 | L7: Estimated (calibrated) | M7: SASO
A8: Amuwo Odofin | B8: Katsina | C8: Katsina | D8: North West | E8: Interstate | G8: Katsina | H8: Amuwo Odofin > Katsina: 1051 | Return Katsina > Amuwo Odofin: 1051 | I8: 1051 | J8: 1051 | K8: =IF(I8="","",I8+J8) -> 2102 | L8: Estimated (calibrated) | M8: SASO
A9: Amuwo Odofin | B9: Kano | C9: Kano | D9: North West | E9: Interstate | G9: Kano | H9: Amuwo Odofin > Kano: 1021 | Return Kano > Amuwo Odofin: 1021 | I9: 1021 | J9: 1021 | K9: =IF(I9="","",I9+J9) -> 2042 | L9: Estimated (calibrated) | M9: Givanas, SASO
A10: Amuwo Odofin | B10: Sokoto | C10: Sokoto | D10: North West | E10: Interstate | G10: Sokoto | H10: Amuwo Odofin > Sokoto: 928 | Return Sokoto > Amuwo Odofin: 928 | I10: 928 | J10: 928 | K10: =IF(I10="","",I10+J10) -> 1856 | L10: Estimated (calibrated) | M10: Givanas
A11: Amuwo Odofin | B11: Funtua | C11: Katsina | D11: North West | E11: Interstate | G11: Funtua | H11: Amuwo Odofin > Funtua: 868 | Return Funtua > Amuwo Odofin: 868 | I11: 868 | J11: 868 | K11: =IF(I11="","",I11+J11) -> 1736 | L11: Estimated (calibrated) | M11: SASO
A12: Amuwo Odofin | B12: Zaria | C12: Kaduna | D12: North West | E12: Interstate | G12: Zaria | H12: Amuwo Odofin > Zaria: 858 | Return Zaria > Amuwo Odofin: 858 | I12: 858 | J12: 858 | K12: =IF(I12="","",I12+J12) -> 1716 | L12: Estimated (calibrated) | M12: SASO
A13: Amuwo Odofin | B13: Kaduna | C13: Kaduna | D13: North West | E13: Interstate | G13: Kaduna | H13: Amuwo Odofin > Kaduna: 779 | Return Kaduna > Amuwo Odofin: 779 | I13: 779 | J13: 779 | K13: =IF(I13="","",I13+J13) -> 1558 | L13: Estimated (calibrated) | M13: SASO
... A19: Apapa | B19: Mowe | C19: Ogun | D19: South West | E19: Interstate | G19: Mowe | H19: Apapa > Mowe: 53 | Return Mowe > Apapa: 53 | I19: 53 | J19: 53 | K19: =IF(I19="","",I19+J19) -> 106 | L19: Estimated (calibrated) | M19: Mega Manu-Local
A20: Apapa | B20: Agbara | C20: Ogun | D20: South West | E20: Interstate | F20: Ojo–Badagry | G20: Agbara | H20: Apapa > Agbara: 43 | Return Agbara > Apapa: 43 | I20: 43 | J20: 43 | K20: =IF(I20="","",I20+J20) -> 86 | L20: Estimated (calibrated) | M20: Mega Manu-Local
A21: Apapa | B21: Sango Ota | C21: Ogun | D21: South West | E21: Interstate | G21: Sango Ota | H21: Apapa > Sango Ota: 42 | Return Sango Ota > Apapa: 42 | I21: 42 | J21: 42 | K21: =IF(I21="","",I21+J21) -> 84 | L21: Estimated (calibrated) | M21: Mega Manu-Local
A22: Apapa | B22: Igbesa | C22: Ogun | D22: South West | E22: Interstate | G22: Igbesa | H22: Apapa > Igbesa: 39 | Return Igbesa > Apapa: 39 | I22: 39 | J22: 39 | K22: =IF(I22="","",I22+J22) -> 78 | L22: Estimated (calibrated) | M22: Mega Manu-Local
A23: Apapa | B23: Ogba | C23: Lagos | D23: South West | E23: Internal (within state) | F23: Mainland | G23: Ogba | H23: Apapa > Ogba: 28 | Return Ogba > Apapa: 28 | I23: 28 | J23: 28 | K23: =IF(I23="","",I23+J23) -> 56 | L23: Estimated (calibrated) | M23: Mega Manu-Local
A24: Apapa | B24: Dopemu | C24: Lagos | D24: South West | E24: Internal (within state) | F24: Mainland | G24: Dopemu | H24: Apapa > Dopemu: 27 | Return Dopemu > Apapa: 27 | I24: 27 | J24: 27 | K24: =IF(I24="","",I24+J24) -> 54 | L24: Estimated (calibrated) | M24: Mega Manu-Local
A25: Apapa | B25: Ikeja | C25: Lagos | D25: South West | E25: Internal (within state) | F25: Mainland | G25: Ikeja | H25: Apapa > Ikeja: 23 | Return Ikeja > Apapa: 23 | I25: 23 | J25: 23 | K25: =IF(I25="","",I25+J25) -> 46 | L25: Estimated (calibrated) | M25: Mega Manu-Local
A26: Apapa | B26: Ojota | C26: Lagos | D26: South West | E26: Internal (within state) | F26: Mainland | G26: Ojota | H26: Apapa > Ojota: 21 | Return Ojota > Apapa: 21 | I26: 21 | J26: 21 | K26: =IF(I26="","",I26+J26) -> 42 | L26: Estimated (calibrated) | M26: Mega Manu-Local
A27: Apapa | B27: Oshodi | C27: Lagos | D27: South West | E27: Internal (within state) | F27: Mainland | G27: Oshodi | H27: Apapa > Oshodi: 17 | Return Oshodi > Apapa: 17 | I27: 17 | J27: 17 | K27: =IF(I27="","",I27+J27) -> 34 | L27: Estimated (calibrated) | M27: Mega Manu-Local
A28: Apapa | B28: Lekki | C28: Lagos | D28: South West | E28: Internal (within state) | F28: Island | G28: Lekki | H28: Apapa > Lekki: 17 | Return Lekki > Apapa: 17 | I28: 17 | J28: 17 | K28: =IF(I28="","",I28+J28) -> 34 | L28: Estimated (calibrated) | M28: Mega Manu-Local
A29: Apapa | B29: Ilupeju | C29: Lagos | D29: South West | E29: Internal (within state) | F29: Mainland | G29: Ilupeju | H29: Apapa > Ilupeju: 16 | Return Ilupeju > Apapa: 16 | I29: 16 | J29: 16 | K29: =IF(I29="","",I29+J29) -> 32 | L29: Estimated (calibrated) | M29: Mega Manu-Local
A30: Apapa | B30: Ajao Estate | C30: Lagos | D30: South West | E30: Internal (within state) | F30: Mainland | G30: Ajao Estate | H30: Apapa > Ajao Estate: 16 | Return Ajao Estate > Apapa: 16 | I30: 16 | J30: 16 | K30: =IF(I30="","",I30+J30) -> 32 | L30: Estimated (calibrated) | M30: Mega Manu-Local
A31: Apapa | B31: Isolo | C31: Lagos | D31: South West | E31: Internal (within state) | F31: Mainland | G31: Isolo | H31: Apapa > Isolo: 15 | Return Isolo > Apapa: 15 | I31: 15 | J31: 15 | K31: =IF(I31="","",I31+J31) -> 30 | L31: Estimated (calibrated) | M31: Mega Manu-Local
A32: Apapa | B32: Matori | C32: Lagos | D32: South West | E32: Internal (within state) | F32: Mainland | G32: Matori | H32: Apapa > Matori: 15 | Return Matori > Apapa: 15 | I32: 15 | J32: 15 | K32: =IF(I32="","",I32+J32) -> 30 | L32: Estimated (calibrated) | M32: Mega Manu-Local
A33: Apapa | B33: Fatai Atere | C33: Lagos | D33: South West | E33: Internal (within state) | F33: Mainland | G33: Fatai Atere | H33: Apapa > Fatai Atere: 12 | Return Fatai Atere > Apapa: 12 | I33: 12 | J33: 12 | K33: =IF(I33="","",I33+J33) -> 24 | L33: Estimated (calibrated) | M33: Mega Manu-Local
A34: Apapa | B34: Okota | C34: Lagos | D34: South West | E34: Internal (within state) | F34: Mainland | G34: Okota | H34: Apapa > Okota: 12 | Return Okota > Apapa: 12 | I34: 12 | J34: 12 | K34: =IF(I34="","",I34+J34) -> 24 | L34: Estimated (calibrated) | M34: Mega Manu-Local
A35: Apapa | B35: Amuwo Odofin | C35: Lagos | D35: South West | E35: Internal (within state) | F35: Mainland | G35: Amuwo Odofin | H35: Apapa > Amuwo Odofin: 10 | Return Amuwo Odofin > Apapa: 10 | I35: 10 | J35: 10 | K35: =IF(I35="","",I35+J35) -> 20 | L35: Estimated (calibrated) | M35: Mega Manu-Local
A36: Apapa | B36: Apapa | C36: Lagos | D36: South West | E36: Internal (within state) | F36: Mainland | G36: Apapa | H36: Apapa > Apapa: 10 | Return Apapa > Apapa: 10 | I36: 10 | J36: 10 | K36: =IF(I36="","",I36+J36) -> 20 | L36: Estimated (calibrated) | M36: Mega Manu-Local | N36: Delivery inside the loading town - 10 km allowance each way
A37: Apapa | B37: Calabar | C37: Cross River | D37: South South | E37: Interstate | G37: Calabar | H37: Apapa > Calabar: 742 | Return Calabar > Apapa: 742 | I37: 742 | J37: 742 | K37: =IF(I37="","",I37+J37) -> 1484 | L37: Estimated (calibrated) | M37: VANDERA
A38: Apapa | B38: Uyo | C38: Akwa Ibom | D38: South South | E38: Interstate | G38: Uyo | H38: Apapa > Uyo: 683 | Return Uyo > Apapa: 683 | I38: 683 | J38: 683 | K38: =IF(I38="","",I38+J38) -> 1366 | L38: Estimated (calibrated) | M38: NIGER BISCUIT
A39: Apapa | B39: Ikot Ekpene | C39: Akwa Ibom | D39: South South | E39: Interstate | G39: Ikot Ekpene | H39: Apapa > Ikot Ekpene: 649 | Return Ikot Ekpene > Apapa: 649 | I39: 649 | J39: 649 | K39: =IF(I39="","",I39+J39) -> 1298 | L39: Estimated (calibrated) | M39: NIGER BISCUIT
A40: Apapa | B40: Port Harcourt | C40: Rivers | D40: South South | E40: Interstate | G40: Port Harcourt | H40: Apapa > Port Harcourt: 606 | Return Port Harcourt > Apapa: 606 | I40: 606 | J40: 606 | K40: =IF(I40="","",I40+J40) -> 1212 | L40: Estimated (calibrated) | M40: NIGER BISCUIT
A41: Apapa | B41: Yenagoa | C41: Bayelsa | D41: South South | E41: Interstate | G41: Yenagoa | H41: Apapa > Yenagoa: 529 | Return Yenagoa > Apapa: 529 | I41: 529 | J41: 529 | K41: =IF(I41="","",I41+J41) -> 1058 | L41: Estimated (calibrated) | M41: NIGER BISCUIT
A42: Apapa | B42: Kwale | C42: Delta | D42: South South | E42: Interstate | G42: Kwale | H42: Apapa > Kwale: 453 | Return Kwale > Apapa: 453 | I42: 453 | J42: 453 | K42: =IF(I42="","",I42+J42) -> 906 | L42: Estimated (calibrated) | M42: NIGER BISCUIT
A43: Apapa | B43: Warri | C43: Delta | D43: South South | E43: Interstate | G43: Warri | H43: Apapa > Warri: 425 | Return Warri > Apapa: 425 | I43: 425 | J43: 425 | K43: =IF(I43="","",I43+J43) -> 850 | L43: Estimated (calibrated) | M43: Interstyle, NIGER BISCUIT
A44: Apapa | B44: Abakaliki | C44: Ebonyi | D44: South East | E44: Interstate | G44: Abakaliki | H44: Apapa > Abakaliki: 663 | Return Abakaliki > Apapa: 663 | I44: 663 | J44: 663 | K44: =IF(I44="","",I44+J44) -> 1326 | L44: Estimated (calibrated) | M44: NIGER BISCUIT
A45: Apapa | B45: Aba | C45: Abia | D45: South East | E45: Interstate | G45: Aba | H45: Apapa > Aba: 612 | Return Aba > Apapa: 612 | I45: 612 | J45: 612 | K45: =IF(I45="","",I45+J45) -> 1224 | L45: Estimated (calibrated) | M45: Mega Manu, NIGER BISCUIT
A46: Apapa | B46: Enugu | C46: Enugu | D46: South East | E46: Interstate | G46: Enugu | H46: Apapa > Enugu: 577 | Return Enugu > Apapa: 577 | I46: 577 | J46: 577 | K46: =IF(I46="","",I46+J46) -> 1154 | L46: Estimated (calibrated) | M46: NIGER BISCUIT
A47: Apapa | B47: Owerri | C47: Imo | D47: South East | E47: Interstate | G47: Owerri | H47: Apapa > Owerri: 542 | Return Owerri > Apapa: 542 | I47: 542 | J47: 542 | K47: =IF(I47="","",I47+J47) -> 1084 | L47: Estimated (calibrated) | M47: NIGER BISCUIT
A48: Apapa | B48: Onitsha | C48: Anambra | D48: South East | E48: Interstate | G48: Onitsha | H48: Apapa > Onitsha: 475 | Return Onitsha > Apapa: 475 | I48: 475 | J48: 475 | K48: =IF(I48="","",I48+J48) -> 950 | L48: Estimated (calibrated) | M48: Mega Manu, NIGER BISCUIT, VANDERA
... A63: JMG Gbagada | B63: Ibadan | C63: Oyo | D63: South West | E63: Interstate | G63: Ibadan | H63: JMG Gbagada > Ibadan: 124 | Return Ibadan > JMG Gbagada: 124 | I63: 124 | J63: 124 | K63: =IF(I63="","",I63+J63) -> 248 | L63: Road-routed (OpenStreetMap) | M63: I'HS, JAMARA, JMG, Jamara
A64: JMG Gbagada | B64: Epe | C64: Lagos | D64: South West | E64: Internal (within state) | F64: Epe & Ibeju-Lekki | G64: Epe | H64: JMG Gbagada > Epe: 85 | Return Epe > JMG Gbagada: 85 | I64: 85 | J64: 85 | K64: =IF(I64="","",I64+J64) -> 170 | L64: Estimated (calibrated) | M64: I'HS, JMG
A65: JMG Gbagada | B65: Abeokuta | C65: Ogun | D65: South West | E65: Interstate | G65: Abeokuta | H65: JMG Gbagada > Abeokuta: 85 | Return Abeokuta > JMG Gbagada: 85 | I65: 85 | J65: 85 | K65: =IF(I65="","",I65+J65) -> 170 | L65: Estimated (calibrated) | M65: JAMARA, JMG, Jamara
A66: JMG Gbagada | B66: Ijebu Ode | C66: Ogun | D66: South West | E66: Interstate | G66: Ijebu Ode | H66: JMG Gbagada > Ijebu Ode: 85 | Return Ijebu Ode > JMG Gbagada: 85 | I66: 85 | J66: 85 | K66: =IF(I66="","",I66+J66) -> 170 | L66: Estimated (calibrated) | M66: JMG, Jamara
A67: JMG Gbagada | B67: Agbara - Badagry | C67: Lagos | D67: South West | E67: Internal (within state) | F67: Ojo–Badagry | G67: Agbara > Badagry | H67: JMG Gbagada > Agbara: 46 | Agbara > Badagry: 34 | Return Badagry > JMG Gbagada: 75 | I67: 81 | J67: 75 | K67: =IF(I67="","",I67+J67) -> 156 | L67: Estimated (calibrated) | M67: JAMARA | N67: Multi-drop: Leg 1 = sum of drop-to-drop legs
A68: JMG Gbagada | B68: Ibeju Lekki | C68: Lagos | D68: South West | E68: Internal (within state) | F68: Epe & Ibeju-Lekki | G68: Ibeju Lekki | H68: JMG Gbagada > Ibeju Lekki: 72 | Return Ibeju Lekki > JMG Gbagada: 72 | I68: 72 | J68: 72 | K68: =IF(I68="","",I68+J68) -> 144 | L68: Estimated (calibrated) | M68: Jamara
A69: JMG Gbagada | B69: IKM - Shagari - Ejigbo - Ipaja - Ayobo - Okokomaiko - Oshodi - Isolo | C69: Lagos | D69: South West | E69: Internal (within state) | F69: Multi-zone | G69: Oshodi > Ejigbo > Shagari Estate > Ipaja > Ayobo > Okokomaiko > Isolo | H69: JMG Gbagada > Oshodi: 7 | Oshodi > Ejigbo: 7 | Ejigbo > Shagari Estate: 7 | Shagari Estate > Ipaja: 4 | Ipaja > Ayobo: 3 | Ayobo > Okokomaiko: 22 | Okokomaiko > Isolo: 21 | Return Isolo > JMG Gbagada: 11 | I69: 71 | J69: 11 | K69: =IF(I69="","",I69+J69) -> 82 | L69: Estimated (calibrated) | M69: JAMARA | N69: Drop order re-sequenced for the shortest loop (written order would be 100 km round trip); Multi-drop: Leg 1 = sum of drop-to-drop legs; IKM not found on maps - route starts at Shagari; please confirm IKM location
A70: JMG Gbagada | B70: Sagamu | C70: Ogun | D70: South West | E70: Interstate | G70: Sagamu | H70: JMG Gbagada > Sagamu: 55 | Return Sagamu > JMG Gbagada: 55 | I70: 55 | J70: 55 | K70: =IF(I70="","",I70+J70) -> 110 | L70: Estimated (calibrated) | M70: JMG, Jamara
A71: JMG Gbagada | B71: Abule Egba - Ijaiye - Moshalashi - Kola - Sango Ota | C71: Ogun | D71: South West | E71: Interstate | G71: Abule Egba > Sango Ota > Kola > Moshalashi > Ijaiye | H71: JMG Gbagada > Abule Egba: 19 | Abule Egba > Sango Ota: 12 | Sango Ota > Kola: 4 | Kola > Moshalashi: 8 | Moshalashi > Ijaiye: 3 | Return Ijaiye > JMG Gbagada: 17 | I71: 46 | J71: 17 | K71: =IF(I71="","",I71+J71) -> 63 | L71: Estimated (calibrated) | M71: JAMARA | N71: Drop order re-sequenced for the shortest loop (written order would be 69 km round trip); Multi-drop: Leg 1 = sum of drop-to-drop legs
A72: JMG Gbagada | B72: Agbara | C72: Ogun | D72: South West | E72: Interstate | F72: Ojo–Badagry | G72: Agbara | H72: JMG Gbagada > Agbara: 46 | Return Agbara > JMG Gbagada: 46 | I72: 46 | J72: 46 | K72: =IF(I72="","",I72+J72) -> 92 | L72: Estimated (calibrated) | M72: Jamara
A73: JMG Gbagada | B73: Ilupeju - Gbagada - Apapa - Mushin - Okota - Fadeyi | C73: Lagos | D73: South West | E73: Internal (within state) | F73: Mainland | G73: Ilupeju > Mushin > Okota > Apapa > Fadeyi > Gbagada | H73: JMG Gbagada > Ilupeju: 5 | Ilupeju > Mushin: 3 | Mushin > Okota: 7 | Okota > Apapa: 12 | Apapa > Fadeyi: 13 | Fadeyi > Gbagada: 4 | Return Gbagada > JMG Gbagada: 3 | I73: 44 | J73: 3 | K73: =IF(I73="","",I73+J73) -> 47 | L73: Estimated (calibrated) | M73: JAMARA | N73: Drop order re-sequenced for the shortest loop (written order would be 60 km round trip); Multi-drop: Leg 1 = sum of drop-to-drop legs
A74: JMG Gbagada | B74: Victoria Island - Lekki - Ajah | C74: Lagos | D74: South West | E74: Internal (within state) | F74: Multi-zone | G74: Victoria Island > Lekki > Ajah | H74: JMG Gbagada > Victoria Island: 20 | Victoria Island > Lekki: 9 | Lekki > Ajah: 14 | Return Ajah > JMG Gbagada: 30 | I74: 43 | J74: 30 | K74: =IF(I74="","",I74+J74) -> 73 | L74: Estimated (calibrated) | M74: JAMARA | N74: Multi-drop: Leg 1 = sum of drop-to-drop legs
A75: JMG Gbagada | B75: Ojodu - Akute - Mowe | C75: Ogun | D75: South West | E75: Interstate | G75: Ojodu > Akute > Mowe | H75: JMG Gbagada > Ojodu: 13 | Ojodu > Akute: 7 | Akute > Mowe: 22 | Return Mowe > JMG Gbagada: 39 | I75: 41 | J75: 39 | K75: =IF(I75="","",I75+J75) -> 80 | L75: Estimated (calibrated) | M75: JAMARA | N75: Multi-drop: Leg 1 = sum of drop-to-drop legs
A76: JMG Gbagada | B76: Mowe | C76: Ogun | D76: South West | E76: Interstate | G76: Mowe | H76: JMG Gbagada > Mowe: 39 | Return Mowe > JMG Gbagada: 39 | I76: 39 | J76: 39 | K76: =IF(I76="","",I76+J76) -> 78 | L76: Estimated (calibrated) | M76: JMG
A77: JMG Gbagada | B77: Ojo | C77: Lagos | D77: South West | E77: Internal (within state) | F77: Ojo–Badagry | G77: Ojo | H77: JMG Gbagada > Ojo: 35 | Return Ojo > JMG Gbagada: 35 | I77: 35 | J77: 35 | K77: =IF(I77="","",I77+J77) -> 70 | L77: Estimated (calibrated) | M77: Jamara
A78: JMG Gbagada | B78: Alaba | C78: Lagos | D78: South West | E78: Internal (within state) | F78: Ojo–Badagry | G78: Alaba | H78: JMG Gbagada > Alaba: 34 | Return Alaba > JMG Gbagada: 34 | I78: 34 | J78: 34 | K78: =IF(I78="","",I78+J78) -> 68 | L78: Estimated (calibrated) | M78: JAMARA, JMG
A79: JMG Gbagada | B79: Festac - Mile 2 - Amuwo Odofin - Okota | C79: Lagos | D79: South West | E79: Internal (within state) | F79: Mainland | G79: Mile 2 > Amuwo Odofin > Festac > Okota | H79: JMG Gbagada > Mile 2: 18 | Mile 2 > Amuwo Odofin: 3 | Amuwo Odofin > Festac: 3 | Festac > Okota: 8 | Return Okota > JMG Gbagada: 14 | I79: 32 | J79: 14 | K79: =IF(I79="","",I79+J79) -> 46 | L79: Estimated (calibrated) | M79: JAMARA | N79: Drop order re-sequenced for the shortest loop (written order would be 50 km round trip); Multi-drop: Leg 1 = sum of drop-to-drop legs
A80: JMG Gbagada | B80: Okokomaiko | C80: Lagos | D80: South West | E80: Internal (within state) | F80: Ojo–Badagry | G80: Okokomaiko | H80: JMG Gbagada > Okokomaiko: 32 | Return Okokomaiko > JMG Gbagada: 32 | I80: 32 | J80: 32 | K80: =IF(I80="","",I80+J80) -> 64 | L80: Estimated (calibrated) | M80: JMG
A81: JMG Gbagada | B81: Sango Ota | C81: Ogun | D81: South West | E81: Interstate | G81: Sango Ota | H81: JMG Gbagada > Sango Ota: 31 | Return Sango Ota > JMG Gbagada: 31 | I81: 31 | J81: 31 | K81: =IF(I81="","",I81+J81) -> 62 | L81: Estimated (calibrated) | M81: JMG, Jamara
A82: JMG Gbagada | B82: Ajah | C82: Lagos | D82: South West | E82: Internal (within state) | F82: Lekki–Ajah | G82: Ajah | H82: JMG Gbagada > Ajah: 30 | Return Ajah > JMG Gbagada: 30 | I82: 30 | J82: 30 | K82: =IF(I82="","",I82+J82) -> 60 | L82: Estimated (calibrated) | M82: JMG, Jamara
A83: JMG Gbagada | B83: Ikeja - Agege - Dopemu - Magodo | C83: Lagos | D83: South West | E83: Internal (within state) | F83: Mainland | G83: Ikeja > Dopemu > Agege > Magodo | H83: JMG Gbagada > Ikeja: 9 | Ikeja > Dopemu: 6 | Dopemu > Agege: 3 | Agege > Magodo: 9 | Return Magodo > JMG Gbagada: 10 | I83: 27 | J83: 10 | K83: =IF(I83="","",I83+J83) -> 37 | L83: Estimated (calibrated) | M83: JAMARA | N83: Multi-drop: Leg 1 = sum of drop-to-drop legs
A84: JMG Gbagada | B84: Trade Fair | C84: Lagos | D84: South West | E84: Internal (within state) | F84: Ojo–Badagry | G84: Trade Fair | H84: JMG Gbagada > Trade Fair: 25 | Return Trade Fair > JMG Gbagada: 25 | I84: 25 | J84: 25 | K84: =IF(I84="","",I84+J84) -> 50 | L84: Estimated (calibrated) | M84: JMG
A85: JMG Gbagada | B85: Ketu - Ikorodu | C85: Lagos | D85: South West | E85: Internal (within state) | F85: Multi-zone | G85: Ketu > Ikorodu | H85: JMG Gbagada > Ketu: 6 | Ketu > Ikorodu: 18 | Return Ikorodu > JMG Gbagada: 20 | I85: 24 | J85: 20 | K85: =IF(I85="","",I85+J85) -> 44 | L85: Estimated (calibrated) | M85: JAMARA | N85: Multi-drop: Leg 1 = sum of drop-to-drop legs
A86: JMG Gbagada | B86: Agbado | C86: Ogun | D86: South West | E86: Interstate | F86: Mainland | G86: Agbado | H86: JMG Gbagada > Agbado: 24 | Return Agbado > JMG Gbagada: 24 | I86: 24 | J86: 24 | K86: =IF(I86="","",I86+J86) -> 48 | L86: Estimated (calibrated) | M86: JMG, Jamara
A87: JMG Gbagada | B87: Magboro | C87: Ogun | D87: South West | E87: Interstate | G87: Magboro | H87: JMG Gbagada > Magboro: 24 | Return Magboro > JMG Gbagada: 24 | I87: 24 | J87: 24 | K87: =IF(I87="","",I87+J87) -> 48 | L87: Estimated (calibrated) | M87: JMG, Jamara
A88: JMG Gbagada | B88: Surulere - Tejuosho - Yaba - Ebute Metta - Oyingbo | C88: Lagos | D88: South West | E88: Internal (within state) | F88: Mainland | G88: Tejuosho > Surulere > Ebute Metta > Oyingbo > Yaba | H88: JMG Gbagada > Tejuosho: 8 | Tejuosho > Surulere: 3 | Surulere > Ebute Metta: 5 | Ebute Metta > Oyingbo: 3 | Oyingbo > Yaba: 4 | Return Yaba > JMG Gbagada: 7 | I88: 22 | J88: 7 | K88: =IF(I88="","",I88+J88) -> 29 | L88: Estimated (calibrated) | M88: JAMARA | N88: Drop order re-sequenced for the shortest loop (written order would be 34 km round trip); Multi-drop: Leg 1 = sum of drop-to-drop legs
A89: JMG Gbagada | B89: Bar Beach | C89: Lagos | D89: South West | E89: Internal (within state) | F89: Island | G89: Bar Beach | H89: JMG Gbagada > Bar Beach: 22 | Return Bar Beach > JMG Gbagada: 22 | I89: 22 | J89: 22 | K89: =IF(I89="","",I89+J89) -> 44 | L89: Estimated (calibrated) | M89: JMG
A90: JMG Gbagada | B90: Festac | C90: Lagos | D90: South West | E90: Internal (within state) | F90: Mainland | G90: Festac | H90: JMG Gbagada > Festac: 21 | Return Festac > JMG Gbagada: 21 | I90: 21 | J90: 21 | K90: =IF(I90="","",I90+J90) -> 42 | L90: Estimated (calibrated) | M90: JMG, Jamara
A91: JMG Gbagada | B91: Ipaja | C91: Lagos | D91: South West | E91: Internal (within state) | F91: Mainland | G91: Ipaja | H91: JMG Gbagada > Ipaja: 21 | Return Ipaja > JMG Gbagada: 21 | I91: 21 | J91: 21 | K91: =IF(I91="","",I91+J91) -> 42 | L91: Estimated (calibrated) | M91: Jamara
A92: JMG Gbagada | B92: Lekki | C92: Lagos | D92: South West | E92: Internal (within state) | F92: Island | G92: Lekki | H92: JMG Gbagada > Lekki: 21 | Return Lekki > JMG Gbagada: 21 | I92: 21 | J92: 21 | K92: =IF(I92="","",I92+J92) -> 42 | L92: Estimated (calibrated) | M92: JMG, Jamara
A93: JMG Gbagada | B93: Oniru | C93: Lagos | D93: South West | E93: Internal (within state) | F93: Island | G93: Oniru | H93: JMG Gbagada > Oniru: 21 | Return Oniru > JMG Gbagada: 21 | I93: 21 | J93: 21 | K93: =IF(I93="","",I93+J93) -> 42 | L93: Estimated (calibrated) | M93: JMG, Jamara
A94: JMG Gbagada | B94: Ikorodu | C94: Lagos | D94: South West | E94: Internal (within state) | F94: Ikorodu | G94: Ikorodu | H94: JMG Gbagada > Ikorodu: 20 | Return Ikorodu > JMG Gbagada: 20 | I94: 20 | J94: 20 | K94: =IF(I94="","",I94+J94) -> 40 | L94: Estimated (calibrated) | M94: JMG, Jamara
A95: JMG Gbagada | B95: Victoria Island | C95: Lagos | D95: South West | E95: Internal (within state) | F95: Island | G95: Victoria Island | H95: JMG Gbagada > Victoria Island: 20 | Return Victoria Island > JMG Gbagada: 20 | I95: 20 | J95: 20 | K95: =IF(I95="","",I95+J95) -> 40 | L95: Estimated (calibrated) | M95: JMG, Jamara
A96: JMG Gbagada | B96: Adeola Odeku | C96: Lagos | D96: South West | E96: Internal (within state) | F96: Island | G96: Adeola Odeku | H96: JMG Gbagada > Adeola Odeku: 20 | Return Adeola Odeku > JMG Gbagada: 20 | I96: 20 | J96: 20 | K96: =IF(I96="","",I96+J96) -> 40 | L96: Estimated (calibrated) | M96: JMG
A97: JMG Gbagada | B97: Lagos Island - Marina | C97: Lagos | D97: South West | E97: Internal (within state) | F97: Island | G97: Lagos Island > Marina | H97: JMG Gbagada > Lagos Island: 16 | Lagos Island > Marina: 3 | Return Marina > JMG Gbagada: 16 | I97: 19 | J97: 16 | K97: =IF(I97="","",I97+J97) -> 35 | L97: Estimated (calibrated) | M97: JAMARA | N97: Multi-drop: Leg 1 = sum of drop-to-drop legs
A98: JMG Gbagada | B98: Abule Egba | C98: Lagos | D98: South West | E98: Internal (within state) | F98: Mainland | G98: Abule Egba | H98: JMG Gbagada > Abule Egba: 19 | Return Abule Egba > JMG Gbagada: 19 | I98: 19 | J98: 19 | K98: =IF(I98="","",I98+J98) -> 38 | L98: Estimated (calibrated) | M98: JMG, Jamara
A99: JMG Gbagada | B99: Ikotun | C99: Lagos | D99: South West | E99: Internal (within state) | F99: Mainland | G99: Ikotun | H99: JMG Gbagada > Ikotun: 19 | Return Ikotun > JMG Gbagada: 19 | I99: 19 | J99: 19 | K99: =IF(I99="","",I99+J99) -> 38 | L99: Estimated (calibrated) | M99: Jamara
A100: JMG Gbagada | B100: Akute | C100: Ogun | D100: South West | E100: Interstate | G100: Akute | H100: JMG Gbagada > Akute: 19 | Return Akute > JMG Gbagada: 19 | I100: 19 | J100: 19 | K100: =IF(I100="","",I100+J100) -> 38 | L100: Estimated (calibrated) | M100: JMG, Jamara
A101: JMG Gbagada | B101: Mile 2 | C101: Lagos | D101: South West | E101: Internal (within state) | F101: Mainland | G101: Mile 2 | H101: JMG Gbagada > Mile 2: 18 | Return Mile 2 > JMG Gbagada: 18 | I101: 18 | J101: 18 | K101: =IF(I101="","",I101+J101) -> 36 | L101: Estimated (calibrated) | M101: JMG, Jamara
A102: JMG Gbagada | B102: Iyana Ipaja | C102: Lagos | D102: South West | E102: Internal (within state) | F102: Mainland | G102: Iyana Ipaja | H102: JMG Gbagada > Iyana Ipaja: 18 | Return Iyana Ipaja > JMG Gbagada: 18 | I102: 18 | J102: 18 | K102: =IF(I102="","",I102+J102) -> 36 | L102: Estimated (calibrated) | M102: JMG
A103: JMG Gbagada | B103: Ijaiye | C103: Lagos | D103: South West | E103: Internal (within state) | F103: Mainland | G103: Ijaiye | H103: JMG Gbagada > Ijaiye: 17 | Return Ijaiye > JMG Gbagada: 17 | I103: 17 | J103: 17 | K103: =IF(I103="","",I103+J103) -> 34 | L103: Estimated (calibrated) | M103: JMG, Jamara
A104: JMG Gbagada | B104: Apapa | C104: Lagos | D104: South West | E104: Internal (within state) | F104: Mainland | G104: Apapa | H104: JMG Gbagada > Apapa: 17 | Return Apapa > JMG Gbagada: 17 | I104: 17 | J104: 17 | K104: =IF(I104="","",I104+J104) -> 34 | L104: Estimated (calibrated) | M104: JMG, Jamara
A105: JMG Gbagada | B105: Lagos Island | C105: Lagos | D105: South West | E105: Internal (within state) | F105: Island | G105: Lagos Island | H105: JMG Gbagada > Lagos Island: 16 | Return Lagos Island > JMG Gbagada: 16 | I105: 16 | J105: 16 | K105: =IF(I105="","",I105+J105) -> 32 | L105: Estimated (calibrated) | M105: JMG, Jamara
A106: JMG Gbagada | B106: Marina | C106: Lagos | D106: South West | E106: Internal (within state) | F106: Island | G106: Marina | H106: JMG Gbagada > Marina: 16 | Return Marina > JMG Gbagada: 16 | I106: 16 | J106: 16 | K106: =IF(I106="","",I106+J106) -> 32 | L106: Estimated (calibrated) | M106: JMG, Jamara
A107: JMG Gbagada | B107: Jankara | C107: Lagos | D107: South West | E107: Internal (within state) | F107: Island | G107: Jankara | H107: JMG Gbagada > Jankara: 15 | Return Jankara > JMG Gbagada: 15 | I107: 15 | J107: 15 | K107: =IF(I107="","",I107+J107) -> 30 | L107: Estimated (calibrated) | M107: JMG
A108: JMG Gbagada | B108: Agege | C108: Lagos | D108: South West | E108: Internal (within state) | F108: Mainland | G108: Agege | H108: JMG Gbagada > Agege: 14 | Return Agege > JMG Gbagada: 14 | I108: 14 | J108: 14 | K108: =IF(I108="","",I108+J108) -> 28 | L108: Estimated (calibrated) | M108: JMG, Jamara
A109: JMG Gbagada | B109: Ejigbo | C109: Lagos | D109: South West | E109: Internal (within state) | F109: Mainland | G109: Ejigbo | H109: JMG Gbagada > Ejigbo: 14 | Return Ejigbo > JMG Gbagada: 14 | I109: 14 | J109: 14 | K109: =IF(I109="","",I109+J109) -> 28 | L109: Estimated (calibrated) | M109: JMG, Jamara
A110: JMG Gbagada | B110: Okota | C110: Lagos | D110: South West | E110: Internal (within state) | F110: Mainland | G110: Okota | H110: JMG Gbagada > Okota: 14 | Return Okota > JMG Gbagada: 14 | I110: 14 | J110: 14 | K110: =IF(I110="","",I110+J110) -> 28 | L110: Estimated (calibrated) | M110: JMG, Jamara
A111: JMG Gbagada | B111: Orile | C111: Lagos | D111: South West | E111: Internal (within state) | F111: Mainland | G111: Orile | H111: JMG Gbagada > Orile: 14 | Return Orile > JMG Gbagada: 14 | I111: 14 | J111: 14 | K111: =IF(I111="","",I111+J111) -> 28 | L111: Estimated (calibrated) | M111: JMG
A112: JMG Gbagada | B112: Ojodu | C112: Lagos | D112: South West | E112: Internal (within state) | F112: Mainland | G112: Ojodu | H112: JMG Gbagada > Ojodu: 13 | Return Ojodu > JMG Gbagada: 13 | I112: 13 | J112: 13 | K112: =IF(I112="","",I112+J112) -> 26 | L112: Estimated (calibrated) | M112: JMG, Jamara
... A130: JMG Gbagada | B130: Bariga | C130: Lagos | D130: South West | E130: Internal (within state) | F130: Mainland | G130: Bariga | H130: JMG Gbagada > Bariga: 3 | Return Bariga > JMG Gbagada: 3 | I130: 3 | J130: 3 | K130: =IF(I130="","",I130+J130) -> 6 | L130: Estimated (calibrated) | M130: JMG
A131: JMG Gbagada | B131: Akwa Ibom (Uyo) | C131: Akwa Ibom | D131: South South | E131: Interstate | G131: Uyo | H131: JMG Gbagada > Uyo: 681 | Return Uyo > JMG Gbagada: 681 | I131: 681 | J131: 681 | K131: =IF(I131="","",I131+J131) -> 1362 | L131: Estimated (calibrated) | M131: JMG
A132: JMG Gbagada | B132: Port Harcourt | C132: Rivers | D132: South South | E132: Interstate | G132: Port Harcourt | H132: JMG Gbagada > Port Harcourt: 603 | Return Port Harcourt > JMG Gbagada: 603 | I132: 603 | J132: 603 | K132: =IF(I132="","",I132+J132) -> 1206 | L132: Estimated (calibrated) | M132: I'HS, JAMARA, JMG
A133: JMG Gbagada | B133: Delta (Asaba, direct) | C133: Delta | D133: South South | E133: Interstate | G133: Asaba | H133: JMG Gbagada > Asaba: 463 | Return Asaba > JMG Gbagada: 463 | I133: 463 | J133: 463 | K133: =IF(I133="","",I133+J133) -> 926 | L133: Estimated (calibrated) | M133: Jamara
A134: JMG Gbagada | B134: Warri | C134: Delta | D134: South South | E134: Interstate | G134: Warri | H134: JMG Gbagada > Warri: 423 | Return Warri > JMG Gbagada: 423 | I134: 423 | J134: 423 | K134: =IF(I134="","",I134+J134) -> 846 | L134: Estimated (calibrated) | M134: JMG
A135: JMG Gbagada | B135: Benin City | C135: Edo | D135: South South | E135: Interstate | G135: Benin City | H135: JMG Gbagada > Benin City: 303 | Return Benin City > JMG Gbagada: 303 | I135: 303 | J135: 303 | K135: =IF(I135="","",I135+J135) -> 606 | L135: Estimated (calibrated) | M135: JAMARA, JMG, Jamara
A136: JMG Gbagada | B136: Anambra (Awka) | C136: Anambra | D136: South East | E136: Interstate | G136: Awka | H136: JMG Gbagada > Awka: 512 | Return Awka > JMG Gbagada: 512 | I136: 512 | J136: 512 | K136: =IF(I136="","",I136+J136) -> 1024 | L136: Estimated (calibrated) | M136: JMG
...

Sheet KM from Oyo (Ibadan)
A1: Loading Point | B1: Destination | C1: Destination State | D1: Region | E1: Delivery Type | F1: Internal Zone | G1: Stops (in drive order) | H1: Leg Breakdown (km) | I1: Leg 1 - Outbound KM | J1: Leg 2 - Return KM | K1: Total Round Trip KM | L1: KM Source | M1: Clients on this lane | N1: Notes
A2: Ibadan | B2: Idiroko | C2: Ogun | D2: South West | E2: Interstate | G2: Idiroko | H2: Ibadan > Idiroko: 201 | Return Idiroko > Ibadan: 201 | I2: 201 | J2: 201 | K2: =IF(I2="","",I2+J2) -> 402 | L2: Estimated (calibrated) | M2: Lebruni
A3: Ibadan | B3: Akure | C3: Ondo | D3: South West | E3: Interstate | G3: Akure | H3: Ibadan > Akure: 187 | Return Akure > Ibadan: 187 | I3: 187 | J3: 187 | K3: =IF(I3="","",I3+J3) -> 374 | L3: Estimated (calibrated) | M3: Lebruni
A4: Ibadan | B4: Lagos Island | C4: Lagos | D4: South West | E4: Interstate | F4: Island | G4: Lagos Island | H4: Ibadan > Lagos Island: 153 | Return Lagos Island > Ibadan: 153 | I4: 153 | J4: 153 | K4: =IF(I4="","",I4+J4) -> 306 | L4: Estimated (calibrated) | M4: Lebruni
A5: Ibadan | B5: Lekki | C5: Lagos | D5: South West | E5: Interstate | F5: Island | G5: Lekki | H5: Ibadan > Lekki: 149 | Return Lekki > Ibadan: 149 | I5: 149 | J5: 149 | K5: =IF(I5="","",I5+J5) -> 298 | L5: Estimated (calibrated) | M5: Lebruni
A6: Ibadan | B6: Ondo Town | C6: Ondo | D6: South West | E6: Interstate | G6: Ondo Town | H6: Ibadan > Ondo Town: 141 | Return Ondo Town > Ibadan: 141 | I6: 141 | J6: 141 | K6: =IF(I6="","",I6+J6) -> 282 | L6: Estimated (calibrated) | M6: Lebruni
A7: Ibadan | B7: Sango Ota | C7: Ogun | D7: South West | E7: Interstate | G7: Sango Ota | H7: Ibadan > Sango Ota: 138 | Return Sango Ota > Ibadan: 138 | I7: 138 | J7: 138 | K7: =IF(I7="","",I7+J7) -> 276 | L7: Estimated (calibrated) | M7: Lebruni
A8: Ibadan | B8: Lagos - Ikeja | C8: Lagos | D8: South West | E8: Interstate | F8: Mainland | G8: Ikeja | H8: Ibadan > Ikeja: 138 | Return Ikeja > Ibadan: 138 | I8: 138 | J8: 138 | K8: =IF(I8="","",I8+J8) -> 276 | L8: Estimated (calibrated) | M8: Lebruni
A9: Ibadan | B9: Ogbomoso | C9: Oyo | D9: South West | E9: Internal (within state) | F9: Outside listed zones | G9: Ogbomoso | H9: Ibadan > Ogbomoso: 119 | Return Ogbomoso > Ibadan: 119 | I9: 119 | J9: 119 | K9: =IF(I9="","",I9+J9) -> 238 | L9: Estimated (calibrated) | M9: Lebruni
A10: Ibadan | B10: Ibafo | C10: Ogun | D10: South West | E10: Interstate | G10: Ibafo | H10: Ibadan > Ibafo: 116 | Return Ibafo > Ibadan: 116 | I10: 116 | J10: 116 | K10: =IF(I10="","",I10+J10) -> 232 | L10: Estimated (calibrated) | M10: Lebruni
A11: Ibadan | B11: Osogbo | C11: Osun | D11: South West | E11: Interstate | G11: Osogbo | H11: Ibadan > Osogbo: 110 | Return Osogbo > Ibadan: 110 | I11: 110 | J11: 110 | K11: =IF(I11="","",I11+J11) -> 220 | L11: Estimated (calibrated) | M11: Lebruni
A12: Ibadan | B12: Sagamu | C12: Ogun | D12: South West | E12: Interstate | G12: Sagamu | H12: Ibadan > Sagamu: 87 | Return Sagamu > Ibadan: 87 | I12: 87 | J12: 87 | K12: =IF(I12="","",I12+J12) -> 174 | L12: Estimated (calibrated) | M12: Lebruni
A13: Ibadan | B13: Abeokuta | C13: Ogun | D13: South West | E13: Interstate | G13: Abeokuta | H13: Ibadan > Abeokuta: 84 | Return Abeokuta > Ibadan: 84 | I13: 84 | J13: 84 | K13: =IF(I13="","",I13+J13) -> 168 | L13: Estimated (calibrated) | M13: Lebruni
A14: Ibadan | B14: Ibadan (Toll Gate) | C14: Oyo | D14: South West | E14: Internal (within state) | F14: Outside listed zones | G14: Ibadan Toll Gate | H14: Ibadan > Ibadan Toll Gate: 12 | Return Ibadan Toll Gate > Ibadan: 12 | I14: 12 | J14: 12 | K14: =IF(I14="","",I14+J14) -> 24 | L14: Estimated (calibrated) | M14: Lebruni
A15: Ibadan | B15: Ibadan | C15: Oyo | D15: South West | E15: Internal (within state) | F15: Outside listed zones | G15: Ibadan | H15: Ibadan > Ibadan: 10 | Return Ibadan > Ibadan: 10 | I15: 10 | J15: 10 | K15: =IF(I15="","",I15+J15) -> 20 | L15: Estimated (calibrated) | M15: JAT, Lebruni | N15: Delivery inside the loading town - 10 km allowance each way
A16: Ibadan | B16: Ikom | C16: Cross River | D16: South South | E16: Interstate | G16: Ikom | H16: Ibadan > Ikom: 719 | Return Ikom > Ibadan: 719 | I16: 719 | J16: 719 | K16: =IF(I16="","",I16+J16) -> 1438 | L16: Estimated (calibrated) | M16: Lebruni
A17: Ibadan | B17: Calabar | C17: Cross River | D17: South South | E17: Interstate | G17: Calabar | H17: Ibadan > Calabar: 710 | Return Calabar > Ibadan: 710 | I17: 710 | J17: 710 | K17: =IF(I17="","",I17+J17) -> 1420 | L17: Estimated (calibrated) | M17: Lebruni
A18: Ibadan | B18: Port Harcourt | C18: Rivers | D18: South South | E18: Interstate | G18: Port Harcourt | H18: Ibadan > Port Harcourt: 574 | Return Port Harcourt > Ibadan: 574 | I18: 574 | J18: 574 | K18: =IF(I18="","",I18+J18) -> 1148 | L18: Estimated (calibrated) | M18: Lebruni
A19: Ibadan | B19: Asaba | C19: Delta | D19: South South | E19: Interstate | G19: Asaba | H19: Ibadan > Asaba: 434 | Return Asaba > Ibadan: 434 | I19: 434 | J19: 434 | K19: =IF(I19="","",I19+J19) -> 868 | L19: Estimated (calibrated) | M19: Lebruni
A20: Ibadan | B20: Warri | C20: Delta | D20: South South | E20: Interstate | G20: Warri | H20: Ibadan > Warri: 393 | Return Warri > Ibadan: 393 | I20: 393 | J20: 393 | K20: =IF(I20="","",I20+J20) -> 786 | L20: Estimated (calibrated) | M20: Lebruni
A21: Ibadan | B21: Agbor | C21: Delta | D21: South South | E21: Interstate | G21: Agbor | H21: Ibadan > Agbor: 357 | Return Agbor > Ibadan: 357 | I21: 357 | J21: 357 | K21: =IF(I21="","",I21+J21) -> 714 | L21: Estimated (calibrated) | M21: JAT, Lebruni
A22: Ibadan | B22: Ekpoma | C22: Edo | D22: South South | E22: Interstate | G22: Ekpoma | H22: Ibadan > Ekpoma: 315 | Return Ekpoma > Ibadan: 315 | I22: 315 | J22: 315 | K22: =IF(I22="","",I22+J22) -> 630 | L22: Estimated (calibrated) | M22: JAT
A23: Ibadan | B23: Benin City | C23: Edo | D23: South South | E23: Interstate | G23: Benin City | H23: Ibadan > Benin City: 273 | Return Benin City > Ibadan: 273 | I23: 273 | J23: 273 | K23: =IF(I23="","",I23+J23) -> 546 | L23: Estimated (calibrated) | M23: Lebruni
A24: Ibadan | B24: Abakaliki | C24: Ebonyi | D24: South East | E24: Interstate | G24: Abakaliki | H24: Ibadan > Abakaliki: 631 | Return Abakaliki > Ibadan: 631 | I24: 631 | J24: 631 | K24: =IF(I24="","",I24+J24) -> 1262 | L24: Estimated (calibrated) | M24: JAT
A25: Ibadan | B25: Aba | C25: Abia | D25: South East | E25: Interstate | G25: Aba | H25: Ibadan > Aba: 580 | Return Aba > Ibadan: 580 | I25: 580 | J25: 580 | K25: =IF(I25="","",I25+J25) -> 1160 | L25: Estimated (calibrated) | M25: JAT, Lebruni
A26: Ibadan | B26: Umuahia | C26: Abia | D26: South East | E26: Interstate | G26: Umuahia | H26: Ibadan > Umuahia: 566 | Return Umuahia > Ibadan: 566 | I26: 566 | J26: 566 | K26: =IF(I26="","",I26+J26) -> 1132 | L26: Estimated (calibrated) | M26: Lebruni
A27: Ibadan | B27: Enugu | C27: Enugu | D27: South East | E27: Interstate | G27: Enugu | H27: Ibadan > Enugu: 544 | Return Enugu > Ibadan: 544 | I27: 544 | J27: 544 | K27: =IF(I27="","",I27+J27) -> 1088 | L27: Estimated (calibrated) | M27: Lebruni
... A68: Ibadan | B68: Yauri | C68: Kebbi | D68: North West | E68: Interstate | G68: Yauri | H68: Ibadan > Yauri: 480 | Return Yauri > Ibadan: 480 | I68: 480 | J68: 480 | K68: =IF(I68="","",I68+J68) -> 960 | L68: Estimated (calibrated) | M68: JAT

Sheet KM from Rivers (PH)
A1: Loading Point | B1: Destination | C1: Destination State | D1: Region | E1: Delivery Type | F1: Internal Zone | G1: Stops (in drive order) | H1: Leg Breakdown (km) | I1: Leg 1 - Outbound KM | J1: Leg 2 - Return KM | K1: Total Round Trip KM | L1: KM Source | M1: Clients on this lane | N1: Notes
A2: Port Harcourt | B2: Obudu Cattle Ranch | C2: Cross River | D2: South South | E2: Interstate | G2: Obudu Cattle Ranch | H2: Port Harcourt > Obudu Cattle Ranch: 412 | Return Obudu Cattle Ranch > Port Harcourt: 412 | I2: 412 | J2: 412 | K2: =IF(I2="","",I2+J2) -> 824 | L2: Estimated (calibrated) | M2: JMG | N2: Measured from JMG Port Harcourt (client main location); sheet lists JMG Gbagada as loading point
A3: Port Harcourt | B3: Ogoja | C3: Cross River | D3: South South | E3: Interstate | G3: Ogoja | H3: Port Harcourt > Ogoja: 375 | Return Ogoja > Port Harcourt: 375 | I3: 375 | J3: 375 | K3: =IF(I3="","",I3+J3) -> 750 | L3: Estimated (calibrated) | M3: JMG | N3: Measured from JMG Port Harcourt (client main location); sheet lists JMG Gbagada as loading point
A4: Port Harcourt | B4: Auchi | C4: Edo | D4: South South | E4: Interstate | G4: Auchi | H4: Port Harcourt > Auchi: 352 | Return Auchi > Port Harcourt: 352 | I4: 352 | J4: 352 | K4: =IF(I4="","",I4+J4) -> 704 | L4: Estimated (calibrated) | M4: JMG | N4: Measured from JMG Port Harcourt (client main location); sheet lists JMG Gbagada as loading point
A5: Port Harcourt | B5: Ekpoma | C5: Edo | D5: South South | E5: Interstate | G5: Ekpoma | H5: Port Harcourt > Ekpoma: 308 | Return Ekpoma > Port Harcourt: 308 | I5: 308 | J5: 308 | K5: =IF(I5="","",I5+J5) -> 616 | L5: Estimated (calibrated) | M5: JMG | N5: Measured from JMG Port Harcourt (client main location); sheet lists JMG Gbagada as loading point
A6: Port Harcourt | B6: Benin City | C6: Edo | D6: South South | E6: Interstate | G6: Benin City | H6: Port Harcourt > Benin City: 300 | Return Benin City > Port Harcourt: 300 | I6: 300 | J6: 300 | K6: =IF(I6="","",I6+J6) -> 600 | L6: Estimated (calibrated) | M6: JMG, WALTER & Hiffy
A7: Port Harcourt | B7: Ikom | C7: Cross River | D7: South South | E7: Interstate | G7: Ikom | H7: Port Harcourt > Ikom: 291 | Return Ikom > Port Harcourt: 291 | I7: 291 | J7: 291 | K7: =IF(I7="","",I7+J7) -> 582 | L7: Estimated (calibrated) | M7: JMG | N7: Measured from JMG Port Harcourt (client main location); sheet lists JMG Gbagada as loading point
A8: Port Harcourt | B8: Uromi | C8: Edo | D8: South South | E8: Interstate | G8: Uromi | H8: Port Harcourt > Uromi: 291 | Return Uromi > Port Harcourt: 291 | I8: 291 | J8: 291 | K8: =IF(I8="","",I8+J8) -> 582 | L8: Estimated (calibrated) | M8: JMG | N8: Measured from JMG Port Harcourt (client main location); sheet lists JMG Gbagada as loading point
A9: Port Harcourt | B9: Sapele | C9: Delta | D9: South South | E9: Interstate | G9: Sapele | H9: Port Harcourt > Sapele: 252 | Return Sapele > Port Harcourt: 252 | I9: 252 | J9: 252 | K9: =IF(I9="","",I9+J9) -> 504 | L9: Estimated (calibrated) | M9: JMG | N9: Measured from JMG Port Harcourt (client main location); sheet lists JMG Gbagada as loading point
A10: Port Harcourt | B10: Agbor | C10: Delta | D10: South South | E10: Interstate | G10: Agbor | H10: Port Harcourt > Agbor: 241 | Return Agbor > Port Harcourt: 241 | I10: 241 | J10: 241 | K10: =IF(I10="","",I10+J10) -> 482 | L10: Estimated (calibrated) | M10: JMG | N10: Measured from JMG Port Harcourt (client main location); sheet lists JMG Gbagada as loading point
A11: Port Harcourt | B11: Warri | C11: Delta | D11: South South | E11: Interstate | G11: Warri | H11: Port Harcourt > Warri: 213 | Return Warri > Port Harcourt: 213 | I11: 213 | J11: 213 | K11: =IF(I11="","",I11+J11) -> 426 | L11: Estimated (calibrated) | M11: JMG | N11: Measured from JMG Port Harcourt (client main location); sheet lists JMG Gbagada as loading point
A12: Port Harcourt | B12: Asaba | C12: Delta | D12: South South | E12: Interstate | G12: Asaba | H12: Port Harcourt > Asaba: 205 | Return Asaba > Port Harcourt: 205 | I12: 205 | J12: 205 | K12: =IF(I12="","",I12+J12) -> 410 | L12: Estimated (calibrated) | M12: JMG | N12: Measured from JMG Port Harcourt (client main location); sheet lists JMG Gbagada as loading point
A13: Port Harcourt | B13: Akamkpa | C13: Cross River | D13: South South | E13: Interstate | G13: Akamkpa | H13: Port Harcourt > Akamkpa: 201 | Return Akamkpa > Port Harcourt: 201 | I13: 201 | J13: 201 | K13: =IF(I13="","",I13+J13) -> 402 | L13: Estimated (calibrated) | M13: JMG | N13: Measured from JMG Port Harcourt (client main location); sheet lists JMG Gbagada as loading point
A14: Port Harcourt | B14: Akpabuyo | C14: Cross River | D14: South South | E14: Interstate | G14: Akpabuyo | H14: Port Harcourt > Akpabuyo: 200 | Return Akpabuyo > Port Harcourt: 200 | I14: 200 | J14: 200 | K14: =IF(I14="","",I14+J14) -> 400 | L14: Estimated (calibrated) | M14: JMG | N14: Measured from JMG Port Harcourt (client main location); sheet lists JMG Gbagada as loading point
A15: Port Harcourt | B15: Abraka | C15: Delta | D15: South South | E15: Interstate | G15: Abraka | H15: Port Harcourt > Abraka: 196 | Return Abraka > Port Harcourt: 196 | I15: 196 | J15: 196 | K15: =IF(I15="","",I15+J15) -> 392 | L15: Estimated (calibrated) | M15: JMG | N15: Measured from JMG Port Harcourt (client main location); sheet lists JMG Gbagada as loading point
A16: Port Harcourt | B16: Odukpani | C16: Cross River | D16: South South | E16: Interstate | G16: Odukpani | H16: Port Harcourt > Odukpani: 191 | Return Odukpani > Port Harcourt: 191 | I16: 191 | J16: 191 | K16: =IF(I16="","",I16+J16) -> 382 | L16: Estimated (calibrated) | M16: JMG | N16: Measured from JMG Port Harcourt (client main location); sheet lists JMG Gbagada as loading point
A17: Port Harcourt | B17: Calabar | C17: Cross River | D17: South South | E17: Interstate | G17: Calabar | H17: Port Harcourt > Calabar: 185 | Return Calabar > Port Harcourt: 185 | I17: 185 | J17: 185 | K17: =IF(I17="","",I17+J17) -> 370 | L17: Estimated (calibrated) | M17: JMG | N17: Measured from JMG Port Harcourt (client main location); sheet lists JMG Gbagada as loading point
A18: Port Harcourt | B18: Mbo | C18: Akwa Ibom | D18: South South | E18: Interstate | G18: Mbo | H18: Port Harcourt > Mbo: 184 | Return Mbo > Port Harcourt: 184 | I18: 184 | J18: 184 | K18: =IF(I18="","",I18+J18) -> 368 | L18: Estimated (calibrated) | M18: JMG | N18: Measured from JMG Port Harcourt (client main location); sheet lists JMG Gbagada as loading point
... A29: Port Harcourt | B29: Ikot Ekpene | C29: Akwa Ibom | D29: South South | E29: Interstate | G29: Ikot Ekpene | H29: Port Harcourt > Ikot Ekpene: 110 | Return Ikot Ekpene > Port Harcourt: 110 | I29: 110 | J29: 110 | K29: =IF(I29="","",I29+J29) -> 220 | L29: Estimated (calibrated) | M29: JMG | N29: Measured from JMG Port Harcourt (client main location); sheet lists JMG Gbagada as loading point
A30: Port Harcourt | B30: Omoku | C30: Rivers | D30: South South | E30: Internal (within state) | F30: Outside listed zones | G30: Omoku | H30: Port Harcourt > Omoku: 95 | Return Omoku > Port Harcourt: 95 | I30: 95 | J30: 95 | K30: =IF(I30="","",I30+J30) -> 190 | L30: Estimated (calibrated) | M30: JMG | N30: Measured from JMG Port Harcourt (client main location); sheet lists JMG Gbagada as loading point
A31: Port Harcourt | B31: Mbiama | C31: Rivers | D31: South South | E31: Internal (within state) | F31: Outside listed zones | G31: Mbiama | H31: Port Harcourt > Mbiama: 95 | Return Mbiama > Port Harcourt: 95 | I31: 95 | J31: 95 | K31: =IF(I31="","",I31+J31) -> 190 | L31: Estimated (calibrated) | M31: JMG | N31: Measured from JMG Port Harcourt (client main location); sheet lists JMG Gbagada as loading point
A32: Port Harcourt | B32: Ikot Abasi | C32: Akwa Ibom | D32: South South | E32: Interstate | G32: Ikot Abasi | H32: Port Harcourt > Ikot Abasi: 83 | Return Ikot Abasi > Port Harcourt: 83 | I32: 83 | J32: 83 | K32: =IF(I32="","",I32+J32) -> 166 | L32: Estimated (calibrated) | M32: JMG | N32: Measured from JMG Port Harcourt (client main location); sheet lists JMG Gbagada as loading point
A33: Port Harcourt | B33: Ahoada | C33: Rivers | D33: South South | E33: Internal (within state) | F33: Outside listed zones | G33: Ahoada | H33: Port Harcourt > Ahoada: 69 | Return Ahoada > Port Harcourt: 69 | I33: 69 | J33: 69 | K33: =IF(I33="","",I33+J33) -> 138 | L33: Estimated (calibrated) | M33: JMG | N33: Measured from JMG Port Harcourt (client main location); sheet lists JMG Gbagada as loading point
A34: Port Harcourt | B34: Abua | C34: Rivers | D34: South South | E34: Internal (within state) | F34: Outside listed zones | G34: Abua | H34: Port Harcourt > Abua: 60 | Return Abua > Port Harcourt: 60 | I34: 60 | J34: 60 | K34: =IF(I34="","",I34+J34) -> 120 | L34: Estimated (calibrated) | M34: JMG | N34: Measured from JMG Port Harcourt (client main location); sheet lists JMG Gbagada as loading point
A35: Port Harcourt | B35: Elele | C35: Rivers | D35: South South | E35: Internal (within state) | F35: Outside listed zones | G35: Elele | H35: Port Harcourt > Elele: 53 | Return Elele > Port Harcourt: 53 | I35: 53 | J35: 53 | K35: =IF(I35="","",I35+J35) -> 106 | L35: Estimated (calibrated) | M35: JMG | N35: Measured from JMG Port Harcourt (client main location); sheet lists JMG Gbagada as loading point
A36: Port Harcourt | B36: Bori | C36: Rivers | D36: South South | E36: Internal (within state) | F36: Outside listed zones | G36: Bori | H36: Port Harcourt > Bori: 53 | Return Bori > Port Harcourt: 53 | I36: 53 | J36: 53 | K36: =IF(I36="","",I36+J36) -> 106 | L36: Estimated (calibrated) | M36: JMG | N36: Measured from JMG Port Harcourt (client main location); sheet lists JMG Gbagada as loading point
A37: Port Harcourt | B37: Isiokpo | C37: Rivers | D37: South South | E37: Internal (within state) | F37: Airport Road | G37: Isiokpo | H37: Port Harcourt > Isiokpo: 34 | Return Isiokpo > Port Harcourt: 34 | I37: 34 | J37: 34 | K37: =IF(I37="","",I37+J37) -> 68 | L37: Estimated (calibrated) | M37: JMG | N37: Measured from JMG Port Harcourt (client main location); sheet lists JMG Gbagada as loading point
A38: Port Harcourt | B38: Omagwa | C38: Rivers | D38: South South | E38: Internal (within state) | F38: Airport Road | G38: Omagwa | H38: Port Harcourt > Omagwa: 31 | Return Omagwa > Port Harcourt: 31 | I38: 31 | J38: 31 | K38: =IF(I38="","",I38+J38) -> 62 | L38: Estimated (calibrated) | M38: JMG | N38: Measured from JMG Port Harcourt (client main location); sheet lists JMG Gbagada as loading point
A39: Port Harcourt | B39: Choba | C39: Rivers | D39: South South | E39: Internal (within state) | F39: Rumuokoro–Choba | G39: Choba | H39: Port Harcourt > Choba: 26 | Return Choba > Port Harcourt: 26 | I39: 26 | J39: 26 | K39: =IF(I39="","",I39+J39) -> 52 | L39: Estimated (calibrated) | M39: JMG | N39: Measured from JMG Port Harcourt (client main location); sheet lists JMG Gbagada as loading point
A40: Port Harcourt | B40: Alakahia | C40: Rivers | D40: South South | E40: Internal (within state) | F40: Rumuokoro–Choba | G40: Alakahia | H40: Port Harcourt > Alakahia: 22 | Return Alakahia > Port Harcourt: 22 | I40: 22 | J40: 22 | K40: =IF(I40="","",I40+J40) -> 44 | L40: Estimated (calibrated) | M40: JMG | N40: Measured from JMG Port Harcourt (client main location); sheet lists JMG Gbagada as loading point
A41: Port Harcourt | B41: Onne | C41: Rivers | D41: South South | E41: Internal (within state) | F41: Eleme–Onne–Oyigbo | G41: Onne | H41: Port Harcourt > Onne: 21 | Return Onne > Port Harcourt: 21 | I41: 21 | J41: 21 | K41: =IF(I41="","",I41+J41) -> 42 | L41: Estimated (calibrated) | M41: JMG | N41: Measured from JMG Port Harcourt (client main location); sheet lists JMG Gbagada as loading point
A42: Port Harcourt | B42: Airport Road | C42: Rivers | D42: South South | E42: Internal (within state) | F42: Airport Road | G42: PH Airport Road | H42: Port Harcourt > PH Airport Road: 19 | Return PH Airport Road > Port Harcourt: 19 | I42: 19 | J42: 19 | K42: =IF(I42="","",I42+J42) -> 38 | L42: Estimated (calibrated) | M42: JMG | N42: Measured from JMG Port Harcourt (client main location); sheet lists JMG Gbagada as loading point
A43: Port Harcourt | B43: Oyigbo | C43: Rivers | D43: South South | E43: Internal (within state) | F43: Eleme–Onne–Oyigbo | G43: Oyigbo | H43: Port Harcourt > Oyigbo: 16 | Return Oyigbo > Port Harcourt: 16 | I43: 16 | J43: 16 | K43: =IF(I43="","",I43+J43) -> 32 | L43: Estimated (calibrated) | M43: JMG | N43: Measured from JMG Port Harcourt (client main location); sheet lists JMG Gbagada as loading point
A44: Port Harcourt | B44: Okrika | C44: Rivers | D44: South South | E44: Internal (within state) | F44: Outside listed zones | G44: Okrika | H44: Port Harcourt > Okrika: 14 | Return Okrika > Port Harcourt: 14 | I44: 14 | J44: 14 | K44: =IF(I44="","",I44+J44) -> 28 | L44: Estimated (calibrated) | M44: JMG | N44: Measured from JMG Port Harcourt (client main location); sheet lists JMG Gbagada as loading point
... A50: Port Harcourt | B50: Trans-Amadi | C50: Rivers | D50: South South | E50: Internal (within state) | F50: GRA–Trans-Amadi | G50: Trans Amadi | H50: Port Harcourt > Trans Amadi: 3 | Return Trans Amadi > Port Harcourt: 3 | I50: 3 | J50: 3 | K50: =IF(I50="","",I50+J50) -> 6 | L50: Estimated (calibrated) | M50: JMG | N50: Measured from JMG Port Harcourt (client main location); sheet lists JMG Gbagada as loading point
A51: Port Harcourt | B51: Nsukka | C51: Enugu | D51: South East | E51: Interstate | G51: Nsukka | H51: Port Harcourt > Nsukka: 300 | Return Nsukka > Port Harcourt: 300 | I51: 300 | J51: 300 | K51: =IF(I51="","",I51+J51) -> 600 | L51: Estimated (calibrated) | M51: JMG | N51: Measured from JMG Port Harcourt (client main location); sheet lists JMG Gbagada as loading point
A52: Port Harcourt | B52: Ebonyi (Abakaliki) | C52: Ebonyi | D52: South East | E52: Interstate | G52: Abakaliki | H52: Port Harcourt > Abakaliki: 266 | Return Abakaliki > Port Harcourt: 266 | I52: 266 | J52: 266 | K52: =IF(I52="","",I52+J52) -> 532 | L52: Estimated (calibrated) | M52: JMG | N52: Measured from JMG Port Harcourt (client main location); sheet lists JMG Gbagada as loading point
A53: Port Harcourt | B53: Enugu | C53: Enugu | D53: South East | E53: Interstate | G53: Enugu | H53: Port Harcourt > Enugu: 246 | Return Enugu > Port Harcourt: 246 | I53: 246 | J53: 246 | K53: =IF(I53="","",I53+J53) -> 492 | L53: Estimated (calibrated) | M53: JMG | N53: Measured from JMG Port Harcourt (client main location); sheet lists JMG Gbagada as loading point
A54: Port Harcourt | B54: Oji River | C54: Enugu | D54: South East | E54: Interstate | G54: Oji River | H54: Port Harcourt > Oji River: 212 | Return Oji River > Port Harcourt: 212 | I54: 212 | J54: 212 | K54: =IF(I54="","",I54+J54) -> 424 | L54: Estimated (calibrated) | M54: JMG | N54: Measured from JMG Port Harcourt (client main location); sheet lists JMG Gbagada as loading point
A55: Port Harcourt | B55: Anambra (Awka) | C55: Anambra | D55: South East | E55: Interstate | G55: Awka | H55: Port Harcourt > Awka: 202 | Return Awka > Port Harcourt: 202 | I55: 202 | J55: 202 | K55: =IF(I55="","",I55+J55) -> 404 | L55: Estimated (calibrated) | M55: JMG | N55: Measured from JMG Port Harcourt (client main location); sheet lists JMG Gbagada as loading point
A56: Port Harcourt | B56: Onitsha | C56: Anambra | D56: South East | E56: Interstate | G56: Onitsha | H56: Port Harcourt > Onitsha: 196 | Return Onitsha > Port Harcourt: 196 | I56: 196 | J56: 196 | K56: =IF(I56="","",I56+J56) -> 392 | L56: Estimated (calibrated) | M56: JMG | N56: Measured from JMG Port Harcourt (client main location); sheet lists JMG Gbagada as loading point
A57: Port Harcourt | B57: Okpoko (Onitsha) | C57: Anambra | D57: South East | E57: Interstate | G57: Okpoko | H57: Port Harcourt > Okpoko: 191 | Return Okpoko > Port Harcourt: 191 | I57: 191 | J57: 191 | K57: =IF(I57="","",I57+J57) -> 382 | L57: Estimated (calibrated) | M57: JMG | N57: Measured from JMG Port Harcourt (client main location); sheet lists JMG Gbagada as loading point
A58: Port Harcourt | B58: Nnewi | C58: Anambra | D58: South East | E58: Interstate | G58: Nnewi | H58: Port Harcourt > Nnewi: 175 | Return Nnewi > Port Harcourt: 175 | I58: 175 | J58: 175 | K58: =IF(I58="","",I58+J58) -> 350 | L58: Estimated (calibrated) | M58: JMG | N58: Measured from JMG Port Harcourt (client main location); sheet lists JMG Gbagada as loading point
A59: Port Harcourt | B59: Arondizuogu | C59: Imo | D59: South East | E59: Interstate | G59: Arondizuogu | H59: Port Harcourt > Arondizuogu: 165 | Return Arondizuogu > Port Harcourt: 165 | I59: 165 | J59: 165 | K59: =IF(I59="","",I59+J59) -> 330 | L59: Estimated (calibrated) | M59: JMG | N59: Measured from JMG Port Harcourt (client main location); sheet lists JMG Gbagada as loading point
A60: Port Harcourt | B60: Ohafia | C60: Abia | D60: South East | E60: Interstate | G60: Ohafia | H60: Port Harcourt > Ohafia: 162 | Return Ohafia > Port Harcourt: 162 | I60: 162 | J60: 162 | K60: =IF(I60="","",I60+J60) -> 324 | L60: Estimated (calibrated) | M60: JMG | N60: Measured from JMG Port Harcourt (client main location); sheet lists JMG Gbagada as loading point
A61: Port Harcourt | B61: Uturu | C61: Abia | D61: South East | E61: Interstate | G61: Uturu | H61: Port Harcourt > Uturu: 156 | Return Uturu > Port Harcourt: 156 | I61: 156 | J61: 156 | K61: =IF(I61="","",I61+J61) -> 312 | L61: Estimated (calibrated) | M61: JMG | N61: Measured from JMG Port Harcourt (client main location); sheet lists JMG Gbagada as loading point
A62: Port Harcourt | B62: Okigwe | C62: Imo | D62: South East | E62: Interstate | G62: Okigwe | H62: Port Harcourt > Okigwe: 153 | Return Okigwe > Port Harcourt: 153 | I62: 153 | J62: 153 | K62: =IF(I62="","",I62+J62) -> 306 | L62: Estimated (calibrated) | M62: JMG | N62: Measured from JMG Port Harcourt (client main location); sheet lists JMG Gbagada as loading point
... A71: Port Harcourt | B71: Otukpa | C71: Benue | D71: North Central | E71: Interstate | G71: Otukpa | H71: Port Harcourt > Otukpa: 349 | Return Otukpa > Port Harcourt: 349 | I71: 349 | J71: 349 | K71: =IF(I71="","",I71+J71) -> 698 | L71: Estimated (calibrated) | M71: JMG | N71: Measured from JMG Port Harcourt (client main location); sheet lists JMG Gbagada as loading point

Sheet KM from FCT (Abuja)
A1: Loading Point | B1: Destination | C1: Destination State | D1: Region | E1: Delivery Type | F1: Internal Zone | G1: Stops (in drive order) | H1: Leg Breakdown (km) | I1: Leg 1 - Outbound KM | J1: Leg 2 - Return KM | K1: Total Round Trip KM | L1: KM Source | M1: Clients on this lane | N1: Notes
A2: Abuja | B2: Lagos (Gbagada) | C2: Lagos | D2: South West | E2: Interstate | F2: Mainland | G2: Lagos (Gbagada) | H2: Abuja > Lagos (Gbagada): 740 | Return Lagos (Gbagada) > Abuja: 740 | I2: 740 | J2: 740 | K2: =IF(I2="","",I2+J2) -> 1480 | L2: Road-routed (OpenStreetMap) | M2: JMG | N2: Measured from JMG Abuja (client main location); sheet lists JMG Gbagada as loading point
A3: Abuja | B3: Abeokuta | C3: Ogun | D3: South West | E3: Interstate | G3: Abeokuta | H3: Abuja > Abeokuta: 703 | Return Abeokuta > Abuja: 703 | I3: 703 | J3: 703 | K3: =IF(I3="","",I3+J3) -> 1406 | L3: Estimated (calibrated) | M3: JMG | N3: Measured from JMG Abuja (client main location); sheet lists JMG Gbagada as loading point
A4: Abuja | B4: Ibadan | C4: Oyo | D4: South West | E4: Interstate | G4: Ibadan | H4: Abuja > Ibadan: 612 | Return Ibadan > Abuja: 612 | I4: 612 | J4: 612 | K4: =IF(I4="","",I4+J4) -> 1224 | L4: Estimated (calibrated) | M4: JMG | N4: Measured from JMG Abuja (client main location); sheet lists JMG Gbagada as loading point
A5: Abuja | B5: Port Harcourt | C5: Rivers | D5: South South | E5: Interstate | G5: Port Harcourt | H5: Abuja > Port Harcourt: 631 | Return Port Harcourt > Abuja: 631 | I5: 631 | J5: 631 | K5: =IF(I5="","",I5+J5) -> 1262 | L5: Estimated (calibrated) | M5: JMG | N5: Measured from JMG Abuja (client main location); sheet lists JMG Gbagada as loading point
A6: Abuja | B6: Warri | C6: Delta | D6: South South | E6: Interstate | G6: Warri | H6: Abuja > Warri: 583 | Return Warri > Abuja: 583 | I6: 583 | J6: 583 | K6: =IF(I6="","",I6+J6) -> 1166 | L6: Estimated (calibrated) | M6: JMG | N6: Measured from JMG Abuja (client main location); sheet lists JMG Gbagada as loading point
A7: Abuja | B7: Benin City | C7: Edo | D7: South South | E7: Interstate | G7: Benin City | H7: Abuja > Benin City: 487 | Return Benin City > Abuja: 487 | I7: 487 | J7: 487 | K7: =IF(I7="","",I7+J7) -> 974 | L7: Estimated (calibrated) | M7: JMG | N7: Measured from JMG Abuja (client main location); sheet lists JMG Gbagada as loading point
A8: Abuja | B8: Gboko | C8: Benue | D8: North Central | E8: Interstate | G8: Gboko | H8: Abuja > Gboko: 338 | Return Gboko > Abuja: 338 | I8: 338 | J8: 338 | K8: =IF(I8="","",I8+J8) -> 676 | L8: Estimated (calibrated) | M8: JMG | N8: Measured from JMG Abuja (client main location); sheet lists JMG Gbagada as loading point
A9: Abuja | B9: Idah | C9: Kogi | D9: North Central | E9: Interstate | G9: Idah | H9: Abuja > Idah: 302 | Return Idah > Abuja: 302 | I9: 302 | J9: 302 | K9: =IF(I9="","",I9+J9) -> 604 | L9: Estimated (calibrated) | M9: JMG | N9: Measured from JMG Abuja (client main location); sheet lists JMG Gbagada as loading point
A10: Abuja | B10: Otukpo | C10: Benue | D10: North Central | E10: Interstate | G10: Otukpo | H10: Abuja > Otukpo: 285 | Return Otukpo > Abuja: 285 | I10: 285 | J10: 285 | K10: =IF(I10="","",I10+J10) -> 570 | L10: Estimated (calibrated) | M10: JMG | N10: Measured from JMG Abuja (client main location); sheet lists JMG Gbagada as loading point
A11: Abuja | B11: Okene | C11: Kogi | D11: North Central | E11: Interstate | G11: Okene | H11: Abuja > Okene: 283 | Return Okene > Abuja: 283 | I11: 283 | J11: 283 | K11: =IF(I11="","",I11+J11) -> 566 | L11: Estimated (calibrated) | M11: JMG | N11: Measured from JMG Abuja (client main location); sheet lists JMG Gbagada as loading point
A12: Abuja | B12: Makurdi | C12: Benue | D12: North Central | E12: Interstate | G12: Makurdi | H12: Abuja > Makurdi: 241 | Return Makurdi > Abuja: 241 | I12: 241 | J12: 241 | K12: =IF(I12="","",I12+J12) -> 482 | L12: Estimated (calibrated) | M12: JMG | N12: Measured from JMG Abuja (client main location); sheet lists JMG Gbagada as loading point
A13: Abuja | B13: Ankpa | C13: Kogi | D13: North Central | E13: Interstate | G13: Ankpa | H13: Abuja > Ankpa: 240 | Return Ankpa > Abuja: 240 | I13: 240 | J13: 240 | K13: =IF(I13="","",I13+J13) -> 480 | L13: Estimated (calibrated) | M13: JMG | N13: Measured from JMG Abuja (client main location); sheet lists JMG Gbagada as loading point
A14: Abuja | B14: Jos | C14: Plateau | D14: North Central | E14: Interstate | G14: Jos | H14: Abuja > Jos: 229 | Return Jos > Abuja: 229 | I14: 229 | J14: 229 | K14: =IF(I14="","",I14+J14) -> 458 | L14: Estimated (calibrated) | M14: JMG | N14: Measured from JMG Abuja (client main location); sheet lists JMG Gbagada as loading point
... A20: Abuja | B20: Keffi | C20: Nasarawa | D20: North Central | E20: Interstate | G20: Keffi | H20: Abuja > Keffi: 62 | Return Keffi > Abuja: 62 | I20: 62 | J20: 62 | K20: =IF(I20="","",I20+J20) -> 124 | L20: Estimated (calibrated) | M20: JMG | N20: Measured from JMG Abuja (client main location); sheet lists JMG Gbagada as loading point
A21: Abuja | B21: Gwagwalada | C21: FCT | D21: North Central | E21: Internal (within state) | F21: Outside listed zones | G21: Gwagwalada | H21: Abuja > Gwagwalada: 61 | Return Gwagwalada > Abuja: 61 | I21: 61 | J21: 61 | K21: =IF(I21="","",I21+J21) -> 122 | L21: Estimated (calibrated) | M21: JMG | N21: Measured from JMG Abuja (client main location); sheet lists JMG Gbagada as loading point
A22: Abuja | B22: Suleja | C22: Niger | D22: North Central | E22: Interstate | G22: Suleja | H22: Abuja > Suleja: 51 | Return Suleja > Abuja: 51 | I22: 51 | J22: 51 | K22: =IF(I22="","",I22+J22) -> 102 | L22: Estimated (calibrated) | M22: JMG | N22: Measured from JMG Abuja (client main location); sheet lists JMG Gbagada as loading point
A23: Abuja | B23: Kuje | C23: FCT | D23: North Central | E23: Internal (within state) | F23: Airport Road–Lugbe | G23: Kuje | H23: Abuja > Kuje: 49 | Return Kuje > Abuja: 49 | I23: 49 | J23: 49 | K23: =IF(I23="","",I23+J23) -> 98 | L23: Estimated (calibrated) | M23: JMG | N23: Measured from JMG Abuja (client main location); sheet lists JMG Gbagada as loading point
A24: Abuja | B24: Zuba | C24: FCT | D24: North Central | E24: Internal (within state) | F24: Kubwa–Bwari | G24: Zuba | H24: Abuja > Zuba: 43 | Return Zuba > Abuja: 43 | I24: 43 | J24: 43 | K24: =IF(I24="","",I24+J24) -> 86 | L24: Estimated (calibrated) | M24: JMG | N24: Measured from JMG Abuja (client main location); sheet lists JMG Gbagada as loading point
A25: Abuja | B25: Bwari | C25: FCT | D25: North Central | E25: Internal (within state) | F25: Kubwa–Bwari | G25: Bwari | H25: Abuja > Bwari: 38 | Return Bwari > Abuja: 38 | I25: 38 | J25: 38 | K25: =IF(I25="","",I25+J25) -> 76 | L25: Estimated (calibrated) | M25: JMG | N25: Measured from JMG Abuja (client main location); sheet lists JMG Gbagada as loading point
A26: Abuja | B26: Karshi | C26: FCT | D26: North Central | E26: Internal (within state) | F26: Nyanya–Karu | G26: Karshi | H26: Abuja > Karshi: 36 | Return Karshi > Abuja: 36 | I26: 36 | J26: 36 | K26: =IF(I26="","",I26+J26) -> 72 | L26: Estimated (calibrated) | M26: JMG | N26: Measured from JMG Abuja (client main location); sheet lists JMG Gbagada as loading point
A27: Abuja | B27: Dei-Dei | C27: FCT | D27: North Central | E27: Internal (within state) | F27: Kubwa–Bwari | G27: Dei Dei | H27: Abuja > Dei Dei: 32 | Return Dei Dei > Abuja: 32 | I27: 32 | J27: 32 | K27: =IF(I27="","",I27+J27) -> 64 | L27: Estimated (calibrated) | M27: JMG | N27: Measured from JMG Abuja (client main location); sheet lists JMG Gbagada as loading point
A28: Abuja | B28: Kubwa | C28: FCT | D28: North Central | E28: Internal (within state) | F28: Kubwa–Bwari | G28: Kubwa | H28: Abuja > Kubwa: 28 | Return Kubwa > Abuja: 28 | I28: 28 | J28: 28 | K28: =IF(I28="","",I28+J28) -> 56 | L28: Estimated (calibrated) | M28: JMG | N28: Measured from JMG Abuja (client main location); sheet lists JMG Gbagada as loading point
A29: Abuja | B29: Pyakasa | C29: FCT | D29: North Central | E29: Internal (within state) | F29: Airport Road–Lugbe | G29: Pyakasa | H29: Abuja > Pyakasa: 22 | Return Pyakasa > Abuja: 22 | I29: 22 | J29: 22 | K29: =IF(I29="","",I29+J29) -> 44 | L29: Estimated (calibrated) | M29: JMG | N29: Measured from JMG Abuja (client main location); sheet lists JMG Gbagada as loading point
A30: Abuja | B30: Kasana | C30: FCT | D30: North Central | E30: Internal (within state) | F30: Kubwa–Bwari | G30: Kasana | H30: Abuja > Kasana: 21 | Return Kasana > Abuja: 21 | I30: 21 | J30: 21 | K30: =IF(I30="","",I30+J30) -> 42 | L30: Estimated (calibrated) | M30: JMG | N30: Measured from JMG Abuja (client main location); sheet lists JMG Gbagada as loading point
A31: Abuja | B31: Lugbe | C31: FCT | D31: North Central | E31: Internal (within state) | F31: Airport Road–Lugbe | G31: Lugbe | H31: Abuja > Lugbe: 21 | Return Lugbe > Abuja: 21 | I31: 21 | J31: 21 | K31: =IF(I31="","",I31+J31) -> 42 | L31: Estimated (calibrated) | M31: JMG | N31: Measured from JMG Abuja (client main location); sheet lists JMG Gbagada as loading point
A32: Abuja | B32: Airport Road | C32: FCT | D32: North Central | E32: Internal (within state) | F32: Airport Road–Lugbe | G32: Abuja Airport Road | H32: Abuja > Abuja Airport Road: 18 | Return Abuja Airport Road > Abuja: 18 | I32: 18 | J32: 18 | K32: =IF(I32="","",I32+J32) -> 36 | L32: Estimated (calibrated) | M32: JMG | N32: Measured from JMG Abuja (client main location); sheet lists JMG Gbagada as loading point
A33: Abuja | B33: Dutse Alhaji | C33: FCT | D33: North Central | E33: Internal (within state) | F33: Kubwa–Bwari | G33: Dutse Alhaji | H33: Abuja > Dutse Alhaji: 18 | Return Dutse Alhaji > Abuja: 18 | I33: 18 | J33: 18 | K33: =IF(I33="","",I33+J33) -> 36 | L33: Estimated (calibrated) | M33: JMG | N33: Measured from JMG Abuja (client main location); sheet lists JMG Gbagada as loading point
A34: Abuja | B34: Kurudu | C34: FCT | D34: North Central | E34: Internal (within state) | F34: Nyanya–Karu | G34: Kurudu | H34: Abuja > Kurudu: 17 | Return Kurudu > Abuja: 17 | I34: 17 | J34: 17 | K34: =IF(I34="","",I34+J34) -> 34 | L34: Estimated (calibrated) | M34: JMG | N34: Measured from JMG Abuja (client main location); sheet lists JMG Gbagada as loading point
... A67: Abuja | B67: Area 11, Garki | C67: FCT | D67: North Central | E67: Internal (within state) | F67: City Centre | G67: Area 11 Garki | H67: Abuja > Area 11 Garki: 3 | Return Area 11 Garki > Abuja: 3 | I67: 3 | J67: 3 | K67: =IF(I67="","",I67+J67) -> 6 | L67: Estimated (calibrated) | M67: JMG | N67: Measured from JMG Abuja (client main location); sheet lists JMG Gbagada as loading point
A68: Abuja | B68: Maiduguri | C68: Borno | D68: North East | E68: Interstate | G68: Maiduguri | H68: Abuja > Maiduguri: 921 | Return Maiduguri > Abuja: 921 | I68: 921 | J68: 921 | K68: =IF(I68="","",I68+J68) -> 1842 | L68: Estimated (calibrated) | M68: JMG | N68: Measured from JMG Abuja (client main location); sheet lists JMG Gbagada as loading point
A69: Abuja | B69: Mubi | C69: Adamawa | D69: North East | E69: Interstate | G69: Mubi | H69: Abuja > Mubi: 860 | Return Mubi > Abuja: 860 | I69: 860 | J69: 860 | K69: =IF(I69="","",I69+J69) -> 1720 | L69: Estimated (calibrated) | M69: JMG | N69: Measured from JMG Abuja (client main location); sheet lists JMG Gbagada as loading point
A70: Abuja | B70: Yobe (Damaturu) | C70: Yobe | D70: North East | E70: Interstate | G70: Damaturu | H70: Abuja > Damaturu: 762 | Return Damaturu > Abuja: 762 | I70: 762 | J70: 762 | K70: =IF(I70="","",I70+J70) -> 1524 | L70: Estimated (calibrated) | M70: JMG | N70: Measured from JMG Abuja (client main location); sheet lists JMG Gbagada as loading point
A71: Abuja | B71: Yola | C71: Adamawa | D71: North East | E71: Interstate | G71: Yola | H71: Abuja > Yola: 730 | Return Yola > Abuja: 730 | I71: 730 | J71: 730 | K71: =IF(I71="","",I71+J71) -> 1460 | L71: Estimated (calibrated) | M71: JMG | N71: Measured from JMG Abuja (client main location); sheet lists JMG Gbagada as loading point
A72: Abuja | B72: Jalingo | C72: Taraba | D72: North East | E72: Interstate | G72: Jalingo | H72: Abuja > Jalingo: 565 | Return Jalingo > Abuja: 565 | I72: 565 | J72: 565 | K72: =IF(I72="","",I72+J72) -> 1130 | L72: Estimated (calibrated) | M72: JMG | N72: Measured from JMG Abuja (client main location); sheet lists JMG Gbagada as loading point
A73: Abuja | B73: Gombe | C73: Gombe | D73: North East | E73: Interstate | G73: Gombe | H73: Abuja > Gombe: 565 | Return Gombe > Abuja: 565 | I73: 565 | J73: 565 | K73: =IF(I73="","",I73+J73) -> 1130 | L73: Estimated (calibrated) | M73: JMG | N73: Measured from JMG Abuja (client main location); sheet lists JMG Gbagada as loading point
A74: Abuja | B74: Bauchi | C74: Bauchi | D74: North East | E74: Interstate | G74: Bauchi | H74: Abuja > Bauchi: 389 | Return Bauchi > Abuja: 389 | I74: 389 | J74: 389 | K74: =IF(I74="","",I74+J74) -> 778 | L74: Estimated (calibrated) | M74: JMG | N74: Measured from JMG Abuja (client main location); sheet lists JMG Gbagada as loading point
A75: Abuja | B75: Birnin Kebbi | C75: Kebbi | D75: North West | E75: Interstate | G75: Birnin Kebbi | H75: Abuja > Birnin Kebbi: 694 | Return Birnin Kebbi > Abuja: 694 | I75: 694 | J75: 694 | K75: =IF(I75="","",I75+J75) -> 1388 | L75: Estimated (calibrated) | M75: JMG | N75: Measured from JMG Abuja (client main location); sheet lists JMG Gbagada as loading point
A76: Abuja | B76: Sokoto | C76: Sokoto | D76: North West | E76: Interstate | G76: Sokoto | H76: Abuja > Sokoto: 676 | Return Sokoto > Abuja: 676 | I76: 676 | J76: 676 | K76: =IF(I76="","",I76+J76) -> 1352 | L76: Estimated (calibrated) | M76: JMG | N76: Measured from JMG Abuja (client main location); sheet lists JMG Gbagada as loading point
A77: Abuja | B77: Zamfara (Gusau) | C77: Zamfara | D77: North West | E77: Interstate | G77: Gusau | H77: Abuja > Gusau: 476 | Return Gusau > Abuja: 476 | I77: 476 | J77: 476 | K77: =IF(I77="","",I77+J77) -> 952 | L77: Estimated (calibrated) | M77: JMG | N77: Measured from JMG Abuja (client main location); sheet lists JMG Gbagada as loading point
A78: Abuja | B78: Kano | C78: Kano | D78: North West | E78: Interstate | G78: Kano | H78: Abuja > Kano: 460 | Return Kano > Abuja: 460 | I78: 460 | J78: 460 | K78: =IF(I78="","",I78+J78) -> 920 | L78: Estimated (calibrated) | M78: JMG | N78: Measured from JMG Abuja (client main location); sheet lists JMG Gbagada as loading point
A79: Abuja | B79: Kaduna | C79: Kaduna | D79: North West | E79: Interstate | G79: Kaduna | H79: Abuja > Kaduna: 212 | Return Kaduna > Abuja: 212 | I79: 212 | J79: 212 | K79: =IF(I79="","",I79+J79) -> 424 | L79: Estimated (calibrated) | M79: JMG | N79: Measured from JMG Abuja (client main location); sheet lists JMG Gbagada as loading point
A80: Abuja | B80: Jega | G80: LOCATION NOT FOUND | K80: =IF(I80="","",I80+J80) | M80: JMG | N80: Measured from JMG Abuja (client main location); sheet lists JMG Gbagada as loading point; Place not recognised - send the exact location/address and it will be filled in

Sheet KM from Nasarawa (Keffi)
A1: Loading Point | B1: Destination | C1: Destination State | D1: Region | E1: Delivery Type | F1: Internal Zone | G1: Stops (in drive order) | H1: Leg Breakdown (km) | I1: Leg 1 - Outbound KM | J1: Leg 2 - Return KM | K1: Total Round Trip KM | L1: KM Source | M1: Clients on this lane | N1: Notes
A2: Keffi | B2: Ogere | C2: Ogun | D2: South West | E2: Interstate | G2: Ogere | H2: Keffi > Ogere: 728 | Return Ogere > Keffi: 728 | I2: 728 | J2: 728 | K2: =IF(I2="","",I2+J2) -> 1456 | L2: Road-routed (OpenStreetMap) | M2: ABBA SALEH
A3: Keffi | B3: Lafia | C3: Nasarawa | D3: North Central | E3: Internal (within state) | F3: Outside listed zones | G3: Lafia | H3: Keffi > Lafia: 127 | Return Lafia > Keffi: 127 | I3: 127 | J3: 127 | K3: =IF(I3="","",I3+J3) -> 254 | L3: Road-routed (OpenStreetMap) | M3: ABBA SALEH | N3: Main location Ogere but loading point Keffi - measured from Keffi as listed

Sheet Internal Zones
A1: State | B1: Depot | C1: Zone (Route) | D1: Route Description | E1: No. of Areas | F1: Zone Centre | G1: Centre - Outbound KM | H1: Centre - Return KM | I1: Centre - Round Trip KM | J1: Far End of Zone | K1: Far End - Outbound KM | L1: Far End - Return KM | M1: Far End - Round Trip KM | N1: KM Source
A2: Lagos | B2: JMG Gbagada | C2: Mainland | D2: Central and western mainland | E2: 74 | F2: Oshodi | G2: 7 | H2: 7 | I2: =G2+H2 -> 14 | J2: Alagbado | K2: 24 | L2: 24 | M2: =K2+L2 -> 48 | N2: Estimated (calibrated)
A3: Lagos | B3: Apapa | C3: Mainland | D3: Central and western mainland | E3: 74 | F3: Oshodi | G3: 17 | H3: 17 | I3: =G3+H3 -> 34 | J3: Alagbado | K3: 36 | L3: 36 | M3: =K3+L3 -> 72 | N3: Estimated (calibrated)
A4: Lagos | B4: Mile 2 | C4: Mainland | D4: Central and western mainland | E4: 74 | F4: Oshodi | G4: 14 | H4: 14 | I4: =G4+H4 -> 28 | J4: Alagbado | K4: 31 | L4: 31 | M4: =K4+L4 -> 62 | N4: Estimated (calibrated)
A5: Lagos | B5: Amuwo Odofin | C5: Mainland | D5: Central and western mainland | E5: 74 | F5: Oshodi | G5: 15 | H5: 15 | I5: =G5+H5 -> 30 | J5: Alagbado | K5: 31 | L5: 31 | M5: =K5+L5 -> 62 | N5: Estimated (calibrated)
A6: Lagos | B6: Isolo | C6: Mainland | D6: Central and western mainland | E6: 74 | F6: Oshodi | G6: 5 | H6: 5 | I6: =G6+H6 -> 10 | J6: Alagbado | K6: 21 | L6: 21 | M6: =K6+L6 -> 42 | N6: Estimated (calibrated)
A7: Lagos | B7: JMG Gbagada | C7: Island | D7: VI, Ikoyi, Lagos Island, Lekki Phase 1 | E7: 17 | F7: Ikoyi / Lagos Island | G7: 17 | H7: 17 | I7: =G7+H7 -> 34 | J7: Lekki Phase 1 | K7: 21 | L7: 21 | M7: =K7+L7 -> 42 | N7: Estimated (calibrated)
A8: Lagos | B8: Apapa | C8: Island | D8: VI, Ikoyi, Lagos Island, Lekki Phase 1 | E8: 17 | F8: Ikoyi / Lagos Island | G8: 9 | H8: 9 | I8: =G8+H8 -> 18 | J8: Lekki Phase 1 | K8: 16 | L8: 16 | M8: =K8+L8 -> 32 | N8: Estimated (calibrated)
A9: Lagos | B9: Mile 2 | C9: Island | D9: VI, Ikoyi, Lagos Island, Lekki Phase 1 | E9: 17 | F9: Ikoyi / Lagos Island | G9: 16 | H9: 16 | I9: =G9+H9 -> 32 | J9: Lekki Phase 1 | K9: 24 | L9: 24 | M9: =K9+L9 -> 48 | N9: Estimated (calibrated)
A10: Lagos | B10: Amuwo Odofin | C10: Island | D10: VI, Ikoyi, Lagos Island, Lekki Phase 1 | E10: 17 | F10: Ikoyi / Lagos Island | G10: 18 | H10: 18 | I10: =G10+H10 -> 36 | J10: Lekki Phase 1 | K10: 26 | L10: 26 | M10: =K10+L10 -> 52 | N10: Estimated (calibrated)
A11: Lagos | B11: Isolo | C11: Island | D11: VI, Ikoyi, Lagos Island, Lekki Phase 1 | E11: 17 | F11: Ikoyi / Lagos Island | G11: 20 | H11: 20 | I11: =G11+H11 -> 40 | J11: Lekki Phase 1 | K11: 26 | L11: 26 | M11: =K11+L11 -> 52 | N11: Estimated (calibrated)
A12: Lagos | B12: JMG Gbagada | C12: Lekki–Ajah | D12: Lekki–Epe Expressway, tollgate to Sangotedo | E12: 23 | F12: Ajah | G12: 30 | H12: 30 | I12: =G12+H12 -> 60 | J12: Awoyaya | K12: 46 | L12: 46 | M12: =K12+L12 -> 92 | N12: Estimated (calibrated)
A13: Lagos | B13: Apapa | C13: Lekki–Ajah | D13: Lekki–Epe Expressway, tollgate to Sangotedo | E13: 23 | F13: Ajah | G13: 31 | H13: 31 | I13: =G13+H13 -> 62 | J13: Awoyaya | K13: 48 | L13: 48 | M13: =K13+L13 -> 96 | N13: Estimated (calibrated)
... A47: Kano | B47: Kano hub (city centre - confirm) | C47: Hotoro–Maiduguri Road | D47: East along Maiduguri Road | E47: 9 | F47: Hotoro | G47: 9 | H47: 9 | I47: =G47+H47 -> 18 | J47: Mariri | K47: 14 | L47: 14 | M47: =K47+L47 -> 28 | N47: Estimated (calibrated)

Sheet Zone Areas
A1: State | B1: Zone (Route) | C1: Area | D1: Route Description
A2: Lagos | B2: Mainland | C2: Ikeja | D2: Central and western mainland
A3: Lagos | B3: Mainland | C3: Ikeja GRA | D3: Central and western mainland
A4: Lagos | B4: Mainland | C4: Alausa | D4: Central and western mainland
A5: Lagos | B5: Mainland | C5: Allen Avenue | D5: Central and western mainland
A6: Lagos | B6: Mainland | C6: Opebi | D6: Central and western mainland
A7: Lagos | B7: Mainland | C7: Oregun | D7: Central and western mainland
A8: Lagos | B8: Mainland | C8: Maryland | D8: Central and western mainland
A9: Lagos | B9: Mainland | C9: Ojota | D9: Central and western mainland
A10: Lagos | B10: Mainland | C10: Ogba | D10: Central and western mainland
A11: Lagos | B11: Mainland | C11: Agidingbi | D11: Central and western mainland
A12: Lagos | B12: Mainland | C12: Omole | D12: Central and western mainland
... A362: Kano | B362: Hotoro–Maiduguri Road | C362: Gama | D362: East along Maiduguri Road

Sheet 3PL Rate Card - Internal
A1: State | B1: Depot | C1: Zone (Route) | D1: Route Description | E1: Round Trip KM (zone centre) | F1: 20FT - Rate per Trip (NGN) | G1: 25FT - Rate per Trip (NGN) | H1: 40FT - Rate per Trip (NGN) | I1: Crane - Rate per Trip (NGN) | J1: Hiab - Rate per Trip (NGN) | K1: Flatbed - Rate per Trip (NGN) | L1: Forklift - Rate per Trip (NGN)
A2: Lagos | B2: JMG Gbagada | C2: Mainland | D2: Central and western mainland | E2: ='Internal Zones'!I2 -> 14
A3: Lagos | B3: Apapa | C3: Mainland | D3: Central and western mainland | E3: ='Internal Zones'!I3 -> 34
A4: Lagos | B4: Mile 2 | C4: Mainland | D4: Central and western mainland | E4: ='Internal Zones'!I4 -> 28
A5: Lagos | B5: Amuwo Odofin | C5: Mainland | D5: Central and western mainland | E5: ='Internal Zones'!I5 -> 30
A6: Lagos | B6: Isolo | C6: Mainland | D6: Central and western mainland | E6: ='Internal Zones'!I6 -> 10
A7: Lagos | B7: JMG Gbagada | C7: Island | D7: VI, Ikoyi, Lagos Island, Lekki Phase 1 | E7: ='Internal Zones'!I7 -> 34
A8: Lagos | B8: Apapa | C8: Island | D8: VI, Ikoyi, Lagos Island, Lekki Phase 1 | E8: ='Internal Zones'!I8 -> 18
A9: Lagos | B9: Mile 2 | C9: Island | D9: VI, Ikoyi, Lagos Island, Lekki Phase 1 | E9: ='Internal Zones'!I9 -> 32
A10: Lagos | B10: Amuwo Odofin | C10: Island | D10: VI, Ikoyi, Lagos Island, Lekki Phase 1 | E10: ='Internal Zones'!I10 -> 36
A11: Lagos | B11: Isolo | C11: Island | D11: VI, Ikoyi, Lagos Island, Lekki Phase 1 | E11: ='Internal Zones'!I11 -> 40
A12: Lagos | B12: JMG Gbagada | C12: Lekki–Ajah | D12: Lekki–Epe Expressway, tollgate to Sangotedo | E12: ='Internal Zones'!I12 -> 60
A13: Lagos | B13: Apapa | C13: Lekki–Ajah | D13: Lekki–Epe Expressway, tollgate to Sangotedo | E13: ='Internal Zones'!I13 -> 62
... A47: Kano | B47: Kano hub (city centre - confirm) | C47: Hotoro–Maiduguri Road | D47: East along Maiduguri Road | E47: ='Internal Zones'!I47 -> 18

Sheet 3PL Rate Card - Interstate
A1: Loading State | B1: Loading Point | C1: Destination | D1: Destination State | E1: Region | F1: Outbound KM | G1: Return KM | H1: Round Trip KM | I1: 20FT - Rate per Trip (NGN) | J1: 25FT - Rate per Trip (NGN) | K1: 40FT - Rate per Trip (NGN) | L1: Crane - Rate per Trip (NGN) | M1: Hiab - Rate per Trip (NGN) | N1: Flatbed - Rate per Trip (NGN) | O1: Forklift - Rate per Trip (NGN)
A2: FCT | B2: Abuja | C2: Lagos (Gbagada) | D2: Lagos | E2: South West | F2: 740 | G2: 740 | H2: =IF(F2="","",F2+G2) -> 1480
A3: FCT | B3: Abuja | C3: Abeokuta | D3: Ogun | E3: South West | F3: 703 | G3: 703 | H3: =IF(F3="","",F3+G3) -> 1406
A4: FCT | B4: Abuja | C4: Ibadan | D4: Oyo | E4: South West | F4: 612 | G4: 612 | H4: =IF(F4="","",F4+G4) -> 1224
A5: FCT | B5: Abuja | C5: Port Harcourt | D5: Rivers | E5: South South | F5: 631 | G5: 631 | H5: =IF(F5="","",F5+G5) -> 1262
A6: FCT | B6: Abuja | C6: Warri | D6: Delta | E6: South South | F6: 583 | G6: 583 | H6: =IF(F6="","",F6+G6) -> 1166
A7: FCT | B7: Abuja | C7: Benin City | D7: Edo | E7: South South | F7: 487 | G7: 487 | H7: =IF(F7="","",F7+G7) -> 974
A8: FCT | B8: Abuja | C8: Gboko | D8: Benue | E8: North Central | F8: 338 | G8: 338 | H8: =IF(F8="","",F8+G8) -> 676
A9: FCT | B9: Abuja | C9: Idah | D9: Kogi | E9: North Central | F9: 302 | G9: 302 | H9: =IF(F9="","",F9+G9) -> 604
A10: FCT | B10: Abuja | C10: Otukpo | D10: Benue | E10: North Central | F10: 285 | G10: 285 | H10: =IF(F10="","",F10+G10) -> 570
A11: FCT | B11: Abuja | C11: Okene | D11: Kogi | E11: North Central | F11: 283 | G11: 283 | H11: =IF(F11="","",F11+G11) -> 566
A12: FCT | B12: Abuja | C12: Makurdi | D12: Benue | E12: North Central | F12: 241 | G12: 241 | H12: =IF(F12="","",F12+G12) -> 482
A13: FCT | B13: Abuja | C13: Ankpa | D13: Kogi | E13: North Central | F13: 240 | G13: 240 | H13: =IF(F13="","",F13+G13) -> 480
... A304: Rivers | B304: Port Harcourt | C304: Otukpa | D304: Benue | E304: North Central | F304: 349 | G304: 349 | H304: =IF(F304="","",F304+G304) -> 698

Sheet Spelling Corrections
A1: As written in your list | B1: Corrected to
A2: AGBARA-BADAGRI | B2: Agbara - Badagry
A3: AKAMPA | B3: Akamkpa
A4: AMUWO | B4: Amuwo Odofin
A5: APO,GUDU | B5: Apo - Gudu
A6: AYA -FCT | B6: Aya (Asokoro)
A7: AYANGBA | B7: Anyigba
A8: Abakalike | B8: Abakaliki
A9: Abekeuta | B9: Abeokuta
A10: Abuja-Direct | B10: Abuja (direct)
A11: Abule-EGBA-Ijayi-Moshalasi-Kola-Sango | B11: Abule Egba - Ijaiye - Moshalashi - Kola - Sango Ota
A12: Ahaoda | B12: Ahoada
... A107: yobe | B107: Yobe (Damaturu)

Sheet Method & Notes
A1: How the KM were worked out
A2: Leg 1 - Outbound | B2: Road distance from the loading point to the destination. For multi-drop routes it is the sum of every drop-to-drop leg, in the drive order shown in "Stops".
A3: Leg 2 - Return | B3: Road distance from the last drop back to the loading point.
A4: Total | B4: Leg 1 + Leg 2 (formula, so editing a blue KM cell updates the total).
A5: KM Source | B5: "Road-routed (OpenStreetMap)" = real driving distance from the OSRM routing engine. "Estimated (calibrated)" = straight-line distance x a road factor tuned against real OSRM results (e.g. Lagos-Ibadan 123.5, Lagos-Abuja 740, Lagos-Kano 984, Keffi-Ogere 729, Isolo-Maiduguri 1,557 km). Trips from the South-West to the South-South/South-East are measured via Benin City. Estimated figures are typically within about 5-10% of Google Maps; they will be replaced with road-routed figures once router.project-osrm.org is allowed in network settings.
A6: Routing fix (multi-drop) | B6: Every multi-drop route was re-sequenced into the shortest loop from the loading point and back. Where the order changed, the Notes column shows how many km the original written order would have cost.
A7: Spellings | B7: Destination names were corrected to their standard spelling (see "Spelling Corrections"). Where a state was given instead of a town, the state capital was used and named in brackets, e.g. "Imo State (Owerri)".
A8: State and Region | B8: Destination State is taken from the corrected town, not from the original sheet (which had errors such as Ibadan = Edo, Ekpoma = Delta, Abakaliki = "Ebo", Koko = "Bin Yauri"). Region uses Nigeria's six geopolitical zones.
A9: Delivery type | B9: Internal = destination in the same state as the loading point; these are mapped to your route zones (Internal Zones / Zone Areas sheets). Interstate = everything else.
A10: Internal zones | B10: KM per zone is given to the zone centre and to the far end of the zone, from each depot. Lagos zones are measured from all five Lagos loading points. Kano has no loading point in your list, so Kano zones are measured from Kano city centre - replace with your Kano hub when known.
A11: 3PL rate cards | B11: Yellow cells are for you to enter the per-trip rate each 3rd-party vendor charges for 20FT, 25FT, 40FT, Crane, Hiab, Flatbed and Forklift trucks, for every internal zone and interstate lane.
A12: Port Harcourt & Abuja rows | B12: Hiab rows list JMG Gbagada as the loading point but the client main location is Port Harcourt / Abuja, so they are measured from Port Harcourt and Abuja city.
A13: Not found (yellow rows) | B13: IKM, Dembal, Nigerian Gas (Lagos) and Jega (Abuja local list) could not be located; Karame-City (Orca) was measured from Apapa as a stand-in. Send the exact addresses and they will be filled in.
A14: Assumed locations | B14: Kpoko = Okpoko (Onitsha); Ijebu Osas = Ijebu-Ososa; Lara (Ogun) = Ilara, Yewa North; Rumukpakolosi = Rumuokwurusi; Delta-direct = Asaba.

Sheet Sheet1
